Workbook

Sheet HISTORIA
A1: HISTORIA CLÍNICA-NUTRICIONAL | AC1: Masculino
A2: Fecha: | B2: 46027 | AC2: Femenino
A3: 1- DATOS PERSONALES
A4: Nombre y Apellido | G4: Ocupación
A5: Cédula | G5: Nivel de actividad en el trabajo
A6: Fecha de nacimiento | G6: Teléfono
A7: Edad | C7: =(B2-C6)/365 -> 126.10137 | G7: Correo electrónico
A8: Estado civil | G8: Deporte/Actividad | K8: Posición
A9: Dirección | K9: Perfil/Dominio
A10: Sexo | C10: Femenino
A11: Motivo de consulta
A12: Tratamiento médico
A13: 2-ANTECEDENTES PERSONALES
A14: Enfermedad(es) importante(s) diagnosticada(s)
A15: Operación(es) realizada(s)
A16: 3- ANTECEDENTES FAMILIARES
A17: Enfermedad(es) importante(s) diagnosticada(s)
A18: 4- HÁBITOS (PSICOBIOLÓGICO Y FUNCIONALES)
A19: Café | E19: Agua
A20: Alcohol | E20: Apetito/Ansiedad
A21: Tabaco | E21: Ciclo menstrual
A22: Consumo de drogas | E22: Alguna otra información relevante:
A23: Horas de sueño
A24: Evacuaciones
A25: Hábitos miccionales
A26: Acidez/Pirosis/Náuseas
A27: 5- HÁBITOS Y CONDUCTAS ALIMENTARIAS
A28: Horas de mayor apetito | G28: Rechazos alimentarios
A29: Comidas fuera de casa
A30: Alergias alimentarias
A31: Intolerancias alimentarias
A32: 6- DEPORTE/ACTIVIDAD FÍSICA/ENERGÍA DE ACTIVIDAD
A33: Tipo de Actividad | E33: Horas/Día | H33: Coeficiente | K33: Coeficiente x hora
A34: Deporte | H34: 3 | K34: =PRODUCT(E34*H34) -> 0
A35: Tv -Lectura | H35: 1 | K35: =PRODUCT(E35*H35) -> 0
A36: Juegos Pasivos | H36: 1.5 | K36: =PRODUCT(E36*H36) -> 0
A37: Juegos Activos | H37: 2.5 | K37: =PRODUCT(E37*H37) -> 0
A38: Escolar | H38: 1 | K38: =PRODUCT(E38*H38) -> 0
A39: Descanso | H39: 0 | K39: =PRODUCT(E39*H39) -> 0
A40: TOTAL | E40: =SUM(E34:G39) -> 0 | K40: =SUM(K34:M39) -> 0
H41: Calorías aproximadas: | K41: =K40*#REF! -> #REF!
A42: 6- DEPORTE/ACTIVIDAD FÍSICA
A43: Tipo de Actividad Física/Deporte | E43: Frecuencia | F43: Horario de entrenamiento | H43: Duración/Hora | K43: Intensidad
A46: 7- SUPLEMENTOS NUTRICIONALES
A47: Suplemento(s) nutricional(es) actual(es)
A48: 9- RECORDATORIO DE INGESTA USUAL
A49: DESAYUNO
A50: HORA: 8 am
A51: MERIENDA MATUTINA
A52: HORA: 6:30-7:00 am
A53: ALMUERZO
A54: HORA: 1:00 pm
A55: MERIENDA VESPERTINA
A56: HORA: 3-4 pm
A57: CENA
... A60: HORA:
A61: CALORIAS APRÓXIMADAS CONSUMIDAS | D61: =(I64*90)+(I65*25)+(I66*60)+(I67*80)+(I68*75)+(I69*55)+(I70*45)+(I71*60) -> 0 | H61: PAVB APRÓXIMADAS CONSUMIDAS | K61: =(I68+I69) *7 -> 0
A63: Comida | B63: Desayuno | C63: Merienda | D63: Almuerzo | E63: Merienda | F63: Cena | H63: Merienda | I63: Total
A64: Leche | I64: =SUM(B64:H64) -> 0
A65: Vegetales | I65: =SUM(B65:H65) -> 0
A66: Frutas | I66: =SUM(B66:H66) -> 0
A67: Almidon | I67: =SUM(B67:H67) -> 0
A68: Carnes semi | I68: =SUM(B68:H68) -> 0
A69: Carnes magras | I69: =SUM(B69:H69) -> 0
A70: Grasas | I70: =SUM(B70:H70) -> 0
A71: Azúcar | I71: =SUM(B71:H71) -> 0
A119: Femenino
A120: Masculino

Sheet LABORATORIO
A1: LABORATORIO
A4: ANALISÍS QUÍMICO Y HEMATOLÓGIO
A5: PARÁMETRO | B5: VALOR CONSULTA 1 | C5: VALOR CONSULTA 2 | D5: VALOR CONSULTA 3 | E5: VALOR CONSULTA 4 | F5: VALORES DE REFERENCIA
A6: Hemoglobina | F6: H: 13 – 18 g/dL M: 12 -14 G/dL
A7: Hematocrito | F7: H: 37 – 49 g/dL M: 36 -46 d/dL
A8: Glucosa | F8: 70 – 100 mg/dL
A9: Colesterol total | F9: Hasta 200 mg/dL
A10: Colesterol HDL | F10: H: mayor a 40 mg/dL M: mayor a 50 mg/dL
A12: Colesterol LDL | F12: Menor 130 mg/dL
A13: Triglicéridos | F13: Hasta 150 mg/dL
A14: Urea | F14: 10 – 50 g/dL
A15: Creatinina | F15: 0.8 – 1.2 mg/dL
A16: Ácido úrico | F16: 2.4 – 7.2 mg/dL
A17: BUN | F17: 8 – 20 mg/dL
A18: Proteínas totales | F18: 5.5 – 8 g/dL
... A46: Insulina | F46: <9 µg/mL
A48: Heces
A49: Orina

Sheet ANTROPOMETRÍA DEPORTISTAS
B1: VALORES ANTROPOMÉTRICOS
A5: Número de evaluación | B5: 1
A6: Fecha de evaluación | C6: =HISTORIA!C2 -> 0 | D6: =HISTORIA!D2 -> 0 | E6: =HISTORIA!E2 -> 0 | F6: =HISTORIA!F2 -> 0 | G6: =HISTORIA!G2 -> 0 | H6: =HISTORIA!H2 -> 0 | I6: =HISTORIA!I2 -> 0 | J6: =HISTORIA!J2 -> 0 | ... N6: =HISTORIA!N2 -> 0
A7: Peso actual (kg)
A8: Talla (m)
A9: Talla (cm)
A10: Talla sentada (cm)
A11: Circunferencias(cm)
A12: Brazo relajado (cm)
A13: Brazo Flexionado en Tensón (cm)
A14: Antebrazo máximo (cm)
A15: Tórax (Mesoesternal) (cm)
A16: Cintura mínimo (cm)
A17: Cadera máximo (cm)
A18: Muslo máximo (cm)
... A37: Circunferencias corregidas por pliegues (cm)
A38: Brazo relajado (cm) | B38: =B12-(3.1416*B23)/10 -> 0 | C38: =C12-(3.1416*C23)/10 -> 0 | D38: =D12-(3.1416*D23)/10 -> 0 | E38: =E12-(3.1416*E23)/10 -> 0 | F38: =F12-(3.1416*F23)/10 -> 0
A39: Caja torácica (cm) | B39: =B15-(3.1416*B24)/10 -> 0 | C39: =C15-(3.1416*C24)/10 -> 0 | D39: =D15-(3.1416*D24)/10 -> 0 | E39: =E15-(3.1416*E24)/10 -> 0 | F39: =F15-(3.1416*F24)/10 -> 0
A40: Cintura (cm) | B40: =B16-(3.1416*B27)/10 -> 0 | C40: =C16-(3.1416*C27)/10 -> 0 | D40: =D16-(3.1416*D27)/10 -> 0 | E40: =E16-(3.1416*E27)/10 -> 0 | F40: =F16-(3.1416*F27)/10 -> 0
A41: Muslo máximo (cm) | B41: =B18-(3.1416*B28)/10 -> 0 | C41: =C18-(3.1416*C28)/10 -> 0 | D41: =D18-(3.1416*D28)/10 -> 0 | E41: =E18-(3.1416*E28)/10 -> 0 | F41: =F18-(3.1416*F28)/10 -> 0
A42: Pantorrilla máximo (cm) | B42: =B20-(3.1416*B29)/10 -> 0 | C42: =C20-(3.1416*C29)/10 -> 0 | D42: =D20-(3.1416*D29)/10 -> 0 | E42: =E20-(3.1416*E29)/10 -> 0 | F42: =F20-(3.1416*F29)/10 -> 0
A43: INDICADORES (2 componentes)
A44: IMC (kg/m2) | B44: =B7/(B8*B8) -> #DIV/0! | C44: =C7/(C8*C8) -> #DIV/0! | D44: =D7/(D8*D8) -> #DIV/0! | E44: =E7/(E8*E8) -> #DIV/0! | F44: =F7/(F8*F8) -> #DIV/0! | G44: =G7/(G8*G8) -> #DIV/0! | H44: =H7/(H8*H8) -> #DIV/0! | I44: =I7/(I8*I8) -> #DIV/0! | ... S44: =S7/(S8*S8) -> #DIV/0!
A45: Contextura | B45: =(B35/(B9/100))*10 -> #DIV/0! | C45: =(C35/(C9/100))*10 -> #DIV/0! | D45: =(D35/(D9/100))*10 -> #DIV/0! | E45: =(E35/(E9/100))*10 -> #DIV/0! | F45: =(F35/(F9/100))*10 -> #DIV/0! | G45: =(G35/(G9/100))*10 -> #DIV/0! | H45: =(H35/(H9/100))*10 -> #DIV/0! | I45: =(I35/(I9/100))*10 -> #DIV/0! | ... S45: =(S35/(S9/100))*10 -> #DIV/0!
A46: A. Grasa Brazo (cm2) | B46: =(B23/10)*B12/2-((B23/10)*(B23/10)*3.1416/4) -> 0 | C46: =(C23/10)*C12/2-((C23/10)*(C23/10)*3.1416/4) -> 0 | D46: =(D23/10)*D12/2-((D23/10)*(D23/10)*3.1416/4) -> 0 | E46: =(E23/10)*E12/2-((E23/10)*(E23/10)*3.1416/4) -> 0 | F46: =(F23/10)*F12/2-((F23/10)*(F23/10)*3.1416/4) -> 0 | G46: =(G23/10)*G12/2-((G23/10)*(G23/10)*3.1416/4) -> 0 | H46: =(H23/10)*H12/2-((H23/10)*(H23/10)*3.1416/4) -> 0 | I46: =(I23/10)*I12/2-((I23/10)*(I23/10)*3.1416/4) -> 0 | ... S46: =(S23/10)*S12/2-((S23/10)*(S23/10)*3.1416/4) -> 0
A47: A. Magra Brazo (cm2) | B47: =(B12-((B23/10)*3.1416))^2/(4*3.1416) -> 0 | C47: =(C12-((C23/10)*3.1416))^2/(4*3.1416) -> 0 | D47: =(D12-((D23/10)*3.1416))^2/(4*3.1416) -> 0 | E47: =(E12-((E23/10)*3.1416))^2/(4*3.1416) -> 0 | F47: =(F12-((F23/10)*3.1416))^2/(4*3.1416) -> 0 | G47: =(G12-((G23/10)*3.1416))^2/(4*3.1416) -> 0 | H47: =(H12-((H23/10)*3.1416))^2/(4*3.1416) -> 0 | I47: =(I12-((I23/10)*3.1416))^2/(4*3.1416) -> 0 | ... S47: =(S12-((S23/10)*3.1416))^2/(4*3.1416) -> 0
A48: Área Magra del Muslo cm2 | B48: =((B19-(B28/10)*3.1416)*(B19-(B28/10)*3.1416)/12.5664) -> 0 | C48: =((C19-(C28/10)*3.1416)*(C19-(C28/10)*3.1416)/12.5664) -> 0 | D48: =((D19-(D28/10)*3.1416)*(D19-(D28/10)*3.1416)/12.5664) -> 0 | E48: =((E19-(E28/10)*3.1416)*(E19-(E28/10)*3.1416)/12.5664) -> 0 | F48: =((F19-(F28/10)*3.1416)*(F19-(F28/10)*3.1416)/12.5664) -> 0 | G48: =((G19-(G28/10)*3.1416)*(G19-(G28/10)*3.1416)/12.5664) -> 0 | H48: =((H19-(H28/10)*3.1416)*(H19-(H28/10)*3.1416)/12.5664) -> 0 | I48: =((I19-(I28/10)*3.1416)*(I19-(I28/10)*3.1416)/12.5664) -> 0 | ... S48: =((S19-(S28/10)*3.1416)*(S19-(S28/10)*3.1416)/12.5664) -> 0
A49: Área Grasa del Muslo cm2 | B49: =(B19/10)*B28/2-((B19/10)*(B28/10)*3.1416/4) -> 0 | C49: =(C19/10)*C28/2-((C19/10)*(C28/10)*3.1416/4) -> 0 | D49: =(D19/10)*D28/2-((D19/10)*(D28/10)*3.1416/4) -> 0 | E49: =(E19/10)*E28/2-((E19/10)*(E28/10)*3.1416/4) -> 0 | F49: =(F19/10)*F28/2-((F19/10)*(F28/10)*3.1416/4) -> 0 | G49: =(G19/10)*G28/2-((G19/10)*(G28/10)*3.1416/4) -> 0 | H49: =(H19/10)*H28/2-((H19/10)*(H28/10)*3.1416/4) -> 0 | I49: =(I19/10)*I28/2-((I19/10)*(I28/10)*3.1416/4) -> 0 | ... S49: =(S19/10)*S28/2-((S19/10)*(S28/10)*3.1416/4) -> 0
A50: Área Magra de la Pantorrilla cm2 | B50: =((B20-(B29/10)*3.1416)*(B20-(B29/10)*3.1416)/12.5664) -> 0 | C50: =((C20-(C29/10)*3.1416)*(C20-(C29/10)*3.1416)/12.5664) -> 0 | D50: =((D20-(D29/10)*3.1416)*(D20-(D29/10)*3.1416)/12.5664) -> 0 | E50: =((E20-(E29/10)*3.1416)*(E20-(E29/10)*3.1416)/12.5664) -> 0 | F50: =((F20-(F29/10)*3.1416)*(F20-(F29/10)*3.1416)/12.5664) -> 0 | G50: =((G20-(G29/10)*3.1416)*(G20-(G29/10)*3.1416)/12.5664) -> 0 | H50: =((H20-(H29/10)*3.1416)*(H20-(H29/10)*3.1416)/12.5664) -> 0 | I50: =((I20-(I29/10)*3.1416)*(I20-(I29/10)*3.1416)/12.5664) -> 0 | ... S50: =((S20-(S29/10)*3.1416)*(S20-(S29/10)*3.1416)/12.5664) -> 0
A51: Área Grasa de la Pantorrilla cm2 | B51: =(B20/10)*B29/2-((B20/10)*(B29/10)*3.1416/4) -> 0 | C51: =(C20/10)*C29/2-((C20/10)*(C29/10)*3.1416/4) -> 0 | D51: =(D20/10)*D29/2-((D20/10)*(D29/10)*3.1416/4) -> 0 | E51: =(E20/10)*E29/2-((E20/10)*(E29/10)*3.1416/4) -> 0 | F51: =(F20/10)*F29/2-((F20/10)*(F29/10)*3.1416/4) -> 0 | G51: =(G20/10)*G29/2-((G20/10)*(G29/10)*3.1416/4) -> 0 | H51: =(H20/10)*H29/2-((H20/10)*(H29/10)*3.1416/4) -> 0 | I51: =(I20/10)*I29/2-((I20/10)*(I29/10)*3.1416/4) -> 0 | ... S51: =(S20/10)*S29/2-((S20/10)*(S29/10)*3.1416/4) -> 0
A52: % Grasa (Carter 1986) | B52: =(3.5803)+(0.1548*(B24+B23+B26+B27+B28+B29)) -> 3.5803 | C52: =(3.5803)+(0.1548*(C24+C23+C26+C27+C28+C29)) -> 3.5803 | D52: =(3.5803)+(0.1548*(D24+D23+D26+D27+D28+D29)) -> 3.5803 | E52: =(3.5803)+(0.1548*(E24+E23+E26+E27+E28+E29)) -> 3.5803 | F52: =(3.5803)+(0.1548*(F24+F23+F26+F27+F28+F29)) -> 3.5803 | G52: =(3.5803)+(0.1548*(G24+G23+G26+G27+G28+G29)) -> 3.5803 | H52: =(3.5803)+(0.1548*(H24+H23+H26+H27+H28+H29)) -> 3.5803 | I52: =(3.5803)+(0.1548*(I24+I23+I26+I27+I28+I29)) -> 3.5803 | ... S52: =(3.5803)+(0.1548*(S24+S23+S26+S27+S28+S29)) -> 3.5803
A53: % Grasa (Durnin y W. 1974) | B53: =((4.95 / (VLOOKUP(HISTORIA!C7, I104:K109, 2, 1) - (VLOOKUP(HISTORIA!C7, I104:K109, 3, 1) *LOG10(SUM(B22:B25))))) - 4.5) * 100 -> #NUM! | C53: =((4.95 / (1.1339 - (0.064 *LOG10(C22+C23+C24+C25)))) - 4.5) * 100 -> #NUM! | D53: =((4.95 / (1.1339 - (0.064 *LOG10(D22+D23+D24+D25)))) - 4.5) * 100 -> #NUM! | E53: =((4.95 / (1.1339 - (0.064 *LOG10(E22+E23+E24+E25)))) - 4.5) * 100 -> #NUM! | F53: =((4.95 / (1.1339 - (0.064 *LOG10(F22+F23+F24+F25)))) - 4.5) * 100 -> #NUM! | H53: =((4.95 / (1.1339 - (0.064 *LOG10(H22+H23+H24+H25)))) - 4.5) * 100 -> #NUM! | I53: =((4.95 / (1.1339 - (0.064 *LOG10(I22+I23+I24+I25)))) - 4.5) * 100 -> #NUM! | J53: =((4.95 / (1.1339 - (0.064 *LOG10(J22+J23+J24+J25)))) - 4.5) * 100 -> #NUM! | K53: =((4.95 / (1.1339 - (0.064 *LOG10(K22+K23+K24+K25)))) - 4.5) * 100 -> #NUM! | L53: =((4.95 / (1.1339 - (0.064 *LOG10(L22+L23+L24+L25)))) - 4.5) * 100 -> #NUM! | M53: =((4.95 / (1.1339 - (0.064 *LOG10(M22+M23+M24+M25)))) - 4.5) * 100 -> #NUM! | N53: =((4.95 / (1.1339 - (0.064 *LOG10(N22+N23+N24+N25)))) - 4.5) * 100 -> #NUM! | O53: =((4.95 / (1.1339 - (0.064 *LOG10(O22+O23+O24+O25)))) - 4.5) * 100 -> #NUM! | ... S53: =((4.95 / (1.1339 - (0.064 *LOG10(S22+S23+S24+S25)))) - 4.5) * 100 -> #NUM!
A54: Sumatoria de 6 Pliegues | B54: =B29+B28+B27+B26+B23+B24 -> 0 | C54: =C29+C28+C27+C26+C23+C24 -> 0 | D54: =D29+D28+D27+D26+D23+D24 -> 0 | E54: =E29+E28+E27+E26+E23+E24 -> 0 | F54: =F29+F28+F27+F26+F23+F24 -> 0 | G54: =G29+G28+G27+G26+G23+G24 -> 0 | H54: =H29+H28+H27+H26+H23+H24 -> 0 | I54: =I29+I28+I27+I26+I23+I24 -> 0 | ... S54: =S29+S28+S27+S26+S23+S24 -> 0
A55: Sumatoria de 8 Pliegues | B55: =B26+B29+B28+B27+B25+B22+B23+B24 -> 0 | C55: =C26+C29+C28+C27+C25+C22+C23+C24 -> 0 | D55: =D26+D29+D28+D27+D25+D22+D23+D24 -> 0 | E55: =E26+E29+E28+E27+E25+E22+E23+E24 -> 0 | F55: =F26+F29+F28+F27+F25+F22+F23+F24 -> 0 | G55: =G26+G29+G28+G27+G25+G22+G23+G24 -> 0 | H55: =H26+H29+H28+H27+H25+H22+H23+H24 -> 0 | I55: =I26+I29+I28+I27+I25+I22+I23+I24 -> 0 | ... S55: =S26+S29+S28+S27+S25+S22+S23+S24 -> 0
A56: Índice cintura/cadera | B56: =B16/B17 -> #DIV/0! | C56: =C16/C17 -> #DIV/0! | D56: =D16/D17 -> #DIV/0! | E56: =E16/E17 -> #DIV/0! | F56: =F16/F17 -> #DIV/0! | G56: =G16/G17 -> #DIV/0! | H56: =H16/H17 -> #DIV/0! | I56: =I16/I17 -> #DIV/0! | ... S56: =S16/S17 -> #DIV/0!
A57: Porcentaje a Utilizar | B57: =B52 -> 3.5803 | C57: =C52 -> 3.5803 | D57: =D52 -> 3.5803 | E57: =E52 -> 3.5803 | F57: =F52 -> 3.5803 | G57: =G52 -> 3.5803 | H57: =H52 -> 3.5803 | I57: =I52 -> 3.5803 | ... S57: =S52 -> 3.5803
A58: Kg. Masa magra | B58: =(100-B57)/100*B7 -> 0 | C58: =(100-C57)/100*C7 -> 0 | D58: =(100-D57)/100*D7 -> 0 | E58: =(100-E57)/100*E7 -> 0 | F58: =(100-F57)/100*F7 -> 0 | G58: =(100-G57)/100*G7 -> 0 | H58: =(100-H57)/100*H7 -> 0 | I58: =(100-I57)/100*I7 -> 0 | ... S58: =(100-S57)/100*S7 -> 0
A59: Kg. Grasa | B59: =B7-B58 -> 0 | C59: =C7-C58 -> 0 | D59: =D7-D58 -> 0 | E59: =E7-E58 -> 0 | F59: =F7-F58 -> 0 | G59: =G7-G58 -> 0 | H59: =H7-H58 -> 0 | I59: =I7-I58 -> 0 | ... S59: =S7-S58 -> 0
A60: Lean Body Mass | B60: =B7-B57 -> -3.5803 | C60: =C7-C57 -> -3.5803 | D60: =D7-D57 -> -3.5803 | E60: =E7-E57 -> -3.5803 | F60: =F7-F57 -> -3.5803 | G60: =G7-G57 -> -3.5803 | H60: =H7-H57 -> -3.5803 | I60: =I7-I57 -> -3.5803 | ... S60: =S7-S57 -> -3.5803
A61: Fat mass | B61: =B7*B57/100 -> 0 | C61: =C7*C57/100 -> 0 | D61: =D7*D57/100 -> 0 | E61: =E7*E57/100 -> 0 | F61: =F7*F57/100 -> 0 | G61: =G7*G57/100 -> 0 | H61: =H7*H57/100 -> 0 | I61: =I7*I57/100 -> 0 | ... S61: =S7*S57/100 -> 0
A62: Indicadores absolutos (Corregidos por pliegues)
A63: Masa Adiposa (Kg) | B63: =(((((B24+B23+B26+B27+B28+B29)*(170.18/B9)-116.41)/34.79)*5.85)+25.6)/((170.18/B9)^3) -> #DIV/0! | C63: =(((((C24+C23+C26+C27+C28+C29)*(170.18/C9)-116.41)/34.79)*5.85)+25.6)/((170.18/C9)^3) -> #DIV/0! | D63: =(((((D24+D23+D26+D27+D28+D29)*(170.18/D9)-116.41)/34.79)*5.85)+25.6)/((170.18/D9)^3) -> #DIV/0! | E63: =(((((E24+E23+E26+E27+E28+E29)*(170.18/E9)-116.41)/34.79)*5.85)+25.6)/((170.18/E9)^3) -> #DIV/0! | F63: =(((((F24+F23+F26+F27+F28+F29)*(170.18/F9)-116.41)/34.79)*5.85)+25.6)/((170.18/F9)^3) -> #DIV/0! | G63: =(((((G24+G23+G26+G27+G28+G29)*(170.18/G9)-116.41)/34.79)*5.85)+25.6)/((170.18/G9)^3) -> #DIV/0! | H63: =(((((H24+H23+H26+H27+H28+H29)*(170.18/H9)-116.41)/34.79)*5.85)+25.6)/((170.18/H9)^3) -> #DIV/0! | I63: =(((((I24+I23+I26+I27+I28+I29)*(170.18/I9)-116.41)/34.79)*5.85)+25.6)/((170.18/I9)^3) -> #DIV/0! | ... S63: =(((((S24+S23+S26+S27+S28+S29)*(170.18/S9)-116.41)/34.79)*5.85)+25.6)/((170.18/S9)^3) -> #DIV/0!
A64: Masa Muscular (Kg) | B64: =(((((B38+B14+B39+B41+B42)*(170.18/B9))-207.21)/13.74*5.4)+24.5)/((170.18/B9)^3) -> #DIV/0! | C64: =(((((C38+C14+C39+C41+C42)*(170.18/C9))-207.21)/13.74*5.4)+24.5)/((170.18/C9)^3) -> #DIV/0! | D64: =(((((D38+D14+D39+D41+D42)*(170.18/D9))-207.21)/13.74*5.4)+24.5)/((170.18/D9)^3) -> #DIV/0! | E64: =(((((E38+E14+E39+E41+E42)*(170.18/E9))-207.21)/13.74*5.4)+24.5)/((170.18/E9)^3) -> #DIV/0! | F64: =(((((F38+F14+F39+F41+F42)*(170.18/F9))-207.21)/13.74*5.4)+24.5)/((170.18/F9)^3) -> #DIV/0! | G64: =(((((G38+G14+G39+G41+G42)*(170.18/G9))-207.21)/13.74*5.4)+24.5)/((170.18/G9)^3) -> #DIV/0! | H64: =(((((H38+H14+H39+H41+H42)*(170.18/H9))-207.21)/13.74*5.4)+24.5)/((170.18/H9)^3) -> #DIV/0! | I64: =(((((I38+I14+I39+I41+I42)*(170.18/I9))-207.21)/13.74*5.4)+24.5)/((170.18/I9)^3) -> #DIV/0! | ... S64: =(((((S38+S14+S39+S41+S42)*(170.18/S9))-207.21)/13.74*5.4)+24.5)/((170.18/S9)^3) -> #DIV/0!
A65: Valoración del Somatotipo (Decimal)
A66: Ectomorfia | B66: =(0.732*B99)-28.58 -> #DIV/0! | C66: =(0.732*C99)-28.58 -> #DIV/0! | D66: =(0.732*D99)-28.58 -> #DIV/0! | E66: =(0.732*E99)-28.58 -> #DIV/0! | F66: =(0.732*F99)-28.58 -> #DIV/0! | G66: =(0.732*G99)-28.58 -> #DIV/0! | H66: =(0.732*H99)-28.58 -> #DIV/0! | I66: =(0.732*I99)-28.58 -> #DIV/0! | ... S66: =(0.732*S99)-28.58 -> #DIV/0!
A67: Mesomorfia | B67: =(0.858*B35)+(0.601*B36)+(0.188*B97)+(0.161*B98)-(0.131*B9)+4.5 -> 4.5 | C67: =(0.858*C35)+(0.601*C36)+(0.188*C97)+(0.161*C98)-(0.131*C9)+4.5 -> 4.5 | D67: =(0.858*D35)+(0.601*D36)+(0.188*D97)+(0.161*D98)-(0.131*D9)+4.5 -> 4.5 | E67: =(0.858*E35)+(0.601*E36)+(0.188*E97)+(0.161*E98)-(0.131*E9)+4.5 -> 4.5 | F67: =(0.858*F35)+(0.601*F36)+(0.188*F97)+(0.161*F98)-(0.131*F9)+4.5 -> 4.5 | G67: =(0.858*G35)+(0.601*G36)+(0.188*G97)+(0.161*G98)-(0.131*G9)+4.5 -> 4.5 | H67: =(0.858*H35)+(0.601*H36)+(0.188*H97)+(0.161*H98)-(0.131*H9)+4.5 -> 4.5 | I67: =(0.858*I35)+(0.601*I36)+(0.188*I97)+(0.161*I98)-(0.131*I9)+4.5 -> 4.5 | ... S67: =(0.858*S35)+(0.601*S36)+(0.188*S97)+(0.161*S98)-(0.131*S9)+4.5 -> 4.5
A68: Endomorfia | B68: =(-0.7182+(0.1451*B94)-(0.00068*B95)+(0.0000014*B96)) -> #DIV/0! | C68: =(-0.7182+(0.1451*C94)-(0.00068*C95)+(0.0000014*C96)) -> #DIV/0! | D68: =(-0.7182+(0.1451*D94)-(0.00068*D95)+(0.0000014*D96)) -> #DIV/0! | E68: =(-0.7182+(0.1451*E94)-(0.00068*E95)+(0.0000014*E96)) -> #DIV/0! | F68: =(-0.7182+(0.1451*F94)-(0.00068*F95)+(0.0000014*F96)) -> #DIV/0! | G68: =(-0.7182+(0.1451*G94)-(0.00068*G95)+(0.0000014*G96)) -> #DIV/0! | H68: =(-0.7182+(0.1451*H94)-(0.00068*H95)+(0.0000014*H96)) -> #DIV/0! | I68: =(-0.7182+(0.1451*I94)-(0.00068*I95)+(0.0000014*I96)) -> #DIV/0! | ... S68: =(-0.7182+(0.1451*S94)-(0.00068*S95)+(0.0000014*S96)) -> #DIV/0!
A69: SOMATOTIPO
A70: Ubicación en la somatocarta
A71: Eje X | B71: =B66-B68 -> #DIV/0! | C71: =C66-C68 -> #DIV/0! | D71: =D66-D68 -> #DIV/0! | E71: =E66-E68 -> #DIV/0! | F71: =F66-F68 -> #DIV/0! | G71: =G66-G68 -> #DIV/0! | H71: =H66-H68 -> #DIV/0! | I71: =I66-I68 -> #DIV/0! | ... S71: =S66-S68 -> #DIV/0!
A72: Eje Y | B72: =(2*B67)-(B68+B66) -> #DIV/0! | C72: =(2*C67)-(C68+C66) -> #DIV/0! | D72: =(2*D67)-(D68+D66) -> #DIV/0! | E72: =(2*E67)-(E68+E66) -> #DIV/0! | F72: =(2*F67)-(F68+F66) -> #DIV/0! | G72: =(2*G67)-(G68+G66) -> #DIV/0! | H72: =(2*H67)-(H68+H66) -> #DIV/0! | I72: =(2*I67)-(I68+I66) -> #DIV/0! | ... S72: =(2*S67)-(S68+S66) -> #DIV/0!
A73: % Grasa Objetivo | B73: 11 | C73: 12 | D73: 13 | E73: 14 | F73: 15 | G73: 16 | H73: 17 | I73: 18 | J73: 19 | K73: 20 | L73: 21 | M73: 22 | N73: 23 | O73: 24 | P73: 25 | Q73: 26 | R73: 27 | S73: 28
A74: Pérdida de grasa requerida (%) | B74: =B57-B73 -> -7.4197 | C74: =C57-C73 -> -8.4197 | D74: =D57-D73 -> -9.4197 | E74: =E57-E73 -> -10.4197 | F74: =F57-F73 -> -11.4197 | G74: =G57-G73 -> -12.4197 | H74: =H57-H73 -> -13.4197 | I74: =I57-I73 -> -14.4197 | ... S74: =S57-S73 -> -24.4197
A75: Pérdida de grasa requerida (Kg) | B75: =(B7*B74)/100 -> 0 | C75: =(C7*C74)/100 -> 0 | D75: =(D7*D74)/100 -> 0 | E75: =(E7*E74)/100 -> 0 | F75: =(F7*F74)/100 -> 0 | G75: =(G7*G74)/100 -> 0 | H75: =(H7*H74)/100 -> 0 | I75: =(I7*I74)/100 -> 0 | ... S75: =(S7*S74)/100 -> 0
A76: Peso Objetivo | B76: =(B58)/(1-B73/100) -> 0 | C76: =(C58)/(1-C73/100) -> 0 | D76: =(D58)/(1-D73/100) -> 0 | E76: =(E58)/(1-E73/100) -> 0 | F76: =(F58)/(1-F73/100) -> 0 | G76: =(G58)/(1-G73/100) -> 0 | H76: =(H58)/(1-H73/100) -> 0 | I76: =(I58)/(1-I73/100) -> 0 | ... S76: =(S58)/(1-S73/100) -> 0
A77: Pérdida de peso Requerida | B77: =B75/0.8 -> 0 | C77: =C75/0.8 -> 0 | D77: =D75/0.8 -> 0 | E77: =E75/0.8 -> 0 | F77: =F75/0.8 -> 0 | G77: =G75/0.8 -> 0 | H77: =H75/0.8 -> 0 | I77: =I75/0.8 -> 0 | ... S77: =S75/0.8 -> 0
A78: Kg. a bajar o subir | B78: =B7-B76 -> 0 | C78: =C7-C76 -> 0 | D78: =D7-D76 -> 0 | E78: =E7-E76 -> 0 | F78: =F7-F76 -> 0 | G78: =G7-G76 -> 0 | H78: =H7-H76 -> 0 | I78: =I7-I76 -> 0 | ... S78: =S7-S76 -> 0
A79: g de grasa a bajar | B79: =(B77*0.8)*1000 -> 0 | C79: =(C77*0.8)*1000 -> 0 | D79: =(D77*0.8)*1000 -> 0 | E79: =(E77*0.8)*1000 -> 0 | F79: =(F77*0.8)*1000 -> 0 | G79: =(G77*0.8)*1000 -> 0 | H79: =(H77*0.8)*1000 -> 0 | I79: =(I77*0.8)*1000 -> 0 | ... S79: =(S77*0.8)*1000 -> 0
A80: Pérdida de M.M aceptable (g) | B80: =(B77*0.2)*1000 -> 0 | C80: =(C77*0.2)*1000 -> 0 | D80: =(D77*0.2)*1000 -> 0 | E80: =(E77*0.2)*1000 -> 0 | F80: =(F77*0.2)*1000 -> 0 | G80: =(G77*0.2)*1000 -> 0 | H80: =(H77*0.2)*1000 -> 0 | I80: =(I77*0.2)*1000 -> 0 | ... S80: =(S77*0.2)*1000 -> 0
A81: Pérdida de peso esperada p/ semana (g) | B81: =(B7*0.6)*10 -> 0 | C81: =(C7*0.6)*10 -> 0 | D81: =(D7*0.6)*10 -> 0 | E81: =(E7*0.6)*10 -> 0 | F81: =(F7*0.6)*10 -> 0 | G81: =(G7*0.6)*10 -> 0 | H81: =(H7*0.6)*10 -> 0 | I81: =(I7*0.6)*10 -> 0 | ... S81: =(S7*0.6)*10 -> 0
A82: Pérdida de peso esperada p/ mes (g) | B82: =B81*4 -> 0 | C82: =C81*4 -> 0 | D82: =D81*4 -> 0 | E82: =E81*4 -> 0 | F82: =F81*4 -> 0 | G82: =G81*4 -> 0 | H82: =H81*4 -> 0 | I82: =I81*4 -> 0 | ... S82: =S81*4 -> 0
A83: Pérdida de grasa semanal (g) | B83: =B81*0.8 -> 0 | C83: =C81*0.8 -> 0 | D83: =D81*0.8 -> 0 | E83: =E81*0.8 -> 0 | F83: =F81*0.8 -> 0 | G83: =G81*0.8 -> 0 | H83: =H81*0.8 -> 0 | I83: =I81*0.8 -> 0 | ... S83: =S81*0.8 -> 0
A84: Pérdida de musculo semanal (g) | B84: =B81*0.2 -> 0 | C84: =C81*0.2 -> 0 | D84: =D81*0.2 -> 0 | E84: =E81*0.2 -> 0 | F84: =F81*0.2 -> 0 | G84: =G81*0.2 -> 0 | H84: =H81*0.2 -> 0 | I84: =I81*0.2 -> 0 | ... S84: =S81*0.2 -> 0
A85: Ganancia de peso esperada (g)
A86: Duración del decít (semanas) | B86: =(B77/B81)*1000 -> #DIV/0! | C86: =(C77/C81)*1000 -> #DIV/0! | D86: =(D77/D81)*1000 -> #DIV/0! | E86: =(E77/E81)*1000 -> #DIV/0! | F86: =(F77/F81)*1000 -> #DIV/0! | G86: =(G77/G81)*1000 -> #DIV/0! | H86: =(H77/H81)*1000 -> #DIV/0! | I86: =(I77/I81)*1000 -> #DIV/0! | ... S86: =(S77/S81)*1000 -> #DIV/0!
A87: Duración del decít (meses) | B87: =B86/4 -> #DIV/0! | C87: =C86/4 -> #DIV/0! | D87: =D86/4 -> #DIV/0! | E87: =E86/4 -> #DIV/0! | F87: =F86/4 -> #DIV/0! | G87: =G86/4 -> #DIV/0! | H87: =H86/4 -> #DIV/0! | I87: =I86/4 -> #DIV/0! | ... S87: =S86/4 -> #DIV/0!
A88: Kcal por Kg de Grasa | B88: =(B83*0.87)*9 -> 0 | C88: =(C83*0.87)*9 -> 0 | D88: =(D83*0.87)*9 -> 0 | E88: =(E83*0.87)*9 -> 0 | F88: =(F83*0.87)*9 -> 0 | G88: =(G83*0.87)*9 -> 0 | H88: =(H83*0.87)*9 -> 0 | I88: =(I83*0.87)*9 -> 0 | ... S88: =(S83*0.87)*9 -> 0
A89: Kcal por Kg de Masa Magra | B89: =(B84*0.3)*4 -> 0 | C89: =(C84*0.3)*4 -> 0 | D89: =(D84*0.3)*4 -> 0 | E89: =(E84*0.3)*4 -> 0 | F89: =(F84*0.3)*4 -> 0 | G89: =(G84*0.3)*4 -> 0 | H89: =(H84*0.3)*4 -> 0 | I89: =(I84*0.3)*4 -> 0 | ... S89: =(S84*0.3)*4 -> 0
A90: DEFICÍT (Kcal/día) | B90: =(B88+B89)/7 -> 0 | C90: =(C88+C89)/7 -> 0 | D90: =(D88+D89)/7 -> 0 | E90: =(E88+E89)/7 -> 0 | F90: =(F88+F89)/7 -> 0 | G90: =(G88+G89)/7 -> 0 | H90: =(H88+H89)/7 -> 0 | I90: =(I88+I89)/7 -> 0 | ... S90: =(S88+S89)/7 -> 0
A92: OTRAS SUMATORIAS
A93: Sumatoria de 3 pliegues | B93: =B24+B23+B26 -> 0 | C93: =C24+C23+C26 -> 0 | D93: =D24+D23+D26 -> 0 | E93: =E24+E23+E26 -> 0 | F93: =F24+F23+F26 -> 0 | G93: =G24+G23+G26 -> 0 | H93: =H24+H23+H26 -> 0 | I93: =I24+I23+I26 -> 0 | ... S93: =S24+S23+S26 -> 0
A94: Sumatoria de 3 pliegues (Corregida) | B94: =(170.18/B9)*B93 -> #DIV/0! | C94: =(170.18/C9)*C93 -> #DIV/0! | D94: =(170.18/D9)*D93 -> #DIV/0! | E94: =(170.18/E9)*E93 -> #DIV/0! | F94: =(170.18/F9)*F93 -> #DIV/0! | G94: =(170.18/G9)*G93 -> #DIV/0! | H94: =(170.18/H9)*H93 -> #DIV/0! | I94: =(170.18/I9)*I93 -> #DIV/0! | ... S94: =(170.18/S9)*S93 -> #DIV/0!
A95: Sumatoria de 3 pliegues (Corregida) (2) | B95: =(B94^2) -> #DIV/0! | C95: =(C94^2) -> #DIV/0! | D95: =(D94^2) -> #DIV/0! | E95: =(E94^2) -> #DIV/0! | F95: =(F94^2) -> #DIV/0! | G95: =(G94^2) -> #DIV/0! | H95: =(H94^2) -> #DIV/0! | I95: =(I94^2) -> #DIV/0! | ... S95: =(S94^2) -> #DIV/0!
A96: Sumatoria de 3 pliegues (Corregida) (3) | B96: =(B94^3) -> #DIV/0! | C96: =(C94^3) -> #DIV/0! | D96: =(D94^3) -> #DIV/0! | E96: =(E94^3) -> #DIV/0! | F96: =(F94^3) -> #DIV/0! | G96: =(G94^3) -> #DIV/0! | H96: =(H94^3) -> #DIV/0! | I96: =(I94^3) -> #DIV/0! | ... S96: =(S94^3) -> #DIV/0!
A97: Biceps Corregido | B97: =(B13-(B23/10)) -> 0 | C97: =(C13-(C23/10)) -> 0 | D97: =(D13-(D23/10)) -> 0 | E97: =(E13-(E23/10)) -> 0 | F97: =(F13-(F23/10)) -> 0 | G97: =(G13-(G23/10)) -> 0 | H97: =(H13-(H23/10)) -> 0 | I97: =(I13-(I23/10)) -> 0 | ... S97: =(S13-(S23/10)) -> 0
A98: Pantorrilla Corregida | B98: =(B20-(B29/10)) -> 0 | C98: =(C20-(C29/10)) -> 0 | D98: =(D20-(D29/10)) -> 0 | E98: =(E20-(E29/10)) -> 0 | F98: =(F20-(F29/10)) -> 0 | G98: =(G20-(G29/10)) -> 0 | H98: =(H20-(H29/10)) -> 0 | I98: =(I20-(I29/10)) -> 0 | ... S98: =(S20-(S29/10)) -> 0
A99: Altura/Peso (1/3) | B99: =B9/(B7^0.3333) -> #DIV/0! | C99: =C9/(C7^0.3333) -> #DIV/0! | D99: =D9/(D7^0.3333) -> #DIV/0! | E99: =E9/(E7^0.3333) -> #DIV/0! | F99: =F9/(F7^0.3333) -> #DIV/0! | G99: =G9/(G7^0.3333) -> #DIV/0! | H99: =H9/(H7^0.3333) -> #DIV/0! | I99: =I9/(I7^0.3333) -> #DIV/0! | ... S99: =S9/(S7^0.3333) -> #DIV/0!
B101: VALORES DE REFERENCIA
B104: % DE GRASA (CARTER 1986) | E104: SOMATOTIPO | I104: Edad Mínima (Col H) | J104: Constante c (Col I) | K104: Constante m (Col J)
I105: 16 | J105: 1.1549 | K105: 0.0678
B106: Deporte | C106: Adultos | D106: Juveniles | E106: Deporte | F106: Adultos | G106: Juveniles | I106: 20 | J106: 1.1599 | K106: 0.0717
B107: Beisbol | E107: Beisbol | I107: 30 | J107: 1.1423 | K107: 0.0632
B108: Baloncesto | E108: Baloncesto | I108: 40 | J108: 1.1333 | K108: 0.0612
B109: Culturismo | E109: Culturismo | I109: 50 | J109: 1.1339 | K109: 0.064
B110: Ciclismo | E110: Ciclismo
B111: Gimnasia | E111: Gimnasia | I111: Edad Mín. | J111: Excelente | K111: Promedio/Saludable | L111: Sobrepeso | M111: Obesidad
B112: Fútbol | D112: 10_12 | E112: Fútbol | I112: 20 | J112: < 21% | K112: 21% - 33% | L112: 33% - 39% | M112: > 39%
B113: Natación | E113: Natación | I113: 40 | J113: < 23% | K113: 23% - 34% | L113: 34% - 40% | M113: > 40%
B114: Tenis | E114: Tenis | I114: 60 | J114: < 24% | K114: 24% - 36% | L114: 36% - 42% | M114: > 42%
B115: Crossfit | C115: 8 a 15 | E115: Crossfit
B123: INDICE CINTURA CADERA
D127: Riesgo
C128: Edad | D128: Bajo | F128: Moderado | H128: Alto | J128: Muy alto
B129: Hombres | C129: 20-29 | D129: <0.83 | F129: 0.83-0.88 | H129: 0.89-0.94 | J129: >0.94
C130: 30-39 | D130: <0.84 | F130: 0.84-0.91 | H130: 0.92-0.96 | J130: >0.96
C131: 40-49 | D131: <0.88 | F131: 0.88-0.95 | H131: 0.96-1.00 | J131: >1.00
C132: 50-59 | D132: <0.90 | F132: 0.90-0.96 | H132: 0.97-1.02 | J132: >1.02
C133: 60-69 | D133: <0.91 | F133: 0.91-0.98 | H133: 0.99-1.03 | J133: >1.03
B134: Mujeres | C134: 20-29 | D134: <0.71 | F134: 0.71-0.77 | H134: 0.78-0.82 | J134: >0.82
C135: 30-39 | D135: <0.72 | F135: 0.72-0.78 | H135: 0.79-0.84 | J135: >0.84
...

Sheet 5 componentes
A1: DATOS PERSONALES | B1: Nombre y apellido | C1: =[1]HISTORIA!C4 -> 0
B2: Fecha de evaluación
B3: Fecha de nacimiento | C3: =HISTORIA!C6 -> 0
B4: Edad (años) | C4: =(C2-C3)/365 -> 0 | D4: =(D2-D3)/365 -> 0 | E4: =(E2-E3)/365 -> 0 | F4: =(F2-F3)/365 -> 0 | G4: =(G2-G3)/365 -> 0 | H4: =(H2-H3)/365 -> 0 | I4: =(I2-I3)/365 -> 0 | J4: =(J2-J3)/365 -> 0 | ... L4: =(L2-L3)/365 -> 0
A5: Mediciones básicas | B5: Peso (kg)
B6: Talla parado (cm)
B7: Talla sentado corregida (cm) | C7: =C8-43 -> -43 | D7: =D8-43 -> -43 | E7: =E8-43 -> -43 | F7: =F8-43 -> -43 | G7: =G8-43 -> -43 | H7: =H8-43 -> -43 | I7: =I8-43 -> -43 | J7: =J8-43 -> -43 | ... L7: =L8-43 -> -43
B8: Talla sentado (cm)
A10: Pliegues cutáneos (mm) | B10: Tríceps
B11: Subescapular
B12: Bíceps
B13: Cresta Ilíaca
B14: Supraespinal
B15: Abdominal
B16: Muslo frontal
B17: Pantorrilla
A19: Circunferencias (cm) | B19: Cabeza
B20: Cuello
B21: Brazo relajado
B22: Brazo flexionado en tensión
B23: Antebrazo máximo
B24: Muñeca
B25: Tórax (Mesoesternal)
B26: Cintura (Mínimo)
B27: Cadera (Máximo)
B28: Muslo máximo
B29: Muslo medio
B30: Pantorrilla
B31: Tobillo
A33: Diámetros óseos (mm) | B33: Biacromial
B34: Tórax transverso
B35: Tórax anteroposterior
B36: Biiliocrestídeo
B37: Humeral (Biepicondilar)
B38: Femoral (Biepicondilar)
B39: Muñeca (Biestiloidea)
A41: Circunferencias corregidas (mm) | B41: Brazo relajado corregido | C41: =C21-(3.1416*C10)/10 -> 0 | D41: =D21-(3.1416*D10)/10 -> 0 | E41: =E21-(3.1416*E10)/10 -> 0 | F41: =F21-(3.1416*F10)/10 -> 0 | G41: =G21-(3.1416*G10)/10 -> 0 | H41: =H21-(3.1416*H10)/10 -> 0 | I41: =I21-(3.1416*I10)/10 -> 0 | J41: =J21-(3.1416*J10)/10 -> 0 | ... L41: =L21-(3.1416*L10)/10 -> 0
B42: Caja torácica corregida | C42: =C25-(3.1416*C11)/10 -> 0 | D42: =D25-(3.1416*D11)/10 -> 0 | E42: =E25-(3.1416*E11)/10 -> 0 | F42: =F25-(3.1416*F11)/10 -> 0 | G42: =G25-(3.1416*G11)/10 -> 0 | H42: =H25-(3.1416*H11)/10 -> 0 | I42: =I25-(3.1416*I11)/10 -> 0 | J42: =J25-(3.1416*J11)/10 -> 0 | ... L42: =L25-(3.1416*L11)/10 -> 0
B43: Muslo máximo corregido | C43: =C28-(3.1416*C16)/10 -> 0 | D43: =D28-(3.1416*D16)/10 -> 0 | E43: =E28-(3.1416*E16)/10 -> 0 | F43: =F28-(3.1416*F16)/10 -> 0 | G43: =G28-(3.1416*G16)/10 -> 0 | H43: =H28-(3.1416*H16)/10 -> 0 | I43: =I28-(3.1416*I16)/10 -> 0 | J43: =J28-(3.1416*J16)/10 -> 0 | ... L43: =L28-(3.1416*L16)/10 -> 0
B44: Pantorrilla corregida | C44: =C30-(3.1416*C17)/10 -> 0 | D44: =D30-(3.1416*D17)/10 -> 0 | E44: =E30-(3.1416*E17)/10 -> 0 | F44: =F30-(3.1416*F17)/10 -> 0 | G44: =G30-(3.1416*G17)/10 -> 0 | H44: =H30-(3.1416*H17)/10 -> 0 | I44: =I30-(3.1416*I17)/10 -> 0 | J44: =J30-(3.1416*J17)/10 -> 0 | ... L44: =L30-(3.1416*L17)/10 -> 0
B45: Cintura corregida | C45: =C26-(3.1416*C15)/10 -> 0 | D45: =D26-(3.1416*D15)/10 -> 0 | E45: =E26-(3.1416*E15)/10 -> 0 | F45: =F26-(3.1416*F15)/10 -> 0 | G45: =G26-(3.1416*G15)/10 -> 0 | H45: =H26-(3.1416*H15)/10 -> 0 | I45: =I26-(3.1416*I15)/10 -> 0 | J45: =J26-(3.1416*J15)/10 -> 0 | ... L45: =L26-(3.1416*L15)/10 -> 0
A47: Composición corporal absoluta (5 componentes) | B47: Masa de la piel (Kg) | C47: =((68.308*C5^0.425*C6^0.725)/10000)*2.07*1.05 -> 0 | D47: =((68.308*D5^0.425*D6^0.725)/10000)*2.07*1.05 -> 0 | E47: =((68.308*E5^0.425*E6^0.725)/10000)*2.07*1.05 -> 0 | F47: =((68.308*F5^0.425*F6^0.725)/10000)*2.07*1.05 -> 0 | G47: =((68.308*G5^0.425*G6^0.725)/10000)*2.07*1.05 -> 0 | H47: =((68.308*H5^0.425*H6^0.725)/10000)*2.07*1.05 -> 0 | I47: =((68.308*I5^0.425*I6^0.725)/10000)*2.07*1.05 -> 0 | J47: =((68.308*J5^0.425*J6^0.725)/10000)*2.07*1.05 -> 0 | ... L47: =((68.308*L5^0.425*L6^0.725)/10000)*2.07*1.05 -> 0
B48: Masa ósea total (Kg) | C48: =((((C19-56)/1.44)*0.18)+1.2)/((170.8/C6)^3)+((((((C33+C36+(2*C37)+(2*C38))*(170.8/C6)-98.88)/5.33)*1.34)+6.7)/((170.8/C6)^3)) -> #DIV/0! | D48: =((((D19-56)/1.44)*0.18)+1.2)/((170.8/D6)^3)+((((((D33+D36+(2*D37)+(2*D38))*(170.8/D6)-98.88)/5.33)*1.34)+6.7)/((170.8/D6)^3)) -> #DIV/0! | E48: =((((E19-56)/1.44)*0.18)+1.2)/((170.8/E6)^3)+((((((E33+E36+(2*E37)+(2*E38))*(170.8/E6)-98.88)/5.33)*1.34)+6.7)/((170.8/E6)^3)) -> #DIV/0! | F48: =((((F19-56)/1.44)*0.18)+1.2)/((170.8/F6)^3)+((((((F33+F36+(2*F37)+(2*F38))*(170.8/F6)-98.88)/5.33)*1.34)+6.7)/((170.8/F6)^3)) -> #DIV/0! | G48: =((((G19-56)/1.44)*0.18)+1.2)/((170.8/G6)^3)+((((((G33+G36+(2*G37)+(2*G38))*(170.8/G6)-98.88)/5.33)*1.34)+6.7)/((170.8/G6)^3)) -> #DIV/0! | H48: =((((H19-56)/1.44)*0.18)+1.2)/((170.8/H6)^3)+((((((H33+H36+(2*H37)+(2*H38))*(170.8/H6)-98.88)/5.33)*1.34)+6.7)/((170.8/H6)^3)) -> #DIV/0! | I48: =((((I19-56)/1.44)*0.18)+1.2)/((170.8/I6)^3)+((((((I33+I36+(2*I37)+(2*I38))*(170.8/I6)-98.88)/5.33)*1.34)+6.7)/((170.8/I6)^3)) -> #DIV/0! | J48: =((((J19-56)/1.44)*0.18)+1.2)/((170.8/J6)^3)+((((((J33+J36+(2*J37)+(2*J38))*(170.8/J6)-98.88)/5.33)*1.34)+6.7)/((170.8/J6)^3)) -> #DIV/0! | ... L48: =((((L19-56)/1.44)*0.18)+1.2)/((170.8/L6)^3)+((((((L33+L36+(2*L37)+(2*L38))*(170.8/L6)-98.88)/5.33)*1.34)+6.7)/((170.8/L6)^3)) -> #DIV/0!
B49: Masa adiposa (Kg) | C49: =(((((C10+C11+C14+C15+C16+C17)*(170.18/C6)-116.41)/34.79)*5.85)+25.6)/((170.18/C6)^3) -> #DIV/0! | D49: =(((((D10+D11+D14+D15+D16+D17)*(170.18/D6)-116.41)/34.79)*5.85)+25.6)/((170.18/D6)^3) -> #DIV/0! | E49: =(((((E10+E11+E14+E15+E16+E17)*(170.18/E6)-116.41)/34.79)*5.85)+25.6)/((170.18/E6)^3) -> #DIV/0! | F49: =(((((F10+F11+F14+F15+F16+F17)*(170.18/F6)-116.41)/34.79)*5.85)+25.6)/((170.18/F6)^3) -> #DIV/0! | G49: =(((((G10+G11+G14+G15+G16+G17)*(170.18/G6)-116.41)/34.79)*5.85)+25.6)/((170.18/G6)^3) -> #DIV/0! | H49: =(((((H10+H11+H14+H15+H16+H17)*(170.18/H6)-116.41)/34.79)*5.85)+25.6)/((170.18/H6)^3) -> #DIV/0! | I49: =(((((I10+I11+I14+I15+I16+I17)*(170.18/I6)-116.41)/34.79)*5.85)+25.6)/((170.18/I6)^3) -> #DIV/0! | J49: =(((((J10+J11+J14+J15+J16+J17)*(170.18/J6)-116.41)/34.79)*5.85)+25.6)/((170.18/J6)^3) -> #DIV/0! | ... L49: =(((((L10+L11+L14+L15+L16+L17)*(170.18/L6)-116.41)/34.79)*5.85)+25.6)/((170.18/L6)^3) -> #DIV/0!
B50: Masa muscular (Kg) | C50: =(((((C41+C23+C43+C44+C42)*(170.18/C6))-207.21)/13.74*5.4)+24.5)/((170.18/C6)^3) -> #DIV/0! | D50: =(((((D41+D23+D43+D44+D42)*(170.18/D6))-207.21)/13.74*5.4)+24.5)/((170.18/D6)^3) -> #DIV/0! | E50: =(((((E41+E23+E43+E44+E42)*(170.18/E6))-207.21)/13.74*5.4)+24.5)/((170.18/E6)^3) -> #DIV/0! | F50: =(((((F41+F23+F43+F44+F42)*(170.18/F6))-207.21)/13.74*5.4)+24.5)/((170.18/F6)^3) -> #DIV/0! | G50: =(((((G41+G23+G43+G44+G42)*(170.18/G6))-207.21)/13.74*5.4)+24.5)/((170.18/G6)^3) -> #DIV/0! | H50: =(((((H41+H23+H43+H44+H42)*(170.18/H6))-207.21)/13.74*5.4)+24.5)/((170.18/H6)^3) -> #DIV/0! | I50: =(((((I41+I23+I43+I44+I42)*(170.18/I6))-207.21)/13.74*5.4)+24.5)/((170.18/I6)^3) -> #DIV/0! | J50: =(((((J41+J23+J43+J44+J42)*(170.18/J6))-207.21)/13.74*5.4)+24.5)/((170.18/J6)^3) -> #DIV/0! | ... L50: =(((((L41+L23+L43+L44+L42)*(170.18/L6))-207.21)/13.74*5.4)+24.5)/((170.18/L6)^3) -> #DIV/0!
B51: Masa residual (Kg) | C51: =(((((C35+C34+C45)*(89.92/C7)-109.35)/7.08)*1.24)+6.1)/((89.92/C7)^3) -> 1.427261 | D51: =(((((D35+D34+D45)*(89.92/D7)-109.35)/7.08)*1.24)+6.1)/((89.92/D7)^3) -> 1.427261 | E51: =(((((E35+E34+E45)*(89.92/E7)-109.35)/7.08)*1.24)+6.1)/((89.92/E7)^3) -> 1.427261 | F51: =(((((F35+F34+F45)*(89.92/F7)-109.35)/7.08)*1.24)+6.1)/((89.92/F7)^3) -> 1.427261 | G51: =(((((G35+G34+G45)*(89.92/G7)-109.35)/7.08)*1.24)+6.1)/((89.92/G7)^3) -> 1.427261 | H51: =(((((H35+H34+H45)*(89.92/H7)-109.35)/7.08)*1.24)+6.1)/((89.92/H7)^3) -> 1.427261 | I51: =(((((I35+I34+I45)*(89.92/I7)-109.35)/7.08)*1.24)+6.1)/((89.92/I7)^3) -> 1.427261 | J51: =(((((J35+J34+J45)*(89.92/J7)-109.35)/7.08)*1.24)+6.1)/((89.92/J7)^3) -> 1.427261 | ... L51: =(((((L35+L34+L45)*(89.92/L7)-109.35)/7.08)*1.24)+6.1)/((89.92/L7)^3) -> 1.427261
B52: Peso estructurado (Kg) | C52: =SUM(C47:C51) -> #DIV/0! | D52: =SUM(D47:D51) -> #DIV/0! | E52: =SUM(E47:E51) -> #DIV/0! | F52: =SUM(F47:F51) -> #DIV/0! | G52: =SUM(G47:G51) -> #DIV/0! | H52: =SUM(H47:H51) -> #DIV/0! | I52: =SUM(I47:I51) -> #DIV/0! | J52: =SUM(J47:J51) -> #DIV/0! | ... L52: =SUM(L47:L51) -> #DIV/0!
B53: Diferencia con peso bruto (Kg) | C53: =C52-C5 -> #DIV/0! | D53: =D52-D5 -> #DIV/0! | E53: =E52-E5 -> #DIV/0! | F53: =F52-F5 -> #DIV/0! | G53: =G52-G5 -> #DIV/0! | H53: =H52-H5 -> #DIV/0! | I53: =I52-I5 -> #DIV/0! | J53: =J52-J5 -> #DIV/0! | ... L53: =L52-L5 -> #DIV/0!
B54: Diferencia con peso bruto (%) | C54: =(100-((C52/C5)*100))*-1 -> #DIV/0! | D54: =(100-((D52/D5)*100))*-1 -> #DIV/0! | E54: =(100-((E52/E5)*100))*-1 -> #DIV/0! | F54: =(100-((F52/F5)*100))*-1 -> #DIV/0! | G54: =(100-((G52/G5)*100))*-1 -> #DIV/0! | H54: =(100-((H52/H5)*100))*-1 -> #DIV/0! | I54: =(100-((I52/I5)*100))*-1 -> #DIV/0! | J54: =(100-((J52/J5)*100))*-1 -> #DIV/0! | ... L54: =(100-((L52/L5)*100))*-1 -> #DIV/0!
A56: Composición corporal porcentual (5 componentes) | B56: Masa de la piel (%) | C56: =(C47*100)/C52 -> #DIV/0! | D56: =(D47*100)/D52 -> #DIV/0! | E56: =(E47*100)/E52 -> #DIV/0! | F56: =(F47*100)/F52 -> #DIV/0! | G56: =(G47*100)/G52 -> #DIV/0! | H56: =(H47*100)/H52 -> #DIV/0! | I56: =(I47*100)/I52 -> #DIV/0! | J56: =(J47*100)/J52 -> #DIV/0! | ... L56: =(L47*100)/L52 -> #DIV/0!
B57: Masa ósea total (%) | C57: =(C48*100)/C52 -> #DIV/0! | D57: =(D48*100)/D52 -> #DIV/0! | E57: =(E48*100)/E52 -> #DIV/0! | F57: =(F48*100)/F52 -> #DIV/0! | G57: =(G48*100)/G52 -> #DIV/0! | H57: =(H48*100)/H52 -> #DIV/0! | I57: =(I48*100)/I52 -> #DIV/0! | J57: =(J48*100)/J52 -> #DIV/0! | ... L57: =(L48*100)/L52 -> #DIV/0!
B58: Masa adiposa (%) | C58: =(C49*100)/C52 -> #DIV/0! | D58: =(D49*100)/D52 -> #DIV/0! | E58: =(E49*100)/E52 -> #DIV/0! | F58: =(F49*100)/F52 -> #DIV/0! | G58: =(G49*100)/G52 -> #DIV/0! | H58: =(H49*100)/H52 -> #DIV/0! | I58: =(I49*100)/I52 -> #DIV/0! | J58: =(J49*100)/J52 -> #DIV/0! | ... L58: =(L49*100)/L52 -> #DIV/0!
B59: Masa muscular (%) | C59: =(C50*100)/C52 -> #DIV/0! | D59: =(D50*100)/D52 -> #DIV/0! | E59: =(E50*100)/E52 -> #DIV/0! | F59: =(F50*100)/F52 -> #DIV/0! | G59: =(G50*100)/G52 -> #DIV/0! | H59: =(H50*100)/H52 -> #DIV/0! | I59: =(I50*100)/I52 -> #DIV/0! | J59: =(J50*100)/J52 -> #DIV/0! | ... L59: =(L50*100)/L52 -> #DIV/0!
B60: Masa residual (%) | C60: =(C51*100)/C52 -> #DIV/0! | D60: =(D51*100)/D52 -> #DIV/0! | E60: =(E51*100)/E52 -> #DIV/0! | F60: =(F51*100)/F52 -> #DIV/0! | G60: =(G51*100)/G52 -> #DIV/0! | H60: =(H51*100)/H52 -> #DIV/0! | I60: =(I51*100)/I52 -> #DIV/0! | J60: =(J51*100)/J52 -> #DIV/0! | ... L60: =(L51*100)/L52 -> #DIV/0!
B61: Masa total (%) | C61: =SUM(C56:C60) -> #DIV/0! | D61: =SUM(D56:D60) -> #DIV/0! | E61: =SUM(E56:E60) -> #DIV/0! | F61: =SUM(F56:F60) -> #DIV/0! | G61: =SUM(G56:G60) -> #DIV/0! | H61: =SUM(H56:H60) -> #DIV/0! | I61: =SUM(I56:I60) -> #DIV/0! | J61: =SUM(J56:J60) -> #DIV/0! | ... L61: =SUM(L56:L60) -> #DIV/0!
A63: Composición corporal absoluta corregida (5 componentes) | B63: Masa de la piel (Kg) | C63: =C47-(C53*C56)/100 -> #DIV/0! | D63: =D47-(D53*D56)/100 -> #DIV/0! | E63: =E47-(E53*E56)/100 -> #DIV/0! | F63: =F47-(F53*F56)/100 -> #DIV/0! | G63: =G47-(G53*G56)/100 -> #DIV/0! | H63: =H47-(H53*H56)/100 -> #DIV/0! | I63: =I47-(I53*I56)/100 -> #DIV/0! | J63: =J47-(J53*J56)/100 -> #DIV/0! | ... L63: =L47-(L53*L56)/100 -> #DIV/0!
B64: Masa ósea total (Kg) | C64: =C48-(C53*C57)/100 -> #DIV/0! | D64: =D48-(D53*D57)/100 -> #DIV/0! | E64: =E48-(E53*E57)/100 -> #DIV/0! | F64: =F48-(F53*F57)/100 -> #DIV/0! | G64: =G48-(G53*G57)/100 -> #DIV/0! | H64: =H48-(H53*H57)/100 -> #DIV/0! | I64: =I48-(I53*I57)/100 -> #DIV/0! | J64: =J48-(J53*J57)/100 -> #DIV/0! | ... L64: =L48-(L53*L57)/100 -> #DIV/0!
B65: Masa adiposa (Kg) | C65: =C49-(C53*C58)/100 -> #DIV/0! | D65: =D49-(D53*D58)/100 -> #DIV/0! | E65: =E49-(E53*E58)/100 -> #DIV/0! | F65: =F49-(F53*F58)/100 -> #DIV/0! | G65: =G49-(G53*G58)/100 -> #DIV/0! | H65: =H49-(H53*H58)/100 -> #DIV/0! | I65: =I49-(I53*I58)/100 -> #DIV/0! | J65: =J49-(J53*J58)/100 -> #DIV/0! | ... L65: =L49-(L53*L58)/100 -> #DIV/0!
B66: Masa muscular (Kg) | C66: =C50-(C53*C59)/100 -> #DIV/0! | D66: =D50-(D53*D59)/100 -> #DIV/0! | E66: =E50-(E53*E59)/100 -> #DIV/0! | F66: =F50-(F53*F59)/100 -> #DIV/0! | G66: =G50-(G53*G59)/100 -> #DIV/0! | H66: =H50-(H53*H59)/100 -> #DIV/0! | I66: =I50-(I53*I59)/100 -> #DIV/0! | J66: =J50-(J53*J59)/100 -> #DIV/0! | ... L66: =L50-(L53*L59)/100 -> #DIV/0!
B67: Masa residual (Kg) | C67: =C51-(C53*C60)/100 -> #DIV/0! | D67: =D51-(D53*D60)/100 -> #DIV/0! | E67: =E51-(E53*E60)/100 -> #DIV/0! | F67: =F51-(F53*F60)/100 -> #DIV/0! | G67: =G51-(G53*G60)/100 -> #DIV/0! | H67: =H51-(H53*H60)/100 -> #DIV/0! | I67: =I51-(I53*I60)/100 -> #DIV/0! | J67: =J51-(J53*J60)/100 -> #DIV/0! | ... L67: =L51-(L53*L60)/100 -> #DIV/0!
B68: Masa total (Kg) | C68: =SUM(C63:C67) -> #DIV/0! | D68: =SUM(D63:D67) -> #DIV/0! | E68: =SUM(E63:E67) -> #DIV/0! | F68: =SUM(F63:F67) -> #DIV/0! | G68: =SUM(G63:G67) -> #DIV/0! | H68: =SUM(H63:H67) -> #DIV/0! | I68: =SUM(I63:I67) -> #DIV/0! | J68: =SUM(J63:J67) -> #DIV/0! | ... L68: =SUM(L63:L67) -> #DIV/0!
B70: Sumatoria de 6 pliegues (mm) | C70: =C10+C11+C14+C15+C16+C17 -> 0 | D70: =D10+D11+D14+D15+D16+D17 -> 0 | E70: =E10+E11+E14+E15+E16+E17 -> 0 | F70: =F10+F11+F14+F15+F16+F17 -> 0 | G70: =G10+G11+G14+G15+G16+G17 -> 0 | H70: =H10+H11+H14+H15+H16+H17 -> 0 | I70: =I10+I11+I14+I15+I16+I17 -> 0 | J70: =J10+J11+J14+J15+J16+J17 -> 0 | ... L70: =L10+L11+L14+L15+L16+L17 -> 0
B71: Cociente muscular/óseo | C71: =C50/C48 -> #DIV/0! | D71: =D50/D48 -> #DIV/0! | E71: =E50/E48 -> #DIV/0! | F71: =F50/F48 -> #DIV/0! | G71: =G50/G48 -> #DIV/0! | H71: =H50/H48 -> #DIV/0! | I71: =I50/I48 -> #DIV/0! | J71: =J50/J48 -> #DIV/0! | ... L71: =L50/L48 -> #DIV/0!
A72: Composición corporal (2 componentes) | B72: IMC (Kg/m2) | C72: =(C5)/((C6/100)^2) -> #DIV/0! | D72: =(D5)/((D6/100)^2) -> #DIV/0! | E72: =(E5)/((E6/100)^2) -> #DIV/0! | F72: =(F5)/((F6/100)^2) -> #DIV/0! | G72: =(G5)/((G6/100)^2) -> #DIV/0! | H72: =(H5)/((H6/100)^2) -> #DIV/0! | I72: =(I5)/((I6/100)^2) -> #DIV/0! | J72: =(J5)/((J6/100)^2) -> #DIV/0! | ... L72: =(L5)/((L6/100)^2) -> #DIV/0!
B73: índice Cintura/Cadera | C73: =C26/C27 -> #DIV/0! | D73: =D26/D27 -> #DIV/0! | E73: =E26/E27 -> #DIV/0! | F73: =F26/F27 -> #DIV/0! | G73: =G26/G27 -> #DIV/0! | H73: =H26/H27 -> #DIV/0! | I73: =I26/I27 -> #DIV/0! | J73: =J26/J27 -> #DIV/0! | ... L73: =L26/L27 -> #DIV/0!
B74: Contextura | C74: =(C37/(C6/100))*10 -> #DIV/0! | D74: =(D37/(D6/100))*10 -> #DIV/0! | E74: =(E37/(E6/100))*10 -> #DIV/0! | F74: =(F37/(F6/100))*10 -> #DIV/0! | G74: =(G37/(G6/100))*10 -> #DIV/0! | H74: =(H37/(H6/100))*10 -> #DIV/0! | I74: =(I37/(I6/100))*10 -> #DIV/0! | J74: =(J37/(J6/100))*10 -> #DIV/0! | ... L74: =(L37/(L6/100))*10 -> #DIV/0!
B75: Área grasa del brazo (cm2) | C75: =(C10/10)*C21/2-((C10/10)*(C10/10)*3.1416/4) -> 0 | D75: =(D10/10)*D21/2-((D10/10)*(D10/10)*3.1416/4) -> 0 | E75: =(E10/10)*E21/2-((E10/10)*(E10/10)*3.1416/4) -> 0 | F75: =(F10/10)*F21/2-((F10/10)*(F10/10)*3.1416/4) -> 0 | G75: =(G10/10)*G21/2-((G10/10)*(G10/10)*3.1416/4) -> 0 | H75: =(H10/10)*H21/2-((H10/10)*(H10/10)*3.1416/4) -> 0 | I75: =(I10/10)*I21/2-((I10/10)*(I10/10)*3.1416/4) -> 0 | J75: =(J10/10)*J21/2-((J10/10)*(J10/10)*3.1416/4) -> 0 | ... L75: =(L10/10)*L21/2-((L10/10)*(L10/10)*3.1416/4) -> 0
B76: Área magra del brazo (cm2) | C76: =((C21-(C10/10)*3.1416)*(C21-(C10/10)*3.1416)/12.5664-10) -> -10 | D76: =((D21-(D10/10)*3.1416)*(D21-(D10/10)*3.1416)/12.5664-10) -> -10 | E76: =((E21-(E10/10)*3.1416)*(E21-(E10/10)*3.1416)/12.5664-10) -> -10 | F76: =((F21-(F10/10)*3.1416)*(F21-(F10/10)*3.1416)/12.5664-10) -> -10 | G76: =((G21-(G10/10)*3.1416)*(G21-(G10/10)*3.1416)/12.5664-10) -> -10 | H76: =((H21-(H10/10)*3.1416)*(H21-(H10/10)*3.1416)/12.5664-10) -> -10 | I76: =((I21-(I10/10)*3.1416)*(I21-(I10/10)*3.1416)/12.5664-10) -> -10 | J76: =((J21-(J10/10)*3.1416)*(J21-(J10/10)*3.1416)/12.5664-10) -> -10 | ... L76: =((L21-(L10/10)*3.1416)*(L21-(L10/10)*3.1416)/12.5664-10) -> -10
B77: Sumatoria de 4 pliegues (mm) | C77: =C10+C11+C12+C13 -> 0 | D77: =D10+D11+D12+D13 -> 0 | E77: =E10+E11+E12+E13 -> 0 | F77: =F10+F11+F12+F13 -> 0 | G77: =G10+G11+G12+G13 -> 0 | H77: =H10+H11+H12+H13 -> 0 | I77: =I10+I11+I12+I13 -> 0 | J77: =J10+J11+J12+J13 -> 0 | ... L77: =L10+L11+L12+L13 -> 0
B78: Sumatoria de 8 pliegues (mm) | C78: =SUM(C10:C17) -> 0 | D78: =SUM(D10:D17) -> 0 | E78: =SUM(E10:E17) -> 0 | F78: =SUM(F10:F17) -> 0 | G78: =SUM(G10:G17) -> 0 | H78: =SUM(H10:H17) -> 0 | I78: =SUM(I10:I17) -> 0 | J78: =SUM(J10:J17) -> 0 | ... L78: =SUM(L10:L17) -> 0
B79: % Grasa (Durnin y W., 1974) | C79: =(((0.2467)*(C12+C10+C11+C13))+((0.12*C26)))-2.18 -> -2.18 | D79: =(((0.2467)*(D12+D10+D11+D13))+((0.12*D26)))-2.18 -> -2.18 | E79: =(((0.2467)*(E12+E10+E11+E13))+((0.12*E26)))-2.18 -> -2.18 | F79: =(((0.2467)*(F12+F10+F11+F13))+((0.12*F26)))-2.18 -> -2.18 | G79: =(((0.2467)*(G12+G10+G11+G13))+((0.12*G26)))-2.18 -> -2.18 | H79: =(((0.2467)*(H12+H10+H11+H13))+((0.12*H26)))-2.18 -> -2.18 | I79: =(((0.2467)*(I12+I10+I11+I13))+((0.12*I26)))-2.18 -> -2.18 | J79: =(((0.2467)*(J12+J10+J11+J13))+((0.12*J26)))-2.18 -> -2.18 | ... L79: =(((0.2467)*(L12+L10+L11+L13))+((0.12*L26)))-2.18 -> -2.18
B80: % Grasa (Carter, 1986) Mujeres | C80: =(3.5803)+(0.1548*(C10+C11+C15+C14+C16+C17)) -> 3.5803 | D80: =(3.5803)+(0.1548*(D10+D11+D15+D14+D16+D17)) -> 3.5803 | E80: =(3.5803)+(0.1548*(E10+E11+E15+E14+E16+E17)) -> 3.5803 | F80: =(3.5803)+(0.1548*(F10+F11+F15+F14+F16+F17)) -> 3.5803 | G80: =(3.5803)+(0.1548*(G10+G11+G15+G14+G16+G17)) -> 3.5803 | H80: =(3.5803)+(0.1548*(H10+H11+H15+H14+H16+H17)) -> 3.5803 | I80: =(3.5803)+(0.1548*(I10+I11+I15+I14+I16+I17)) -> 3.5803 | J80: =(3.5803)+(0.1548*(J10+J11+J15+J14+J16+J17)) -> 3.5803 | ... L80: =(3.5803)+(0.1548*(L10+L11+L15+L14+L16+L17)) -> 3.5803
B81: Porcentaje a utilizar | C81: =C80 -> 3.5803 | D81: =D80 -> 3.5803 | E81: =E80 -> 3.5803 | F81: =F80 -> 3.5803 | G81: =G80 -> 3.5803 | H81: =H80 -> 3.5803 | I81: =I80 -> 3.5803 | J81: =J80 -> 3.5803 | ... L81: =L80 -> 3.5803
B82: Masa magra (Kg) | C82: =((100-C81)*C5)/100 -> 0 | D82: =((100-D81)*D5)/100 -> 0 | E82: =((100-E81)*E5)/100 -> 0 | F82: =((100-F81)*F5)/100 -> 0 | G82: =((100-G81)*G5)/100 -> 0 | H82: =((100-H81)*H5)/100 -> 0 | I82: =((100-I81)*I5)/100 -> 0 | J82: =((100-J81)*J5)/100 -> 0 | ... L82: =((100-L81)*L5)/100 -> 0
B83: Masa grasa (Kg) | C83: =C5-C82 -> 0 | D83: =D5-D82 -> 0 | E83: =E5-E82 -> 0 | F83: =F5-F82 -> 0 | G83: =G5-G82 -> 0 | H83: =H5-H82 -> 0 | I83: =I5-I82 -> 0 | J83: =J5-J82 -> 0 | ... L83: =L5-L82 -> 0
B84: % Grasa objetivo mínimo | C84: 6 | D84: 6 | E84: 6 | F84: 6 | G84: 6 | H84: 6 | I84: 6 | J84: 6 | K84: 6 | L84: 6
B85: % Grasa objetivo máximo | C85: 8 | D85: 8 | E85: 8 | F85: 8 | G85: 8 | H85: 8 | I85: 8 | J85: 8 | K85: 8 | L85: 8
B86: Peso objetivo mínimo (Kg) | C86: =(C82)/(1-C84/100) -> 0 | D86: =(D82)/(1-D84/100) -> 0 | E86: =(E82)/(1-E84/100) -> 0 | F86: =(F82)/(1-F84/100) -> 0 | G86: =(G82)/(1-G84/100) -> 0 | H86: =(H82)/(1-H84/100) -> 0 | I86: =(I82)/(1-I84/100) -> 0 | J86: =(J82)/(1-J84/100) -> 0 | ... L86: =(L82)/(1-L84/100) -> 0
B87: Peso objetivo máximo (Kg) | C87: =(C82)/(1-C85/100) -> 0 | D87: =(D82)/(1-D85/100) -> 0 | E87: =(E82)/(1-E85/100) -> 0 | F87: =(F82)/(1-F85/100) -> 0 | G87: =(G82)/(1-G85/100) -> 0 | H87: =(H82)/(1-H85/100) -> 0 | I87: =(I82)/(1-I85/100) -> 0 | J87: =(J82)/(1-J85/100) -> 0 | ... L87: =(L82)/(1-L85/100) -> 0
B88: Pérdida de grasa objetivo (Kg) | C88: =C86-C5 -> 0 | D88: =D86-D5 -> 0 | E88: =E86-E5 -> 0 | F88: =F86-F5 -> 0 | G88: =G86-G5 -> 0 | H88: =H86-H5 -> 0 | I88: =I86-I5 -> 0 | J88: =J86-J5 -> 0 | ... L88: =L86-L5 -> 0
B89: Índice de sustancia activa (AKS) | C89: =(C82*100000/(C6^3)) -> #DIV/0! | D89: =(D82*100000/(D6^3)) -> #DIV/0! | E89: =(E82*100000/(E6^3)) -> #DIV/0! | F89: =(F82*100000/(F6^3)) -> #DIV/0! | G89: =(G82*100000/(G6^3)) -> #DIV/0! | H89: =(H82*100000/(H6^3)) -> #DIV/0! | I89: =(I82*100000/(I6^3)) -> #DIV/0! | J89: =(J82*100000/(J6^3)) -> #DIV/0! | ... L89: =(L82*100000/(L6^3)) -> #DIV/0!
A90: DATOS BÁSICOS | B90: Nombre y apellido | C90: =C1 -> 0 | D90: =D1 -> 0 | E90: =E1 -> 0 | F90: =F1 -> 0 | G90: =G1 -> 0 | H90: =H1 -> 0 | I90: =I1 -> 0 | J90: =J1 -> 0 | ... L90: =L1 -> 0
B91: Estatura (cm) | C91: =C6 -> 0 | D91: =D6 -> 0 | E91: =E6 -> 0 | F91: =F6 -> 0 | G91: =G6 -> 0 | H91: =H6 -> 0 | I91: =I6 -> 0 | J91: =J6 -> 0 | ... L91: =L6 -> 0
B92: Peso (Kg) | C92: =C5 -> 0 | D92: =D5 -> 0 | E92: =E5 -> 0 | F92: =F5 -> 0 | G92: =G5 -> 0 | H92: =H5 -> 0 | I92: =I5 -> 0 | J92: =J5 -> 0 | ... L92: =L5 -> 0
B93: Altura/peso^1/3: | C93: =C91/(C92^0.3333) -> #DIV/0! | D93: =D91/(D92^0.3333) -> #DIV/0! | E93: =E91/(E92^0.3333) -> #DIV/0! | F93: =F91/(F92^0.3333) -> #DIV/0! | G93: =G91/(G92^0.3333) -> #DIV/0! | H93: =H91/(H92^0.3333) -> #DIV/0! | I93: =I91/(I92^0.3333) -> #DIV/0! | J93: =J91/(J92^0.3333) -> #DIV/0! | ... L93: =L91/(L92^0.3333) -> #DIV/0!
A94: PLIEGUES (mm) | B94: Tríceps | C94: =C10 -> 0 | D94: =D10 -> 0 | E94: =E10 -> 0 | F94: =F10 -> 0 | G94: =G10 -> 0 | H94: =H10 -> 0 | I94: =I10 -> 0 | J94: =J10 -> 0 | ... L94: =L10 -> 0
B95: Subescapular | C95: =C11 -> 0 | D95: =D11 -> 0 | E95: =E11 -> 0 | F95: =F11 -> 0 | G95: =G11 -> 0 | H95: =H11 -> 0 | I95: =I11 -> 0 | J95: =J11 -> 0 | ... L95: =L11 -> 0
B96: Supraespinal | C96: =C17 -> 0 | D96: =D17 -> 0 | E96: =E17 -> 0 | F96: =F17 -> 0 | G96: =G17 -> 0 | H96: =H17 -> 0 | I96: =I17 -> 0 | J96: =J17 -> 0 | ... L96: =L17 -> 0
B97: Pantorrilla media | C97: =C17 -> 0 | D97: =D17 -> 0 | E97: =E17 -> 0 | F97: =F17 -> 0 | G97: =G17 -> 0 | H97: =H17 -> 0 | I97: =I17 -> 0 | J97: =J17 -> 0 | ... L97: =L17 -> 0
A98: CIRCUNFERENCIAS (cm) | B98: Bíceps flexionado | C98: =C22 -> 0 | D98: =D22 -> 0 | E98: =E22 -> 0 | F98: =F22 -> 0 | G98: =G22 -> 0 | H98: =H22 -> 0 | I98: =I22 -> 0 | J98: =J22 -> 0 | ... L98: =L22 -> 0
B99: Pantorrilla máxima | C99: =C30 -> 0 | D99: =D30 -> 0 | E99: =E30 -> 0 | F99: =F30 -> 0 | G99: =G30 -> 0 | H99: =H30 -> 0 | I99: =I30 -> 0 | J99: =J30 -> 0 | ... L99: =L30 -> 0
A100: DIÁMETROS (mm) | B100: HUMERO-biepicondylar | C100: =C37 -> 0 | D100: =D37 -> 0 | E100: =E37 -> 0 | F100: =F37 -> 0 | G100: =G37 -> 0 | H100: =H37 -> 0 | I100: =I37 -> 0 | J100: =J37 -> 0 | ... L100: =L37 -> 0
B101: FEMUR-biepicondylar | C101: =C38 -> 0 | D101: =D38 -> 0 | E101: =E38 -> 0 | F101: =F38 -> 0 | G101: =G38 -> 0 | H101: =H38 -> 0 | I101: =I38 -> 0 | J101: =J38 -> 0 | ... L101: =L38 -> 0
A102: SUMATORIAS | B102: Sum 3 skinfolds | C102: =SUM(C94:C96) -> 0 | D102: =SUM(D94:D96) -> 0 | E102: =SUM(E94:E96) -> 0 | F102: =SUM(F94:F96) -> 0 | G102: =SUM(G94:G96) -> 0 | H102: =SUM(H94:H96) -> 0 | I102: =SUM(I94:I96) -> 0 | J102: =SUM(J94:J96) -> 0 | ... L102: =SUM(L94:L96) -> 0
B103: Sum 3 (ht-corrected) | C103: =(170.18/C91)*C102 -> #DIV/0! | D103: =(170.18/D91)*D102 -> #DIV/0! | E103: =(170.18/E91)*E102 -> #DIV/0! | F103: =(170.18/F91)*F102 -> #DIV/0! | G103: =(170.18/G91)*G102 -> #DIV/0! | H103: =(170.18/H91)*H102 -> #DIV/0! | I103: =(170.18/I91)*I102 -> #DIV/0! | J103: =(170.18/J91)*J102 -> #DIV/0! | ... L103: =(170.18/L91)*L102 -> #DIV/0!
B104: Sum 3 squared | C104: =(C103^2) -> #DIV/0! | D104: =(D103^2) -> #DIV/0! | E104: =(E103^2) -> #DIV/0! | F104: =(F103^2) -> #DIV/0! | G104: =(G103^2) -> #DIV/0! | H104: =(H103^2) -> #DIV/0! | I104: =(I103^2) -> #DIV/0! | J104: =(J103^2) -> #DIV/0! | ... L104: =(L103^2) -> #DIV/0!
B105: Sum 3 cubed | C105: =(C103^3) -> #DIV/0! | D105: =(D103^3) -> #DIV/0! | E105: =(E103^3) -> #DIV/0! | F105: =(F103^3) -> #DIV/0! | G105: =(G103^3) -> #DIV/0! | H105: =(H103^3) -> #DIV/0! | I105: =(I103^3) -> #DIV/0! | J105: =(J103^3) -> #DIV/0! | ... L105: =(L103^3) -> #DIV/0!
A106: OTROS | B106: Corrected Biceps G | C106: =(C98-(C94/10)) -> 0 | D106: =(D98-(D94/10)) -> 0 | E106: =(E98-(E94/10)) -> 0 | F106: =(F98-(F94/10)) -> 0 | G106: =(G98-(G94/10)) -> 0 | H106: =(H98-(H94/10)) -> 0 | I106: =(I98-(I94/10)) -> 0 | J106: =(J98-(J94/10)) -> 0 | ... L106: =(L98-(L94/10)) -> 0
B107: Corrected Calf G | C107: =(C99-(C97/10)) -> 0 | D107: =(D99-(D97/10)) -> 0 | E107: =(E99-(E97/10)) -> 0 | F107: =(F99-(F97/10)) -> 0 | G107: =(G99-(G97/10)) -> 0 | H107: =(H99-(H97/10)) -> 0 | I107: =(I99-(I97/10)) -> 0 | J107: =(J99-(J97/10)) -> 0 | ... L107: =(L99-(L97/10)) -> 0
A108: VALORACIÓN DEL SOMATOTIPO (decimal) | B108: ENDOMORFIA | C108: =(-0.7182+(0.1451*C103)-(0.00068*C104)+(0.0000014*C105)) -> #DIV/0! | D108: =(-0.7182+(0.1451*D103)-(0.00068*D104)+(0.0000014*D105)) -> #DIV/0! | E108: =(-0.7182+(0.1451*E103)-(0.00068*E104)+(0.0000014*E105)) -> #DIV/0! | F108: =(-0.7182+(0.1451*F103)-(0.00068*F104)+(0.0000014*F105)) -> #DIV/0! | G108: =(-0.7182+(0.1451*G103)-(0.00068*G104)+(0.0000014*G105)) -> #DIV/0! | H108: =(-0.7182+(0.1451*H103)-(0.00068*H104)+(0.0000014*H105)) -> #DIV/0! | I108: =(-0.7182+(0.1451*I103)-(0.00068*I104)+(0.0000014*I105)) -> #DIV/0! | J108: =(-0.7182+(0.1451*J103)-(0.00068*J104)+(0.0000014*J105)) -> #DIV/0! | ... L108: =(-0.7182+(0.1451*L103)-(0.00068*L104)+(0.0000014*L105)) -> #DIV/0!
...

Sheet REFERENTES
A1: PESO (kg) | K1: ALTURA TIBIAL LATERAL (cm)
A2: Edad | B2: n | C2: Media | D2: Mediana | E2: Desv. Est. | F2: Máximo | G2: Mínimo | H2: IC95%sup | I2: IC95%inf | K2: Edad | L2: n | M2: Media | N2: Mediana | O2: Desv. Est. | P2: Máximo | Q2: Mínimo | R2: IC95%sup | S2: IC95%inf
A3: 7 | B3: 1 | C3: 27 | D3: 27 | E3: , | F3: 27 | G3: 27 | K3: 7 | L3: 1 | M3: 32 | N3: 32 | O3: , | P3: 32 | Q3: 32
A4: 8 | B4: 10 | C4: 28.46 | D4: 28.25 | E4: 5.968 | F4: 39.5 | G4: 19.9 | H4: =C4+(1.96*E4)/(B4)^0.5 -> 32.159005 | I4: =C4-(1.96*E4)/(B4)^0.5 -> 24.760995 | K4: 8 | L4: 10 | M4: 33.89 | N4: 34.1 | O4: 2.792 | P4: 37.7 | Q4: 28.6 | R4: =M4+(1.96*O4)/(L4)^0.5 -> 35.6205 | S4: =M4-(1.96*O4)/(L4)^0.5 -> 32.1595
A5: 9 | B5: 17 | C5: 33.659 | D5: 33.8 | E5: 6.02 | F5: 45.2 | G5: 25.2 | H5: =C5+(1.96*E5)/(B5)^0.5 -> 36.520726 | I5: =C5-(1.96*E5)/(B5)^0.5 -> 30.797274 | K5: 9 | L5: 17 | M5: 36.688 | N5: 36.5 | O5: 2.348 | P5: 41 | Q5: 32.9 | R5: =M5+(1.96*O5)/(L5)^0.5 -> 37.804168 | S5: =M5-(1.96*O5)/(L5)^0.5 -> 35.571832
A6: 10 | B6: 22 | C6: 38.25 | D6: 36.75 | E6: 10.395 | F6: 76.7 | G6: 25 | H6: =C6+(1.96*E6)/(B6)^0.5 -> 42.593794 | I6: =C6-(1.96*E6)/(B6)^0.5 -> 33.906206 | K6: 10 | L6: 22 | M6: 38.627 | N6: 38.75 | O6: 2.458 | P6: 45.6 | Q6: 34.3 | R6: =M6+(1.96*O6)/(L6)^0.5 -> 39.654133 | S6: =M6-(1.96*O6)/(L6)^0.5 -> 37.599867
A7: 11 | B7: 21 | C7: 42.671 | D7: 38.9 | E7: 9.677 | F7: 58 | G7: 25.2 | H7: =C7+(1.96*E7)/(B7)^0.5 -> 46.809921 | I7: =C7-(1.96*E7)/(B7)^0.5 -> 38.532079 | K7: 11 | L7: 20 | M7: 39.36 | N7: 39.55 | O7: 1.876 | P7: 41.9 | Q7: 35 | R7: =M7+(1.96*O7)/(L7)^0.5 -> 40.182193 | S7: =M7-(1.96*O7)/(L7)^0.5 -> 38.537807
A8: 12 | B8: 39 | C8: 44.287 | D8: 44.4 | E8: 8.681 | F8: 73.6 | G8: 28.5 | H8: =C8+(1.96*E8)/(B8)^0.5 -> 47.011542 | I8: =C8-(1.96*E8)/(B8)^0.5 -> 41.562458 | K8: 12 | L8: 39 | M8: 40.679 | N8: 41 | O8: 2.412 | P8: 45.6 | Q8: 36.2 | R8: =M8+(1.96*O8)/(L8)^0.5 -> 41.436009 | S8: =M8-(1.96*O8)/(L8)^0.5 -> 39.921991
A9: 13 | B9: 41 | C9: 49.117 | D9: 49.6 | E9: 9.841 | F9: 78.9 | G9: 32.9 | H9: =C9+(1.96*E9)/(B9)^0.5 -> 52.129336 | I9: =C9-(1.96*E9)/(B9)^0.5 -> 46.104664 | K9: 13 | L9: 41 | M9: 40.971 | N9: 41 | O9: 2.288 | P9: 45.5 | Q9: 36.1 | R9: =M9+(1.96*O9)/(L9)^0.5 -> 41.671358 | S9: =M9-(1.96*O9)/(L9)^0.5 -> 40.270642
A10: 14 | B10: 45 | C10: 52.024 | D10: 50.7 | E10: 8.186 | F10: 72.8 | G10: 39.1 | H10: =C10+(1.96*E10)/(B10)^0.5 -> 54.415782 | I10: =C10-(1.96*E10)/(B10)^0.5 -> 49.632218 | K10: 14 | L10: 45 | M10: 41.44 | N10: 41.4 | O10: 2.091 | P10: 46.2 | Q10: 37 | R10: =M10+(1.96*O10)/(L10)^0.5 -> 42.050947 | S10: =M10-(1.96*O10)/(L10)^0.5 -> 40.829053
A11: 15 | B11: 12 | C11: 52.875 | D11: 52.15 | E11: 6.157 | F11: 65.8 | G11: 41.3 | H11: =C11+(1.96*E11)/(B11)^0.5 -> 56.358651 | I11: =C11-(1.96*E11)/(B11)^0.5 -> 49.391349 | K11: 15 | L11: 12 | M11: 41.408 | N11: 41.85 | O11: 1.75 | P11: 43.9 | Q11: 37.2 | R11: =M11+(1.96*O11)/(L11)^0.5 -> 42.398156 | S11: =M11-(1.96*O11)/(L11)^0.5 -> 40.417844
A12: 16 | B12: 13 | C12: 51.877 | D12: 50.3 | E12: 6.162 | F12: 64.3 | G12: 45.2 | H12: =C12+(1.96*E12)/(B12)^0.5 -> 55.226701 | I12: =C12-(1.96*E12)/(B12)^0.5 -> 48.527299 | K12: 16 | L12: 12 | M12: 41.008 | N12: 41 | O12: 2.271 | P12: 45.1 | Q12: 37.6 | R12: =M12+(1.96*O12)/(L12)^0.5 -> 42.292939 | S12: =M12-(1.96*O12)/(L12)^0.5 -> 39.723061
A13: 17 | B13: 4 | C13: 48.15 | D13: 49 | E13: 2.428 | F13: 49.9 | G13: 44.7 | H13: =C13+(1.96*E13)/(B13)^0.5 -> 50.52944 | I13: =C13-(1.96*E13)/(B13)^0.5 -> 45.77056 | K13: 17 | L13: 4 | M13: 39.7 | N13: 40.6 | O13: 4.017 | P13: 43.5 | Q13: 34.1 | R13: =M13+(1.96*O13)/(L13)^0.5 -> 43.63666 | S13: =M13-(1.96*O13)/(L13)^0.5 -> 35.76334
A14: 18 | B14: 2 | C14: 54 | D14: 54 | E14: 7.92 | F14: 59.6 | G14: 48.4 | H14: =C14+(1.96*E14)/(B14)^0.5 -> 64.97656 | I14: =C14-(1.96*E14)/(B14)^0.5 -> 43.02344 | K14: 18 | L14: 2 | M14: 46.05 | N14: 46.05 | O14: 1.344 | P14: 47 | Q14: 45.1 | R14: =M14+(1.96*O14)/(L14)^0.5 -> 47.912689 | S14: =M14-(1.96*O14)/(L14)^0.5 -> 44.187311
A16: TALLA (cm)
A17: Edad | B17: n | C17: Media | D17: Mediana | E17: Desv. Est. | F17: Máximo | G17: Mínimo | H17: IC95%sup | I17: IC95%inf | K17: LONGITUD TIBIAL MEDIAL-MALEOLAR MEDIAL (cm)
A18: 7 | B18: 1 | C18: 121.5 | D18: 121.5 | E18: , | F18: 121.5 | G18: 121.5 | K18: Edad | L18: n | M18: Media | N18: Mediana | O18: Desv. Est. | P18: Máximo | Q18: Mínimo | R18: IC95%sup | S18: IC95%inf
A19: 8 | B19: 10 | C19: 128.24 | D19: 129 | E19: 7.038 | F19: 137.4 | G19: 115.4 | H19: =C19+(1.96*E19)/(B19)^0.5 -> 132.6022 | I19: =C19-(1.96*E19)/(B19)^0.5 -> 123.8778 | K19: 7 | L19: 1 | M19: 26.3 | N19: 26.3 | O19: , | P19: 26.3 | Q19: 26.3
A20: 9 | B20: 17 | C20: 136.718 | D20: 135 | E20: 6.652 | F20: 151.6 | G20: 127.9 | H20: =C20+(1.96*E20)/(B20)^0.5 -> 139.88016 | I20: =C20-(1.96*E20)/(B20)^0.5 -> 133.55584 | K20: 8 | L20: 10 | M20: 29 | N20: 28.95 | O20: 2.108 | P20: 31.5 | Q20: 24.2 | R20: =M20+(1.96*O20)/(L20)^0.5 -> 30.306552 | S20: =M20-(1.96*O20)/(L20)^0.5 -> 27.693448
A21: 10 | B21: 22 | C21: 141.564 | D21: 142.2 | E21: 5.929 | F21: 152.4 | G21: 129 | H21: =C21+(1.96*E21)/(B21)^0.5 -> 144.04157 | I21: =C21-(1.96*E21)/(B21)^0.5 -> 139.08643 | K21: 9 | L21: 17 | M21: 31.059 | N21: 31 | O21: 1.958 | P21: 34.5 | Q21: 28.4 | R21: =M21+(1.96*O21)/(L21)^0.5 -> 31.989774 | S21: =M21-(1.96*O21)/(L21)^0.5 -> 30.128226
A22: 11 | B22: 21 | C22: 147.243 | D22: 146.8 | E22: 8.496 | F22: 159 | G22: 129 | H22: =C22+(1.96*E22)/(B22)^0.5 -> 150.8768 | I22: =C22-(1.96*E22)/(B22)^0.5 -> 143.6092 | K22: 10 | L22: 22 | M22: 32.695 | N22: 33.1 | O22: 2.067 | P22: 37.6 | Q22: 28.7 | R22: =M22+(1.96*O22)/(L22)^0.5 -> 33.558744 | S22: =M22-(1.96*O22)/(L22)^0.5 -> 31.831256
A23: 12 | B23: 39 | C23: 151.077 | D23: 150.1 | E23: 7.439 | F23: 168.8 | G23: 134.4 | H23: =C23+(1.96*E23)/(B23)^0.5 -> 153.41174 | I23: =C23-(1.96*E23)/(B23)^0.5 -> 148.74226 | K23: 11 | L23: 20 | M23: 33.525 | N23: 33.3 | O23: 1.908 | P23: 36.2 | Q23: 29 | R23: =M23+(1.96*O23)/(L23)^0.5 -> 34.361218 | S23: =M23-(1.96*O23)/(L23)^0.5 -> 32.688782
A24: 13 | B24: 41 | C24: 154.498 | D24: 156.1 | E24: 6.409 | F24: 163.7 | G24: 139.4 | H24: =C24+(1.96*E24)/(B24)^0.5 -> 156.4598 | I24: =C24-(1.96*E24)/(B24)^0.5 -> 152.5362 | K24: 12 | L24: 38 | M24: 34.642 | N24: 35 | O24: 2.397 | P24: 39.6 | Q24: 30.5 | R24: =M24+(1.96*O24)/(L24)^0.5 -> 35.404136 | S24: =M24-(1.96*O24)/(L24)^0.5 -> 33.879864
A25: 14 | B25: 45 | C25: 157.633 | D25: 157.2 | E25: 5.34 | F25: 172.1 | G25: 147.4 | H25: =C25+(1.96*E25)/(B25)^0.5 -> 159.19324 | I25: =C25-(1.96*E25)/(B25)^0.5 -> 156.07276 | K25: 13 | L25: 41 | M25: 35.093 | N25: 35.1 | O25: 2.065 | P25: 39.8 | Q25: 30.4 | R25: =M25+(1.96*O25)/(L25)^0.5 -> 35.725098 | S25: =M25-(1.96*O25)/(L25)^0.5 -> 34.460902
A26: 15 | B26: 12 | C26: 158.917 | D26: 158.75 | E26: 6.175 | F26: 169.4 | G26: 150.4 | H26: =C26+(1.96*E26)/(B26)^0.5 -> 162.41084 | I26: =C26-(1.96*E26)/(B26)^0.5 -> 155.42316 | K26: 14 | L26: 45 | M26: 35.707 | N26: 36 | O26: 2.132 | P26: 41.1 | Q26: 31.1 | R26: =M26+(1.96*O26)/(L26)^0.5 -> 36.329927 | S26: =M26-(1.96*O26)/(L26)^0.5 -> 35.084073
A27: 16 | B27: 13 | C27: 157.092 | D27: 157 | E27: 5.731 | F27: 168.2 | G27: 145.3 | H27: =C27+(1.96*E27)/(B27)^0.5 -> 160.20741 | I27: =C27-(1.96*E27)/(B27)^0.5 -> 153.97659 | K27: 15 | L27: 12 | M27: 35.608 | N27: 35.7 | O27: 1.563 | P27: 37.8 | Q27: 33.4 | R27: =M27+(1.96*O27)/(L27)^0.5 -> 36.492351 | S27: =M27-(1.96*O27)/(L27)^0.5 -> 34.723649
A28: 17 | B28: 4 | C28: 159.925 | D28: 159.15 | E28: 4.17 | F28: 165.1 | G28: 156.3 | H28: =C28+(1.96*E28)/(B28)^0.5 -> 164.0116 | I28: =C28-(1.96*E28)/(B28)^0.5 -> 155.8384 | K28: 16 | L28: 12 | M28: 34.433 | N28: 34.1 | O28: 2.171 | P28: 38.7 | Q28: 30.3 | R28: =M28+(1.96*O28)/(L28)^0.5 -> 35.661359 | S28: =M28-(1.96*O28)/(L28)^0.5 -> 33.204641
A29: 18 | B29: 2 | C29: 158.95 | D29: 158.95 | E29: 9.97 | F29: 166 | G29: 151.9 | H29: =C29+(1.96*E29)/(B29)^0.5 -> 172.76772 | I29: =C29-(1.96*E29)/(B29)^0.5 -> 145.13228 | K29: 17 | L29: 4 | M29: 34.8 | N29: 35.05 | O29: 1.525 | P29: 36.3 | Q29: 32.8 | R29: =M29+(1.96*O29)/(L29)^0.5 -> 36.2945 | S29: =M29-(1.96*O29)/(L29)^0.5 -> 33.3055
K30: 18 | L30: 2 | M30: 34.2 | N30: 34.2 | O30: 4.808 | P30: 37.6 | Q30: 30.8 | R30: =M30+(1.96*O30)/(L30)^0.5 -> 40.863548 | S30: =M30-(1.96*O30)/(L30)^0.5 -> 27.536452
A31: TALLA SENTADO (cm)
A32: Edad | B32: n | C32: Media | D32: Mediana | E32: Desv. Est. | F32: Máximo | G32: Mínimo | H32: IC95%sup | I32: IC95%inf | K32: LONGITUD DEL PIE (cm)
A33: 7 | B33: 1 | C33: 67.4 | D33: 67.4 | E33: , | F33: 67.4 | G33: 67.4 | K33: Edad | L33: n | M33: Media | N33: Mediana | O33: Desv. Est. | P33: Máximo | Q33: Mínimo | R33: IC95%sup | S33: IC95%inf
A34: 8 | B34: 10 | C34: 69.21 | D34: 69.5 | E34: 3.567 | F34: 74.3 | G34: 64 | H34: =C34+(1.96*E34)/(B34)^0.5 -> 71.42085 | I34: =C34-(1.96*E34)/(B34)^0.5 -> 66.99915 | K34: 7 | L34: 1 | M34: 18.8 | N34: 18.8 | O34: , | P34: 18.8 | Q34: 18.8
A35: 9 | B35: 17 | C35: 72.053 | D35: 71.7 | E35: 2.865 | F35: 76.6 | G35: 65.6 | H35: =C35+(1.96*E35)/(B35)^0.5 -> 73.414935 | I35: =C35-(1.96*E35)/(B35)^0.5 -> 70.691065 | K35: 8 | L35: 10 | M35: 19.71 | N35: 19.75 | O35: 1.062 | P35: 21.2 | Q35: 17.7 | R35: =M35+(1.96*O35)/(L35)^0.5 -> 20.368234 | S35: =M35-(1.96*O35)/(L35)^0.5 -> 19.051766
A36: 10 | B36: 22 | C36: 74.541 | D36: 74.65 | E36: 3.432 | F36: 80.3 | G36: 68 | H36: =C36+(1.96*E36)/(B36)^0.5 -> 75.975142 | I36: =C36-(1.96*E36)/(B36)^0.5 -> 73.106858 | K36: 9 | L36: 17 | M36: 21.218 | N36: 21.3 | O36: 1.325 | P36: 23.2 | Q36: 19.2 | R36: =M36+(1.96*O36)/(L36)^0.5 -> 21.847865 | S36: =M36-(1.96*O36)/(L36)^0.5 -> 20.588135
A37: 11 | B37: 21 | C37: 78.395 | D37: 79.4 | E37: 5.201 | F37: 85.9 | G37: 68 | H37: =C37+(1.96*E37)/(B37)^0.5 -> 80.619504 | I37: =C37-(1.96*E37)/(B37)^0.5 -> 76.170496 | K37: 10 | L37: 22 | M37: 21.85 | N37: 21.75 | O37: 1.409 | P37: 25.3 | Q37: 19.7 | R37: =M37+(1.96*O37)/(L37)^0.5 -> 22.438784 | S37: =M37-(1.96*O37)/(L37)^0.5 -> 21.261216
A38: 12 | B38: 39 | C38: 79.856 | D38: 79.3 | E38: 4.313 | F38: 89.1 | G38: 71.9 | H38: =C38+(1.96*E38)/(B38)^0.5 -> 81.20964 | I38: =C38-(1.96*E38)/(B38)^0.5 -> 78.50236 | K38: 11 | L38: 20 | M38: 22.76 | N38: 22.95 | O38: 1.397 | P38: 25.2 | Q38: 19.7 | R38: =M38+(1.96*O38)/(L38)^0.5 -> 23.372262 | S38: =M38-(1.96*O38)/(L38)^0.5 -> 22.147738
A39: 13 | B39: 41 | C39: 81.824 | D39: 81.3 | E39: 3.976 | F39: 88.4 | G39: 74.8 | H39: =C39+(1.96*E39)/(B39)^0.5 -> 83.041056 | I39: =C39-(1.96*E39)/(B39)^0.5 -> 80.606944 | K39: 12 | L39: 39 | M39: 23.015 | N39: 23.1 | O39: 1.234 | P39: 25.3 | Q39: 19.7 | R39: =M39+(1.96*O39)/(L39)^0.5 -> 23.402292 | S39: =M39-(1.96*O39)/(L39)^0.5 -> 22.627708
A40: 14 | B40: 45 | C40: 84.149 | D40: 83.9 | E40: 2.87 | F40: 90.3 | G40: 78.2 | H40: =C40+(1.96*E40)/(B40)^0.5 -> 84.987555 | I40: =C40-(1.96*E40)/(B40)^0.5 -> 83.310445 | K40: 13 | L40: 40 | M40: 23.235 | N40: 23.2 | O40: 1.266 | P40: 26.2 | Q40: 20.3 | R40: =M40+(1.96*O40)/(L40)^0.5 -> 23.627337 | S40: =M40-(1.96*O40)/(L40)^0.5 -> 22.842663
A41: 15 | B41: 12 | C41: 85.15 | D41: 84.95 | E41: 3.153 | F41: 90.3 | G41: 81 | H41: =C41+(1.96*E41)/(B41)^0.5 -> 86.933978 | I41: =C41-(1.96*E41)/(B41)^0.5 -> 83.366022 | K41: 14 | L41: 45 | M41: 23.318 | N41: 23.4 | O41: 0.936 | P41: 25.1 | Q41: 21.3 | R41: =M41+(1.96*O41)/(L41)^0.5 -> 23.59148 | S41: =M41-(1.96*O41)/(L41)^0.5 -> 23.04452
A42: 16 | B42: 13 | C42: 84.608 | D42: 85 | E42: 2.268 | F42: 88.5 | G42: 79.5 | H42: =C42+(1.96*E42)/(B42)^0.5 -> 85.840899 | I42: =C42-(1.96*E42)/(B42)^0.5 -> 83.375101 | K42: 15 | L42: 12 | M42: 22.85 | N42: 23 | O42: 0.782 | P42: 23.9 | Q42: 21.8 | R42: =M42+(1.96*O42)/(L42)^0.5 -> 23.292458 | S42: =M42-(1.96*O42)/(L42)^0.5 -> 22.407542
A43: 17 | B43: 4 | C43: 84.45 | D43: 84.65 | E43: 1.047 | F43: 85.5 | G43: 83 | H43: =C43+(1.96*E43)/(B43)^0.5 -> 85.47606 | I43: =C43-(1.96*E43)/(B43)^0.5 -> 83.42394 | K43: 16 | L43: 12 | M43: 22.817 | N43: 22.75 | O43: 0.758 | P43: 24.6 | Q43: 21.6 | R43: =M43+(1.96*O43)/(L43)^0.5 -> 23.245879 | S43: =M43-(1.96*O43)/(L43)^0.5 -> 22.388121
A44: 18 | B44: 2 | C44: 88.75 | D44: 88.75 | E44: 3.889 | F44: 91.5 | G44: 86 | H44: =C44+(1.96*E44)/(B44)^0.5 -> 94.139879 | I44: =C44-(1.96*E44)/(B44)^0.5 -> 83.360121 | K44: 17 | L44: 4 | M44: 22.7 | N44: 22.85 | O44: 0.883 | P44: 23.6 | Q44: 21.5 | R44: =M44+(1.96*O44)/(L44)^0.5 -> 23.56534 | S44: =M44-(1.96*O44)/(L44)^0.5 -> 21.83466
K45: 18 | L45: 2 | M45: 21.9 | N45: 21.9 | O45: 1.414 | P45: 22.9 | Q45: 20.9 | R45: =M45+(1.96*O45)/(L45)^0.5 -> 23.859704 | S45: =M45-(1.96*O45)/(L45)^0.5 -> 19.940296
A46: ENVERGADURA (cm)
A47: Edad | B47: n | C47: Media | D47: Mediana | E47: Desv. Est. | F47: Máximo | G47: Mínimo | H47: IC95%sup | I47: IC95%inf
A48: 7 | B48: 1 | C48: 118.7 | D48: 118.7 | E48: , | F48: 118.7 | G48: 118.7 | K48: DIÁMETRO BIACROMIAL (cm)
A49: 8 | B49: 10 | C49: 128.23 | D49: 128.7 | E49: 6.397 | F49: 137 | G49: 115.1 | H49: =C49+(1.96*E49)/(B49)^0.5 -> 132.1949 | I49: =C49-(1.96*E49)/(B49)^0.5 -> 124.2651 | K49: Edad | L49: n | M49: Media | N49: Mediana | O49: Desv. Est. | P49: Máximo | Q49: Mínimo | R49: IC95%sup | S49: IC95%inf
A50: 9 | B50: 17 | C50: 137.624 | D50: 135.4 | E50: 7.224 | F50: 148.4 | G50: 127.8 | H50: =C50+(1.96*E50)/(B50)^0.5 -> 141.05807 | I50: =C50-(1.96*E50)/(B50)^0.5 -> 134.18993 | K50: 7 | L50: 1 | M50: 27.3 | N50: 27.3 | O50: , | P50: 27.3 | Q50: 27.3
A51: 10 | B51: 22 | C51: 143.873 | D51: 143.2 | E51: 7.888 | F51: 159.2 | G51: 131.4 | H51: =C51+(1.96*E51)/(B51)^0.5 -> 147.16919 | I51: =C51-(1.96*E51)/(B51)^0.5 -> 140.57681 | K51: 8 | L51: 10 | M51: 27.98 | N51: 27.8 | O51: 1.679 | P51: 30.4 | Q51: 24.6 | R51: =M51+(1.96*O51)/(L51)^0.5 -> 29.020655 | S51: =M51-(1.96*O51)/(L51)^0.5 -> 26.939345
A52: 11 | B52: 21 | C52: 149.229 | D52: 152.5 | E52: 8.243 | F52: 160 | G52: 129.7 | H52: =C52+(1.96*E52)/(B52)^0.5 -> 152.75459 | I52: =C52-(1.96*E52)/(B52)^0.5 -> 145.70341 | K52: 9 | L52: 17 | M52: 29.406 | N52: 29.3 | O52: 1.41 | P52: 31.3 | Q52: 26.1 | R52: =M52+(1.96*O52)/(L52)^0.5 -> 30.076271 | S52: =M52-(1.96*O52)/(L52)^0.5 -> 28.735729
A53: 12 | B53: 39 | C53: 153.492 | D53: 154.2 | E53: 7.854 | F53: 170 | G53: 138 | H53: =C53+(1.96*E53)/(B53)^0.5 -> 155.95699 | I53: =C53-(1.96*E53)/(B53)^0.5 -> 151.02701 | K53: 10 | L53: 22 | M53: 30.968 | N53: 30.9 | O53: 2.211 | P53: 36.5 | Q53: 26.8 | R53: =M53+(1.96*O53)/(L53)^0.5 -> 31.891918 | S53: =M53-(1.96*O53)/(L53)^0.5 -> 30.044082
A54: 13 | B54: 40 | C54: 156.98 | D54: 158.85 | E54: 6.954 | F54: 174 | G54: 140.6 | H54: =C54+(1.96*E54)/(B54)^0.5 -> 159.13507 | I54: =C54-(1.96*E54)/(B54)^0.5 -> 154.82493 | K54: 11 | L54: 21 | M54: 32.143 | N54: 32.1 | O54: 1.918 | P54: 35.7 | Q54: 28.2 | R54: =M54+(1.96*O54)/(L54)^0.5 -> 32.963342 | S54: =M54-(1.96*O54)/(L54)^0.5 -> 31.322658
A55: 14 | B55: 44 | C55: 160.316 | D55: 160.95 | E55: 6.397 | F55: 178.2 | G55: 148.3 | H55: =C55+(1.96*E55)/(B55)^0.5 -> 162.20619 | I55: =C55-(1.96*E55)/(B55)^0.5 -> 158.42581 | K55: 12 | L55: 39 | M55: 32.936 | N55: 33.2 | O55: 1.701 | P55: 36 | Q55: 29.3 | R55: =M55+(1.96*O55)/(L55)^0.5 -> 33.469861 | S55: =M55-(1.96*O55)/(L55)^0.5 -> 32.402139
A56: 15 | B56: 12 | C56: 157.525 | D56: 159.5 | E56: 5.228 | F56: 167 | G56: 150.5 | H56: =C56+(1.96*E56)/(B56)^0.5 -> 160.48302 | I56: =C56-(1.96*E56)/(B56)^0.5 -> 154.56698 | K56: 13 | L56: 41 | M56: 33.551 | N56: 33.5 | O56: 1.856 | P56: 37.7 | Q56: 30.1 | R56: =M56+(1.96*O56)/(L56)^0.5 -> 34.119123 | S56: =M56-(1.96*O56)/(L56)^0.5 -> 32.982877
A57: 16 | B57: 12 | C57: 158.633 | D57: 157.55 | E57: 7.811 | F57: 174.5 | G57: 148.5 | H57: =C57+(1.96*E57)/(B57)^0.5 -> 163.05249 | I57: =C57-(1.96*E57)/(B57)^0.5 -> 154.21351 | K57: 14 | L57: 45 | M57: 34.642 | N57: 34.4 | O57: 1.864 | P57: 38.9 | Q57: 31.1 | R57: =M57+(1.96*O57)/(L57)^0.5 -> 35.186623 | S57: =M57-(1.96*O57)/(L57)^0.5 -> 34.097377
A58: 17 | B58: 4 | C58: 159.575 | D58: 160.3 | E58: 7.239 | F58: 167.6 | G58: 150.1 | H58: =C58+(1.96*E58)/(B58)^0.5 -> 166.66922 | I58: =C58-(1.96*E58)/(B58)^0.5 -> 152.48078 | K58: 15 | L58: 12 | M58: 33.675 | N58: 33.85 | O58: 1.642 | P58: 37.2 | Q58: 31 | R58: =M58+(1.96*O58)/(L58)^0.5 -> 34.604049 | S58: =M58-(1.96*O58)/(L58)^0.5 -> 32.745951
A59: 18 | B59: 2 | C59: 156.55 | D59: 156.55 | E59: 12.657 | F59: 165.5 | G59: 147.6 | H59: =C59+(1.96*E59)/(B59)^0.5 -> 174.09171 | I59: =C59-(1.96*E59)/(B59)^0.5 -> 139.00829 | K59: 16 | L59: 13 | M59: 33.485 | N59: 34 | O59: 1.79 | P59: 35.9 | Q59: 30.2 | R59: =M59+(1.96*O59)/(L59)^0.5 -> 34.458055 | S59: =M59-(1.96*O59)/(L59)^0.5 -> 32.511945
K60: 17 | L60: 4 | M60: 33.55 | N60: 33.4 | O60: 1.33 | P60: 35.2 | Q60: 32.2 | R60: =M60+(1.96*O60)/(L60)^0.5 -> 34.8534 | S60: =M60-(1.96*O60)/(L60)^0.5 -> 32.2466
K61: 18 | L61: 2 | M61: 34.3 | N61: 34.3 | O61: 0.283 | P61: 34.5 | Q61: 34.1 | R61: =M61+(1.96*O61)/(L61)^0.5 -> 34.692218 | S61: =M61-(1.96*O61)/(L61)^0.5 -> 33.907782
A62: LONGITUD ACROMIAL-RADIAL (cm)
A63: Edad | B63: n | C63: Media | D63: Mediana | E63: Desv. Est. | F63: Máximo | G63: Mínimo | H63: IC95%sup | I63: IC95%inf
A64: 7 | B64: 1 | C64: 23.2 | D64: 23.2 | E64: , | F64: 23.2 | G64: 23.2 | K64: DIÁMETRO TÓRAX TRANSVERSO (cm)
A65: 8 | B65: 10 | C65: 24.49 | D65: 24.55 | E65: 1.309 | F65: 26.6 | G65: 21.8 | H65: =C65+(1.96*E65)/(B65)^0.5 -> 25.301327 | I65: =C65-(1.96*E65)/(B65)^0.5 -> 23.678673 | K65: Edad | L65: n | M65: Media | N65: Mediana | O65: Desv. Est. | P65: Máximo | Q65: Mínimo | R65: IC95%sup | S65: IC95%inf
A66: 9 | B66: 17 | C66: 26.453 | D66: 26.3 | E66: 1.637 | F66: 28.9 | G66: 22.7 | H66: =C66+(1.96*E66)/(B66)^0.5 -> 27.23118 | I66: =C66-(1.96*E66)/(B66)^0.5 -> 25.67482 | K66: 7 | L66: 1 | M66: 20 | N66: 20 | O66: , | P66: 20 | Q66: 20
A67: 10 | B67: 22 | C67: 27.4 | D67: 27.55 | E67: 1.654 | F67: 31.3 | G67: 24.3 | H67: =C67+(1.96*E67)/(B67)^0.5 -> 28.091163 | I67: =C67-(1.96*E67)/(B67)^0.5 -> 26.708837 | K67: 8 | L67: 10 | M67: 19.35 | N67: 19.75 | O67: 0.842 | P67: 20.3 | Q67: 18.1 | R67: =M67+(1.96*O67)/(L67)^0.5 -> 19.871877 | S67: =M67-(1.96*O67)/(L67)^0.5 -> 18.828123
A68: 11 | B68: 20 | C68: 28.31 | D68: 28.6 | E68: 1.883 | F68: 31.2 | G68: 24.7 | H68: =C68+(1.96*E68)/(B68)^0.5 -> 29.135261 | I68: =C68-(1.96*E68)/(B68)^0.5 -> 27.484739 | K68: 9 | L68: 17 | M68: 20.435 | N68: 20.7 | O68: 0.964 | P68: 21.8 | Q68: 18.6 | R68: =M68+(1.96*O68)/(L68)^0.5 -> 20.893257 | S68: =M68-(1.96*O68)/(L68)^0.5 -> 19.976743
A69: 12 | B69: 39 | C69: 29.244 | D69: 29.4 | E69: 1.803 | F69: 33.6 | G69: 25.6 | H69: =C69+(1.96*E69)/(B69)^0.5 -> 29.809874 | I69: =C69-(1.96*E69)/(B69)^0.5 -> 28.678126 | K69: 10 | L69: 22 | M69: 22.05 | N69: 21.7 | O69: 2.234 | P69: 29.4 | Q69: 19.5 | R69: =M69+(1.96*O69)/(L69)^0.5 -> 22.983529 | S69: =M69-(1.96*O69)/(L69)^0.5 -> 21.116471
A70: 13 | B70: 41 | C70: 30.044 | D70: 30.2 | E70: 1.631 | F70: 33.7 | G70: 25.3 | H70: =C70+(1.96*E70)/(B70)^0.5 -> 30.54325 | I70: =C70-(1.96*E70)/(B70)^0.5 -> 29.54475 | K70: 11 | L70: 21 | M70: 22.271 | N70: 22.1 | O70: 1.763 | P70: 25.6 | Q70: 19.8 | R70: =M70+(1.96*O70)/(L70)^0.5 -> 23.025048 | S70: =M70-(1.96*O70)/(L70)^0.5 -> 21.516952
A71: 14 | B71: 45 | C71: 30.538 | D71: 30.4 | E71: 1.454 | F71: 35 | G71: 27.5 | H71: =C71+(1.96*E71)/(B71)^0.5 -> 30.962829 | I71: =C71-(1.96*E71)/(B71)^0.5 -> 30.113171 | K71: 12 | L71: 39 | M71: 22.805 | N71: 22.7 | O71: 1.734 | P71: 27.6 | Q71: 18.5 | R71: =M71+(1.96*O71)/(L71)^0.5 -> 23.349218 | S71: =M71-(1.96*O71)/(L71)^0.5 -> 22.260782
A72: 15 | B72: 12 | C72: 30.633 | D72: 30.65 | E72: 1.323 | F72: 33.2 | G72: 28 | H72: =C72+(1.96*E72)/(B72)^0.5 -> 31.381558 | I72: =C72-(1.96*E72)/(B72)^0.5 -> 29.884442 | K72: 13 | L72: 41 | M72: 23.38 | N72: 23.3 | O72: 1.64 | P72: 27.5 | Q72: 20.4 | R72: =M72+(1.96*O72)/(L72)^0.5 -> 23.882005 | S72: =M72-(1.96*O72)/(L72)^0.5 -> 22.877995
A73: 16 | B73: 12 | C73: 30.467 | D73: 30.35 | E73: 1.845 | F73: 34.4 | G73: 27.3 | H73: =C73+(1.96*E73)/(B73)^0.5 -> 31.510907 | I73: =C73-(1.96*E73)/(B73)^0.5 -> 29.423093 | K73: 14 | L73: 45 | M73: 24.264 | N73: 24.3 | O73: 1.554 | P73: 28 | Q73: 19.6 | R73: =M73+(1.96*O73)/(L73)^0.5 -> 24.718047 | S73: =M73-(1.96*O73)/(L73)^0.5 -> 23.809953
A74: 17 | B74: 4 | C74: 30.675 | D74: 30.95 | E74: 1.801 | F74: 32.3 | G74: 28.5 | H74: =C74+(1.96*E74)/(B74)^0.5 -> 32.43998 | I74: =C74-(1.96*E74)/(B74)^0.5 -> 28.91002 | K74: 15 | L74: 12 | M74: 22.942 | N74: 22.7 | O74: 1.381 | P74: 25.1 | Q74: 20.7 | R74: =M74+(1.96*O74)/(L74)^0.5 -> 23.723374 | S74: =M74-(1.96*O74)/(L74)^0.5 -> 22.160626
A75: 18 | B75: 2 | C75: 29.8 | D75: 29.8 | E75: 1.414 | F75: 30.8 | G75: 28.8 | H75: =C75+(1.96*E75)/(B75)^0.5 -> 31.759704 | I75: =C75-(1.96*E75)/(B75)^0.5 -> 27.840296 | K75: 16 | L75: 13 | M75: 23.492 | N75: 23.7 | O75: 2.215 | P75: 27.5 | Q75: 19.3 | R75: =M75+(1.96*O75)/(L75)^0.5 -> 24.696088 | S75: =M75-(1.96*O75)/(L75)^0.5 -> 22.287912
K76: 17 | L76: 4 | M76: 21.875 | N76: 21.6 | O76: 1.32 | P76: 23.6 | Q76: 20.7 | R76: =M76+(1.96*O76)/(L76)^0.5 -> 23.1686 | S76: =M76-(1.96*O76)/(L76)^0.5 -> 20.5814
K77: 18 | L77: 2 | M77: 23.3 | N77: 23.3 | O77: 0.424 | P77: 23.6 | Q77: 23 | R77: =M77+(1.96*O77)/(L77)^0.5 -> 23.887634 | S77: =M77-(1.96*O77)/(L77)^0.5 -> 22.712366
A78: LONGITUD RADIAL-ESTILOIDEA (cm)
A79: Edad | B79: n | C79: Media | D79: Mediana | E79: Desv. Est. | F79: Máximo | G79: Mínimo | H79: IC95%sup | I79: IC95%inf
A80: 7 | B80: 1 | C80: 16.1 | D80: 16.1 | E80: , | F80: 16.1 | G80: 16.1 | K80: DIÁMETRO TÓRAX ANTERO-POSTERIOR (cm)
A81: 8 | B81: 10 | C81: 18.69 | D81: 18.5 | E81: 1.436 | F81: 21.2 | G81: 16.1 | H81: =C81+(1.96*E81)/(B81)^0.5 -> 19.580042 | I81: =C81-(1.96*E81)/(B81)^0.5 -> 17.799958 | K81: Edad | L81: n | M81: Media | N81: Mediana | O81: Desv. Est. | P81: Máximo | Q81: Mínimo | R81: IC95%sup | S81: IC95%inf
A82: 9 | B82: 17 | C82: 20.018 | D82: 20 | E82: 1.032 | F82: 22 | G82: 18.1 | H82: =C82+(1.96*E82)/(B82)^0.5 -> 20.508582 | I82: =C82-(1.96*E82)/(B82)^0.5 -> 19.527418 | K82: 7 | L82: 1 | M82: 16.6 | N82: 16.6 | O82: , | P82: 16.6 | Q82: 16.6
A83: 10 | B83: 22 | C83: 21.191 | D83: 21.15 | E83: 1.452 | F83: 24.8 | G83: 18.8 | H83: =C83+(1.96*E83)/(B83)^0.5 -> 21.797752 | I83: =C83-(1.96*E83)/(B83)^0.5 -> 20.584248 | K83: 8 | L83: 10 | M83: 14.31 | N83: 14.35 | O83: 1.077 | P83: 16.6 | Q83: 12.8 | R83: =M83+(1.96*O83)/(L83)^0.5 -> 14.977532 | S83: =M83-(1.96*O83)/(L83)^0.5 -> 13.642468
A84: 11 | B84: 19 | C84: 21.679 | D84: 22.2 | E84: 1.377 | F84: 23.6 | G84: 18.1 | H84: =C84+(1.96*E84)/(B84)^0.5 -> 22.298175 | I84: =C84-(1.96*E84)/(B84)^0.5 -> 21.059825 | K84: 9 | L84: 17 | M84: 15.006 | N84: 14.6 | O84: 1.341 | P84: 17.1 | Q84: 12.6 | R84: =M84+(1.96*O84)/(L84)^0.5 -> 15.643471 | S84: =M84-(1.96*O84)/(L84)^0.5 -> 14.368529
A85: 12 | B85: 39 | C85: 22.2 | D85: 22.2 | E85: 1.328 | F85: 24.7 | G85: 19.3 | H85: =C85+(1.96*E85)/(B85)^0.5 -> 22.616794 | I85: =C85-(1.96*E85)/(B85)^0.5 -> 21.783206 | K85: 10 | L85: 22 | M85: 15.477 | N85: 15.4 | O85: 1.585 | P85: 20.8 | Q85: 13.6 | R85: =M85+(1.96*O85)/(L85)^0.5 -> 16.139329 | S85: =M85-(1.96*O85)/(L85)^0.5 -> 14.814671
A86: 13 | B86: 41 | C86: 22.822 | D86: 23 | E86: 1.245 | F86: 24.8 | G86: 19.8 | H86: =C86+(1.96*E86)/(B86)^0.5 -> 23.203095 | I86: =C86-(1.96*E86)/(B86)^0.5 -> 22.440905 | K86: 11 | L86: 21 | M86: 15.705 | N86: 15.7 | O86: 1.252 | P86: 18 | Q86: 12.3 | R86: =M86+(1.96*O86)/(L86)^0.5 -> 16.240489 | S86: =M86-(1.96*O86)/(L86)^0.5 -> 15.169511
A87: 14 | B87: 45 | C87: 23.267 | D87: 23 | E87: 1.119 | F87: 26.1 | G87: 20.7 | H87: =C87+(1.96*E87)/(B87)^0.5 -> 23.593949 | I87: =C87-(1.96*E87)/(B87)^0.5 -> 22.940051 | K87: 12 | L87: 39 | M87: 15.928 | N87: 15.7 | O87: 1.582 | P87: 22.8 | Q87: 13.2 | R87: =M87+(1.96*O87)/(L87)^0.5 -> 16.424513 | S87: =M87-(1.96*O87)/(L87)^0.5 -> 15.431487
A88: 15 | B88: 12 | C88: 23.158 | D88: 23.35 | E88: 0.948 | F88: 24.4 | G88: 21 | H88: =C88+(1.96*E88)/(B88)^0.5 -> 23.694381 | I88: =C88-(1.96*E88)/(B88)^0.5 -> 22.621619 | K88: 13 | L88: 41 | M88: 16.327 | N88: 15.9 | O88: 1.448 | P88: 20.2 | Q88: 13.2 | R88: =M88+(1.96*O88)/(L88)^0.5 -> 16.770234 | S88: =M88-(1.96*O88)/(L88)^0.5 -> 15.883766
A89: 16 | B89: 12 | C89: 22.908 | D89: 22.8 | E89: 1.802 | F89: 26.1 | G89: 20.7 | H89: =C89+(1.96*E89)/(B89)^0.5 -> 23.927577 | I89: =C89-(1.96*E89)/(B89)^0.5 -> 21.888423 | K89: 14 | L89: 45 | M89: 16.462 | N89: 16.4 | O89: 1.375 | P89: 20 | Q89: 13.7 | R89: =M89+(1.96*O89)/(L89)^0.5 -> 16.863747 | S89: =M89-(1.96*O89)/(L89)^0.5 -> 16.060253
A90: 17 | B90: 4 | C90: 23.625 | D90: 23.65 | E90: 0.585 | F90: 24.3 | G90: 22.9 | H90: =C90+(1.96*E90)/(B90)^0.5 -> 24.1983 | I90: =C90-(1.96*E90)/(B90)^0.5 -> 23.0517 | K90: 15 | L90: 12 | M90: 16.575 | N90: 16.9 | O90: 1.256 | P90: 18.7 | Q90: 14.7 | R90: =M90+(1.96*O90)/(L90)^0.5 -> 17.285649 | S90: =M90-(1.96*O90)/(L90)^0.5 -> 15.864351
A91: 18 | B91: 2 | C91: 22.9 | D91: 22.9 | E91: 2.687 | F91: 24.8 | G91: 21 | H91: =C91+(1.96*E91)/(B91)^0.5 -> 26.623992 | I91: =C91-(1.96*E91)/(B91)^0.5 -> 19.176008 | K91: 16 | L91: 13 | M91: 16.8 | N91: 17.1 | O91: 1.178 | P91: 18.8 | Q91: 15.3 | R91: =M91+(1.96*O91)/(L91)^0.5 -> 17.440368 | S91: =M91-(1.96*O91)/(L91)^0.5 -> 16.159632
K92: 17 | L92: 4 | M92: 15.75 | N92: 15.55 | O92: 0.889 | P92: 16.9 | Q92: 15 | R92: =M92+(1.96*O92)/(L92)^0.5 -> 16.62122 | S92: =M92-(1.96*O92)/(L92)^0.5 -> 14.87878
K93: 18 | L93: 2 | M93: 17.75 | N93: 17.75 | O93: 0.919 | P93: 18.4 | Q93: 17.1 | R93: =M93+(1.96*O93)/(L93)^0.5 -> 19.023669 | S93: =M93-(1.96*O93)/(L93)^0.5 -> 16.476331
A95: LONGITUD ESTILOIDEA-DACTILAR (cm)
A96: Edad | B96: n | C96: Media | D96: Mediana | E96: Desv. Est. | F96: Máximo | G96: Mínimo | H96: IC95%sup | I96: IC95%inf | K96: DIÁMTRO BI-ILIOCRESTÍDEO (cm)
A97: 7 | B97: 1 | C97: 13.9 | D97: 13.9 | E97: , | F97: 13.9 | G97: 13.9 | K97: Edad | L97: n | M97: Media | N97: Mediana | O97: Desv. Est. | P97: Máximo | Q97: Mínimo | R97: IC95%sup | S97: IC95%inf
A98: 8 | B98: 10 | C98: 14.76 | D98: 14.8 | E98: 0.677 | F98: 15.6 | G98: 13.6 | H98: =C98+(1.96*E98)/(B98)^0.5 -> 15.179609 | I98: =C98-(1.96*E98)/(B98)^0.5 -> 14.340391 | K98: 7 | L98: 1 | M98: 20 | N98: 20 | O98: , | P98: 20 | Q98: 20
A99: 9 | B99: 17 | C99: 15.882 | D99: 15.9 | E99: 0.928 | F99: 17.1 | G99: 13.5 | H99: =C99+(1.96*E99)/(B99)^0.5 -> 16.323143 | I99: =C99-(1.96*E99)/(B99)^0.5 -> 15.440857 | K99: 8 | L99: 10 | M99: 20.61 | N99: 20.2 | O99: 2.266 | P99: 25.3 | Q99: 17.9 | R99: =M99+(1.96*O99)/(L99)^0.5 -> 22.014481 | S99: =M99-(1.96*O99)/(L99)^0.5 -> 19.205519
A100: 10 | B100: 22 | C100: 16.677 | D100: 16.55 | E100: 1.039 | F100: 18.9 | G100: 15.2 | H100: =C100+(1.96*E100)/(B100)^0.5 -> 17.11117 | I100: =C100-(1.96*E100)/(B100)^0.5 -> 16.24283 | K100: 9 | L100: 17 | M100: 21.888 | N100: 21.6 | O100: 1.56 | P100: 24.5 | Q100: 19 | R100: =M100+(1.96*O100)/(L100)^0.5 -> 22.629577 | S100: =M100-(1.96*O100)/(L100)^0.5 -> 21.146423
A101: 11 | B101: 20 | C101: 17.375 | D101: 17.25 | E101: 0.924 | F101: 19.1 | G101: 15.2 | H101: =C101+(1.96*E101)/(B101)^0.5 -> 17.779961 | I101: =C101-(1.96*E101)/(B101)^0.5 -> 16.970039 | K101: 10 | L101: 22 | M101: 22.877 | N101: 22.75 | O101: 1.895 | P101: 28.6 | Q101: 20 | R101: =M101+(1.96*O101)/(L101)^0.5 -> 23.66887 | S101: =M101-(1.96*O101)/(L101)^0.5 -> 22.08513
A102: 12 | B102: 39 | C102: 17.554 | D102: 17.6 | E102: 0.974 | F102: 19.9 | G102: 15.4 | H102: =C102+(1.96*E102)/(B102)^0.5 -> 17.859691 | I102: =C102-(1.96*E102)/(B102)^0.5 -> 17.248309 | K102: 11 | L102: 21 | M102: 23.824 | N102: 24.2 | O102: 2.049 | P102: 27.3 | Q102: 20.2 | R102: =M102+(1.96*O102)/(L102)^0.5 -> 24.700372 | S102: =M102-(1.96*O102)/(L102)^0.5 -> 22.947628
...

Sheet REQUERIMIENTOS
A1: REQUERIMIENTOS Y LISTA DE INTERCAMBIO
A3: Peso actual | B3: ='ANTROPOMETRÍA DEPORTISTAS'!B7 -> 0 | C3: Peso usual | D3: ='ANTROPOMETRÍA DEPORTISTAS'!#REF! -> #REF! | E3: Peso mínimo | G3: Peso máximo | H3: ='ANTROPOMETRÍA DEPORTISTAS'!#REF! -> #REF! | I3: Peso a utilizar
A4: Talla | B4: ='ANTROPOMETRÍA DEPORTISTAS'!B9 -> 0 | I4: Peso Magro | J4: ='ANTROPOMETRÍA DEPORTISTAS'!B58 -> 0 | K4: % de cambio de peso | O4: LBM | P4: LBM
K5: Tiempo | L5: Significativo | M5: Severo
A6: PESO TEÓRICO | E6: PESO TEÓRICO | I6: Porcentaje de cambio de peso | K6: 1 semana | L6: 1 – 2 % | M6: > 2 %
A7: WEST | C7: Derivada del IMC | E7: Hamwi | I7: =((D3-B3)/D3)*100 -> #REF! | K7: 1 mes | L7: 3 – 5 % | M7: > 5 %
A8: Hombres | B8: =22.1*(POWER(B4/100,2)) -> 0 | C8: Hombres | D8: =23*(POWER(B3/100,2)) -> 0 | E8: Hombres | F8: =(B4-152)*1.08+48.5 -> -115.66 | G8: Hombres | H8: =23*(POWER(F4/100,2)) -> 0 | I8: Peso ajustado (Obesidad) | K8: 3 meses | L8: 6 – 8 % | M8: > 8 %
A9: Mujeres | B9: =20.6*(POWER(B4/100,2)) -> 0 | C9: Mujeres | D9: =21.5*(POWER(B3/100,2)) -> 0 | E9: Mujeres | F9: =(B4-152)*0.88+45.5 -> -88.26 | G9: Mujeres | H9: =21.5*(POWER(F4/100,2)) -> 0 | I9: =(B3-F9)*0.25+F9 -> -66.195 | K9: 6 meses | L9: 9 – 10% | M9: > 10 %
A12: METODO TRADICIONAL | E12: MÉTODO DIRECTO | J12: HARRIS Y BENEDICT | P12: HARRIS Y BENEDICT (ROZA) | U12: CUNNINGHAM (1980)
A13: Peso Utilizar | C13: =J3 -> 0 | E13: Hipocalórica | G13: =(J3*F13) -> 0 | H13: < 25 kcal/kg Peso | J13: RCB (Masculino) | L13: =(66.47+(13.75*J3)+(5*B4)-(6.75*HISTORIA!C7)) -> -784.71425 | P13: RCB (Masculino) | R13: =88.362+(13.397*J3)+(4.799*B4)-(5.677*HISTORIA!C7) -> -627.51548 | U13: RCB (Masculino) | W13: =(500+(22*O5)) -> 500
A14: RCB (Masculino) | C14: =(J3*24*1) -> 0 | E14: Normocalórica | G14: =F14*J3 -> 0 | H14: 25-30 kcal/kg Peso | J14: RCB (Femenino) | L14: =(655.1+(9.56*J3)+(1.85*B4)-(4.7*HISTORIA!C7)) -> 62.423562 | P14: RCB (Femenino) | R14: =447.593+(9.247*J3)+(3.098*B4)-(4.33*HISTORIA!C7) -> -98.425932 | U14: RCB (Femenino) | W14: =(500+(22*P5)) -> 500
A15: RCB (Femenino) | C15: =(J3*24*0.98) -> 0 | E15: Hipercalórica | G15: =F15*J3 -> 0 | H15: > 30 kcal/kg Peso | J15: Factor de Actividad | P15: Factor de Actividad | R15: =L15 -> 0 | U15: Factor de Actividad | W15: =S7 -> 0
A16: ETA (Masculino) | C16: =C14/10 -> 0 | J16: Factor de estrés | L16: 1 | P16: RCT (Masculino) | R16: =R13*R15 -> 0 | U16: RCT (Masculino) | W16: =W13*W15 -> 0
A17: ETA (Femenino) | C17: =(C15)/10 -> 0 | E17: MÉTODO HOLLIDAY | J17: RCT (Masculino) | L17: =L13*L15*L16 -> 0 | P17: RCT (Femenino) | R17: =R14*R15 -> 0 | U17: RCT (Femenino) | W17: =W14*W15 -> 0
A18: Actividad Física | C18: 1.5 | E18: 0-10 Kg | F18: 100 Kcal/Kg/día | J18: RCT (Femenino) | L18: =L14*L15*L16 -> 0
A19: RCT (Masculino) | C19: =(C14+C16)*C18 -> 0 | E19: 10,1-20 Kg | F19: 1000 Kcal + 50 Kcal por cada Kg por encima
A20: RCT (Femenino) | C20: =(C15+C17)*C18 -> 0 | E20: >20 Kg | F20: 1000 Kcal + 20 Kcal por cada Kg por encima de 20 Kg | J20: FACTOR DE ACTIVIDAD FÍSICA | N20: MULLER EQUATION | S20: MIFFLIN - ST.JEOR | Y20: 1.2 - Sedentary:
E21: RCB: | H21: 2040 | J21: Sedentary | L21: 1.2 | N21: RCB (Masculino) | P21: =((13.587*'ANTROPOMETRÍA DEPORTISTAS'!B58)+(9.613*'ANTROPOMETRÍA DEPORTISTAS'!B59)+(198*1)-(3.351*HISTORIA!C7)+674) -> 449.43431 | S21: RCB (Masculino) | U21: =(9.99*J3)+(6.25*B4)-(4.92*HISTORIA!C7)+5 -> -615.41874 | Y21: You work a desk job and don’t exercise
E22: ENERGÍA DE ACTIVIDAD: | H22: =HISTORIA!K41 -> #REF! | J22: Light Activity | L22: 1375 | N22: RCB (Femenino) | P22: =((13.587*'ANTROPOMETRÍA DEPORTISTAS'!B58)+(9.613*'ANTROPOMETRÍA DEPORTISTAS'!B59)+(198*0)-(3.351*HISTORIA!C7)+674) -> 251.43431 | S22: RCB (Femenino) | U22: =(9.99*J3)+(6.25*B4)-(4.92*HISTORIA!C7)-161 -> -781.41874 | Y22: 1.375 - Light Activity:
A23: ACTIVIDAD FÍSICA (AF) | E23: ETA: 10% | J23: Moderate Activity | L23: 1.55 | N23: Factor de Actividad | P23: =L15 -> 0 | S23: Factor de Actividad | U23: =L15 -> 0 | Y23: You work a desk job but do a bit of regular exercise. Or you don’t exercise but you work at a
A24: Sedentario | C24: 1 | E24: REQUERIMIENTO CALÓRICO TOTAL | J24: Very Active | L24: 1.725 | N24: RCT (Masculino) | P24: =P21*P23 -> 0 | S24: RCT (Masculino) | U24: =U21*U23 -> 0 | Y24: job that’s pretty active (a nurse, teacher, etc.) where you’re on your for feet most of the day.
A25: Muy Leve | C25: 1.25 | J25: Extra Active | L25: 1.9 | N25: RCT (Femenino) | P25: =P22*P23 -> 0 | S25: RCT (Femenino) | U25: =U22*U23 -> 0 | Y25: 1.55 - Moderate Activity:
A26: Leve | C26: 1.5 | Y26: Most of you will probably fall into this category. Maybe you work a sedentary job, but you
A27: Moderada | C27: 1.75 | Y27: train like a madman. Or maybe you train moderately, but you also have a job where you
A28: Intensa | C28: 2 | T28: Restricción | V28: Valor (Kcal) | Y28: stand on your feet all the time. Someone who doesn’t train but works a hard labor job
T29: 0.1 | V29: =0.1 -> 0.1 | Y29: would also fall into this category.
G30: FORMÚLA DIETÉTICA | M30: Suplementos | T30: 0.12 | V30: =0.12 -> 0.12 | Y30: 1.725 - Very Active:
G31: RCT a Utilizar | T31: 0.15 | V31: =0.15 -> 0.15 | Y31: You train hard most days of the week, and you also work a job where you’re on your feet
I32: % | J32: kcal | K32: g | L32: g/kg Peso | M32: Aporte de Macros | T32: 0.2 | V32: =0.2 -> 0.2 | Y32: quite a bit. Overall, you’re active most of the day.
G33: Proteínas | I33: 15 | J33: =(I33/100)*J31 -> 0 | K33: =J33/4 +M33 -> 0 | L33: =K33/J3 -> #DIV/0! | T33: 0.25 | V33: =0.25 -> 0.25 | Y33: 1.9 - Extra Active:
G34: Grasas | I34: 35 | J34: =(I34*J31)/100 -> 0 | K34: =J34/9 + M34 -> 0 | L34: =K34/J3 -> #DIV/0! | T34: 0.3 | V34: =0.3 -> 0.3 | Y34: You train hard and work a job that is physically intense in nature. As an example, you’re a
G35: CHO | I35: =100-I33-I34 -> 50 | J35: =(I35*J31)/100 -> 0 | K35: =J35/4 + M35 -> 0 | L35: =K35/J3 -> #DIV/0! | Y35: roofer who also goes to the gym five days a week.
G36: Colesterol
G37: Fibra | I37: =(L37*J31)/1000 -> 0
G38: Sodio
G39: Agua | I39: =L39*C13 -> 0
C41: Intervalos de edad.
A42: Rangos óptimos de proteína: | C42: 0-30 | D42: 31-40 | E42: 41-50 | F42: 51-60 | G42: 61-70
A43: No caloric Deficit | C43: 1,8-2,0 | D43: 2,0-2,3 | E43: 2,3-2,6 | F43: 2,6-2,9 | G43: 2,9-3,2 | H43: Kg de masa magra
A44: Deficit Calorico | C44: 2,2-2,4 | D44: 2,4-2,8 | E44: 2,8-3,1 | F44: 3,1-3,5 | G44: 3,5-3,8 | H44: Kg de masa magra
A46: LISTA DE INTERCAMBIO | J46: DISTRIBUCIÓN DE COMIDAS
A47: Alimento | B47: Int | C47: Proteínas | D47: Grasas | E47: CHO | F47: Fibra | G47: Colesterol | H47: Sodio | J47: Comida | K47: Pre Desayuno | L47: Desayuno | M47: Merienda | N47: Almuerzo | P47: Merienda | Q47: Cena | R47: Merienda | S47: Total | T47: Requerimiento
A48: Leche Completa | C48: =B48*8 -> 0 | D48: =B48*8 -> 0 | E48: =B48*12 -> 0 | F48: =B48*0 -> 0 | G48: =B48*33 -> 0 | H48: =B48*115 -> 0 | J48: Leche | S48: =SUM(K48:R48) -> 0 | T48: =B48 -> 0
A49: Leche Descremada | C49: =B49*8 -> 0 | D49: =B49*2.5 -> 0 | E49: =B49*12 -> 0 | F49: =B49*0 -> 0 | G49: =B49*13.5 -> 0 | H49: =B49*138 -> 0 | J49: Vegetales | S49: =SUM(K49:R49) -> 0 | T49: =B50 -> 0
A50: Vegetales | C50: =B50*2 -> 0 | D50: =B50*0 -> 0 | E50: =B50*5 -> 0 | F50: =B50*1 -> 0 | G50: =B50*0 -> 0 | H50: =B50*11.5 -> 0 | J50: Frutas | S50: =SUM(K50:R50) -> 0 | T50: =B51 -> 0
A51: Frutas | C51: =B51*0 -> 0 | D51: =B51*0 -> 0 | E51: =B51*15 -> 0 | F51: =B51*2 -> 0 | G51: =B51*0 -> 0 | H51: =B51*0 -> 0 | J51: Almidon | S51: =SUM(K51:R51) -> 0 | T51: =B53 -> 0
A52: Subtotal | B52: =(K35-E52)/15 -> 0 | C52: =SUM(C48:C51) -> 0 | D52: =SUM(D48:D51) -> 0 | E52: =SUM(E48:E51) -> 0 | F52: =SUM(F48:F51) -> 0 | G52: =SUM(G48:G51) -> 0 | H52: =SUM(H48:H51) -> 0 | J52: Carnes magras | S52: =SUM(K52:R52) -> 0 | T52: =B55 -> 0
A53: Almidon | C53: =B53*2 -> 0 | D53: =B53*0 -> 0 | E53: =B53*15 -> 0 | F53: =B53*2.5 -> 0 | G53: =B53*0 -> 0 | H53: =B53*46 -> 0 | J53: Carnes semimagras | S53: =SUM(K53:R53) -> 0 | T53: =B56 -> 0
A54: Subtotal | B54: =(K33-C54)/7 -> 0 | C54: =SUM(C48:C51,C53) -> 0 | D54: =SUM(D48:D51,D53) -> 0 | E54: =SUM(E48:E51,E53) -> 0 | F54: =SUM(F48:F51,F53) -> 0 | G54: =SUM(G48:G51,G53) -> 0 | H54: =SUM(H48:H51,H53) -> 0 | J54: Grasas | S54: =SUM(K54:R54) -> 0 | T54: =B58 -> 0
A55: Carnes magras | C55: =B55*7 -> 0 | D55: =B55*3 -> 0 | E55: =B55*0 -> 0 | F55: =B55*0 -> 0 | G55: =B55*25 -> 0 | H55: =B55*2 -> 0 | J55: Azúcar | S55: =SUM(K55:R55) -> 0 | T55: =B59 -> 0
A56: Carnes semimagras | B56: =B54-B55 -> 0 | C56: =B56*7 -> 0 | D56: =B56*4 -> 0 | E56: =B56*0 -> 0 | F56: =B56*0 -> 0 | G56: =B56*25 -> 0 | H56: =B56*2 -> 0
A57: Subtotal | B57: =(K34-D57)/5 -> 0 | C57: =SUM(C54:C56) -> 0 | D57: =SUM(D54:D56) -> 0 | E57: =SUM(E54:E56) -> 0 | F57: =SUM(F54:F56) -> 0 | G57: =SUM(G54:G56) -> 0 | H57: =SUM(H54:H56) -> 0 | S57: =(S48*90)+(S49*25)+(S50*60)+(S51*80)+(S52*55)+(S53*70)+(S54*45)+(S55*60) -> 0
A58: Grasas | C58: =B58*0 -> 0 | D58: =B58*5 -> 0 | E58: =B58*0 -> 0 | F58: =B58*0 -> 0 | G58: =B58*2 -> 0 | H58: =B58*2 -> 0
A59: Total | C59: =C57+C58 -> 0 | D59: =D57+D58 -> 0 | E59: =E57+E58 -> 0 | F59: =F57+F58 -> 0 | G59: =G57+G58 -> 0 | H59: =H57+H58 -> 0
A60: Requerimiento | C60: =K33-M33 -> 0 | D60: =K34-M34 -> 0 | E60: =K35-M35 -> 0 | F60: =I37 -> 0 | G60: =I36 -> 0 | H60: =I38 -> 0
A61: Adecuación | C61: =(C59*100)/C60 -> #DIV/0! | D61: =(D59*100)/D60 -> #DIV/0! | E61: =(E59*100)/E60 -> #DIV/0! | F61: =(F59*100)/F60 -> #DIV/0! | G61: =(G59*100)/G60 -> #DIV/0! | H61: =(H59*100)/H60 -> #DIV/0!

Sheet RESUMEN ANTROPOMETRICO
B2: Evaluación | D2: 1era evaluación | E2: Control 1° | F2: Control 2° | G2: Control 3° | H2: Control 4° | I2: Control 5° | J2: Control 6° | K2: Control 7° | L2: Control 8° | M2: Control 9°
B3: Fecha de evaluación | D3: ='ANTROPOMETRÍA DEPORTISTAS'!B6 -> 0 | E3: ='ANTROPOMETRÍA DEPORTISTAS'!C6 -> 0 | F3: ='ANTROPOMETRÍA DEPORTISTAS'!D6 -> 0 | G3: ='ANTROPOMETRÍA DEPORTISTAS'!E6 -> 0 | H3: ='ANTROPOMETRÍA DEPORTISTAS'!F6 -> 0 | I3: ='ANTROPOMETRÍA DEPORTISTAS'!G6 -> 0 | J3: ='ANTROPOMETRÍA DEPORTISTAS'!H6 -> 0 | K3: ='ANTROPOMETRÍA DEPORTISTAS'!I6 -> 0 | ... M3: ='ANTROPOMETRÍA DEPORTISTAS'!K6 -> 0
B4: Peso Actual (Kg) | D4: ='ANTROPOMETRÍA DEPORTISTAS'!B7 -> 0 | E4: ='ANTROPOMETRÍA DEPORTISTAS'!C7 -> 0 | F4: ='ANTROPOMETRÍA DEPORTISTAS'!D7 -> 0 | G4: ='ANTROPOMETRÍA DEPORTISTAS'!E7 -> 0 | H4: ='ANTROPOMETRÍA DEPORTISTAS'!F7 -> 0 | I4: ='ANTROPOMETRÍA DEPORTISTAS'!G7 -> 0 | J4: ='ANTROPOMETRÍA DEPORTISTAS'!H7 -> 0 | K4: ='ANTROPOMETRÍA DEPORTISTAS'!I7 -> 0 | ... M4: ='ANTROPOMETRÍA DEPORTISTAS'!K7 -> 0
B5: Talla parada (cm) | D5: ='ANTROPOMETRÍA DEPORTISTAS'!B9 -> 0 | E5: ='ANTROPOMETRÍA DEPORTISTAS'!C9 -> 0 | F5: ='ANTROPOMETRÍA DEPORTISTAS'!D9 -> 0 | G5: ='ANTROPOMETRÍA DEPORTISTAS'!E9 -> 0 | H5: ='ANTROPOMETRÍA DEPORTISTAS'!F9 -> 0 | I5: ='ANTROPOMETRÍA DEPORTISTAS'!G9 -> 0 | J5: ='ANTROPOMETRÍA DEPORTISTAS'!H9 -> 0 | K5: ='ANTROPOMETRÍA DEPORTISTAS'!I9 -> 0 | ... M5: ='ANTROPOMETRÍA DEPORTISTAS'!K9 -> 0
B6: ='ANTROPOMETRÍA DEPORTISTAS'!A52 -> % Grasa (Carter 1986) | D6: ='ANTROPOMETRÍA DEPORTISTAS'!B52 -> 3.5803 | E6: ='ANTROPOMETRÍA DEPORTISTAS'!C52 -> 3.5803 | F6: ='ANTROPOMETRÍA DEPORTISTAS'!D52 -> 3.5803 | G6: ='ANTROPOMETRÍA DEPORTISTAS'!E52 -> 3.5803 | H6: ='ANTROPOMETRÍA DEPORTISTAS'!F52 -> 3.5803 | I6: ='ANTROPOMETRÍA DEPORTISTAS'!G52 -> 3.5803 | J6: ='ANTROPOMETRÍA DEPORTISTAS'!H52 -> 3.5803 | K6: ='ANTROPOMETRÍA DEPORTISTAS'!I52 -> 3.5803 | ... M6: ='ANTROPOMETRÍA DEPORTISTAS'!K52 -> 3.5803
B7: ='ANTROPOMETRÍA DEPORTISTAS'!A53 -> % Grasa (Durnin y W. 1974) | D7: ='ANTROPOMETRÍA DEPORTISTAS'!B53 -> #NUM! | E7: ='ANTROPOMETRÍA DEPORTISTAS'!C52 -> 3.5803 | F7: ='ANTROPOMETRÍA DEPORTISTAS'!D52 -> 3.5803 | G7: ='ANTROPOMETRÍA DEPORTISTAS'!E52 -> 3.5803 | H7: ='ANTROPOMETRÍA DEPORTISTAS'!F52 -> 3.5803 | I7: ='ANTROPOMETRÍA DEPORTISTAS'!G52 -> 3.5803 | J7: ='ANTROPOMETRÍA DEPORTISTAS'!H52 -> 3.5803 | K7: ='ANTROPOMETRÍA DEPORTISTAS'!I52 -> 3.5803 | L7: ='ANTROPOMETRÍA DEPORTISTAS'!J52 -> 3.5803 | M7: ='ANTROPOMETRÍA DEPORTISTAS'!K52 -> 3.5803
B8: Interpretación | D8: =IF('ANTROPOMETRÍA DEPORTISTAS'!B53<21, "Excelente", IF('ANTROPOMETRÍA DEPORTISTAS'!B53=34, "Saludable/Normal", IF('ANTROPOMETRÍA DEPORTISTAS'!B53=40, "Sobrepeso", "Sobrepeso II"))) -> #NUM!
B9: Kg de Masa Magra | D9: ='ANTROPOMETRÍA DEPORTISTAS'!B58 -> 0 | E9: ='ANTROPOMETRÍA DEPORTISTAS'!C58 -> 0 | F9: ='ANTROPOMETRÍA DEPORTISTAS'!D58 -> 0 | G9: ='ANTROPOMETRÍA DEPORTISTAS'!E58 -> 0 | H9: ='ANTROPOMETRÍA DEPORTISTAS'!F58 -> 0 | I9: ='ANTROPOMETRÍA DEPORTISTAS'!G58 -> 0 | J9: ='ANTROPOMETRÍA DEPORTISTAS'!H58 -> 0 | K9: ='ANTROPOMETRÍA DEPORTISTAS'!I58 -> 0 | ... M9: ='ANTROPOMETRÍA DEPORTISTAS'!K58 -> 0
B10: Kg de Grasa | D10: ='ANTROPOMETRÍA DEPORTISTAS'!B59 -> 0 | E10: ='ANTROPOMETRÍA DEPORTISTAS'!C59 -> 0 | F10: ='ANTROPOMETRÍA DEPORTISTAS'!D59 -> 0 | G10: ='ANTROPOMETRÍA DEPORTISTAS'!E59 -> 0 | H10: ='ANTROPOMETRÍA DEPORTISTAS'!F59 -> 0 | I10: ='ANTROPOMETRÍA DEPORTISTAS'!G59 -> 0 | J10: ='ANTROPOMETRÍA DEPORTISTAS'!H59 -> 0 | K10: ='ANTROPOMETRÍA DEPORTISTAS'!I59 -> 0 | ... M10: ='ANTROPOMETRÍA DEPORTISTAS'!K59 -> 0
B11: Masa Muscular (Kg) | D11: ='ANTROPOMETRÍA DEPORTISTAS'!B64 -> #DIV/0! | E11: ='ANTROPOMETRÍA DEPORTISTAS'!C64 -> #DIV/0! | F11: ='ANTROPOMETRÍA DEPORTISTAS'!D64 -> #DIV/0! | G11: ='ANTROPOMETRÍA DEPORTISTAS'!E64 -> #DIV/0! | H11: ='ANTROPOMETRÍA DEPORTISTAS'!F64 -> #DIV/0! | I11: ='ANTROPOMETRÍA DEPORTISTAS'!G64 -> #DIV/0! | J11: ='ANTROPOMETRÍA DEPORTISTAS'!H64 -> #DIV/0! | K11: ='ANTROPOMETRÍA DEPORTISTAS'!I64 -> #DIV/0! | ... M11: ='ANTROPOMETRÍA DEPORTISTAS'!K64 -> #DIV/0!
B12: Masa Adiposa (Kg) | D12: ='ANTROPOMETRÍA DEPORTISTAS'!B63 -> #DIV/0! | E12: ='ANTROPOMETRÍA DEPORTISTAS'!C63 -> #DIV/0! | F12: ='ANTROPOMETRÍA DEPORTISTAS'!D63 -> #DIV/0! | G12: ='ANTROPOMETRÍA DEPORTISTAS'!E63 -> #DIV/0! | H12: ='ANTROPOMETRÍA DEPORTISTAS'!F63 -> #DIV/0! | I12: ='ANTROPOMETRÍA DEPORTISTAS'!G63 -> #DIV/0! | J12: ='ANTROPOMETRÍA DEPORTISTAS'!H63 -> #DIV/0! | K12: ='ANTROPOMETRÍA DEPORTISTAS'!I63 -> #DIV/0! | ... M12: ='ANTROPOMETRÍA DEPORTISTAS'!K63 -> #DIV/0!
B13: Sumatoria de 6 pliegues | D13: ='ANTROPOMETRÍA DEPORTISTAS'!B54 -> 0 | E13: ='ANTROPOMETRÍA DEPORTISTAS'!C54 -> 0 | F13: ='ANTROPOMETRÍA DEPORTISTAS'!D54 -> 0 | G13: ='ANTROPOMETRÍA DEPORTISTAS'!E54 -> 0 | H13: ='ANTROPOMETRÍA DEPORTISTAS'!F54 -> 0 | I13: ='ANTROPOMETRÍA DEPORTISTAS'!G54 -> 0 | J13: ='ANTROPOMETRÍA DEPORTISTAS'!H54 -> 0 | K13: ='ANTROPOMETRÍA DEPORTISTAS'!I54 -> 0 | ... M13: ='ANTROPOMETRÍA DEPORTISTAS'!K54 -> 0
B14: Somatotipo | D14: =IF(AND('ANTROPOMETRÍA DEPORTISTAS'!B68>'ANTROPOMETRÍA DEPORTISTAS'!B67, 'ANTROPOMETRÍA DEPORTISTAS'!B68>'ANTROPOMETRÍA DEPORTISTAS'!B66), "Endomorfo", IF(AND('ANTROPOMETRÍA DEPORTISTAS'!B67>'ANTROPOMETRÍA DEPORTISTAS'!B68, 'ANTROPOMETRÍA DEPORTISTAS'!B67>'ANTROPOMETRÍA DEPORTISTAS'!B66), "Mesomorfo", IF(AND('ANTROPOMETRÍA DEPORTISTAS'!B66>'ANTROPOMETRÍA DEPORTISTAS'!B68, 'ANTROPOMETRÍA DEPORTISTAS'!B66>'ANTROPOMETRÍA DEPORTISTAS'!B67), "Ectomorfo", "Somatotipo Balanceado"))) -> #DIV/0! | E14: =IF(AND('ANTROPOMETRÍA DEPORTISTAS'!C68>'ANTROPOMETRÍA DEPORTISTAS'!C67, 'ANTROPOMETRÍA DEPORTISTAS'!C68>'ANTROPOMETRÍA DEPORTISTAS'!C66), "Endomorfo", IF(AND('ANTROPOMETRÍA DEPORTISTAS'!C67>'ANTROPOMETRÍA DEPORTISTAS'!C68, 'ANTROPOMETRÍA DEPORTISTAS'!C67>'ANTROPOMETRÍA DEPORTISTAS'!C66), "Mesomorfo", IF(AND('ANTROPOMETRÍA DEPORTISTAS'!C66>'ANTROPOMETRÍA DEPORTISTAS'!C68, 'ANTROPOMETRÍA DEPORTISTAS'!C66>'ANTROPOMETRÍA DEPORTISTAS'!C67), "Ectomorfo", "Somatotipo Balanceado"))) -> #DIV/0! | F14: =IF(AND('ANTROPOMETRÍA DEPORTISTAS'!D68>'ANTROPOMETRÍA DEPORTISTAS'!D67, 'ANTROPOMETRÍA DEPORTISTAS'!D68>'ANTROPOMETRÍA DEPORTISTAS'!D66), "Endomorfo", IF(AND('ANTROPOMETRÍA DEPORTISTAS'!D67>'ANTROPOMETRÍA DEPORTISTAS'!D68, 'ANTROPOMETRÍA DEPORTISTAS'!D67>'ANTROPOMETRÍA DEPORTISTAS'!D66), "Mesomorfo", IF(AND('ANTROPOMETRÍA DEPORTISTAS'!D66>'ANTROPOMETRÍA DEPORTISTAS'!D68, 'ANTROPOMETRÍA DEPORTISTAS'!D66>'ANTROPOMETRÍA DEPORTISTAS'!D67), "Ectomorfo", "Somatotipo Balanceado"))) -> #DIV/0! | G14: =IF(AND('ANTROPOMETRÍA DEPORTISTAS'!E68>'ANTROPOMETRÍA DEPORTISTAS'!E67, 'ANTROPOMETRÍA DEPORTISTAS'!E68>'ANTROPOMETRÍA DEPORTISTAS'!E66), "Endomorfo", IF(AND('ANTROPOMETRÍA DEPORTISTAS'!E67>'ANTROPOMETRÍA DEPORTISTAS'!E68, 'ANTROPOMETRÍA DEPORTISTAS'!E67>'ANTROPOMETRÍA DEPORTISTAS'!E66), "Mesomorfo", IF(AND('ANTROPOMETRÍA DEPORTISTAS'!E66>'ANTROPOMETRÍA DEPORTISTAS'!E68, 'ANTROPOMETRÍA DEPORTISTAS'!E66>'ANTROPOMETRÍA DEPORTISTAS'!E67), "Ectomorfo", "Somatotipo Balanceado"))) -> #DIV/0! | H14: =IF(AND('ANTROPOMETRÍA DEPORTISTAS'!F68>'ANTROPOMETRÍA DEPORTISTAS'!F67, 'ANTROPOMETRÍA DEPORTISTAS'!F68>'ANTROPOMETRÍA DEPORTISTAS'!F66), "Endomorfo", IF(AND('ANTROPOMETRÍA DEPORTISTAS'!F67>'ANTROPOMETRÍA DEPORTISTAS'!F68, 'ANTROPOMETRÍA DEPORTISTAS'!F67>'ANTROPOMETRÍA DEPORTISTAS'!F66), "Mesomorfo", IF(AND('ANTROPOMETRÍA DEPORTISTAS'!F66>'ANTROPOMETRÍA DEPORTISTAS'!F68, 'ANTROPOMETRÍA DEPORTISTAS'!F66>'ANTROPOMETRÍA DEPORTISTAS'!F67), "Ectomorfo", "Somatotipo Balanceado"))) -> #DIV/0! | I14: =IF(AND('ANTROPOMETRÍA DEPORTISTAS'!G68>'ANTROPOMETRÍA DEPORTISTAS'!G67, 'ANTROPOMETRÍA DEPORTISTAS'!G68>'ANTROPOMETRÍA DEPORTISTAS'!G66), "Endomorfo", IF(AND('ANTROPOMETRÍA DEPORTISTAS'!G67>'ANTROPOMETRÍA DEPORTISTAS'!G68, 'ANTROPOMETRÍA DEPORTISTAS'!G67>'ANTROPOMETRÍA DEPORTISTAS'!G66), "Mesomorfo", IF(AND('ANTROPOMETRÍA DEPORTISTAS'!G66>'ANTROPOMETRÍA DEPORTISTAS'!G68, 'ANTROPOMETRÍA DEPORTISTAS'!G66>'ANTROPOMETRÍA DEPORTISTAS'!G67), "Ectomorfo", "Somatotipo Balanceado"))) -> #DIV/0! | J14: =IF(AND('ANTROPOMETRÍA DEPORTISTAS'!H68>'ANTROPOMETRÍA DEPORTISTAS'!H67, 'ANTROPOMETRÍA DEPORTISTAS'!H68>'ANTROPOMETRÍA DEPORTISTAS'!H66), "Endomorfo", IF(AND('ANTROPOMETRÍA DEPORTISTAS'!H67>'ANTROPOMETRÍA DEPORTISTAS'!H68, 'ANTROPOMETRÍA DEPORTISTAS'!H67>'ANTROPOMETRÍA DEPORTISTAS'!H66), "Mesomorfo", IF(AND('ANTROPOMETRÍA DEPORTISTAS'!H66>'ANTROPOMETRÍA DEPORTISTAS'!H68, 'ANTROPOMETRÍA DEPORTISTAS'!H66>'ANTROPOMETRÍA DEPORTISTAS'!H67), "Ectomorfo", "Somatotipo Balanceado"))) -> #DIV/0! | K14: =IF(AND('ANTROPOMETRÍA DEPORTISTAS'!I68>'ANTROPOMETRÍA DEPORTISTAS'!I67, 'ANTROPOMETRÍA DEPORTISTAS'!I68>'ANTROPOMETRÍA DEPORTISTAS'!I66), "Endomorfo", IF(AND('ANTROPOMETRÍA DEPORTISTAS'!I67>'ANTROPOMETRÍA DEPORTISTAS'!I68, 'ANTROPOMETRÍA DEPORTISTAS'!I67>'ANTROPOMETRÍA DEPORTISTAS'!I66), "Mesomorfo", IF(AND('ANTROPOMETRÍA DEPORTISTAS'!I66>'ANTROPOMETRÍA DEPORTISTAS'!I68, 'ANTROPOMETRÍA DEPORTISTAS'!I66>'ANTROPOMETRÍA DEPORTISTAS'!I67), "Ectomorfo", "Somatotipo Balanceado"))) -> #DIV/0! | ... M14: =IF(AND('ANTROPOMETRÍA DEPORTISTAS'!K68>'ANTROPOMETRÍA DEPORTISTAS'!K67, 'ANTROPOMETRÍA DEPORTISTAS'!K68>'ANTROPOMETRÍA DEPORTISTAS'!K66), "Endomorfo", IF(AND('ANTROPOMETRÍA DEPORTISTAS'!K67>'ANTROPOMETRÍA DEPORTISTAS'!K68, 'ANTROPOMETRÍA DEPORTISTAS'!K67>'ANTROPOMETRÍA DEPORTISTAS'!K66), "Mesomorfo", IF(AND('ANTROPOMETRÍA DEPORTISTAS'!K66>'ANTROPOMETRÍA DEPORTISTAS'!K68, 'ANTROPOMETRÍA DEPORTISTAS'!K66>'ANTROPOMETRÍA DEPORTISTAS'!K67), "Ectomorfo", "Somatotipo Balanceado"))) -> #DIV/0!
B17: DATOS DEL INFORME
B19: Fecha de evaluación | D19: ='ANTROPOMETRÍA DEPORTISTAS'!B6 -> 0 | E19: ='ANTROPOMETRÍA DEPORTISTAS'!C6 -> 0 | F19: ='ANTROPOMETRÍA DEPORTISTAS'!D6 -> 0 | G19: ='ANTROPOMETRÍA DEPORTISTAS'!E6 -> 0 | H19: ='ANTROPOMETRÍA DEPORTISTAS'!F6 -> 0 | I19: ='ANTROPOMETRÍA DEPORTISTAS'!G6 -> 0 | J19: ='ANTROPOMETRÍA DEPORTISTAS'!H6 -> 0 | K19: ='ANTROPOMETRÍA DEPORTISTAS'!I6 -> 0 | ... M19: ='ANTROPOMETRÍA DEPORTISTAS'!K6 -> 0
B20: Peso actual (kg) | D20: ='ANTROPOMETRÍA DEPORTISTAS'!B7 -> 0 | E20: ='ANTROPOMETRÍA DEPORTISTAS'!C7 -> 0 | F20: ='ANTROPOMETRÍA DEPORTISTAS'!D7 -> 0 | G20: ='ANTROPOMETRÍA DEPORTISTAS'!E7 -> 0 | H20: ='ANTROPOMETRÍA DEPORTISTAS'!F7 -> 0 | I20: ='ANTROPOMETRÍA DEPORTISTAS'!G7 -> 0 | J20: ='ANTROPOMETRÍA DEPORTISTAS'!H7 -> 0 | K20: ='ANTROPOMETRÍA DEPORTISTAS'!I7 -> 0 | ... M20: ='ANTROPOMETRÍA DEPORTISTAS'!K7 -> 0
B21: Talla (m) | D21: ='ANTROPOMETRÍA DEPORTISTAS'!B8 -> 0 | E21: ='ANTROPOMETRÍA DEPORTISTAS'!C8 -> 0 | F21: ='ANTROPOMETRÍA DEPORTISTAS'!D8 -> 0 | G21: ='ANTROPOMETRÍA DEPORTISTAS'!E8 -> 0 | H21: ='ANTROPOMETRÍA DEPORTISTAS'!F8 -> 0 | I21: ='ANTROPOMETRÍA DEPORTISTAS'!G8 -> 0 | J21: ='ANTROPOMETRÍA DEPORTISTAS'!H8 -> 0 | K21: ='ANTROPOMETRÍA DEPORTISTAS'!I8 -> 0 | ... M21: ='ANTROPOMETRÍA DEPORTISTAS'!K8 -> 0
B22: Talla (cm) | D22: ='ANTROPOMETRÍA DEPORTISTAS'!B9 -> 0 | E22: ='ANTROPOMETRÍA DEPORTISTAS'!C9 -> 0 | F22: ='ANTROPOMETRÍA DEPORTISTAS'!D9 -> 0 | G22: ='ANTROPOMETRÍA DEPORTISTAS'!E9 -> 0 | H22: ='ANTROPOMETRÍA DEPORTISTAS'!F9 -> 0 | I22: ='ANTROPOMETRÍA DEPORTISTAS'!G9 -> 0 | J22: ='ANTROPOMETRÍA DEPORTISTAS'!H9 -> 0 | K22: ='ANTROPOMETRÍA DEPORTISTAS'!I9 -> 0 | ... M22: ='ANTROPOMETRÍA DEPORTISTAS'!K9 -> 0
B23: Circunferencias(cm)
B24: Brazo relajado (cm) | D24: ='ANTROPOMETRÍA DEPORTISTAS'!B12 -> 0 | E24: ='ANTROPOMETRÍA DEPORTISTAS'!C12 -> 0 | F24: ='ANTROPOMETRÍA DEPORTISTAS'!D12 -> 0 | G24: ='ANTROPOMETRÍA DEPORTISTAS'!E12 -> 0 | H24: ='ANTROPOMETRÍA DEPORTISTAS'!F12 -> 0 | I24: ='ANTROPOMETRÍA DEPORTISTAS'!G12 -> 0 | J24: ='ANTROPOMETRÍA DEPORTISTAS'!H12 -> 0 | K24: ='ANTROPOMETRÍA DEPORTISTAS'!I12 -> 0 | ... M24: ='ANTROPOMETRÍA DEPORTISTAS'!K12 -> 0
B25: Brazo Flexionado en Tensión (cm) | D25: ='ANTROPOMETRÍA DEPORTISTAS'!B13 -> 0 | E25: ='ANTROPOMETRÍA DEPORTISTAS'!C13 -> 0 | F25: ='ANTROPOMETRÍA DEPORTISTAS'!D13 -> 0 | G25: ='ANTROPOMETRÍA DEPORTISTAS'!E13 -> 0 | H25: ='ANTROPOMETRÍA DEPORTISTAS'!F13 -> 0 | I25: ='ANTROPOMETRÍA DEPORTISTAS'!G13 -> 0 | J25: ='ANTROPOMETRÍA DEPORTISTAS'!H13 -> 0 | K25: ='ANTROPOMETRÍA DEPORTISTAS'!I13 -> 0 | ... M25: ='ANTROPOMETRÍA DEPORTISTAS'!K13 -> 0
B26: Antebrazo máximo (cm) | D26: ='ANTROPOMETRÍA DEPORTISTAS'!B14 -> 0 | E26: ='ANTROPOMETRÍA DEPORTISTAS'!C14 -> 0 | F26: ='ANTROPOMETRÍA DEPORTISTAS'!D14 -> 0 | G26: ='ANTROPOMETRÍA DEPORTISTAS'!E14 -> 0 | H26: ='ANTROPOMETRÍA DEPORTISTAS'!F14 -> 0 | I26: ='ANTROPOMETRÍA DEPORTISTAS'!G14 -> 0 | J26: ='ANTROPOMETRÍA DEPORTISTAS'!H14 -> 0 | K26: ='ANTROPOMETRÍA DEPORTISTAS'!I14 -> 0 | ... M26: ='ANTROPOMETRÍA DEPORTISTAS'!K14 -> 0
B27: Tórax (Mesoesternal) (cm) | D27: ='ANTROPOMETRÍA DEPORTISTAS'!B15 -> 0 | E27: ='ANTROPOMETRÍA DEPORTISTAS'!C15 -> 0 | F27: ='ANTROPOMETRÍA DEPORTISTAS'!D15 -> 0 | G27: ='ANTROPOMETRÍA DEPORTISTAS'!E15 -> 0 | H27: ='ANTROPOMETRÍA DEPORTISTAS'!F15 -> 0 | I27: ='ANTROPOMETRÍA DEPORTISTAS'!G15 -> 0 | J27: ='ANTROPOMETRÍA DEPORTISTAS'!H15 -> 0 | K27: ='ANTROPOMETRÍA DEPORTISTAS'!I15 -> 0 | ... M27: ='ANTROPOMETRÍA DEPORTISTAS'!K15 -> 0
B28: Cintura mínimo (cm) | D28: ='ANTROPOMETRÍA DEPORTISTAS'!B16 -> 0 | E28: ='ANTROPOMETRÍA DEPORTISTAS'!C16 -> 0 | F28: ='ANTROPOMETRÍA DEPORTISTAS'!D16 -> 0 | G28: ='ANTROPOMETRÍA DEPORTISTAS'!E16 -> 0 | H28: ='ANTROPOMETRÍA DEPORTISTAS'!F16 -> 0 | I28: ='ANTROPOMETRÍA DEPORTISTAS'!G16 -> 0 | J28: ='ANTROPOMETRÍA DEPORTISTAS'!H16 -> 0 | K28: ='ANTROPOMETRÍA DEPORTISTAS'!I16 -> 0 | ... M28: ='ANTROPOMETRÍA DEPORTISTAS'!K16 -> 0
B29: Cadera máximo (cm) | D29: ='ANTROPOMETRÍA DEPORTISTAS'!B17 -> 0 | E29: ='ANTROPOMETRÍA DEPORTISTAS'!C17 -> 0 | F29: ='ANTROPOMETRÍA DEPORTISTAS'!D17 -> 0 | G29: ='ANTROPOMETRÍA DEPORTISTAS'!E17 -> 0 | H29: ='ANTROPOMETRÍA DEPORTISTAS'!F17 -> 0 | I29: ='ANTROPOMETRÍA DEPORTISTAS'!G17 -> 0 | J29: ='ANTROPOMETRÍA DEPORTISTAS'!H17 -> 0 | K29: ='ANTROPOMETRÍA DEPORTISTAS'!I17 -> 0 | ... M29: ='ANTROPOMETRÍA DEPORTISTAS'!K17 -> 0
B30: Muslo máximo (cm) | D30: ='ANTROPOMETRÍA DEPORTISTAS'!B18 -> 0 | E30: ='ANTROPOMETRÍA DEPORTISTAS'!C18 -> 0 | F30: ='ANTROPOMETRÍA DEPORTISTAS'!D18 -> 0 | G30: ='ANTROPOMETRÍA DEPORTISTAS'!E18 -> 0 | H30: ='ANTROPOMETRÍA DEPORTISTAS'!F18 -> 0 | I30: ='ANTROPOMETRÍA DEPORTISTAS'!G18 -> 0 | J30: ='ANTROPOMETRÍA DEPORTISTAS'!H18 -> 0 | K30: ='ANTROPOMETRÍA DEPORTISTAS'!I18 -> 0 | ... M30: ='ANTROPOMETRÍA DEPORTISTAS'!K18 -> 0
B31: Muslo medial (cm) | D31: ='ANTROPOMETRÍA DEPORTISTAS'!B19 -> 0 | E31: ='ANTROPOMETRÍA DEPORTISTAS'!C19 -> 0 | F31: ='ANTROPOMETRÍA DEPORTISTAS'!D19 -> 0 | G31: ='ANTROPOMETRÍA DEPORTISTAS'!E19 -> 0 | H31: ='ANTROPOMETRÍA DEPORTISTAS'!F19 -> 0 | I31: ='ANTROPOMETRÍA DEPORTISTAS'!G19 -> 0 | J31: ='ANTROPOMETRÍA DEPORTISTAS'!H19 -> 0 | K31: ='ANTROPOMETRÍA DEPORTISTAS'!I19 -> 0 | ... M31: ='ANTROPOMETRÍA DEPORTISTAS'!K19 -> 0
B32: Pantorrilla máximo (cm) | D32: ='ANTROPOMETRÍA DEPORTISTAS'!B20 -> 0 | E32: ='ANTROPOMETRÍA DEPORTISTAS'!C20 -> 0 | F32: ='ANTROPOMETRÍA DEPORTISTAS'!D20 -> 0 | G32: ='ANTROPOMETRÍA DEPORTISTAS'!E20 -> 0 | H32: ='ANTROPOMETRÍA DEPORTISTAS'!F20 -> 0 | I32: ='ANTROPOMETRÍA DEPORTISTAS'!G20 -> 0 | J32: ='ANTROPOMETRÍA DEPORTISTAS'!H20 -> 0 | K32: ='ANTROPOMETRÍA DEPORTISTAS'!I20 -> 0 | ... M32: ='ANTROPOMETRÍA DEPORTISTAS'!K20 -> 0
B33: Pliegues (mm)
B34: Bíceps (mm) | D34: ='ANTROPOMETRÍA DEPORTISTAS'!B22 -> 0 | E34: ='ANTROPOMETRÍA DEPORTISTAS'!C22 -> 0 | F34: ='ANTROPOMETRÍA DEPORTISTAS'!D22 -> 0 | G34: ='ANTROPOMETRÍA DEPORTISTAS'!E22 -> 0 | H34: ='ANTROPOMETRÍA DEPORTISTAS'!F22 -> 0 | I34: ='ANTROPOMETRÍA DEPORTISTAS'!G22 -> 0 | J34: ='ANTROPOMETRÍA DEPORTISTAS'!H22 -> 0 | K34: ='ANTROPOMETRÍA DEPORTISTAS'!I22 -> 0 | ... M34: ='ANTROPOMETRÍA DEPORTISTAS'!K22 -> 0
B35: Tríceps (mm) | D35: ='ANTROPOMETRÍA DEPORTISTAS'!B23 -> 0 | E35: ='ANTROPOMETRÍA DEPORTISTAS'!C23 -> 0 | F35: ='ANTROPOMETRÍA DEPORTISTAS'!D23 -> 0 | G35: ='ANTROPOMETRÍA DEPORTISTAS'!E23 -> 0 | H35: ='ANTROPOMETRÍA DEPORTISTAS'!F23 -> 0 | I35: ='ANTROPOMETRÍA DEPORTISTAS'!G23 -> 0 | J35: ='ANTROPOMETRÍA DEPORTISTAS'!H23 -> 0 | K35: ='ANTROPOMETRÍA DEPORTISTAS'!I23 -> 0 | ... M35: ='ANTROPOMETRÍA DEPORTISTAS'!K23 -> 0
B36: Subescapular (mm) | D36: ='ANTROPOMETRÍA DEPORTISTAS'!B24 -> 0 | E36: ='ANTROPOMETRÍA DEPORTISTAS'!C24 -> 0 | F36: ='ANTROPOMETRÍA DEPORTISTAS'!D24 -> 0 | G36: ='ANTROPOMETRÍA DEPORTISTAS'!E24 -> 0 | H36: ='ANTROPOMETRÍA DEPORTISTAS'!F24 -> 0 | I36: ='ANTROPOMETRÍA DEPORTISTAS'!G24 -> 0 | J36: ='ANTROPOMETRÍA DEPORTISTAS'!H24 -> 0 | K36: ='ANTROPOMETRÍA DEPORTISTAS'!I24 -> 0 | ... M36: ='ANTROPOMETRÍA DEPORTISTAS'!K24 -> 0
B37: Ileo-crestal (mm) | D37: ='ANTROPOMETRÍA DEPORTISTAS'!B25 -> 0 | E37: ='ANTROPOMETRÍA DEPORTISTAS'!C25 -> 0 | F37: ='ANTROPOMETRÍA DEPORTISTAS'!D25 -> 0 | G37: ='ANTROPOMETRÍA DEPORTISTAS'!E25 -> 0 | H37: ='ANTROPOMETRÍA DEPORTISTAS'!F25 -> 0 | I37: ='ANTROPOMETRÍA DEPORTISTAS'!G25 -> 0 | J37: ='ANTROPOMETRÍA DEPORTISTAS'!H25 -> 0 | K37: ='ANTROPOMETRÍA DEPORTISTAS'!I25 -> 0 | ... M37: ='ANTROPOMETRÍA DEPORTISTAS'!K25 -> 0
B38: Supra-espinal (mm) | D38: ='ANTROPOMETRÍA DEPORTISTAS'!B26 -> 0 | E38: ='ANTROPOMETRÍA DEPORTISTAS'!C26 -> 0 | F38: ='ANTROPOMETRÍA DEPORTISTAS'!D26 -> 0 | G38: ='ANTROPOMETRÍA DEPORTISTAS'!E26 -> 0 | H38: ='ANTROPOMETRÍA DEPORTISTAS'!F26 -> 0 | I38: ='ANTROPOMETRÍA DEPORTISTAS'!G26 -> 0 | J38: ='ANTROPOMETRÍA DEPORTISTAS'!H26 -> 0 | K38: ='ANTROPOMETRÍA DEPORTISTAS'!I26 -> 0 | ... M38: ='ANTROPOMETRÍA DEPORTISTAS'!K26 -> 0
B39: Abdominal (mm) | D39: ='ANTROPOMETRÍA DEPORTISTAS'!B27 -> 0 | E39: ='ANTROPOMETRÍA DEPORTISTAS'!C27 -> 0 | F39: ='ANTROPOMETRÍA DEPORTISTAS'!D27 -> 0 | G39: ='ANTROPOMETRÍA DEPORTISTAS'!E27 -> 0 | H39: ='ANTROPOMETRÍA DEPORTISTAS'!F27 -> 0 | I39: ='ANTROPOMETRÍA DEPORTISTAS'!G27 -> 0 | J39: ='ANTROPOMETRÍA DEPORTISTAS'!H27 -> 0 | K39: ='ANTROPOMETRÍA DEPORTISTAS'!I27 -> 0 | ... M39: ='ANTROPOMETRÍA DEPORTISTAS'!K27 -> 0
B40: Muslo frontal (mm) | D40: ='ANTROPOMETRÍA DEPORTISTAS'!B28 -> 0 | E40: ='ANTROPOMETRÍA DEPORTISTAS'!C28 -> 0 | F40: ='ANTROPOMETRÍA DEPORTISTAS'!D28 -> 0 | G40: ='ANTROPOMETRÍA DEPORTISTAS'!E28 -> 0 | H40: ='ANTROPOMETRÍA DEPORTISTAS'!F28 -> 0 | I40: ='ANTROPOMETRÍA DEPORTISTAS'!G28 -> 0 | J40: ='ANTROPOMETRÍA DEPORTISTAS'!H28 -> 0 | K40: ='ANTROPOMETRÍA DEPORTISTAS'!I28 -> 0 | ... M40: ='ANTROPOMETRÍA DEPORTISTAS'!K28 -> 0
B41: Pantorrilla (mm) | D41: ='ANTROPOMETRÍA DEPORTISTAS'!B29 -> 0 | E41: ='ANTROPOMETRÍA DEPORTISTAS'!C29 -> 0 | F41: ='ANTROPOMETRÍA DEPORTISTAS'!D29 -> 0 | G41: ='ANTROPOMETRÍA DEPORTISTAS'!E29 -> 0 | H41: ='ANTROPOMETRÍA DEPORTISTAS'!F29 -> 0 | I41: ='ANTROPOMETRÍA DEPORTISTAS'!G29 -> 0 | J41: ='ANTROPOMETRÍA DEPORTISTAS'!H29 -> 0 | K41: ='ANTROPOMETRÍA DEPORTISTAS'!I29 -> 0 | ... M41: ='ANTROPOMETRÍA DEPORTISTAS'!K29 -> 0
B42: Diametros óseos (cm)
B43: Humeral (Biepicondilar) | D43: ='ANTROPOMETRÍA DEPORTISTAS'!B35 -> 0 | E43: ='ANTROPOMETRÍA DEPORTISTAS'!C35 -> 0 | F43: ='ANTROPOMETRÍA DEPORTISTAS'!D35 -> 0 | G43: ='ANTROPOMETRÍA DEPORTISTAS'!E35 -> 0 | H43: ='ANTROPOMETRÍA DEPORTISTAS'!F35 -> 0 | I43: ='ANTROPOMETRÍA DEPORTISTAS'!G35 -> 0 | J43: ='ANTROPOMETRÍA DEPORTISTAS'!H35 -> 0 | K43: ='ANTROPOMETRÍA DEPORTISTAS'!I35 -> 0 | ... M43: ='ANTROPOMETRÍA DEPORTISTAS'!K35 -> 0
B44: Femoral (Biepicondilar) | D44: ='ANTROPOMETRÍA DEPORTISTAS'!B36 -> 0 | E44: ='ANTROPOMETRÍA DEPORTISTAS'!C36 -> 0 | F44: ='ANTROPOMETRÍA DEPORTISTAS'!D36 -> 0 | G44: ='ANTROPOMETRÍA DEPORTISTAS'!E36 -> 0 | H44: ='ANTROPOMETRÍA DEPORTISTAS'!F36 -> 0 | I44: ='ANTROPOMETRÍA DEPORTISTAS'!G36 -> 0 | J44: ='ANTROPOMETRÍA DEPORTISTAS'!H36 -> 0 | K44: ='ANTROPOMETRÍA DEPORTISTAS'!I36 -> 0 | ... M44: ='ANTROPOMETRÍA DEPORTISTAS'!K36 -> 0
B45: INDICADORES DEL INFORME
B47: Fecha de evaluación | D47: ='ANTROPOMETRÍA DEPORTISTAS'!B6 -> 0 | E47: ='ANTROPOMETRÍA DEPORTISTAS'!C6 -> 0 | F47: ='ANTROPOMETRÍA DEPORTISTAS'!D6 -> 0 | G47: ='ANTROPOMETRÍA DEPORTISTAS'!E6 -> 0 | H47: ='ANTROPOMETRÍA DEPORTISTAS'!F6 -> 0 | I47: ='ANTROPOMETRÍA DEPORTISTAS'!G6 -> 0 | J47: ='ANTROPOMETRÍA DEPORTISTAS'!H6 -> 0 | K47: ='ANTROPOMETRÍA DEPORTISTAS'!I6 -> 0 | ... M47: ='ANTROPOMETRÍA DEPORTISTAS'!K6 -> 0
B48: IMC (kg/m2) | D48: ='ANTROPOMETRÍA DEPORTISTAS'!B44 -> #DIV/0! | E48: ='ANTROPOMETRÍA DEPORTISTAS'!C44 -> #DIV/0! | F48: ='ANTROPOMETRÍA DEPORTISTAS'!D44 -> #DIV/0! | G48: ='ANTROPOMETRÍA DEPORTISTAS'!E44 -> #DIV/0! | H48: ='ANTROPOMETRÍA DEPORTISTAS'!F44 -> #DIV/0! | I48: ='ANTROPOMETRÍA DEPORTISTAS'!G44 -> #DIV/0! | J48: ='ANTROPOMETRÍA DEPORTISTAS'!H44 -> #DIV/0! | K48: ='ANTROPOMETRÍA DEPORTISTAS'!I44 -> #DIV/0! | ... N48: ='ANTROPOMETRÍA DEPORTISTAS'!L44 -> #DIV/0!
B49: Contextura | D49: ='ANTROPOMETRÍA DEPORTISTAS'!B45 -> #DIV/0! | E49: ='ANTROPOMETRÍA DEPORTISTAS'!C45 -> #DIV/0! | F49: ='ANTROPOMETRÍA DEPORTISTAS'!D45 -> #DIV/0! | G49: ='ANTROPOMETRÍA DEPORTISTAS'!E45 -> #DIV/0! | H49: ='ANTROPOMETRÍA DEPORTISTAS'!F45 -> #DIV/0! | I49: ='ANTROPOMETRÍA DEPORTISTAS'!G45 -> #DIV/0! | J49: ='ANTROPOMETRÍA DEPORTISTAS'!H45 -> #DIV/0! | K49: ='ANTROPOMETRÍA DEPORTISTAS'!I45 -> #DIV/0! | ... N49: ='ANTROPOMETRÍA DEPORTISTAS'!L45 -> #DIV/0!

Sheet Feedback
E3: Evaluación | G3: 2 | H3: 3 | I3: 3 | J3: 4 | K3: 5
E4: Fecha:
E5: Cumplimiento 1/10
E6: Observaciones:

Sheet DATOS ANTROPOMÉTRICOS
A14: DATOS ANTROPOMETRICOS
B16: FECHA DE EVALUACION
A17: BASICOS
A18: Peso (kg)
A19: Talla (cm)
A20: PLIEGUES CUTANEOS (mm)
A21: Tríceps
A22: Subescapular
A23: Bíceps
A24: Cresta Iliaca
A25: Supraespinal
A26: Abdominal
A27: Muslo Frontal
A28: Pantorrilla Medial
... A38: ESTIMACIÓN DE VARIABLES ANTROPOMETRICAS
A39: % Grasa Durning & W. (adultos 17 años y mas) | B39: =IF(HISTORIA!C10="masculino",(495/(1.1765-(0.0744*LOG10(B21+B22+B23+B24)))-450),(495/(1.1567-(0.0717*LOG10(B21+B22+B23+B24)))-450)) -> #NUM! | C39: =IF(HISTORIA!C10="masculino",(495/(1.1765-(0.0744*LOG10(C21+C22+C23+C24)))-450),(495/(1.1567-(0.0717*LOG10(C21+C22+C23+C24)))-450)) -> #NUM! | D39: =IF(HISTORIA!C10="masculino",(495/(1.1765-(0.0744*LOG10(D21+D22+D23+D24)))-450),(495/(1.1567-(0.0717*LOG10(D21+D22+D23+D24)))-450)) -> #NUM! | E39: =IF(HISTORIA!C10="masculino",(495/(1.1765-(0.0744*LOG10(E21+E22+E23+E24)))-450),(495/(1.1567-(0.0717*LOG10(E21+E22+E23+E24)))-450)) -> #NUM! | F39: =IF(HISTORIA!C10="masculino",(495/(1.1765-(0.0744*LOG10(F21+F22+F23+F24)))-450),(495/(1.1567-(0.0717*LOG10(F21+F22+F23+F24)))-450)) -> #NUM! | G39: =IF(HISTORIA!C10="masculino",(495/(1.1765-(0.0744*LOG10(G21+G22+G23+G24)))-450),(495/(1.1567-(0.0717*LOG10(G21+G22+G23+G24)))-450)) -> #NUM! | H39: =IF(HISTORIA!C10="masculino",(495/(1.1765-(0.0744*LOG10(H21+H22+H23+H24)))-450),(495/(1.1567-(0.0717*LOG10(H21+H22+H23+H24)))-450)) -> #NUM! | I39: =IF(HISTORIA!C10="masculino",(495/(1.1765-(0.0744*LOG10(I21+I22+I23+I24)))-450),(495/(1.1567-(0.0717*LOG10(I21+I22+I23+I24)))-450)) -> #NUM! | J39: =IF(HISTORIA!C10="masculino",(495/(1.1765-(0.0744*LOG10(J21+J22+J23+J24)))-450),(495/(1.1567-(0.0717*LOG10(J21+J22+J23+J24)))-450)) -> #NUM! | K39: =IF(HISTORIA!C10="masculino",(495/(1.1765-(0.0744*LOG10(K21+K22+K23+K24)))-450),(495/(1.1567-(0.0717*LOG10(K21+K22+K23+K24)))-450)) -> #NUM! | L39: =IF(HISTORIA!C10="masculino",(495/(1.1765-(0.0744*LOG10(L21+L22+L23+L24)))-450),(495/(1.1567-(0.0717*LOG10(L21+L22+L23+L24)))-450)) -> #NUM! | M39: =IF(HISTORIA!C10="masculino",(495/(1.1765-(0.0744*LOG10(M21+M22+M23+M24)))-450),(495/(1.1567-(0.0717*LOG10(M21+M22+M23+M24)))-450)) -> #NUM!
A40: % Grasa Carter-Yuhasz (Atletas) | B40: =IF(HISTORIA!C10="masculino",(0.1051*(B21+B22+B25+B26+B27+B28)+2.585),(0.1548*(B21+B22+B25+B26+B27+B28)+3.58)) -> 3.58 | C40: =IF(HISTORIA!C10="masculino",(0.1051*(C21+C22+C25+C26+C27+C28)+2.585),(0.1548*(C21+C22+C25+C26+C27+C28)+3.58)) -> 3.58 | D40: =IF(HISTORIA!C10="masculino",(0.1051*(D21+D22+D25+D26+D27+D28)+2.585),(0.1548*(D21+D22+D25+D26+D27+D28)+3.58)) -> 3.58 | E40: =IF(HISTORIA!C10="masculino",(0.1051*(E21+E22+E25+E26+E27+E28)+2.585),(0.1548*(E21+E22+E25+E26+E27+E28)+3.58)) -> 3.58 | F40: =IF(HISTORIA!C10="masculino",(0.1051*(F21+F22+F25+F26+F27+F28)+2.585),(0.1548*(F21+F22+F25+F26+F27+F28)+3.58)) -> 3.58 | G40: =IF(HISTORIA!C10="masculino",(0.1051*(G21+G22+G25+G26+G27+G28)+2.585),(0.1548*(G21+G22+G25+G26+G27+G28)+3.58)) -> 3.58 | H40: =IF(HISTORIA!C10="masculino",(0.1051*(H21+H22+H25+H26+H27+H28)+2.585),(0.1548*(H21+H22+H25+H26+H27+H28)+3.58)) -> 3.58 | I40: =IF(HISTORIA!C10="masculino",(0.1051*(I21+I22+I25+I26+I27+I28)+2.585),(0.1548*(I21+I22+I25+I26+I27+I28)+3.58)) -> 3.58 | J40: =IF(HISTORIA!C10="masculino",(0.1051*(J21+J22+J25+J26+J27+J28)+2.585),(0.1548*(J21+J22+J25+J26+J27+J28)+3.58)) -> 3.58 | K40: =IF(HISTORIA!C10="masculino",(0.1051*(K21+K22+K25+K26+K27+K28)+2.585),(0.1548*(K21+K22+K25+K26+K27+K28)+3.58)) -> 3.58 | L40: =IF(HISTORIA!C10="masculino",(0.1051*(L21+L22+L25+L26+L27+L28)+2.585),(0.1548*(L21+L22+L25+L26+L27+L28)+3.58)) -> 3.58 | M40: =IF(HISTORIA!C10="masculino",(0.1051*(M21+M22+M25+M26+M27+M28)+2.585),(0.1548*(M21+M22+M25+M26+M27+M28)+3.58)) -> 3.58
A41: % Grasa Durnin ADULTOS | B41: =(((0.2467)*(B21+B22++B23+B24))+((0.12*B32)))+4.98 -> 4.98 | C41: =(((0.2467)*(C21+C22++C23+C24))+((0.12*C32)))+4.98 -> 4.98 | D41: =(((0.2467)*(D21+D22++D23+D24))+((0.12*D32)))+4.98 -> 4.98 | E41: =(((0.2467)*(E21+E22++E23+E24))+((0.12*E32)))+4.98 -> 4.98 | F41: =(((0.2467)*(F21+F22++F23+F24))+((0.12*F32)))+4.98 -> 4.98 | G41: =(((0.2467)*(G21+G22++G23+G24))+((0.12*G32)))+4.98 -> 4.98 | H41: =(((0.2467)*(H21+H22++H23+H24))+((0.12*H32)))+4.98 -> 4.98 | I41: =(((0.2467)*(I21+I22++I23+I24))+((0.12*I32)))+4.98 -> 4.98 | ... M41: =(((0.2467)*(M21+M22++M23+M24))+((0.12*M32)))+4.98 -> 4.98
A42: % Grasa Brook (1-11 años) | B42: =IF(HISTORIA!C10="masculino",(530/(1.169-(0.078*LOG10(B21+B22+B23+B25)))-489),(530/(1.2063-(0.0999*LOG10(B21+B22+B23+B25)))-489)) -> #NUM! | C42: =IF(HISTORIA!C10="masculino",(530/(1.169-(0.078*LOG10(C21+C22+C23+C25)))-489),(530/(1.2063-(0.0999*LOG10(C21+C22+C23+C25)))-489)) -> #NUM! | D42: =IF(HISTORIA!C10="masculino",(530/(1.169-(0.078*LOG10(D21+D22+D23+D25)))-489),(530/(1.2063-(0.0999*LOG10(D21+D22+D23+D25)))-489)) -> #NUM! | E42: =IF(HISTORIA!C10="masculino",(530/(1.169-(0.078*LOG10(E21+E22+E23+E25)))-489),(530/(1.2063-(0.0999*LOG10(E21+E22+E23+E25)))-489)) -> #NUM! | F42: =IF(HISTORIA!C10="masculino",(530/(1.169-(0.078*LOG10(F21+F22+F23+F25)))-489),(530/(1.2063-(0.0999*LOG10(F21+F22+F23+F25)))-489)) -> #NUM! | G42: =IF(HISTORIA!C10="masculino",(530/(1.169-(0.078*LOG10(G21+G22+G23+G25)))-489),(530/(1.2063-(0.0999*LOG10(G21+G22+G23+G25)))-489)) -> #NUM! | H42: =IF(HISTORIA!C10="masculino",(530/(1.169-(0.078*LOG10(H21+H22+H23+H25)))-489),(530/(1.2063-(0.0999*LOG10(H21+H22+H23+H25)))-489)) -> #NUM! | I42: =IF(HISTORIA!C10="masculino",(530/(1.169-(0.078*LOG10(I21+I22+I23+I25)))-489),(530/(1.2063-(0.0999*LOG10(I21+I22+I23+I25)))-489)) -> #NUM! | J42: =IF(HISTORIA!C10="masculino",(530/(1.169-(0.078*LOG10(J21+J22+J23+J25)))-489),(530/(1.2063-(0.0999*LOG10(J21+J22+J23+J25)))-489)) -> #NUM! | K42: =IF(HISTORIA!C10="masculino",(530/(1.169-(0.078*LOG10(K21+K22+K23+K25)))-489),(530/(1.2063-(0.0999*LOG10(K21+K22+K23+K25)))-489)) -> #NUM! | L42: =IF(HISTORIA!C10="masculino",(530/(1.169-(0.078*LOG10(L21+L22+L23+L25)))-489),(530/(1.2063-(0.0999*LOG10(L21+L22+L23+L25)))-489)) -> #NUM! | M42: =IF(HISTORIA!C10="masculino",(530/(1.169-(0.078*LOG10(M21+M22+M23+M25)))-489),(530/(1.2063-(0.0999*LOG10(M21+M22+M23+M25)))-489)) -> #NUM!
A43: % Grasa Durnin (12-16 años) | B43: =IF(HISTORIA!C10="masculino",(530/(1.1533-(0.0643*LOG10(B21+B22+B23+B25)))-489),(530/(1.1369-(0.0598*LOG10(B21+B22+B23+B25)))-489)) -> #NUM! | C43: =IF(HISTORIA!C10="masculino",(530/(1.1533-(0.0643*LOG10(C21+C22+C23+C25)))-489),(530/(1.1369-(0.0598*LOG10(C21+C22+C23+C25)))-489)) -> #NUM! | D43: =IF(HISTORIA!C10="masculino",(530/(1.1533-(0.0643*LOG10(D21+D22+D23+D25)))-489),(530/(1.1369-(0.0598*LOG10(D21+D22+D23+D25)))-489)) -> #NUM! | E43: =IF(HISTORIA!C10="masculino",(530/(1.1533-(0.0643*LOG10(E21+E22+E23+E25)))-489),(530/(1.1369-(0.0598*LOG10(E21+E22+E23+E25)))-489)) -> #NUM! | F43: =IF(HISTORIA!C10="masculino",(530/(1.1533-(0.0643*LOG10(F21+F22+F23+F25)))-489),(530/(1.1369-(0.0598*LOG10(F21+F22+F23+F25)))-489)) -> #NUM! | G43: =IF(HISTORIA!C10="masculino",(530/(1.1533-(0.0643*LOG10(G21+G22+G23+G25)))-489),(530/(1.1369-(0.0598*LOG10(G21+G22+G23+G25)))-489)) -> #NUM! | H43: =IF(HISTORIA!C10="masculino",(530/(1.1533-(0.0643*LOG10(H21+H22+H23+H25)))-489),(530/(1.1369-(0.0598*LOG10(H21+H22+H23+H25)))-489)) -> #NUM! | I43: =IF(HISTORIA!C10="masculino",(530/(1.1533-(0.0643*LOG10(I21+I22+I23+I25)))-489),(530/(1.1369-(0.0598*LOG10(I21+I22+I23+I25)))-489)) -> #NUM! | J43: =IF(HISTORIA!C10="masculino",(530/(1.1533-(0.0643*LOG10(J21+J22+J23+J25)))-489),(530/(1.1369-(0.0598*LOG10(J21+J22+J23+J25)))-489)) -> #NUM! | K43: =IF(HISTORIA!C10="masculino",(530/(1.1533-(0.0643*LOG10(K21+K22+K23+K25)))-489),(530/(1.1369-(0.0598*LOG10(K21+K22+K23+K25)))-489)) -> #NUM! | L43: =IF(HISTORIA!C10="masculino",(530/(1.1533-(0.0643*LOG10(L21+L22+L23+L25)))-489),(530/(1.1369-(0.0598*LOG10(L21+L22+L23+L25)))-489)) -> #NUM! | M43: =IF(HISTORIA!C10="masculino",(530/(1.1533-(0.0643*LOG10(M21+M22+M23+M25)))-489),(530/(1.1369-(0.0598*LOG10(M21+M22+M23+M25)))-489)) -> #NUM!
A44: % Grasa Seleccionado | B44: 22.4 | C44: 31.8
A45: % Grasa Minimo Permitido | B45: 15 | C45: 15
A46: % Grasa Maximo Permitido | B46: 20 | C46: 20
A47: Peso de la Grasa (pg) | B47: =(B18*(B44/100)) -> 0 | C47: =(C18*(C44/100)) -> 0 | D47: =(D18*(D44/100)) -> 0 | E47: =(E18*(E44/100)) -> 0 | F47: =(F18*(F44/100)) -> 0 | G47: =(G18*(G44/100)) -> 0 | H47: =(H18*(H44/100)) -> 0 | I47: =(I18*(I44/100)) -> 0 | ... M47: =(M18*(M44/100)) -> 0
A48: Peso Magro (pm) | B48: =B18-B47 -> 0 | C48: =C18-C47 -> 0 | D48: =D18-D47 -> 0 | E48: =E18-E47 -> 0 | F48: =F18-F47 -> 0 | G48: =G18-G47 -> 0 | H48: =H18-H47 -> 0 | I48: =I18-I47 -> 0 | ... M48: =M18-M47 -> 0
A49: % Peso Magro (%pm) | B49: =(B48*100)/B18 -> #DIV/0! | C49: =(C48*100)/C18 -> #DIV/0! | D49: =(D48*100)/D18 -> #DIV/0! | E49: =(E48*100)/E18 -> #DIV/0! | F49: =(F48*100)/F18 -> #DIV/0! | G49: =(G48*100)/G18 -> #DIV/0! | H49: =(H48*100)/H18 -> #DIV/0! | I49: =(I48*100)/I18 -> #DIV/0! | ... M49: =(M48*100)/M18 -> #DIV/0!
A50: Indice de Masa Corporal (IMC) | B50: =B18/(POWER(B19/100,2)) -> #DIV/0! | C50: =C18/(POWER(C19/100,2)) -> #DIV/0! | D50: =D18/(POWER(D19/100,2)) -> #DIV/0! | E50: =E18/(POWER(E19/100,2)) -> #DIV/0! | F50: =F18/(POWER(F19/100,2)) -> #DIV/0! | G50: =G18/(POWER(G19/100,2)) -> #DIV/0! | H50: =H18/(POWER(H19/100,2)) -> #DIV/0! | I50: =I18/(POWER(I19/100,2)) -> #DIV/0! | ... M50: =M18/(POWER(M19/100,2)) -> #DIV/0!
A51: Relacion Cintura/Cadera (ICC) | B51: =B32/B33 -> #DIV/0! | C51: =C32/C33 -> #DIV/0! | D51: =D32/D33 -> #DIV/0! | E51: =E32/E33 -> #DIV/0! | F51: =F32/F33 -> #DIV/0! | G51: =G32/G33 -> #DIV/0! | H51: =H32/H33 -> #DIV/0! | I51: =I32/I33 -> #DIV/0! | ... M51: =M32/M33 -> #DIV/0!
A52: Adiposidad Relativa (AR) | B52: =(B21+B22+B24+B26+B27+B28)*(170.18/B19) -> #DIV/0! | C52: =(C21+C22+C24+C26+C27+C28)*(170.18/C19) -> #DIV/0! | D52: =(D21+D22+D24+D26+D27+D28)*(170.18/D19) -> #DIV/0! | E52: =(E21+E22+E24+E26+E27+E28)*(170.18/E19) -> #DIV/0! | F52: =(F21+F22+F24+F26+F27+F28)*(170.18/F19) -> #DIV/0! | G52: =(G21+G22+G24+G26+G27+G28)*(170.18/G19) -> #DIV/0! | H52: =(H21+H22+H24+H26+H27+H28)*(170.18/H19) -> #DIV/0! | I52: =(I21+I22+I24+I26+I27+I28)*(170.18/I19) -> #DIV/0! | ... M52: =(M21+M22+M24+M26+M27+M28)*(170.18/M19) -> #DIV/0!
A53: Peso Proporcional (PP) | B53: =B18*(POWER(170.18/B19,3)) -> #DIV/0! | C53: =C18*(POWER(170.18/C19,3)) -> #DIV/0! | D53: =D18*(POWER(170.18/D19,3)) -> #DIV/0! | E53: =E18*(POWER(170.18/E19,3)) -> #DIV/0! | F53: =F18*(POWER(170.18/F19,3)) -> #DIV/0! | G53: =G18*(POWER(170.18/G19,3)) -> #DIV/0! | H53: =H18*(POWER(170.18/H19,3)) -> #DIV/0! | I53: =I18*(POWER(170.18/I19,3)) -> #DIV/0! | ... M53: =M18*(POWER(170.18/M19,3)) -> #DIV/0!
A54: Sumatoria de 4 Pliegues | B54: =B21+B22+B23+B24 -> 0 | C54: =C21+C22+C23+C24 -> 0 | D54: =D21+D22+D23+D24 -> 0 | E54: =E21+E22+E23+E24 -> 0 | F54: =F21+F22+F23+F24 -> 0 | G54: =G21+G22+G23+G24 -> 0 | H54: =H21+H22+H23+H24 -> 0 | I54: =I21+I22+I23+I24 -> 0 | ... M54: =M21+M22+M23+M24 -> 0
A55: Sumatoria de 6 Pliegues | B55: =B21+B22+B25+B26+B27+B28 -> 0 | C55: =C21+C22+C25+C26+C27+C28 -> 0 | D55: =D21+D22+D25+D26+D27+D28 -> 0 | E55: =E21+E22+E25+E26+E27+E28 -> 0 | F55: =F21+F22+F25+F26+F27+F28 -> 0 | G55: =G21+G22+G25+G26+G27+G28 -> 0 | H55: =H21+H22+H25+H26+H27+H28 -> 0 | I55: =I21+I22+I25+I26+I27+I28 -> 0 | ... M55: =M21+M22+M25+M26+M27+M28 -> 0
A56: Sumatoria de 8 Pliegues | B56: =SUM(B21:B28) -> 0 | C56: =SUM(C21:C28) -> 0 | D56: =SUM(D21:D28) -> 0 | E56: =SUM(E21:E28) -> 0 | F56: =SUM(F21:F28) -> 0 | G56: =SUM(G21:G28) -> 0 | H56: =SUM(H21:H28) -> 0 | I56: =SUM(I21:I28) -> 0 | ... M56: =SUM(M21:M28) -> 0
A57: PESO
A58: Peso Minimo Permitido | B58: =(B48*100)/(100-B45) -> 0 | C58: =(C48*100)/(100-C45) -> 0 | D58: =(D48*100)/(100-D45) -> 0 | E58: =(E48*100)/(100-E45) -> 0 | F58: =(F48*100)/(100-F45) -> 0 | G58: =(G48*100)/(100-G45) -> 0 | H58: =(H48*100)/(100-H45) -> 0 | I58: =(I48*100)/(100-I45) -> 0 | ... M58: =(M48*100)/(100-M45) -> 0
A59: Peso Maximo Permitido | B59: =(B48*100)/(100-B46) -> 0 | C59: =(C48*100)/(100-C46) -> 0 | D59: =(D48*100)/(100-D46) -> 0 | E59: =(E48*100)/(100-E46) -> 0 | F59: =(F48*100)/(100-F46) -> 0 | G59: =(G48*100)/(100-G46) -> 0 | H59: =(H48*100)/(100-H46) -> 0 | I59: =(I48*100)/(100-I46) -> 0 | ... M59: =(M48*100)/(100-M46) -> 0
A60: Peso Objetivo | B60: 84 | C60: 84
A61: Kg a Subir o Bajar | B61: =B18-B60 -> -84 | C61: =C18-C60 -> -84 | D61: =D18-D60 -> 0 | E61: =E18-E60 -> 0 | F61: =F18-F60 -> 0 | G61: =G18-G60 -> 0 | H61: =H18-H60 -> 0 | I61: =I18-I60 -> 0 | ... M61: =M18-M60 -> 0
A62: SOMATOTIPO
A63: Endomorfia | B63: =(0.1451*((B21+B22+B25)*(170.18/B19)))-(0.00068* POWER(((B21+B22+B25)*(170.18/B19)),2))+(0.00000014*POWER(((B21+B22+B25)*(170.18/B19)),3))-0.7182 -> #DIV/0! | C63: =(0.1451*((C21+C22+C25)*(170.18/C19)))-(0.00068* POWER(((C21+C22+C25)*(170.18/C19)),2))+(0.00000014*POWER(((C21+C22+C25)*(170.18/C19)),3))-0.7182 -> #DIV/0! | D63: =(0.1451*((D21+D22+D25)*(170.18/D19)))-(0.00068* POWER(((D21+D22+D25)*(170.18/D19)),2))+(0.00000014*POWER(((D21+D22+D25)*(170.18/D19)),3))-0.7182 -> #DIV/0! | E63: =(0.1451*((E21+E22+E25)*(170.18/E19)))-(0.00068* POWER(((E21+E22+E25)*(170.18/E19)),2))+(0.00000014*POWER(((E21+E22+E25)*(170.18/E19)),3))-0.7182 -> #DIV/0! | F63: =(0.1451*((F21+F22+F25)*(170.18/F19)))-(0.00068* POWER(((F21+F22+F25)*(170.18/F19)),2))+(0.00000014*POWER(((F21+F22+F25)*(170.18/F19)),3))-0.7182 -> #DIV/0! | G63: =(0.1451*((G21+G22+G25)*(170.18/G19)))-(0.00068* POWER(((G21+G22+G25)*(170.18/G19)),2))+(0.00000014*POWER(((G21+G22+G25)*(170.18/G19)),3))-0.7182 -> #DIV/0! | H63: =(0.1451*((H21+H22+H25)*(170.18/H19)))-(0.00068* POWER(((H21+H22+H25)*(170.18/H19)),2))+(0.00000014*POWER(((H21+H22+H25)*(170.18/H19)),3))-0.7182 -> #DIV/0! | I63: =(0.1451*((I21+I22+I25)*(170.18/I19)))-(0.00068* POWER(((I21+I22+I25)*(170.18/I19)),2))+(0.00000014*POWER(((I21+I22+I25)*(170.18/I19)),3))-0.7182 -> #DIV/0! | ... M63: =(0.1451*((M21+M22+M25)*(170.18/M19)))-(0.00068* POWER(((M21+M22+M25)*(170.18/M19)),2))+(0.00000014*POWER(((M21+M22+M25)*(170.18/M19)),3))-0.7182 -> #DIV/0!
A64: Mesomorfia | B64: =(0.858*B36)+(0.601*B37)+(0.188*(B31-(B21/10)))+(0.161*(B34-(B28/10)))-(0.131*B19)+4.5 -> 4.5 | C64: =(0.858*C36)+(0.601*C37)+(0.188*(C31-(C21/10)))+(0.161*(C34-(C28/10)))-(0.131*C19)+4.5 -> 4.5 | D64: =(0.858*D36)+(0.601*D37)+(0.188*(D31-(D21/10)))+(0.161*(D34-(D28/10)))-(0.131*D19)+4.5 -> 4.5 | E64: =(0.858*E36)+(0.601*E37)+(0.188*(E31-(E21/10)))+(0.161*(E34-(E28/10)))-(0.131*E19)+4.5 -> 4.5 | F64: =(0.858*F36)+(0.601*F37)+(0.188*(F31-(F21/10)))+(0.161*(F34-(F28/10)))-(0.131*F19)+4.5 -> 4.5 | G64: =(0.858*G36)+(0.601*G37)+(0.188*(G31-(G21/10)))+(0.161*(G34-(G28/10)))-(0.131*G19)+4.5 -> 4.5 | H64: =(0.858*H36)+(0.601*H37)+(0.188*(H31-(H21/10)))+(0.161*(H34-(H28/10)))-(0.131*H19)+4.5 -> 4.5 | I64: =(0.858*I36)+(0.601*I37)+(0.188*(I31-(I21/10)))+(0.161*(I34-(I28/10)))-(0.131*I19)+4.5 -> 4.5 | ... M64: =(0.858*M36)+(0.601*M37)+(0.188*(M31-(M21/10)))+(0.161*(M34-(M28/10)))-(0.131*M19)+4.5 -> 4.5
A65: Ectomorfia | B65: =IF(B66>=40.75,(B66*0.732)-28.58,IF(AND(B66<40.15,B66>38.25),(B66*0.463)-17.63,IF(B66<=38.25,0.1))) -> #DIV/0! | C65: =IF(C66>=40.75,(C66*0.732)-28.58,IF(AND(C66<40.15,C66>38.25),(C66*0.463)-17.63,IF(C6<=38.25,0.1))) -> #DIV/0! | D65: =IF(D66>=40.75,(D66*0.732)-28.58,IF(AND(D66<40.15,D66>38.25),(D66*0.463)-17.63,IF(D6<=38.25,0.1))) -> #DIV/0! | E65: =IF(E66>=40.75,(E66*0.732)-28.58,IF(AND(E66<40.15,E66>38.25),(E66*0.463)-17.63,IF(E6<=38.25,0.1))) -> #DIV/0! | F65: =IF(F66>=40.75,(F66*0.732)-28.58,IF(AND(F66<40.15,F66>38.25),(F66*0.463)-17.63,IF(F6<=38.25,0.1))) -> #DIV/0! | G65: =IF(G66>=40.75,(G66*0.732)-28.58,IF(AND(G66<40.15,G66>38.25),(G66*0.463)-17.63,IF(G6<=38.25,0.1))) -> #DIV/0! | H65: =IF(H66>=40.75,(H66*0.732)-28.58,IF(AND(H66<40.15,H66>38.25),(H66*0.463)-17.63,IF(H6<=38.25,0.1))) -> #DIV/0! | I65: =IF(I66>=40.75,(I66*0.732)-28.58,IF(AND(I66<40.15,I66>38.25),(I66*0.463)-17.63,IF(I6<=38.25,0.1))) -> #DIV/0! | J65: =IF(J66>=40.75,(J66*0.732)-28.58,IF(AND(J66<40.15,J66>38.25),(J66*0.463)-17.63,IF(J6<=38.25,0.1))) -> #DIV/0! | ... M65: =IF(M66>=40.75,(M66*0.732)-28.58,IF(AND(M66<40.15,M66>38.25),(M66*0.463)-17.63,IF(M6<=38.25,0.1))) -> #DIV/0!
A66: HWR* | B66: =B19/POWER(B18,1/3) -> #DIV/0! | C66: =C19/POWER(C18,1/3) -> #DIV/0! | D66: =D19/POWER(D18,1/3) -> #DIV/0! | E66: =E19/POWER(E18,1/3) -> #DIV/0! | F66: =F19/POWER(F18,1/3) -> #DIV/0! | G66: =G19/POWER(G18,1/3) -> #DIV/0! | H66: =H19/POWER(H18,1/3) -> #DIV/0! | I66: =I19/POWER(I18,1/3) -> #DIV/0! | ... M66: =M19/POWER(M18,1/3) -> #DIV/0!
A84: FEMENINO
A85: MASCULINO

Sheet SOMATOCARTA
A14: ANÁLISIS ANTROPOMÉTRICO
B15: Fecha | C15: Endomorfia | D15: Mesomorfia | E15: Ectomorfia | F15: Coodenada X | G15: Coordanda Y
B16: ='DATOS ANTROPOMÉTRICOS'!B17 -> 0 | C16: ='DATOS ANTROPOMÉTRICOS'!B63 -> #DIV/0! | D16: ='DATOS ANTROPOMÉTRICOS'!B64 -> 4.5 | E16: ='DATOS ANTROPOMÉTRICOS'!B65 -> #DIV/0! | F16: =E16-C16 -> #DIV/0! | G16: =(2*D16)-(E16+C16) -> #DIV/0!
B17: ='DATOS ANTROPOMÉTRICOS'!C17 -> 0 | C17: ='DATOS ANTROPOMÉTRICOS'!C63 -> #DIV/0! | D17: ='DATOS ANTROPOMÉTRICOS'!C64 -> 4.5 | E17: ='DATOS ANTROPOMÉTRICOS'!C65 -> #DIV/0! | F17: =E17-C17 -> #DIV/0! | G17: =(2*D17)-(E17+C17) -> #DIV/0!
B18: ='DATOS ANTROPOMÉTRICOS'!D17 -> 0 | C18: ='DATOS ANTROPOMÉTRICOS'!D63 -> #DIV/0! | D18: ='DATOS ANTROPOMÉTRICOS'!D64 -> 4.5 | E18: ='DATOS ANTROPOMÉTRICOS'!D65 -> #DIV/0! | F18: =E18-C18 -> #DIV/0! | G18: =(2*D18)-(E18+C18) -> #DIV/0!
B19: ='DATOS ANTROPOMÉTRICOS'!B20 -> 0 | C19: ='DATOS ANTROPOMÉTRICOS'!D63 -> #DIV/0! | D19: ='DATOS ANTROPOMÉTRICOS'!E64 -> 4.5 | E19: ='DATOS ANTROPOMÉTRICOS'!E65 -> #DIV/0! | F19: =E19-C19 -> #DIV/0! | G19: =(2*D19)-(E19+C19) -> #DIV/0!
B20: ='DATOS ANTROPOMÉTRICOS'!E17 -> 0 | C20: ='DATOS ANTROPOMÉTRICOS'!E63 -> #DIV/0! | D20: ='DATOS ANTROPOMÉTRICOS'!F64 -> 4.5 | E20: ='DATOS ANTROPOMÉTRICOS'!E65 -> #DIV/0! | F20: =E20-C20 -> #DIV/0! | G20: =(2*D20)-(E20+C20) -> #DIV/0!
B21: ='DATOS ANTROPOMÉTRICOS'!F17 -> 0 | C21: ='DATOS ANTROPOMÉTRICOS'!F63 -> #DIV/0! | D21: ='DATOS ANTROPOMÉTRICOS'!G64 -> 4.5 | E21: ='DATOS ANTROPOMÉTRICOS'!F65 -> #DIV/0! | F21: =E21-C21 -> #DIV/0! | G21: =(2*D21)-(E21+C21) -> #DIV/0!
B22: ='DATOS ANTROPOMÉTRICOS'!G17 -> 0 | C22: ='DATOS ANTROPOMÉTRICOS'!G63 -> #DIV/0! | D22: ='DATOS ANTROPOMÉTRICOS'!F64 -> 4.5 | E22: ='DATOS ANTROPOMÉTRICOS'!G65 -> #DIV/0! | F22: =E22-C22 -> #DIV/0! | G22: =(2*D22)-(E22+C22) -> #DIV/0!
B23: ='DATOS ANTROPOMÉTRICOS'!H17 -> 0 | C23: ='DATOS ANTROPOMÉTRICOS'!H63 -> #DIV/0! | D23: ='DATOS ANTROPOMÉTRICOS'!H64 -> 4.5 | E23: ='DATOS ANTROPOMÉTRICOS'!H65 -> #DIV/0! | F23: =E23-C23 -> #DIV/0! | G23: =(2*D23)-(E23+C23) -> #DIV/0!
B24: ='DATOS ANTROPOMÉTRICOS'!I17 -> 0 | C24: ='DATOS ANTROPOMÉTRICOS'!I63 -> #DIV/0! | D24: ='DATOS ANTROPOMÉTRICOS'!I64 -> 4.5 | E24: ='DATOS ANTROPOMÉTRICOS'!I65 -> #DIV/0! | F24: =E24-C24 -> #DIV/0! | G24: =(2*D24)-(E24+C24) -> #DIV/0!
B25: ='DATOS ANTROPOMÉTRICOS'!J17 -> 0 | C25: ='DATOS ANTROPOMÉTRICOS'!J63 -> #DIV/0! | D25: ='DATOS ANTROPOMÉTRICOS'!J64 -> 4.5 | E25: ='DATOS ANTROPOMÉTRICOS'!J65 -> #DIV/0! | F25: =E25-C25 -> #DIV/0! | G25: =(2*D25)-(E25+C25) -> #DIV/0!
B26: ='DATOS ANTROPOMÉTRICOS'!K17 -> 0 | C26: ='DATOS ANTROPOMÉTRICOS'!K63 -> #DIV/0! | D26: ='DATOS ANTROPOMÉTRICOS'!K64 -> 4.5 | E26: ='DATOS ANTROPOMÉTRICOS'!K65 -> #DIV/0! | F26: =E26-C26 -> #DIV/0! | G26: =(2*D26)-(E26+C26) -> #DIV/0!

Sheet INFORME 2 COMPONENTES PEDIATRIA
A4: INFORME NUTRICIONAL ANTROPOMÉTRICO
E5: 2 COMPONENTES
A7: DATOS PERSONALES
A9: Nombre y Apellido | C9: =HISTORIA!C4 -> 0 | E9: Fecha de Nacimiento | G9: =HISTORIA!C8 -> 0 | I9: Deporte
A11: MEDICIONES CORPORALES
A12: Numero de Evaluacion | C12: 1 | E12: 2 | G12: 3 | I12: 4
A13: Fecha de Evaluacion
A14: BASICAS
A15: Peso (kg) | B15: Peso (kg)
A16: Talla (cm) | B16: Talla (cm)
A17: PLIEGUES CUTÁNEOS (mm)
A18: Tricep | B18: Tricep
A19: Subescapular | B19: Subescapular
A20: Bícep | B20: Bícep
A21: Cresta Ilíaca | B21: Cresta Ilíaca
A22: Supraespinal | B22: Supraespinal
A23: Abdominal | B23: Abdominal
A24: Muslo Medio | B24: Muslo Medio
A25: Pantorrilla | B25: Pantorrilla
A26: CIRCUNFERENCIAS (cm)
A27: Brazo relajado | B27: Brazo relajado
A28: Brazo flexionado | B28: Brazo flexionado en tensión
A29: Cintura (Mínimo) | B29: Cintura (Mínimo)
A30: Cadera (Máximo) | B30: Cadera (Máximo)
A31: Muslo máximo | B31: Muslo máximo
A32: Muslo medio | B32: Muslo medio
A33: Pantorrilla | B33: Pantorrilla
A34: RESULTADOS DE COMPOSICIÓN CORPORAL - METODO DE 2 COMPONENTES
A35: Indicadores | C35: 1 | E35: 2 | G35: 3 | I35: 4
C36: Valor | D36: Categoria | E36: Valor | F36: Categoria | G36: Valor | H36: Categoria | I36: Valor | J36: Categoria
A37: % Grasa Brook (1-11 años) | C37: =IF($A37="% Grasa (Durnin y W., 1974)",#REF!,IF($A37="% Grasa (Carter, 1986)",#REF!,IF($A37="% Grasa Brook (1-11 años)",#REF!,IF($A37="% Grasa Durnin (12-16 años)",#REF!)))) -> #REF! | E37: =IF($A37="% Grasa (Durnin y W., 1974)",#REF!,IF($A37="% Grasa (Carter, 1986)",#REF!,IF($A37="% Grasa Brook (1-11 años)",#REF!,IF($A37="% Grasa Durnin (12-16 años)",#REF!)))) -> #REF! | G37: =IF($A37="% Grasa (Durnin y W., 1974)",#REF!,IF($A37="% Grasa (Carter, 1986)",#REF!,IF($A37="% Grasa Brook (1-11 años)",#REF!,IF($A37="% Grasa Durnin (12-16 años)",#REF!)))) -> #REF! | I37: =IF($A37="% Grasa (Durnin y W., 1974)",#REF!,IF($A37="% Grasa (Carter, 1986)",#REF!,IF($A37="% Grasa Brook (1-11 años)",#REF!,IF($A37="% Grasa Durnin (12-16 años)",#REF!)))) -> #REF!
A38: % Peso Magro | C38: =#REF! -> #REF! | E38: =#REF! -> #REF! | G38: =#REF! -> #REF! | I38: =#REF! -> #REF!
A39: Sum de 8 pliegues (mm) | C39: =IF($A39="Sum de 8 pliegues (mm)",#REF!,IF($A39="Sum de 6 pliegues (mm)",#REF!,IF($A39="Sum de 4 pliegues (mm)",#REF!))) -> #REF! | E39: =IF($A39="Sum de 8 pliegues (mm)",#REF!,IF($A39="Sum de 6 pliegues (mm)",#REF!,IF($A39="Sum de 4 pliegues (mm)",#REF!))) -> #REF! | G39: =IF($A39="Sum de 8 pliegues (mm)",#REF!,IF($A39="Sum de 6 pliegues (mm)",#REF!,IF($A39="Sum de 4 pliegues (mm)",#REF!))) -> #REF! | I39: =IF($A39="Sum de 8 pliegues (mm)",#REF!,IF($A39="Sum de 6 pliegues (mm)",#REF!,IF($A39="Sum de 4 pliegues (mm)",#REF!))) -> #REF!
A40: DAGNOSTICO NUTRICIONAL ANTROPOMÉTRICO
A41: Indicadores | C41: 1 | E41: 2 | G41: 3 | I41: 4
C42: Valor | D42: Categoria | E42: Valor | F42: Categoria | G42: Valor | H42: Categoria | I42: Valor | J42: Categoria
A43: Talla adulta | C43: =#REF! -> #REF! | E43: =#REF! -> #REF! | G43: =#REF! -> #REF! | I43: =#REF! -> #REF!
A44: PGP | C44: =#REF! -> #REF! | E44: =#REF! -> #REF! | G44: =#REF! -> #REF! | I44: =#REF! -> #REF!
A45: Peso/Edad | C45: =#REF! -> #REF! | D45: =IF($C45="+3DE",#REF!,IF($C45="P97 - +3DE",#REF!,IF($C45="P97",#REF!,IF($C45="P90 - P97",#REF!,IF($C45="p90",#REF!,IF($C45="P90 - P50",#REF!,IF($C45="P50",#REF!,IF($C45="P50 - P10",#REF!,IF($C45="P10",#REF!,IF($C45="P10 - P3",#REF!,IF($C45="P3",#REF!,IF($C45="P3 - -3DE",#REF!,IF($C45="-3DE",#REF!,IF($C45="-3DE - -4DE",#REF!,IF($C45="-4DE",#REF!))))))))))))))) -> #REF! | E45: =#REF! -> #REF! | F45: =IF($E45="+3DE",#REF!,IF($E45="P97 - +3DE",#REF!,IF($E45="P97",#REF!,IF($E45="P90 - P97",#REF!,IF($E45="p90",#REF!,IF($E45="P90 - P50",#REF!,IF($E45="P50",#REF!,IF($E45="P50 - P10",#REF!,IF($E45="P10",#REF!,IF($E45="P10 - P3",#REF!,IF($E45="P3",#REF!,IF($E45="P3 - -3DE",#REF!,IF($E45="-3DE",#REF!,IF($E45="-3DE - -4DE",#REF!,IF($E45="-4DE",#REF!))))))))))))))) -> #REF! | G45: =#REF! -> #REF! | H45: =IF($G45="+3DE",#REF!,IF($G45="P97 - +3DE",#REF!,IF($G45="P97",#REF!,IF($G45="P90 - P97",#REF!,IF($G45="p90",#REF!,IF($G45="P90 - P50",#REF!,IF($G45="P50",#REF!,IF($G45="P50 - P10",#REF!,IF($G45="P10",#REF!,IF($G45="P10 - P3",#REF!,IF($G45="P3",#REF!,IF($G45="P3 - -3DE",#REF!,IF($G45="-3DE",#REF!,IF($G45="-3DE - -4DE",#REF!,IF($G45="-4DE",#REF!))))))))))))))) -> #REF! | I45: =#REF! -> #REF! | J45: =IF($I45="+3DE",#REF!,IF($I45="P97 - +3DE",#REF!,IF($I45="P97",#REF!,IF($I45="P90 - P97",#REF!,IF($I45="p90",#REF!,IF($I45="P90 - P50",#REF!,IF($I45="P50",#REF!,IF($I45="P50 - P10",#REF!,IF($I45="P10",#REF!,IF($I45="P10 - P3",#REF!,IF($I45="P3",#REF!,IF($I45="P3 - -3DE",#REF!,IF($I45="-3DE",#REF!,IF($I45="-3DE - -4DE",#REF!,IF($I45="-4DE",#REF!))))))))))))))) -> #REF!
A46: Talla/Edad | C46: =#REF! -> #REF! | D46: =IF($C46="+3DE",#REF!,IF($C46="P97 - +3DE",#REF!,IF($C46="P97",#REF!,IF($C46="P90 - P97",#REF!,IF($C46="p90",#REF!,IF($C46="P90 - P50",#REF!,IF($C46="P50",#REF!,IF($C46="P50 - P10",#REF!,IF($C46="P10",#REF!,IF($C46="P10 - P3",#REF!,IF($C46="P3",#REF!,IF($C46="P3 - -3DE",#REF!,IF($C46="-3DE",#REF!,IF($C46="-3DE - -4DE",#REF!,IF($C46="-4DE",#REF!))))))))))))))) -> #REF! | E46: =#REF! -> #REF! | F46: =IF($E46="+3DE",#REF!,IF($E46="P97 - +3DE",#REF!,IF($E46="P97",#REF!,IF($E46="P90 - P97",#REF!,IF($E46="p90",#REF!,IF($E46="P90 - P50",#REF!,IF($E46="P50",#REF!,IF($E46="P50 - P10",#REF!,IF($E46="P10",#REF!,IF($E46="P10 - P3",#REF!,IF($E46="P3",#REF!,IF($E46="P3 - -3DE",#REF!,IF($E46="-3DE",#REF!,IF($E46="-3DE - -4DE",#REF!,IF($E46="-4DE",#REF!))))))))))))))) -> #REF! | G46: =#REF! -> #REF! | H46: =IF($G46="+3DE",#REF!,IF($G46="P97 - +3DE",#REF!,IF($G46="P97",#REF!,IF($G46="P90 - P97",#REF!,IF($G46="p90",#REF!,IF($G46="P90 - P50",#REF!,IF($G46="P50",#REF!,IF($G46="P50 - P10",#REF!,IF($G46="P10",#REF!,IF($G46="P10 - P3",#REF!,IF($G46="P3",#REF!,IF($G46="P3 - -3DE",#REF!,IF($G46="-3DE",#REF!,IF($G46="-3DE - -4DE",#REF!,IF($G46="-4DE",#REF!))))))))))))))) -> #REF! | I46: =#REF! -> #REF! | J46: =IF($I46="+3DE",#REF!,IF($I46="P97 - +3DE",#REF!,IF($I46="P97",#REF!,IF($I46="P90 - P97",#REF!,IF($I46="p90",#REF!,IF($I46="P90 - P50",#REF!,IF($I46="P50",#REF!,IF($I46="P50 - P10",#REF!,IF($I46="P10",#REF!,IF($I46="P10 - P3",#REF!,IF($I46="P3",#REF!,IF($I46="P3 - -3DE",#REF!,IF($I46="-3DE",#REF!,IF($I46="-3DE - -4DE",#REF!,IF($I46="-4DE",#REF!))))))))))))))) -> #REF!
A47: Peso/Talla | C47: =#REF! -> #REF! | D47: =IF($C47="+3DE",#REF!,IF($C47="P97 - +3DE",#REF!,IF($C47="P97",#REF!,IF($C47="P90 - P97",#REF!,IF($C47="p90",#REF!,IF($C47="P90 - P50",#REF!,IF($C47="P50",#REF!,IF($C47="P50 - P10",#REF!,IF($C47="P10",#REF!,IF($C47="P10 - P3",#REF!,IF($C47="P3",#REF!,IF($C47="P3 - -3DE",#REF!,IF($C47="-3DE",#REF!,IF($C47="-3DE - -4DE",#REF!,IF($C47="-4DE",#REF!))))))))))))))) -> #REF! | E47: =#REF! -> #REF! | F47: =IF($E47="+3DE",#REF!,IF($E47="P97 - +3DE",#REF!,IF($E47="P97",#REF!,IF($E47="P90 - P97",#REF!,IF($E47="p90",#REF!,IF($E47="P90 - P50",#REF!,IF($E47="P50",#REF!,IF($E47="P50 - P10",#REF!,IF($E47="P10",#REF!,IF($E47="P10 - P3",#REF!,IF($E47="P3",#REF!,IF($E47="P3 - -3DE",#REF!,IF($E47="-3DE",#REF!,IF($E47="-3DE - -4DE",#REF!,IF($E47="-4DE",#REF!))))))))))))))) -> #REF! | G47: =#REF! -> #REF! | H47: =IF($G47="+3DE",#REF!,IF($G47="P97 - +3DE",#REF!,IF($G47="P97",#REF!,IF($G47="P90 - P97",#REF!,IF($G47="p90",#REF!,IF($G47="P90 - P50",#REF!,IF($G47="P50",#REF!,IF($G47="P50 - P10",#REF!,IF($G47="P10",#REF!,IF($G47="P10 - P3",#REF!,IF($G47="P3",#REF!,IF($G47="P3 - -3DE",#REF!,IF($G47="-3DE",#REF!,IF($G47="-3DE - -4DE",#REF!,IF($G47="-4DE",#REF!))))))))))))))) -> #REF! | I47: =#REF! -> #REF! | J47: =IF($I47="+3DE",#REF!,IF($I47="P97 - +3DE",#REF!,IF($I47="P97",#REF!,IF($I47="P90 - P97",#REF!,IF($I47="p90",#REF!,IF($I47="P90 - P50",#REF!,IF($I47="P50",#REF!,IF($I47="P50 - P10",#REF!,IF($I47="P10",#REF!,IF($I47="P10 - P3",#REF!,IF($I47="P3",#REF!,IF($I47="P3 - -3DE",#REF!,IF($I47="-3DE",#REF!,IF($I47="-3DE - -4DE",#REF!,IF($I47="-4DE",#REF!))))))))))))))) -> #REF!
A48: IMC/Edad | C48: =#REF! -> #REF! | D48: =IF($C48="+3DE",#REF!,IF($C48="P97 - +3DE",#REF!,IF($C48="P97",#REF!,IF($C48="P90 - P97",#REF!,IF($C48="p90",#REF!,IF($C48="P90 - P50",#REF!,IF($C48="P50",#REF!,IF($C48="P50 - P10",#REF!,IF($C48="P10",#REF!,IF($C48="P10 - P3",#REF!,IF($C48="P3",#REF!,IF($C48="P3 - -3DE",#REF!,IF($C48="-3DE",#REF!,IF($C48="-3DE - -4DE",#REF!,IF($C48="-4DE",#REF!))))))))))))))) -> #REF! | E48: =#REF! -> #REF! | F48: =IF($E48="+3DE",#REF!,IF($E48="P97 - +3DE",#REF!,IF($E48="P97",#REF!,IF($E48="P90 - P97",#REF!,IF($E48="p90",#REF!,IF($E48="P90 - P50",#REF!,IF($E48="P50",#REF!,IF($E48="P50 - P10",#REF!,IF($E48="P10",#REF!,IF($E48="P10 - P3",#REF!,IF($E48="P3",#REF!,IF($E48="P3 - -3DE",#REF!,IF($E48="-3DE",#REF!,IF($E48="-3DE - -4DE",#REF!,IF($E48="-4DE",#REF!))))))))))))))) -> #REF! | G48: =#REF! -> #REF! | H48: =IF($G48="+3DE",#REF!,IF($G48="P97 - +3DE",#REF!,IF($G48="P97",#REF!,IF($G48="P90 - P97",#REF!,IF($G48="p90",#REF!,IF($G48="P90 - P50",#REF!,IF($G48="P50",#REF!,IF($G48="P50 - P10",#REF!,IF($G48="P10",#REF!,IF($G48="P10 - P3",#REF!,IF($G48="P3",#REF!,IF($G48="P3 - -3DE",#REF!,IF($G48="-3DE",#REF!,IF($G48="-3DE - -4DE",#REF!,IF($G48="-4DE",#REF!))))))))))))))) -> #REF! | I48: =#REF! -> #REF! | J48: =IF($I48="+3DE",#REF!,IF($I48="P97 - +3DE",#REF!,IF($I48="P97",#REF!,IF($I48="P90 - P97",#REF!,IF($I48="p90",#REF!,IF($I48="P90 - P50",#REF!,IF($I48="P50",#REF!,IF($I48="P50 - P10",#REF!,IF($I48="P10",#REF!,IF($I48="P10 - P3",#REF!,IF($I48="P3",#REF!,IF($I48="P3 - -3DE",#REF!,IF($I48="-3DE",#REF!,IF($I48="-3DE - -4DE",#REF!,IF($I48="-4DE",#REF!))))))))))))))) -> #REF!
A49: DIAGNOSTICO
A51: SOMATOTIPO (HEATH - CARTER, 1990)
A53: El somatotipo describe numéricamente tus características físicas, qué aspecto tienes como atleta y qué tanto te asemejas a un futbolista promedio. Esto se hace a través de tres números, cada uno representa tu forma física: la gordura o adiposidad (endomorfia), la robustez músculo-esquelética (mesomorfia) y la delgadez (ectomorfia). Dependiendo del deporte que estes realizando y la posición de la misma dichos valores pueden variar de un sujeto a otro. En tu evaluación, los valores obtenidos fueron:
A58: Deporte | D58: Endomorfia | F58: Mesomorfia | H58: Ectomorfia
A59: EDAD
A61: Resultados sujeto evaluado | D61: Ectomorfia | F61: Mesomorfia | H61: Ectomorfia
A62: -1 | D62: =IF($A62=#REF!,#REF!,IF($A62=#REF!,#REF!,IF($A62=#REF!,#REF!,IF($A62=#REF!,#REF!)))) -> #REF! | F62: =IF($A62=#REF!,#REF!,IF($A62=#REF!,#REF!,IF($A62=#REF!,#REF!,IF($A62=#REF!,#REF!)))) -> #REF! | H62: =IF($A62=#REF!,#REF!,IF($A62=#REF!,#REF!,IF($A62=#REF!,#REF!,IF($A62=#REF!,#REF!)))) -> #REF!
D64: Clasificacion
A94: CONCLUSIONES Y RECOMENDACIONES
A99: Protocolo de medición: ISAK. Instrumentos empleados: Balanza (precisión 100 g), Calibrador de pliegues cutáneos Slim Guide (0,5 mm), Cinta métrica Luftkin (0,1 mm), Vernier Rosscraft (0,1 mm).
