Workbook

Sheet HISTORIA
A1: HISTORIA CLÍNICO-NUTRICIONAL | AC1: Masculino
A2: Fecha: | B2: 46045 | AC2: Femenino
A3: 1- DATOS PERSONALES
A4: Nombre y Apellido | C4: Javier Ignacio Alvarez Izaguirre | G4: Ocupación | I4: Desarrollo de sotfware
A5: Cédula | C5: 29625616 | G5: Nivel de actividad en el trabajo | I5: Muy activo
A6: Fecha de nacimiento | C6: 37404 | G6: Teléfono
A7: Edad | C7: =(B2-C6)/365 -> 23.673973 | G7: Correo electrónico
A8: Estado civil | G8: Deporte/Actividad | K8: Posición
A9: Dirección | C9: La Alameda | K9: Perfil
A10: Sexo | C10: Masculino
A11: Motivo de consulta | C11: Afirma relación rara con la comida. Perder grasa como objetivo visual
A12: Tratamiento médico | C12: Ashwagandha a veces, Magnesio, Melatonina cuando le cuesta dormir. 3 meses de creatina, para un mes y proteina en polvo.
A13: 2-ANTECEDENTES PERSONALES
A14: Enfermedad(es) importante(s) diagnosticada(s) | E14: Niega
A15: Operación(es) realizada(s) | E15: Rinoplastia
A16: 3- ANTECEDENTES FAMILIARES
A17: Enfermedad(es) importante(s) diagnosticada(s) | E17: Abuela materna DM, HTA.
A18: 4- HÁBITOS (PSICOBIOLÓGICO Y FUNCIONALES)
A19: Café | C19: 3 tazas sin azúcar | E19: Agua | H19: 4 litros aprox diarios
A20: Alcohol | C20: Niega | E20: Apetito/Ansiedad | H20: Alto
A21: Tabaco | C21: NIega | E21: Alguna otra información relevante:
A22: Consumo de drogas | C22: Niega
A23: Horas de sueño nocturnas | C23: Reparador. A veces intermitente
A24: Hábitos intestinales | D24: Regular
A25: Hábitos miccionales | D25: Regular
A26: Acidez/Pirosis/Náuseas | D26: Niega
A27: 5- HÁBITOS Y CONDUCTAS ALIMENTARIAS
A28: Horas de mayor apetito | D28: Noche | G28: Rechazos alimentarios | J28: Queso de cabra y mostaza
A29: Comidas fuera de casa | D29: 1 vez a la semana
A30: Alergias alimentarias | D30: NIega
A31: Intolerancias alimentarias | D31: Niega
A32: 6- DEPORTE/ACTIVIDAD FÍSICA/ENERGÍA DE ACTIVIDAD
A33: Tipo de Actividad | E33: Horas/Día | H33: Coeficiente | K33: Coeficiente x hora
A34: Deporte | H34: 3 | K34: =PRODUCT(E34*H34) -> 0
A35: Tv -Lectura | H35: 1 | K35: =PRODUCT(E35*H35) -> 0
A36: Juegos Pasivos | H36: 1.5 | K36: =PRODUCT(E36*H36) -> 0
A37: Juegos Activos | H37: 2.5 | K37: =PRODUCT(E37*H37) -> 0
A38: Escolar | H38: 1 | K38: =PRODUCT(E38*H38) -> 0
A39: Descanso | H39: 0 | K39: =PRODUCT(E39*H39) -> 0
A40: TOTAL | E40: =SUM(E34:G39) -> 0 | K40: =SUM(K34:M39) -> 0
H41: Calorías aproximadas: | K41: =K40*'ANTROPOMETRÍA DEPORTISTAS'!C7 -> 0
A42: 6- DEPORTE/ACTIVIDAD FÍSICA
A43: Tipo de Actividad Física/Deporte | E43: Frecuencia | F43: Horario de entrenamiento | H43: Duración/Hora | K43: Intensidad
A44: Sala de musculación | E44: 5 | F44: 6:00 de la pm | H44: Cero cardio y pocos abs
A46: 7- SUPLEMENTOS NUTRICIONALES
A47: Suplemento(s) nutricional(es) actual(es)
A49: RECORDATORIO DE INGESTA
A50: Pre- DESAYUNO
A51: HORA: 5:30 am
A52: Desayuno | C52: 150 g de avena cruda + agua + 1 cda de miel + 4 huevos + 1 cambur ó
A53: HORA: 9:00 am
A54: MERIENDA MATUTINA 1 | C54: A vces pica frutos secos ;o 2 cuadritos de chocolate. Pica full lechosa.
A55: HORA: 1:00 pm
A56: ALMUERZO | C56: 200-250 g de pollo o carne + 200 g de arroz + a veces incluye plátano 1/3 + vegetales + agua
A57: HORA: 1:00-2:00 pm
A58: MERIENDA VESPERTINA | C58: Pre entreno: 1 cambur. A veces (mitad de la semana incluye medio almuerzo)
A59: HORA: 6:00 pm
A60: CENA | C60: 4 reb de pan cuadrado+ 4 huevos + 100 g de queso + 2 lonjas de jamon + 1 puño de frutos secos mixtos (merey mayormente). A veces lechosa si le da ansiedad.
A61: HORA: 9:00-10 pm
A62: MERIENDA NOCTURNA | C62: Pica mucho OJO
A63: HORA:
A64: CALORIAS APRÓXIMADAS CONSUMIDAS | D64: =(I67*90)+(I68*25)+(I69*60)+(I70*80)+(I71*75)+(I72*55)+(I73*45)+(I74*60) -> 3075 | H64: PAVB APRÓXIMADAS CONSUMIDAS | K64: =(I71+I72)*7 -> 161 | N64: =K64/'ANTROPOMETRÍA DEPORTISTAS'!B7 -> 1.7878956
N65: CHO: | O65: =I70*15 -> 217.5 | P65: =O65/'ANTROPOMETRÍA DEPORTISTAS'!B7 -> 2.4153248
A66: Comida | B66: Desayuno | C66: Merienda | D66: Almuerzo | E66: Merienda | F66: Cena | H66: Merienda | I66: Total
A67: Leche | I67: =SUM(B67:H67) -> 0
A68: Vegetales | D68: 2 | I68: =SUM(B68:H68) -> 2
A69: Frutas | B69: 1 | C69: 1 | E69: 1 | I69: =SUM(B69:H69) -> 3
A70: Almidon | B70: 7 | D70: 2.5 | E70: 1 | F70: 4 | I70: =SUM(B70:H70) -> 14.5
A71: Carnes semi | B71: 4 | D71: 7 | E71: 4 | F71: 6 | I71: =SUM(B71:H71) -> 21
A72: Carnes magras | F72: 2 | I72: =SUM(B72:H72) -> 2
A73: Grasas | I73: =SUM(B73:H73) -> 0
A74: Azúcar | I74: =SUM(B74:H74) -> 0
A122: Femenino
A123: Masculino

Sheet LABORATORIO
A1: LABORATORIO
A4: ANALISÍS QUÍMICO Y HEMATOLÓGIO
A5: PARÁMETRO | B5: VALOR CONSULTA 1 | C5: VALOR CONSULTA 2 | D5: VALOR CONSULTA 3 | E5: VALORES DE REFERENCIA
A6: Hemoglobina | E6: H: 13 – 18 g/dL M: 12 -14 G/dL
A7: Hematocrito | E7: H: 37 – 49 g/dL M: 36 -46 d/dL
A8: Glucosa | E8: 70 – 100 mg/dL
A9: Colesterol total | E9: Hasta 200 mg/dL
A10: Colesterol HDL | E10: H: mayor a 40 mg/dL M: mayor a 50 mg/dL
A12: Colesterol LDL | E12: Menor 130 mg/dL
A13: Triglicéridos | E13: Hasta 150 mg/dL
A14: Urea | E14: 10 – 50 g/dL
A15: Creatinina | E15: 0.8 – 1.2 mg/dL
A16: Ácido úrico | E16: 2.4 – 7.2 mg/dL
A17: BUN | E17: 8 – 20 mg/dL
A18: Proteínas totales | E18: 5.5 – 8 g/dL
... A46: Insulina | E46: <9 µg/mL
A48: Heces
A49: Orina

Sheet ANTROPOMETRÍA DEPORTISTAS
B1: VALORES ANTROPOMÉTRICOS | O1: VALORES ANTROPOMÉTRICOS
A5: Número de evaluación | B5: 1
A6: Fecha de evaluación | B6: 45994
A7: Peso actual (kg) | B7: 90.05
A8: Talla (m) | B8: 1.86
A9: Talla (cm) | B9: =B8*100 -> 186 | C9: =C8*100 -> 0 | D9: =D8*100 -> 0 | E9: =E8*100 -> 0 | F9: =F8*100 -> 0 | G9: =G8*100 -> 0 | H9: =H8*100 -> 0 | I9: =I8*100 -> 0 | ... O9: =O8*100 -> 0
A10: Talla sentada (cm)
A11: Circunferencias(cm)
A12: Brazo relajado (cm) | B12: 39.1
A13: Brazo Flexionado en Tensión (cm) | B13: 41.5
A14: Antebrazo máximo (cm) | B14: 31
A15: Tórax (Mesoesternal) (cm) | B15: 108
A16: Cintura mínimo (cm) | B16: 85
A17: Cadera máximo (cm) | B17: 99.8
A18: Muslo máximo (cm) | B18: 61.3
A19: Muslo medial (cm) | B19: 58.3
A20: Pantorrilla máximo (cm) | B20: 38.6
A21: Pliegues (mm)
A22: Bíceps (mm) | B22: 3.5
A23: Tríceps (mm) | B23: 6.5
A24: Subescapular (mm) | B24: 11.5
A25: Ileo-crestal (mm) | B25: 15.5
A26: Supra-espinal (mm) | B26: 14
A27: Abdominal (mm) | B27: 28.5
A28: Muslo frontal (mm) | B28: 10.5
A29: Pantorrilla (mm) | B29: 6.5
A30: Diametros óseos (cm)
A31: Biacromial (cm)
A32: Toráx Tranverso (cm)
A33: Toráx Anteroposterior (cm)
A34: Biilocrestídio (cm)
A35: Humeral (Biepicondilar) | B35: 8
A36: Femoral (Biepicondilar) | B36: 10.5
A37: Circunferencias corregidas por pliegues (cm)
A38: Brazo relajado (cm) | B38: =B12-(3.1416*B23)/10 -> 37.05796 | C38: =C12-(3.1416*C23)/10 -> 0 | D38: =D12-(3.1416*D23)/10 -> 0 | E38: =E12-(3.1416*E23)/10 -> 0 | F38: =F12-(3.1416*F23)/10 -> 0 | G38: =G12-(3.1416*G23)/10 -> 0 | H38: =H12-(3.1416*H23)/10 -> 0 | I38: =I12-(3.1416*I23)/10 -> 0 | ... O38: =O12-(3.1416*O23)/10 -> 0
A39: Caja torácica (cm) | B39: =B15-(3.1416*B24)/10 -> 104.38716 | C39: =C15-(3.1416*C24)/10 -> 0 | D39: =D15-(3.1416*D24)/10 -> 0 | E39: =E15-(3.1416*E24)/10 -> 0 | F39: =F15-(3.1416*F24)/10 -> 0 | G39: =G15-(3.1416*G24)/10 -> 0 | H39: =H15-(3.1416*H24)/10 -> 0 | I39: =I15-(3.1416*I24)/10 -> 0 | ... O39: =O15-(3.1416*O24)/10 -> 0
A40: Cintura (cm) | B40: =B16-(3.1416*B27)/10 -> 76.04644 | C40: =C16-(3.1416*C27)/10 -> 0 | D40: =D16-(3.1416*D27)/10 -> 0 | E40: =E16-(3.1416*E27)/10 -> 0 | F40: =F16-(3.1416*F27)/10 -> 0 | G40: =G16-(3.1416*G27)/10 -> 0 | H40: =H16-(3.1416*H27)/10 -> 0 | I40: =I16-(3.1416*I27)/10 -> 0 | ... O40: =O16-(3.1416*O27)/10 -> 0
A41: Muslo máximo (cm) | B41: =B18-(3.1416*B28)/10 -> 58.00132 | C41: =C18-(3.1416*C28)/10 -> 0 | D41: =D18-(3.1416*D28)/10 -> 0 | E41: =E18-(3.1416*E28)/10 -> 0 | F41: =F18-(3.1416*F28)/10 -> 0 | G41: =G18-(3.1416*G28)/10 -> 0 | H41: =H18-(3.1416*H28)/10 -> 0 | I41: =I18-(3.1416*I28)/10 -> 0 | ... O41: =O18-(3.1416*O28)/10 -> 0
A42: Pantorrilla máximo (cm) | B42: =B20-(3.1416*B29)/10 -> 36.55796 | C42: =C20-(3.1416*C29)/10 -> 0 | D42: =D20-(3.1416*D29)/10 -> 0 | E42: =E20-(3.1416*E29)/10 -> 0 | F42: =F20-(3.1416*F29)/10 -> 0 | G42: =G20-(3.1416*G29)/10 -> 0 | H42: =H20-(3.1416*H29)/10 -> 0 | I42: =I20-(3.1416*I29)/10 -> 0 | ... O42: =O20-(3.1416*O29)/10 -> 0
A43: INDICADORES (2 componentes)
A44: IMC (kg/m2) | B44: =B7/(B8*B8) -> 26.029021 | C44: =C7/(C8*C8) -> #DIV/0! | D44: =D7/(D8*D8) -> #DIV/0! | E44: =E7/(E8*E8) -> #DIV/0! | F44: =F7/(F8*F8) -> #DIV/0! | G44: =G7/(G8*G8) -> #DIV/0! | H44: =H7/(H8*H8) -> #DIV/0! | I44: =I7/(I8*I8) -> #DIV/0! | ... S44: =S7/(S8*S8) -> #DIV/0!
A45: Contextura | B45: =(B35/(B9/100))*10 -> 43.010753 | C45: =(C35/(C9/100))*10 -> #DIV/0! | D45: =(D35/(D9/100))*10 -> #DIV/0! | E45: =(E35/(E9/100))*10 -> #DIV/0! | F45: =(F35/(F9/100))*10 -> #DIV/0! | G45: =(G35/(G9/100))*10 -> #DIV/0! | H45: =(H35/(H9/100))*10 -> #DIV/0! | I45: =(I35/(I9/100))*10 -> #DIV/0! | ... S45: =(S35/(S9/100))*10 -> #DIV/0!
A46: A. Grasa Brazo (cm2) | B46: =(B23/10)*B12/2-((B23/10)*(B23/10)*3.1416/4) -> 12.375669 | C46: =(C23/10)*C12/2-((C23/10)*(C23/10)*3.1416/4) -> 0 | D46: =(D23/10)*D12/2-((D23/10)*(D23/10)*3.1416/4) -> 0 | E46: =(E23/10)*E12/2-((E23/10)*(E23/10)*3.1416/4) -> 0 | F46: =(F23/10)*F12/2-((F23/10)*(F23/10)*3.1416/4) -> 0 | G46: =(G23/10)*G12/2-((G23/10)*(G23/10)*3.1416/4) -> 0 | H46: =(H23/10)*H12/2-((H23/10)*(H23/10)*3.1416/4) -> 0 | I46: =(I23/10)*I12/2-((I23/10)*(I23/10)*3.1416/4) -> 0 | ... S46: =(S23/10)*S12/2-((S23/10)*(S23/10)*3.1416/4) -> 0
A47: A. Magra Brazo (cm2) | B47: =(B12-((B23/10)*3.1416))^2/(4*3.1416) -> 109.28288 | C47: =(C12-((C23/10)*3.1416))^2/(4*3.1416) -> 0 | D47: =(D12-((D23/10)*3.1416))^2/(4*3.1416) -> 0 | E47: =(E12-((E23/10)*3.1416))^2/(4*3.1416) -> 0 | F47: =(F12-((F23/10)*3.1416))^2/(4*3.1416) -> 0 | G47: =(G12-((G23/10)*3.1416))^2/(4*3.1416) -> 0 | H47: =(H12-((H23/10)*3.1416))^2/(4*3.1416) -> 0 | I47: =(I12-((I23/10)*3.1416))^2/(4*3.1416) -> 0 | ... S47: =(S12-((S23/10)*3.1416))^2/(4*3.1416) -> 0
A48: Área Magra del Muslo (cm2) | B48: =((B19-(B28/10)*3.1416)*(B19-(B28/10)*3.1416)/12.5664) -> 240.73284 | C48: =((C19-(C28/10)*3.1416)*(C19-(C28/10)*3.1416)/12.5664) -> 0 | D48: =((D19-(D28/10)*3.1416)*(D19-(D28/10)*3.1416)/12.5664) -> 0 | E48: =((E19-(E28/10)*3.1416)*(E19-(E28/10)*3.1416)/12.5664) -> 0 | F48: =((F19-(F28/10)*3.1416)*(F19-(F28/10)*3.1416)/12.5664) -> 0 | G48: =((G19-(G28/10)*3.1416)*(G19-(G28/10)*3.1416)/12.5664) -> 0 | H48: =((H19-(H28/10)*3.1416)*(H19-(H28/10)*3.1416)/12.5664) -> 0 | I48: =((I19-(I28/10)*3.1416)*(I19-(I28/10)*3.1416)/12.5664) -> 0 | ... S48: =((S19-(S28/10)*3.1416)*(S19-(S28/10)*3.1416)/12.5664) -> 0
A49: Área Grasa del Muslo (cm2) | B49: =(B19/10)*B28/2-((B19/10)*(B28/10)*3.1416/4) -> 25.799674 | C49: =(C19/10)*C28/2-((C19/10)*(C28/10)*3.1416/4) -> 0 | D49: =(D19/10)*D28/2-((D19/10)*(D28/10)*3.1416/4) -> 0 | E49: =(E19/10)*E28/2-((E19/10)*(E28/10)*3.1416/4) -> 0 | F49: =(F19/10)*F28/2-((F19/10)*(F28/10)*3.1416/4) -> 0 | G49: =(G19/10)*G28/2-((G19/10)*(G28/10)*3.1416/4) -> 0 | H49: =(H19/10)*H28/2-((H19/10)*(H28/10)*3.1416/4) -> 0 | I49: =(I19/10)*I28/2-((I19/10)*(I28/10)*3.1416/4) -> 0 | ... S49: =(S19/10)*S28/2-((S19/10)*(S28/10)*3.1416/4) -> 0
A50: Área Magra de la Pantorrilla (cm2) | B50: =((B20-(B29/10)*3.1416)*(B20-(B29/10)*3.1416)/12.5664) -> 106.3538 | C50: =((C20-(C29/10)*3.1416)*(C20-(C29/10)*3.1416)/12.5664) -> 0 | D50: =((D20-(D29/10)*3.1416)*(D20-(D29/10)*3.1416)/12.5664) -> 0 | E50: =((E20-(E29/10)*3.1416)*(E20-(E29/10)*3.1416)/12.5664) -> 0 | F50: =((F20-(F29/10)*3.1416)*(F20-(F29/10)*3.1416)/12.5664) -> 0 | G50: =((G20-(G29/10)*3.1416)*(G20-(G29/10)*3.1416)/12.5664) -> 0 | H50: =((H20-(H29/10)*3.1416)*(H20-(H29/10)*3.1416)/12.5664) -> 0 | I50: =((I20-(I29/10)*3.1416)*(I20-(I29/10)*3.1416)/12.5664) -> 0 | ... S50: =((S20-(S29/10)*3.1416)*(S20-(S29/10)*3.1416)/12.5664) -> 0
A51: Área Grasa de la Pantorrilla (cm2) | B51: =(B20/10)*B29/2-((B20/10)*(B29/10)*3.1416/4) -> 10.574431 | C51: =(C20/10)*C29/2-((C20/10)*(C29/10)*3.1416/4) -> 0 | D51: =(D20/10)*D29/2-((D20/10)*(D29/10)*3.1416/4) -> 0 | E51: =(E20/10)*E29/2-((E20/10)*(E29/10)*3.1416/4) -> 0 | F51: =(F20/10)*F29/2-((F20/10)*(F29/10)*3.1416/4) -> 0 | G51: =(G20/10)*G29/2-((G20/10)*(G29/10)*3.1416/4) -> 0 | H51: =(H20/10)*H29/2-((H20/10)*(H29/10)*3.1416/4) -> 0 | I51: =(I20/10)*I29/2-((I20/10)*(I29/10)*3.1416/4) -> 0 | ... S51: =(S20/10)*S29/2-((S20/10)*(S29/10)*3.1416/4) -> 0
A52: % Grasa (Carter 1986) | B52: =(2.585)+(0.1051*(B24+B23+B27+B26+B28+B29)) -> 10.73025 | C52: =(2.585)+(0.1051*(C24+C23+C27+C26+C28+C29)) -> 2.585 | D52: =(2.585)+(0.1051*(D24+D23+D27+D26+D28+D29)) -> 2.585 | E52: =(2.585)+(0.1051*(E24+E23+E27+E26+E28+E29)) -> 2.585 | F52: =(2.585)+(0.1051*(F24+F23+F27+F26+F28+F29)) -> 2.585 | G52: =(2.585)+(0.1051*(G24+G23+G27+G26+G28+G29)) -> 2.585 | H52: =(2.585)+(0.1051*(H24+H23+H27+H26+H28+H29)) -> 2.585 | I52: =(2.585)+(0.1051*(I24+I23+I27+I26+I28+I29)) -> 2.585 | ... S52: =(2.585)+(0.1051*(S24+S23+S27+S26+S28+S29)) -> 2.585
A53: % Grasa (Durnin y W. 1974) | B53: =((4.95 / (VLOOKUP(HISTORIA!C7, I104:K109, 2, 1) - (VLOOKUP(HISTORIA!C7, I104:K109, 3, 1) *LOG10(SUM(B22:B25))))) - 4.5) * 100 -> 15.230089 | C53: =((4.95 / (VLOOKUP(HISTORIA!C7, I104:K109, 2, 1) - (VLOOKUP(HISTORIA!C7, I104:K109, 3, 1) *LOG10(SUM(C22:C25))))) - 4.5) * 100 -> #NUM! | D53: =((4.95 / (VLOOKUP(HISTORIA!C7, J104:L109, 2, 1) - (VLOOKUP(HISTORIA!C7, J104:L109, 3, 1) *LOG10(SUM(D22:D25))))) - 4.5) * 100 -> #NUM! | E53: =((4.95 / (VLOOKUP(HISTORIA!C7, K104:M109, 2, 1) - (VLOOKUP(HISTORIA!C7, K104:M109, 3, 1) *LOG10(SUM(E22:E25))))) - 4.5) * 100 -> #NUM! | F53: =((4.95 / (VLOOKUP(HISTORIA!D7, L104:N109, 2, 1) - (VLOOKUP(HISTORIA!D7, L104:N109, 3, 1) *LOG10(SUM(F22:F25))))) - 4.5) * 100 -> #N/A | G53: =(((0.2467)*(G22+G23+G24+G25))+((0.12*G16)))-2.18 -> -2.18 | H53: =(((0.2467)*(H22+H23+H24+H25))+((0.12*H16)))-2.18 -> -2.18 | I53: =(((0.2467)*(I22+I23+I24+I25))+((0.12*I16)))-2.18 -> -2.18 | J53: =(((0.2467)*(J22+J23+J24+J25))+((0.12*J16)))-2.18 -> -2.18 | K53: =(((0.2467)*(K22+K23+K24+K25))+((0.12*K16)))-2.18 -> -2.18 | L53: =(((0.2467)*(L22+L23+L24+L25))+((0.12*L16)))-2.18 -> -2.18 | M53: =(((0.2467)*(M22+M23+M24+M25))+((0.12*M16)))-2.18 -> -2.18 | N53: =(((0.2467)*(N22+N23+N24+N25))+((0.12*N16)))-2.18 -> -2.18 | ... S53: =(((0.2467)*(S22+S23+S24+S25))+((0.12*S16)))-2.18 -> -2.18
A54: Sumatoria de 6 Pliegues | B54: =B29+B28+B26+B27+B23+B24 -> 77.5 | C54: =C29+C28+C26+C27+C23+C24 -> 0 | D54: =D29+D28+D26+D27+D23+D24 -> 0 | E54: =E29+E28+E26+E27+E23+E24 -> 0 | F54: =F29+F28+F26+F27+F23+F24 -> 0 | G54: =G29+G28+G26+G27+G23+G24 -> 0 | H54: =H29+H28+H26+H27+H23+H24 -> 0 | I54: =I29+I28+I26+I27+I23+I24 -> 0 | ... S54: =S29+S28+S26+S27+S23+S24 -> 0
A55: Sumatoria de 8 Pliegues | B55: =B25+B29+B28+B26+B27+B22+B23+B24 -> 96.5 | C55: =C25+C29+C28+C26+C27+C22+C23+C24 -> 0 | D55: =D25+D29+D28+D26+D27+D22+D23+D24 -> 0 | E55: =E25+E29+E28+E26+E27+E22+E23+E24 -> 0 | F55: =F25+F29+F28+F26+F27+F22+F23+F24 -> 0 | G55: =G25+G29+G28+G26+G27+G22+G23+G24 -> 0 | H55: =H25+H29+H28+H26+H27+H22+H23+H24 -> 0 | I55: =I25+I29+I28+I26+I27+I22+I23+I24 -> 0 | ... S55: =S25+S29+S28+S26+S27+S22+S23+S24 -> 0
A56: Índice cintura/cadera | B56: =B16/B17 -> 0.85170341 | C56: =C16/C17 -> #DIV/0! | D56: =D16/D17 -> #DIV/0! | E56: =E16/E17 -> #DIV/0! | F56: =F16/F17 -> #DIV/0! | G56: =G16/G17 -> #DIV/0! | H56: =H16/H17 -> #DIV/0! | I56: =I16/I17 -> #DIV/0! | ... S56: =S16/S17 -> #DIV/0!
A57: Porcentaje a Utilizar | B57: =B52 -> 10.73025 | C57: =C52 -> 2.585 | D57: =D52 -> 2.585 | E57: =E52 -> 2.585 | F57: =F52 -> 2.585 | G57: =G52 -> 2.585 | H57: =H52 -> 2.585 | I57: =I52 -> 2.585 | ... S57: =S52 -> 2.585
A58: Kg. Masa magra | B58: =(100-B57)/100*B7 -> 80.38741 | C58: =(100-C57)/100*C7 -> 0 | D58: =(100-D57)/100*D7 -> 0 | E58: =(100-E57)/100*E7 -> 0 | F58: =(100-F57)/100*F7 -> 0 | G58: =(100-G57)/100*G7 -> 0 | H58: =(100-H57)/100*H7 -> 0 | I58: =(100-I57)/100*I7 -> 0 | ... S58: =(100-S57)/100*S7 -> 0
A59: Kg. Grasa | B59: =B7-B58 -> 9.6625901 | C59: =C7-C58 -> 0 | D59: =D7-D58 -> 0 | E59: =E7-E58 -> 0 | F59: =F7-F58 -> 0 | G59: =G7-G58 -> 0 | H59: =H7-H58 -> 0 | I59: =I7-I58 -> 0 | ... S59: =S7-S58 -> 0
A60: I. MLG | B60: =(B58/(B8*B8)) -> 23.236042 | C60: =(C58/(C8*C8)) -> #DIV/0! | D60: =(D58/(D8*D8)) -> #DIV/0! | E60: =(E58/(E8*E8)) -> #DIV/0! | F60: =(F58/(F8*F8)) -> #DIV/0! | G60: =(G58/(G8*G8)) -> #DIV/0! | H60: =(H58/(H8*H8)) -> #DIV/0! | I60: =(I58/(I8*I8)) -> #DIV/0! | ... S60: =(S58/(S8*S8)) -> #DIV/0!
A61: I. MG | B61: =(B59/(B8*B8)) -> 2.792979 | C61: =(C59/(C8*C8)) -> #DIV/0! | D61: =(D59/(D8*D8)) -> #DIV/0! | E61: =(E59/(E8*E8)) -> #DIV/0! | F61: =(F59/(F8*F8)) -> #DIV/0! | G61: =(G59/(G8*G8)) -> #DIV/0! | H61: =(H59/(H8*H8)) -> #DIV/0! | I61: =(I59/(I8*I8)) -> #DIV/0! | ... S61: =(S59/(S8*S8)) -> #DIV/0!
A62: Indicadores absolutos (Corregidos por pliegues)
A63: Masa Adiposa (Kg) | B63: =(((((B23+B24+B26+B27+B28+B29)*(170.18/B9)-116.41)/34.79)*5.85)+25.6)/((170.18/B9)^3) -> 23.434141 | C63: =(((((C23+C24+C26+C27+C28+C29)*(170.18/C9)-116.41)/34.79)*5.85)+25.6)/((170.18/C9)^3) -> #DIV/0! | D63: =(((((D23+D24+D26+D27+D28+D29)*(170.18/D9)-116.41)/34.79)*5.85)+25.6)/((170.18/D9)^3) -> #DIV/0! | E63: =(((((E23+E24+E26+E27+E28+E29)*(170.18/E9)-116.41)/34.79)*5.85)+25.6)/((170.18/E9)^3) -> #DIV/0! | F63: =(((((F23+F24+F26+F27+F28+F29)*(170.18/F9)-116.41)/34.79)*5.85)+25.6)/((170.18/F9)^3) -> #DIV/0! | G63: =(((((G23+G24+G26+G27+G28+G29)*(170.18/G9)-116.41)/34.79)*5.85)+25.6)/((170.18/G9)^3) -> #DIV/0! | H63: =(((((H23+H24+H26+H27+H28+H29)*(170.18/H9)-116.41)/34.79)*5.85)+25.6)/((170.18/H9)^3) -> #DIV/0! | I63: =(((((I23+I24+I26+I27+I28+I29)*(170.18/I9)-116.41)/34.79)*5.85)+25.6)/((170.18/I9)^3) -> #DIV/0! | ... S63: =(((((S23+S24+S26+S27+S28+S29)*(170.18/S9)-116.41)/34.79)*5.85)+25.6)/((170.18/S9)^3) -> #DIV/0!
A64: Masa Muscular (Kg) | B64: =(((((B38+B14+B39+B41+B42)*(170.18/B9))-207.21)/13.74*5.4)+24.5)/((170.18/B9)^3) -> 51.016377 | C64: =(((((C38+C14+C39+C41+C42)*(170.18/C9))-207.21)/13.74*5.4)+24.5)/((170.18/C9)^3) -> #DIV/0! | D64: =(((((D38+D14+D39+D41+D42)*(170.18/D9))-207.21)/13.74*5.4)+24.5)/((170.18/D9)^3) -> #DIV/0! | E64: =(((((E38+E14+E39+E41+E42)*(170.18/E9))-207.21)/13.74*5.4)+24.5)/((170.18/E9)^3) -> #DIV/0! | F64: =(((((F38+F14+F39+F41+F42)*(170.18/F9))-207.21)/13.74*5.4)+24.5)/((170.18/F9)^3) -> #DIV/0! | G64: =(((((G38+G14+G39+G41+G42)*(170.18/G9))-207.21)/13.74*5.4)+24.5)/((170.18/G9)^3) -> #DIV/0! | H64: =(((((H38+H14+H39+H41+H42)*(170.18/H9))-207.21)/13.74*5.4)+24.5)/((170.18/H9)^3) -> #DIV/0! | I64: =(((((I38+I14+I39+I41+I42)*(170.18/I9))-207.21)/13.74*5.4)+24.5)/((170.18/I9)^3) -> #DIV/0! | ... S64: =(((((S38+S14+S39+S41+S42)*(170.18/S9))-207.21)/13.74*5.4)+24.5)/((170.18/S9)^3) -> #DIV/0!
A65: Valoración del Somatotipo (Decimal)
A66: Ectomorfia | B66: =(0.732*B98)-28.58 -> 1.800478 | C66: =(0.732*C98)-28.58 -> #DIV/0! | D66: =(0.732*D98)-28.58 -> #DIV/0! | E66: =(0.732*E98)-28.58 -> #DIV/0! | F66: =(0.732*F98)-28.58 -> #DIV/0! | G66: =(0.732*G98)-28.58 -> #DIV/0! | H66: =(0.732*H98)-28.58 -> #DIV/0! | I66: =(0.732*I98)-28.58 -> #DIV/0! | ... S66: =(0.732*S98)-28.58 -> #DIV/0!
A67: Mesomorfia | B67: =(0.858*B35)+(0.601*B36)+(0.188*B96)+(0.161*B97)-(0.131*B9)+4.5 -> 7.09825 | C67: =(0.858*C35)+(0.601*C36)+(0.188*C96)+(0.161*C97)-(0.131*C9)+4.5 -> 4.5 | D67: =(0.858*D35)+(0.601*D36)+(0.188*D96)+(0.161*D97)-(0.131*D9)+4.5 -> 4.5 | E67: =(0.858*E35)+(0.601*E36)+(0.188*E96)+(0.161*E97)-(0.131*E9)+4.5 -> 4.5 | F67: =(0.858*F35)+(0.601*F36)+(0.188*F96)+(0.161*F97)-(0.131*F9)+4.5 -> 4.5 | G67: =(0.858*G35)+(0.601*G36)+(0.188*G96)+(0.161*G97)-(0.131*G9)+4.5 -> 4.5 | H67: =(0.858*H35)+(0.601*H36)+(0.188*H96)+(0.161*H97)-(0.131*H9)+4.5 -> 4.5 | I67: =(0.858*I35)+(0.601*I36)+(0.188*I96)+(0.161*I97)-(0.131*I9)+4.5 -> 4.5 | ... S67: =(0.858*S35)+(0.601*S36)+(0.188*S96)+(0.161*S97)-(0.131*S9)+4.5 -> 4.5
A68: Endomorfia | B68: =(-0.7182+(0.1451*B93)-(0.00068*B94)+(0.0000014*B95)) -> 2.9823074 | C68: =(-0.7182+(0.1451*C93)-(0.00068*C94)+(0.0000014*C95)) -> #DIV/0! | D68: =(-0.7182+(0.1451*D93)-(0.00068*D94)+(0.0000014*D95)) -> #DIV/0! | E68: =(-0.7182+(0.1451*E93)-(0.00068*E94)+(0.0000014*E95)) -> #DIV/0! | F68: =(-0.7182+(0.1451*F93)-(0.00068*F94)+(0.0000014*F95)) -> #DIV/0! | G68: =(-0.7182+(0.1451*G93)-(0.00068*G94)+(0.0000014*G95)) -> #DIV/0! | H68: =(-0.7182+(0.1451*H93)-(0.00068*H94)+(0.0000014*H95)) -> #DIV/0! | I68: =(-0.7182+(0.1451*I93)-(0.00068*I94)+(0.0000014*I95)) -> #DIV/0! | ... S68: =(-0.7182+(0.1451*S93)-(0.00068*S94)+(0.0000014*S95)) -> #DIV/0!
A69: SOMATOTIPO
A70: Ubicación en la somatocarta
A71: Eje X | B71: =B66-B68 -> -1.1818294 | C71: =C66-C68 -> #DIV/0! | D71: =D66-D68 -> #DIV/0! | E71: =E66-E68 -> #DIV/0! | F71: =F66-F68 -> #DIV/0! | G71: =G66-G68 -> #DIV/0! | H71: =H66-H68 -> #DIV/0! | I71: =I66-I68 -> #DIV/0! | ... S71: =S66-S68 -> #DIV/0!
A72: Eje Y | B72: =(2*B67)-(B68+B66) -> 9.4137147 | C72: =(2*C67)-(C68+C66) -> #DIV/0! | D72: =(2*D67)-(D68+D66) -> #DIV/0! | E72: =(2*E67)-(E68+E66) -> #DIV/0! | F72: =(2*F67)-(F68+F66) -> #DIV/0! | G72: =(2*G67)-(G68+G66) -> #DIV/0! | H72: =(2*H67)-(H68+H66) -> #DIV/0! | I72: =(2*I67)-(I68+I66) -> #DIV/0! | ... S72: =(2*S67)-(S68+S66) -> #DIV/0!
A73: % Grasa Objetivo | B73: 14 | C73: 15 | D73: 16 | E73: 17 | F73: 18 | G73: 19 | H73: 20 | I73: 21 | J73: 22 | K73: 23 | L73: 24 | M73: 25 | N73: 26 | O73: 27 | P73: 28 | Q73: 29 | R73: 30 | S73: 31
A74: Pérdida de grasa requerida (%) | B74: =B57-B73 -> -3.26975 | C74: =C57-C73 -> -12.415 | D74: =D57-D73 -> -13.415 | E74: =E57-E73 -> -14.415 | F74: =F57-F73 -> -15.415 | G74: =G57-G73 -> -16.415 | H74: =H57-H73 -> -17.415 | I74: =I57-I73 -> -18.415 | ... S74: =S57-S73 -> -28.415
A75: Pérdida de grasa requerida (Kg) | B75: =(B7*B74)/100 -> -2.9444099 | C75: =(C7*C74)/100 -> 0 | D75: =(D7*D74)/100 -> 0 | E75: =(E7*E74)/100 -> 0 | F75: =(F7*F74)/100 -> 0 | G75: =(G7*G74)/100 -> 0 | H75: =(H7*H74)/100 -> 0 | I75: =(I7*I74)/100 -> 0 | ... S75: =(S7*S74)/100 -> 0
A76: Peso Objetivo | B76: =(B58)/(1-B73/100) -> 93.473732 | C76: =(C58)/(1-C73/100) -> 0 | D76: =(D58)/(1-D73/100) -> 0 | E76: =(E58)/(1-E73/100) -> 0 | F76: =(F58)/(1-F73/100) -> 0 | G76: =(G58)/(1-G73/100) -> 0 | H76: =(H58)/(1-H73/100) -> 0 | I76: =(I58)/(1-I73/100) -> 0 | ... S76: =(S58)/(1-S73/100) -> 0
A77: Pérdida o ganancia de peso Requerida | B77: =B75/0.8 -> -3.6805123 | C77: =C75/0.8 -> 0 | D77: =D75/0.8 -> 0 | E77: =E75/0.8 -> 0 | F77: =F75/0.8 -> 0 | G77: =G75/0.8 -> 0 | H77: =H75/0.8 -> 0 | I77: =I75/0.8 -> 0 | ... S77: =S75/0.8 -> 0
A78: Kg. a bajar o subir | B78: =B7-B76 -> -3.4237324 | C78: =C7-C76 -> 0 | D78: =D7-D76 -> 0 | E78: =E7-E76 -> 0 | F78: =F7-F76 -> 0 | G78: =G7-G76 -> 0 | H78: =H7-H76 -> 0 | I78: =I7-I76 -> 0 | ... S78: =S7-S76 -> 0
A79: g de grasa a bajar | B79: =(B77*0.8)*1000 -> -2944.4099 | C79: =(C77*0.8)*1000 -> 0 | D79: =(D77*0.8)*1000 -> 0 | E79: =(E77*0.8)*1000 -> 0 | F79: =(F77*0.8)*1000 -> 0 | G79: =(G77*0.8)*1000 -> 0 | H79: =(H77*0.8)*1000 -> 0 | I79: =(I77*0.8)*1000 -> 0 | ... S79: =(S77*0.8)*1000 -> 0
A80: Pérdida de M.M aceptable (g) | B80: =(B77*0.2)*1000 -> -736.10247 | C80: =(C77*0.2)*1000 -> 0 | D80: =(D77*0.2)*1000 -> 0 | E80: =(E77*0.2)*1000 -> 0 | F80: =(F77*0.2)*1000 -> 0 | G80: =(G77*0.2)*1000 -> 0 | H80: =(H77*0.2)*1000 -> 0 | I80: =(I77*0.2)*1000 -> 0 | ... S80: =(S77*0.2)*1000 -> 0
A81: Pérdida de peso esperada p/ semana (g) | B81: =(B7*0.6)*10 -> 540.3 | C81: =(C7*0.6)*10 -> 0 | D81: =(D7*0.6)*10 -> 0 | E81: =(E7*0.6)*10 -> 0 | F81: =(F7*0.6)*10 -> 0 | G81: =(G7*0.6)*10 -> 0 | H81: =(H7*0.6)*10 -> 0 | I81: =(I7*0.6)*10 -> 0 | ... S81: =(S7*0.6)*10 -> 0
A82: Pérdida de peso esperada p/ mes (g) | B82: =B81*4 -> 2161.2 | C82: =C81*4 -> 0 | D82: =D81*4 -> 0 | E82: =E81*4 -> 0 | F82: =F81*4 -> 0 | G82: =G81*4 -> 0 | H82: =H81*4 -> 0 | I82: =I81*4 -> 0 | ... S82: =S81*4 -> 0
A83: Pérdida de grasa semanal (g) | B83: =B81*0.8 -> 432.24 | C83: =C81*0.8 -> 0 | D83: =D81*0.8 -> 0 | E83: =E81*0.8 -> 0 | F83: =F81*0.8 -> 0 | G83: =G81*0.8 -> 0 | H83: =H81*0.8 -> 0 | I83: =I81*0.8 -> 0 | ... S83: =S81*0.8 -> 0
A84: Pérdida de musculo semanal (g) | B84: =B81*0.2 -> 108.06 | C84: =C81*0.2 -> 0 | D84: =D81*0.2 -> 0 | E84: =E81*0.2 -> 0 | F84: =F81*0.2 -> 0 | G84: =G81*0.2 -> 0 | H84: =H81*0.2 -> 0 | I84: =I81*0.2 -> 0 | ... S84: =S81*0.2 -> 0
A85: Duración del decít (semanas) | B85: =(B77/B81)*1000 -> -6.8119792 | C85: =(C77/C81)*1000 -> #DIV/0! | D85: =(D77/D81)*1000 -> #DIV/0! | E85: =(E77/E81)*1000 -> #DIV/0! | F85: =(F77/F81)*1000 -> #DIV/0! | G85: =(G77/G81)*1000 -> #DIV/0! | H85: =(H77/H81)*1000 -> #DIV/0! | I85: =(I77/I81)*1000 -> #DIV/0! | ... S85: =(S77/S81)*1000 -> #DIV/0!
A86: Duración del decít (meses) | B86: =B85/4 -> -1.7029948 | C86: =C85/4 -> #DIV/0! | D86: =D85/4 -> #DIV/0! | E86: =E85/4 -> #DIV/0! | F86: =F85/4 -> #DIV/0! | G86: =G85/4 -> #DIV/0! | H86: =H85/4 -> #DIV/0! | I86: =I85/4 -> #DIV/0! | ... S86: =S85/4 -> #DIV/0!
A87: Kcal por Kg de Grasa | B87: =(B83*0.87)*9 -> 3384.4392 | C87: =(C83*0.87)*9 -> 0 | D87: =(D83*0.87)*9 -> 0 | E87: =(E83*0.87)*9 -> 0 | F87: =(F83*0.87)*9 -> 0 | G87: =(G83*0.87)*9 -> 0 | H87: =(H83*0.87)*9 -> 0 | I87: =(I83*0.87)*9 -> 0 | ... S87: =(S83*0.87)*9 -> 0
A88: Kcal por Kg de Masa Magra | B88: =(B84*0.3)*4 -> 129.672 | C88: =(C84*0.3)*4 -> 0 | D88: =(D84*0.3)*4 -> 0 | E88: =(E84*0.3)*4 -> 0 | F88: =(F84*0.3)*4 -> 0 | G88: =(G84*0.3)*4 -> 0 | H88: =(H84*0.3)*4 -> 0 | I88: =(I84*0.3)*4 -> 0 | ... S88: =(S84*0.3)*4 -> 0
A89: DEFICÍT (Kcal/día) | B89: =(B87+B88)/7 -> 502.01589 | C89: =(C87+C88)/7 -> 0 | D89: =(D87+D88)/7 -> 0 | E89: =(E87+E88)/7 -> 0 | F89: =(F87+F88)/7 -> 0 | G89: =(G87+G88)/7 -> 0 | H89: =(H87+H88)/7 -> 0 | I89: =(I87+I88)/7 -> 0 | ... S89: =(S87+S88)/7 -> 0
A91: OTRAS SUMATORIAS
A92: Sumatoria de 3 pliegues | B92: =B24+B23+B26 -> 32 | C92: =C24+C23+C26 -> 0 | D92: =D24+D23+D26 -> 0 | E92: =E24+E23+E26 -> 0 | F92: =F24+F23+F26 -> 0 | G92: =G24+G23+G26 -> 0 | H92: =H24+H23+H26 -> 0 | I92: =I24+I23+I26 -> 0 | ... S92: =S24+S23+S26 -> 0
A93: Sumatoria de 3 pliegues (Corregida) | B93: =(170.18/B9)*B92 -> 29.27828 | C93: =(170.18/C9)*C92 -> #DIV/0! | D93: =(170.18/D9)*D92 -> #DIV/0! | E93: =(170.18/E9)*E92 -> #DIV/0! | F93: =(170.18/F9)*F92 -> #DIV/0! | G93: =(170.18/G9)*G92 -> #DIV/0! | H93: =(170.18/H9)*H92 -> #DIV/0! | I93: =(170.18/I9)*I92 -> #DIV/0! | ... S93: =(170.18/S9)*S92 -> #DIV/0!
A94: Sumatoria de 3 pliegues (Corregida) (2) | B94: =(B93^2) -> 857.21765 | C94: =(C93^2) -> #DIV/0! | D94: =(D93^2) -> #DIV/0! | E94: =(E93^2) -> #DIV/0! | F94: =(F93^2) -> #DIV/0! | G94: =(G93^2) -> #DIV/0! | H94: =(H93^2) -> #DIV/0! | I94: =(I93^2) -> #DIV/0! | ... S94: =(S93^2) -> #DIV/0!
A95: Sumatoria de 3 pliegues (Corregida) (3) | B95: =(B93^3) -> 25097.858 | C95: =(C93^3) -> #DIV/0! | D95: =(D93^3) -> #DIV/0! | E95: =(E93^3) -> #DIV/0! | F95: =(F93^3) -> #DIV/0! | G95: =(G93^3) -> #DIV/0! | H95: =(H93^3) -> #DIV/0! | I95: =(I93^3) -> #DIV/0! | ... S95: =(S93^3) -> #DIV/0!
A96: Biceps Corregido | B96: =(B13-(B23/10)) -> 40.85 | C96: =(C13-(C23/10)) -> 0 | D96: =(D13-(D23/10)) -> 0 | E96: =(E13-(E23/10)) -> 0 | F96: =(F13-(F23/10)) -> 0 | G96: =(G13-(G23/10)) -> 0 | H96: =(H13-(H23/10)) -> 0 | I96: =(I13-(I23/10)) -> 0 | ... S96: =(S13-(S23/10)) -> 0
A97: Pantorrilla Corregida | B97: =(B20-(B29/10)) -> 37.95 | C97: =(C20-(C29/10)) -> 0 | D97: =(D20-(D29/10)) -> 0 | E97: =(E20-(E29/10)) -> 0 | F97: =(F20-(F29/10)) -> 0 | G97: =(G20-(G29/10)) -> 0 | H97: =(H20-(H29/10)) -> 0 | I97: =(I20-(I29/10)) -> 0 | ... S97: =(S20-(S29/10)) -> 0
A98: Altura/Peso (1/3) | B98: =B9/(B7^0.3333) -> 41.503385 | C98: =C9/(C7^0.3333) -> #DIV/0! | D98: =D9/(D7^0.3333) -> #DIV/0! | E98: =E9/(E7^0.3333) -> #DIV/0! | F98: =F9/(F7^0.3333) -> #DIV/0! | G98: =G9/(G7^0.3333) -> #DIV/0! | H98: =H9/(H7^0.3333) -> #DIV/0! | I98: =I9/(I7^0.3333) -> #DIV/0! | ... S98: =S9/(S7^0.3333) -> #DIV/0!
B100: VALORES DE REFERENCIA
B103: % DE GRASA (CARTER 1986) | E103: SOMATOTIPO
I104: Edad Mínima | J104: Constante c | K104: Constante m
B105: Deporte | C105: Adultos | D105: Juveniles | F105: Componentes | G105: Juveniles | I105: 17 | J105: 1.162 | K105: 0.063
B106: Beisbol | C106: 8_14 | F106: – Bajos: 2 - 2 ½ | I106: 20 | J106: 1.1631 | K106: 0.0632
B107: Baloncesto | C107: 6_12 | F107: – Moderados: 2 ½ - 5 | I107: 30 | J107: 1.1422 | K107: 0.0544
...

Sheet 5 COMPONENTES
A1: DATOS PERSONALES | B1: Nombre y apellido | C1: =HISTORIA!C4 -> Javier Ignacio Alvarez Izaguirre
B2: Fecha de evaluación
B3: Fecha de nacimiento | C3: =HISTORIA!C6 -> 37404
B4: Edad (años) | C4: =(C2-C3)/365 -> -102.47671 | D4: =(D2-D3)/365 -> 0 | E4: =(E2-E3)/365 -> 0 | F4: =(F2-F3)/365 -> 0 | G4: =(G2-G3)/365 -> 0 | H4: =(H2-H3)/365 -> 0 | I4: =(I2-I3)/365 -> 0 | J4: =(J2-J3)/365 -> 0 | ... L4: =(L2-L3)/365 -> 0
A5: Mediciones básicas | B5: Peso (kg)
B6: Talla parado (cm) | C6: 185 | D6: 185 | E6: 185 | F6: 185 | G6: 185 | H6: 185 | I6: 185 | J6: 185 | K6: 185 | L6: 185
B7: Talla sentado corregida (cm) | C7: =C8-43 -> -43 | D7: =D8-43 -> -43 | E7: =E8-43 -> -43 | F7: =F8-43 -> -43 | G7: =G8-43 -> -43 | H7: =H8-43 -> -43 | I7: =I8-43 -> -43 | J7: =J8-43 -> -43 | ... L7: =L8-43 -> -43
B8: Talla sentado (cm)
A10: Pliegues cutáneos (mm) | B10: Tríceps
B11: Subescapular
B12: Bíceps
B13: Cresta Ilíaca
B14: Supraespinal
B15: Abdominal
B16: Muslo frontal
B17: Pantorrilla
A19: Circunferencias (cm) | B19: Cabeza
B20: Cuello
B21: Brazo relajado
B22: Brazo flexionado en tensión
B23: Antebrazo máximo
B24: Muñeca
B25: Tórax (Mesoesternal)
B26: Cintura (Mínimo)
B27: Cadera (Máximo)
B28: Muslo máximo
B29: Muslo medio
B30: Pantorrilla
B31: Tobillo
A33: Diámetros óseos (mm) | B33: Biacromial
B34: Tórax transverso
B35: Tórax anteroposterior
B36: Biiliocrestídeo
B37: Humeral (Biepicondilar)
B38: Femoral (Biepicondilar)
B39: Muñeca (Biestiloidea)
A41: Circunferencias corregidas (mm) | B41: Brazo relajado corregido | C41: =C21-(3.1416*C10)/10 -> 0 | D41: =D21-(3.1416*D10)/10 -> 0 | E41: =E21-(3.1416*E10)/10 -> 0 | F41: =F21-(3.1416*F10)/10 -> 0 | G41: =G21-(3.1416*G10)/10 -> 0 | H41: =H21-(3.1416*H10)/10 -> 0 | I41: =I21-(3.1416*I10)/10 -> 0 | J41: =J21-(3.1416*J10)/10 -> 0 | ... L41: =L21-(3.1416*L10)/10 -> 0
B42: Caja torácica corregida | C42: =C25-(3.1416*C11)/10 -> 0 | D42: =D25-(3.1416*D11)/10 -> 0 | E42: =E25-(3.1416*E11)/10 -> 0 | F42: =F25-(3.1416*F11)/10 -> 0 | G42: =G25-(3.1416*G11)/10 -> 0 | H42: =H25-(3.1416*H11)/10 -> 0 | I42: =I25-(3.1416*I11)/10 -> 0 | J42: =J25-(3.1416*J11)/10 -> 0 | ... L42: =L25-(3.1416*L11)/10 -> 0
B43: Muslo máximo corregido | C43: =C28-(3.1416*C16)/10 -> 0 | D43: =D28-(3.1416*D16)/10 -> 0 | E43: =E28-(3.1416*E16)/10 -> 0 | F43: =F28-(3.1416*F16)/10 -> 0 | G43: =G28-(3.1416*G16)/10 -> 0 | H43: =H28-(3.1416*H16)/10 -> 0 | I43: =I28-(3.1416*I16)/10 -> 0 | J43: =J28-(3.1416*J16)/10 -> 0 | ... L43: =L28-(3.1416*L16)/10 -> 0
B44: Pantorrilla corregida | C44: =C30-(3.1416*C17)/10 -> 0 | D44: =D30-(3.1416*D17)/10 -> 0 | E44: =E30-(3.1416*E17)/10 -> 0 | F44: =F30-(3.1416*F17)/10 -> 0 | G44: =G30-(3.1416*G17)/10 -> 0 | H44: =H30-(3.1416*H17)/10 -> 0 | I44: =I30-(3.1416*I17)/10 -> 0 | J44: =J30-(3.1416*J17)/10 -> 0 | ... L44: =L30-(3.1416*L17)/10 -> 0
B45: Cintura corregida | C45: =C26-(3.1416*C15)/10 -> 0 | D45: =D26-(3.1416*D15)/10 -> 0 | E45: =E26-(3.1416*E15)/10 -> 0 | F45: =F26-(3.1416*F15)/10 -> 0 | G45: =G26-(3.1416*G15)/10 -> 0 | H45: =H26-(3.1416*H15)/10 -> 0 | I45: =I26-(3.1416*I15)/10 -> 0 | J45: =J26-(3.1416*J15)/10 -> 0 | ... L45: =L26-(3.1416*L15)/10 -> 0
A47: Composición corporal absoluta (5 componentes) | B47: Masa de la piel (Kg) | C47: =((68.308*C5^0.425*C6^0.725)/10000)*2.07*1.05 -> 0 | D47: =((68.308*D5^0.425*D6^0.725)/10000)*2.07*1.05 -> 0 | E47: =((68.308*E5^0.425*E6^0.725)/10000)*2.07*1.05 -> 0 | F47: =((68.308*F5^0.425*F6^0.725)/10000)*2.07*1.05 -> 0 | G47: =((68.308*G5^0.425*G6^0.725)/10000)*2.07*1.05 -> 0 | H47: =((68.308*H5^0.425*H6^0.725)/10000)*2.07*1.05 -> 0 | I47: =((68.308*I5^0.425*I6^0.725)/10000)*2.07*1.05 -> 0 | J47: =((68.308*J5^0.425*J6^0.725)/10000)*2.07*1.05 -> 0 | ... L47: =((68.308*L5^0.425*L6^0.725)/10000)*2.07*1.05 -> 0
B48: Masa ósea total (Kg) | C48: =((((C19-56)/1.44)*0.18)+1.2)/((170.8/C6)^3)+((((((C33+C36+(2*C37)+(2*C38))*(170.8/C6)-98.88)/5.33)*1.34)+6.7)/((170.8/C6)^3)) -> -30.445475 | D48: =((((D19-56)/1.44)*0.18)+1.2)/((170.8/D6)^3)+((((((D33+D36+(2*D37)+(2*D38))*(170.8/D6)-98.88)/5.33)*1.34)+6.7)/((170.8/D6)^3)) -> -30.445475 | E48: =((((E19-56)/1.44)*0.18)+1.2)/((170.8/E6)^3)+((((((E33+E36+(2*E37)+(2*E38))*(170.8/E6)-98.88)/5.33)*1.34)+6.7)/((170.8/E6)^3)) -> -30.445475 | F48: =((((F19-56)/1.44)*0.18)+1.2)/((170.8/F6)^3)+((((((F33+F36+(2*F37)+(2*F38))*(170.8/F6)-98.88)/5.33)*1.34)+6.7)/((170.8/F6)^3)) -> -30.445475 | G48: =((((G19-56)/1.44)*0.18)+1.2)/((170.8/G6)^3)+((((((G33+G36+(2*G37)+(2*G38))*(170.8/G6)-98.88)/5.33)*1.34)+6.7)/((170.8/G6)^3)) -> -30.445475 | H48: =((((H19-56)/1.44)*0.18)+1.2)/((170.8/H6)^3)+((((((H33+H36+(2*H37)+(2*H38))*(170.8/H6)-98.88)/5.33)*1.34)+6.7)/((170.8/H6)^3)) -> -30.445475 | I48: =((((I19-56)/1.44)*0.18)+1.2)/((170.8/I6)^3)+((((((I33+I36+(2*I37)+(2*I38))*(170.8/I6)-98.88)/5.33)*1.34)+6.7)/((170.8/I6)^3)) -> -30.445475 | J48: =((((J19-56)/1.44)*0.18)+1.2)/((170.8/J6)^3)+((((((J33+J36+(2*J37)+(2*J38))*(170.8/J6)-98.88)/5.33)*1.34)+6.7)/((170.8/J6)^3)) -> -30.445475 | ... L48: =((((L19-56)/1.44)*0.18)+1.2)/((170.8/L6)^3)+((((((L33+L36+(2*L37)+(2*L38))*(170.8/L6)-98.88)/5.33)*1.34)+6.7)/((170.8/L6)^3)) -> -30.445475
B49: Masa adiposa (Kg) | C49: =(((((C10+C11+C14+C15+C16+C17)*(170.18/C6)-116.41)/34.79)*5.85)+25.6)/((170.18/C6)^3) -> 7.7406835 | D49: =(((((D10+D11+D14+D15+D16+D17)*(170.18/D6)-116.41)/34.79)*5.85)+25.6)/((170.18/D6)^3) -> 7.7406835 | E49: =(((((E10+E11+E14+E15+E16+E17)*(170.18/E6)-116.41)/34.79)*5.85)+25.6)/((170.18/E6)^3) -> 7.7406835 | F49: =(((((F10+F11+F14+F15+F16+F17)*(170.18/F6)-116.41)/34.79)*5.85)+25.6)/((170.18/F6)^3) -> 7.7406835 | G49: =(((((G10+G11+G14+G15+G16+G17)*(170.18/G6)-116.41)/34.79)*5.85)+25.6)/((170.18/G6)^3) -> 7.7406835 | H49: =(((((H10+H11+H14+H15+H16+H17)*(170.18/H6)-116.41)/34.79)*5.85)+25.6)/((170.18/H6)^3) -> 7.7406835 | I49: =(((((I10+I11+I14+I15+I16+I17)*(170.18/I6)-116.41)/34.79)*5.85)+25.6)/((170.18/I6)^3) -> 7.7406835 | J49: =(((((J10+J11+J14+J15+J16+J17)*(170.18/J6)-116.41)/34.79)*5.85)+25.6)/((170.18/J6)^3) -> 7.7406835 | ... L49: =(((((L10+L11+L14+L15+L16+L17)*(170.18/L6)-116.41)/34.79)*5.85)+25.6)/((170.18/L6)^3) -> 7.7406835
B50: Masa muscular (Kg) | C50: =(((((C41+C23+C43+C44+C42)*(170.18/C6))-207.21)/13.74*5.4)+24.5)/((170.18/C6)^3) -> -73.143956 | D50: =(((((D41+D23+D43+D44+D42)*(170.18/D6))-207.21)/13.74*5.4)+24.5)/((170.18/D6)^3) -> -73.143956 | E50: =(((((E41+E23+E43+E44+E42)*(170.18/E6))-207.21)/13.74*5.4)+24.5)/((170.18/E6)^3) -> -73.143956 | F50: =(((((F41+F23+F43+F44+F42)*(170.18/F6))-207.21)/13.74*5.4)+24.5)/((170.18/F6)^3) -> -73.143956 | G50: =(((((G41+G23+G43+G44+G42)*(170.18/G6))-207.21)/13.74*5.4)+24.5)/((170.18/G6)^3) -> -73.143956 | H50: =(((((H41+H23+H43+H44+H42)*(170.18/H6))-207.21)/13.74*5.4)+24.5)/((170.18/H6)^3) -> -73.143956 | I50: =(((((I41+I23+I43+I44+I42)*(170.18/I6))-207.21)/13.74*5.4)+24.5)/((170.18/I6)^3) -> -73.143956 | J50: =(((((J41+J23+J43+J44+J42)*(170.18/J6))-207.21)/13.74*5.4)+24.5)/((170.18/J6)^3) -> -73.143956 | ... L50: =(((((L41+L23+L43+L44+L42)*(170.18/L6))-207.21)/13.74*5.4)+24.5)/((170.18/L6)^3) -> -73.143956
B51: Masa residual (Kg) | C51: =(((((C35+C34+C45)*(89.92/C7)-109.35)/7.08)*1.24)+6.1)/((89.92/C7)^3) -> 1.427261 | D51: =(((((D35+D34+D45)*(89.92/D7)-109.35)/7.08)*1.24)+6.1)/((89.92/D7)^3) -> 1.427261 | E51: =(((((E35+E34+E45)*(89.92/E7)-109.35)/7.08)*1.24)+6.1)/((89.92/E7)^3) -> 1.427261 | F51: =(((((F35+F34+F45)*(89.92/F7)-109.35)/7.08)*1.24)+6.1)/((89.92/F7)^3) -> 1.427261 | G51: =(((((G35+G34+G45)*(89.92/G7)-109.35)/7.08)*1.24)+6.1)/((89.92/G7)^3) -> 1.427261 | H51: =(((((H35+H34+H45)*(89.92/H7)-109.35)/7.08)*1.24)+6.1)/((89.92/H7)^3) -> 1.427261 | I51: =(((((I35+I34+I45)*(89.92/I7)-109.35)/7.08)*1.24)+6.1)/((89.92/I7)^3) -> 1.427261 | J51: =(((((J35+J34+J45)*(89.92/J7)-109.35)/7.08)*1.24)+6.1)/((89.92/J7)^3) -> 1.427261 | ... L51: =(((((L35+L34+L45)*(89.92/L7)-109.35)/7.08)*1.24)+6.1)/((89.92/L7)^3) -> 1.427261
B52: Peso estructurado (Kg) | C52: =SUM(C47:C51) -> -94.421487 | D52: =SUM(D47:D51) -> -94.421487 | E52: =SUM(E47:E51) -> -94.421487 | F52: =SUM(F47:F51) -> -94.421487 | G52: =SUM(G47:G51) -> -94.421487 | H52: =SUM(H47:H51) -> -94.421487 | I52: =SUM(I47:I51) -> -94.421487 | J52: =SUM(J47:J51) -> -94.421487 | ... L52: =SUM(L47:L51) -> -94.421487
B53: Diferencia con peso bruto (Kg) | C53: =C52-C5 -> -94.421487 | D53: =D52-D5 -> -94.421487 | E53: =E52-E5 -> -94.421487 | F53: =F52-F5 -> -94.421487 | G53: =G52-G5 -> -94.421487 | H53: =H52-H5 -> -94.421487 | I53: =I52-I5 -> -94.421487 | J53: =J52-J5 -> -94.421487 | ... L53: =L52-L5 -> -94.421487
B54: Diferencia con peso bruto (%) | C54: =(100-((C52/C5)*100))*-1 -> #DIV/0! | D54: =(100-((D52/D5)*100))*-1 -> #DIV/0! | E54: =(100-((E52/E5)*100))*-1 -> #DIV/0! | F54: =(100-((F52/F5)*100))*-1 -> #DIV/0! | G54: =(100-((G52/G5)*100))*-1 -> #DIV/0! | H54: =(100-((H52/H5)*100))*-1 -> #DIV/0! | I54: =(100-((I52/I5)*100))*-1 -> #DIV/0! | J54: =(100-((J52/J5)*100))*-1 -> #DIV/0! | ... L54: =(100-((L52/L5)*100))*-1 -> #DIV/0!
A56: Composición corporal porcentual (5 componentes) | B56: Masa de la piel (%) | C56: =(C47*100)/C52 -> 0 | D56: =(D47*100)/D52 -> 0 | E56: =(E47*100)/E52 -> 0 | F56: =(F47*100)/F52 -> 0 | G56: =(G47*100)/G52 -> 0 | H56: =(H47*100)/H52 -> 0 | I56: =(I47*100)/I52 -> 0 | J56: =(J47*100)/J52 -> 0 | ... L56: =(L47*100)/L52 -> 0
B57: Masa ósea total (%) | C57: =(C48*100)/C52 -> 32.244223 | D57: =(D48*100)/D52 -> 32.244223 | E57: =(E48*100)/E52 -> 32.244223 | F57: =(F48*100)/F52 -> 32.244223 | G57: =(G48*100)/G52 -> 32.244223 | H57: =(H48*100)/H52 -> 32.244223 | I57: =(I48*100)/I52 -> 32.244223 | J57: =(J48*100)/J52 -> 32.244223 | ... L57: =(L48*100)/L52 -> 32.244223
B58: Masa adiposa (%) | C58: =(C49*100)/C52 -> -8.1980106 | D58: =(D49*100)/D52 -> -8.1980106 | E58: =(E49*100)/E52 -> -8.1980106 | F58: =(F49*100)/F52 -> -8.1980106 | G58: =(G49*100)/G52 -> -8.1980106 | H58: =(H49*100)/H52 -> -8.1980106 | I58: =(I49*100)/I52 -> -8.1980106 | J58: =(J49*100)/J52 -> -8.1980106 | ... L58: =(L49*100)/L52 -> -8.1980106
B59: Masa muscular (%) | C59: =(C50*100)/C52 -> 77.465372 | D59: =(D50*100)/D52 -> 77.465372 | E59: =(E50*100)/E52 -> 77.465372 | F59: =(F50*100)/F52 -> 77.465372 | G59: =(G50*100)/G52 -> 77.465372 | H59: =(H50*100)/H52 -> 77.465372 | I59: =(I50*100)/I52 -> 77.465372 | J59: =(J50*100)/J52 -> 77.465372 | ... L59: =(L50*100)/L52 -> 77.465372
B60: Masa residual (%) | C60: =(C51*100)/C52 -> -1.5115849 | D60: =(D51*100)/D52 -> -1.5115849 | E60: =(E51*100)/E52 -> -1.5115849 | F60: =(F51*100)/F52 -> -1.5115849 | G60: =(G51*100)/G52 -> -1.5115849 | H60: =(H51*100)/H52 -> -1.5115849 | I60: =(I51*100)/I52 -> -1.5115849 | J60: =(J51*100)/J52 -> -1.5115849 | ... L60: =(L51*100)/L52 -> -1.5115849
B61: Masa total (%) | C61: =SUM(C56:C60) -> 100 | D61: =SUM(D56:D60) -> 100 | E61: =SUM(E56:E60) -> 100 | F61: =SUM(F56:F60) -> 100 | G61: =SUM(G56:G60) -> 100 | H61: =SUM(H56:H60) -> 100 | I61: =SUM(I56:I60) -> 100 | J61: =SUM(J56:J60) -> 100 | ... L61: =SUM(L56:L60) -> 100
A63: Composición corporal absoluta corregida (5 componentes) | B63: Masa de la piel (Kg) | C63: =C47-(C53*C56)/100 -> 0 | D63: =D47-(D53*D56)/100 -> 0 | E63: =E47-(E53*E56)/100 -> 0 | F63: =F47-(F53*F56)/100 -> 0 | G63: =G47-(G53*G56)/100 -> 0 | H63: =H47-(H53*H56)/100 -> 0 | I63: =I47-(I53*I56)/100 -> 0 | J63: =J47-(J53*J56)/100 -> 0 | ... L63: =L47-(L53*L56)/100 -> 0
B64: Masa ósea total (Kg) | C64: =C48-(C53*C57)/100 -> 0 | D64: =D48-(D53*D57)/100 -> 0 | E64: =E48-(E53*E57)/100 -> 0 | F64: =F48-(F53*F57)/100 -> 0 | G64: =G48-(G53*G57)/100 -> 0 | H64: =H48-(H53*H57)/100 -> 0 | I64: =I48-(I53*I57)/100 -> 0 | J64: =J48-(J53*J57)/100 -> 0 | ... L64: =L48-(L53*L57)/100 -> 0
B65: Masa adiposa (Kg) | C65: =C49-(C53*C58)/100 -> 0 | D65: =D49-(D53*D58)/100 -> 0 | E65: =E49-(E53*E58)/100 -> 0 | F65: =F49-(F53*F58)/100 -> 0 | G65: =G49-(G53*G58)/100 -> 0 | H65: =H49-(H53*H58)/100 -> 0 | I65: =I49-(I53*I58)/100 -> 0 | J65: =J49-(J53*J58)/100 -> 0 | ... L65: =L49-(L53*L58)/100 -> 0
B66: Masa muscular (Kg) | C66: =C50-(C53*C59)/100 -> 0 | D66: =D50-(D53*D59)/100 -> 0 | E66: =E50-(E53*E59)/100 -> 0 | F66: =F50-(F53*F59)/100 -> 0 | G66: =G50-(G53*G59)/100 -> 0 | H66: =H50-(H53*H59)/100 -> 0 | I66: =I50-(I53*I59)/100 -> 0 | J66: =J50-(J53*J59)/100 -> 0 | ... L66: =L50-(L53*L59)/100 -> 0
B67: Masa residual (Kg) | C67: =C51-(C53*C60)/100 -> 0 | D67: =D51-(D53*D60)/100 -> 0 | E67: =E51-(E53*E60)/100 -> 0 | F67: =F51-(F53*F60)/100 -> 0 | G67: =G51-(G53*G60)/100 -> 0 | H67: =H51-(H53*H60)/100 -> 0 | I67: =I51-(I53*I60)/100 -> 0 | J67: =J51-(J53*J60)/100 -> 0 | ... L67: =L51-(L53*L60)/100 -> 0
B68: Masa total (Kg) | C68: =SUM(C63:C67) -> 0 | D68: =SUM(D63:D67) -> 0 | E68: =SUM(E63:E67) -> 0 | F68: =SUM(F63:F67) -> 0 | G68: =SUM(G63:G67) -> 0 | H68: =SUM(H63:H67) -> 0 | I68: =SUM(I63:I67) -> 0 | J68: =SUM(J63:J67) -> 0 | ... L68: =SUM(L63:L67) -> 0
B70: Sumatoria de 6 pliegues (mm) | C70: =C10+C11+C14+C15+C16+C17 -> 0 | D70: =D10+D11+D14+D15+D16+D17 -> 0 | E70: =E10+E11+E14+E15+E16+E17 -> 0 | F70: =F10+F11+F14+F15+F16+F17 -> 0 | G70: =G10+G11+G14+G15+G16+G17 -> 0 | H70: =H10+H11+H14+H15+H16+H17 -> 0 | I70: =I10+I11+I14+I15+I16+I17 -> 0 | J70: =J10+J11+J14+J15+J16+J17 -> 0 | ... L70: =L10+L11+L14+L15+L16+L17 -> 0
B71: Cociente muscular/óseo | C71: =C50/C48 -> 2.4024574 | D71: =D50/D48 -> 2.4024574 | E71: =E50/E48 -> 2.4024574 | F71: =F50/F48 -> 2.4024574 | G71: =G50/G48 -> 2.4024574 | H71: =H50/H48 -> 2.4024574 | I71: =I50/I48 -> 2.4024574 | J71: =J50/J48 -> 2.4024574 | ... L71: =L50/L48 -> 2.4024574
A72: Composición corporal (2 componentes) | B72: IMC (Kg/m2) | C72: =(C5)/((C6/100)^2) -> 0 | D72: =(D5)/((D6/100)^2) -> 0 | E72: =(E5)/((E6/100)^2) -> 0 | F72: =(F5)/((F6/100)^2) -> 0 | G72: =(G5)/((G6/100)^2) -> 0 | H72: =(H5)/((H6/100)^2) -> 0 | I72: =(I5)/((I6/100)^2) -> 0 | J72: =(J5)/((J6/100)^2) -> 0 | ... L72: =(L5)/((L6/100)^2) -> 0
B73: índice Cintura/Cadera | C73: =C26/C27 -> #DIV/0! | D73: =D26/D27 -> #DIV/0! | E73: =E26/E27 -> #DIV/0! | F73: =F26/F27 -> #DIV/0! | G73: =G26/G27 -> #DIV/0! | H73: =H26/H27 -> #DIV/0! | I73: =I26/I27 -> #DIV/0! | J73: =J26/J27 -> #DIV/0! | ... L73: =L26/L27 -> #DIV/0!
B74: Contextura | C74: =(C37/(C6/100))*10 -> 0 | D74: =(D37/(D6/100))*10 -> 0 | E74: =(E37/(E6/100))*10 -> 0 | F74: =(F37/(F6/100))*10 -> 0 | G74: =(G37/(G6/100))*10 -> 0 | H74: =(H37/(H6/100))*10 -> 0 | I74: =(I37/(I6/100))*10 -> 0 | J74: =(J37/(J6/100))*10 -> 0 | ... L74: =(L37/(L6/100))*10 -> 0
B75: Área grasa del brazo (cm2) | C75: =(C10/10)*C21/2-((C10/10)*(C10/10)*3.1416/4) -> 0 | D75: =(D10/10)*D21/2-((D10/10)*(D10/10)*3.1416/4) -> 0 | E75: =(E10/10)*E21/2-((E10/10)*(E10/10)*3.1416/4) -> 0 | F75: =(F10/10)*F21/2-((F10/10)*(F10/10)*3.1416/4) -> 0 | G75: =(G10/10)*G21/2-((G10/10)*(G10/10)*3.1416/4) -> 0 | H75: =(H10/10)*H21/2-((H10/10)*(H10/10)*3.1416/4) -> 0 | I75: =(I10/10)*I21/2-((I10/10)*(I10/10)*3.1416/4) -> 0 | J75: =(J10/10)*J21/2-((J10/10)*(J10/10)*3.1416/4) -> 0 | ... L75: =(L10/10)*L21/2-((L10/10)*(L10/10)*3.1416/4) -> 0
B76: Área magra del brazo (cm2) | C76: =((C21-(C10/10)*3.1416)*(C21-(C10/10)*3.1416)/12.5664-10) -> -10 | D76: =((D21-(D10/10)*3.1416)*(D21-(D10/10)*3.1416)/12.5664-10) -> -10 | E76: =((E21-(E10/10)*3.1416)*(E21-(E10/10)*3.1416)/12.5664-10) -> -10 | F76: =((F21-(F10/10)*3.1416)*(F21-(F10/10)*3.1416)/12.5664-10) -> -10 | G76: =((G21-(G10/10)*3.1416)*(G21-(G10/10)*3.1416)/12.5664-10) -> -10 | H76: =((H21-(H10/10)*3.1416)*(H21-(H10/10)*3.1416)/12.5664-10) -> -10 | I76: =((I21-(I10/10)*3.1416)*(I21-(I10/10)*3.1416)/12.5664-10) -> -10 | J76: =((J21-(J10/10)*3.1416)*(J21-(J10/10)*3.1416)/12.5664-10) -> -10 | ... L76: =((L21-(L10/10)*3.1416)*(L21-(L10/10)*3.1416)/12.5664-10) -> -10
B77: Sumatoria de 4 pliegues (mm) | C77: =C10+C11+C12+C13 -> 0 | D77: =D10+D11+D12+D13 -> 0 | E77: =E10+E11+E12+E13 -> 0 | F77: =F10+F11+F12+F13 -> 0 | G77: =G10+G11+G12+G13 -> 0 | H77: =H10+H11+H12+H13 -> 0 | I77: =I10+I11+I12+I13 -> 0 | J77: =J10+J11+J12+J13 -> 0 | ... L77: =L10+L11+L12+L13 -> 0
B78: Sumatoria de 8 pliegues (mm) | C78: =SUM(C10:C17) -> 0 | D78: =SUM(D10:D17) -> 0 | E78: =SUM(E10:E17) -> 0 | F78: =SUM(F10:F17) -> 0 | G78: =SUM(G10:G17) -> 0 | H78: =SUM(H10:H17) -> 0 | I78: =SUM(I10:I17) -> 0 | J78: =SUM(J10:J17) -> 0 | ... L78: =SUM(L10:L17) -> 0
B79: % Grasa (Durnin y W., 1974) | C79: =(((0.2467)*(C12+C10+C11+C13))+((0.12*C26)))-2.18 -> -2.18 | D79: =(((0.2467)*(D12+D10+D11+D13))+((0.12*D26)))-2.18 -> -2.18 | E79: =(((0.2467)*(E12+E10+E11+E13))+((0.12*E26)))-2.18 -> -2.18 | F79: =(((0.2467)*(F12+F10+F11+F13))+((0.12*F26)))-2.18 -> -2.18 | G79: =(((0.2467)*(G12+G10+G11+G13))+((0.12*G26)))-2.18 -> -2.18 | H79: =(((0.2467)*(H12+H10+H11+H13))+((0.12*H26)))-2.18 -> -2.18 | I79: =(((0.2467)*(I12+I10+I11+I13))+((0.12*I26)))-2.18 -> -2.18 | J79: =(((0.2467)*(J12+J10+J11+J13))+((0.12*J26)))-2.18 -> -2.18 | ... L79: =(((0.2467)*(L12+L10+L11+L13))+((0.12*L26)))-2.18 -> -2.18
B80: % Grasa (Carter, 1986) Hombres | C80: =(2.585)+(0.1051*(C10+C11+C15+C14+C16+C17)) -> 2.585 | D80: =(2.585)+(0.1051*(D10+D11+D15+D14+D16+D17)) -> 2.585 | E80: =(2.585)+(0.1051*(E10+E11+E15+E14+E16+E17)) -> 2.585 | F80: =(2.585)+(0.1051*(F10+F11+F15+F14+F16+F17)) -> 2.585 | G80: =(2.585)+(0.1051*(G10+G11+G15+G14+G16+G17)) -> 2.585 | H80: =(2.585)+(0.1051*(H10+H11+H15+H14+H16+H17)) -> 2.585 | I80: =(2.585)+(0.1051*(I10+I11+I15+I14+I16+I17)) -> 2.585 | J80: =(2.585)+(0.1051*(J10+J11+J15+J14+J16+J17)) -> 2.585 | ... L80: =(2.585)+(0.1051*(L10+L11+L15+L14+L16+L17)) -> 2.585
B81: Porcentaje a utilizar | C81: =C80 -> 2.585 | D81: =D80 -> 2.585 | E81: =E80 -> 2.585 | F81: =F80 -> 2.585 | G81: =G80 -> 2.585 | H81: =H80 -> 2.585 | I81: =I80 -> 2.585 | J81: =J80 -> 2.585 | ... L81: =L80 -> 2.585
B82: Masa magra (Kg) | C82: =((100-C81)*C5)/100 -> 0 | D82: =((100-D81)*D5)/100 -> 0 | E82: =((100-E81)*E5)/100 -> 0 | F82: =((100-F81)*F5)/100 -> 0 | G82: =((100-G81)*G5)/100 -> 0 | H82: =((100-H81)*H5)/100 -> 0 | I82: =((100-I81)*I5)/100 -> 0 | J82: =((100-J81)*J5)/100 -> 0 | ... L82: =((100-L81)*L5)/100 -> 0
B83: Masa grasa (Kg) | C83: =C5-C82 -> 0 | D83: =D5-D82 -> 0 | E83: =E5-E82 -> 0 | F83: =F5-F82 -> 0 | G83: =G5-G82 -> 0 | H83: =H5-H82 -> 0 | I83: =I5-I82 -> 0 | J83: =J5-J82 -> 0 | ... L83: =L5-L82 -> 0
B84: % Grasa objetivo mínimo | C84: 6 | D84: 6 | E84: 6 | F84: 6 | G84: 6 | H84: 6 | I84: 6 | J84: 6 | K84: 6 | L84: 6
B85: % Grasa objetivo máximo | C85: 8 | D85: 8 | E85: 8 | F85: 8 | G85: 8 | H85: 8 | I85: 8 | J85: 8 | K85: 8 | L85: 8
B86: Peso objetivo mínimo (Kg) | C86: =(C82)/(1-C84/100) -> 0 | D86: =(D82)/(1-D84/100) -> 0 | E86: =(E82)/(1-E84/100) -> 0 | F86: =(F82)/(1-F84/100) -> 0 | G86: =(G82)/(1-G84/100) -> 0 | H86: =(H82)/(1-H84/100) -> 0 | I86: =(I82)/(1-I84/100) -> 0 | J86: =(J82)/(1-J84/100) -> 0 | ... L86: =(L82)/(1-L84/100) -> 0
B87: Peso objetivo máximo (Kg) | C87: =(C82)/(1-C85/100) -> 0 | D87: =(D82)/(1-D85/100) -> 0 | E87: =(E82)/(1-E85/100) -> 0 | F87: =(F82)/(1-F85/100) -> 0 | G87: =(G82)/(1-G85/100) -> 0 | H87: =(H82)/(1-H85/100) -> 0 | I87: =(I82)/(1-I85/100) -> 0 | J87: =(J82)/(1-J85/100) -> 0 | ... L87: =(L82)/(1-L85/100) -> 0
B88: Pérdida de grasa objetivo (Kg) | C88: =C86-C5 -> 0 | D88: =D86-D5 -> 0 | E88: =E86-E5 -> 0 | F88: =F86-F5 -> 0 | G88: =G86-G5 -> 0 | H88: =H86-H5 -> 0 | I88: =I86-I5 -> 0 | J88: =J86-J5 -> 0 | ... L88: =L86-L5 -> 0
B89: Índice de sustancia activa (AKS) | C89: =(C82*100000/(C6^3)) -> 0 | D89: =(D82*100000/(D6^3)) -> 0 | E89: =(E82*100000/(E6^3)) -> 0 | F89: =(F82*100000/(F6^3)) -> 0 | G89: =(G82*100000/(G6^3)) -> 0 | H89: =(H82*100000/(H6^3)) -> 0 | I89: =(I82*100000/(I6^3)) -> 0 | J89: =(J82*100000/(J6^3)) -> 0 | ... L89: =(L82*100000/(L6^3)) -> 0
A90: DATOS BÁSICOS | B90: Nombre y apellido | C90: =C1 -> Javier Ignacio Alvarez Izaguirre | D90: =D1 -> 0 | E90: =E1 -> 0 | F90: =F1 -> 0 | G90: =G1 -> 0 | H90: =H1 -> 0 | I90: =I1 -> 0 | J90: =J1 -> 0 | ... L90: =L1 -> 0
B91: Estatura (cm) | C91: =C6 -> 185 | D91: =D6 -> 185 | E91: =E6 -> 185 | F91: =F6 -> 185 | G91: =G6 -> 185 | H91: =H6 -> 185 | I91: =I6 -> 185 | J91: =J6 -> 185 | ... L91: =L6 -> 185
B92: Peso (Kg) | C92: =C5 -> 0 | D92: =D5 -> 0 | E92: =E5 -> 0 | F92: =F5 -> 0 | G92: =G5 -> 0 | H92: =H5 -> 0 | I92: =I5 -> 0 | J92: =J5 -> 0 | ... L92: =L5 -> 0
B93: Altura/peso^1/3: | C93: =C91/(C92^0.3333) -> #DIV/0! | D93: =D91/(D92^0.3333) -> #DIV/0! | E93: =E91/(E92^0.3333) -> #DIV/0! | F93: =F91/(F92^0.3333) -> #DIV/0! | G93: =G91/(G92^0.3333) -> #DIV/0! | H93: =H91/(H92^0.3333) -> #DIV/0! | I93: =I91/(I92^0.3333) -> #DIV/0! | J93: =J91/(J92^0.3333) -> #DIV/0! | ... L93: =L91/(L92^0.3333) -> #DIV/0!
A94: PLIEGUES (mm) | B94: Tríceps | C94: =C10 -> 0 | D94: =D10 -> 0 | E94: =E10 -> 0 | F94: =F10 -> 0 | G94: =G10 -> 0 | H94: =H10 -> 0 | I94: =I10 -> 0 | J94: =J10 -> 0 | ... L94: =L10 -> 0
B95: Subescapular | C95: =C11 -> 0 | D95: =D11 -> 0 | E95: =E11 -> 0 | F95: =F11 -> 0 | G95: =G11 -> 0 | H95: =H11 -> 0 | I95: =I11 -> 0 | J95: =J11 -> 0 | ... L95: =L11 -> 0
B96: Supraespinal | C96: =C17 -> 0 | D96: =D17 -> 0 | E96: =E17 -> 0 | F96: =F17 -> 0 | G96: =G17 -> 0 | H96: =H17 -> 0 | I96: =I17 -> 0 | J96: =J17 -> 0 | ... L96: =L17 -> 0
B97: Pantorrilla media | C97: =C17 -> 0 | D97: =D17 -> 0 | E97: =E17 -> 0 | F97: =F17 -> 0 | G97: =G17 -> 0 | H97: =H17 -> 0 | I97: =I17 -> 0 | J97: =J17 -> 0 | ... L97: =L17 -> 0
A98: CIRCUNFERENCIAS (cm) | B98: Bíceps flexionado | C98: =C22 -> 0 | D98: =D22 -> 0 | E98: =E22 -> 0 | F98: =F22 -> 0 | G98: =G22 -> 0 | H98: =H22 -> 0 | I98: =I22 -> 0 | J98: =J22 -> 0 | ... L98: =L22 -> 0
B99: Pantorrilla máxima | C99: =C30 -> 0 | D99: =D30 -> 0 | E99: =E30 -> 0 | F99: =F30 -> 0 | G99: =G30 -> 0 | H99: =H30 -> 0 | I99: =I30 -> 0 | J99: =J30 -> 0 | ... L99: =L30 -> 0
A100: DIÁMETROS (mm) | B100: HUMERO-biepicondylar | C100: =C37 -> 0 | D100: =D37 -> 0 | E100: =E37 -> 0 | F100: =F37 -> 0 | G100: =G37 -> 0 | H100: =H37 -> 0 | I100: =I37 -> 0 | J100: =J37 -> 0 | ... L100: =L37 -> 0
B101: FEMUR-biepicondylar | C101: =C38 -> 0 | D101: =D38 -> 0 | E101: =E38 -> 0 | F101: =F38 -> 0 | G101: =G38 -> 0 | H101: =H38 -> 0 | I101: =I38 -> 0 | J101: =J38 -> 0 | ... L101: =L38 -> 0
A102: SUMATORIAS | B102: Sum 3 skinfolds | C102: =SUM(C94:C96) -> 0 | D102: =SUM(D94:D96) -> 0 | E102: =SUM(E94:E96) -> 0 | F102: =SUM(F94:F96) -> 0 | G102: =SUM(G94:G96) -> 0 | H102: =SUM(H94:H96) -> 0 | I102: =SUM(I94:I96) -> 0 | J102: =SUM(J94:J96) -> 0 | ... L102: =SUM(L94:L96) -> 0
B103: Sum 3 (ht-corrected) | C103: =(170.18/C91)*C102 -> 0 | D103: =(170.18/D91)*D102 -> 0 | E103: =(170.18/E91)*E102 -> 0 | F103: =(170.18/F91)*F102 -> 0 | G103: =(170.18/G91)*G102 -> 0 | H103: =(170.18/H91)*H102 -> 0 | I103: =(170.18/I91)*I102 -> 0 | J103: =(170.18/J91)*J102 -> 0 | ... L103: =(170.18/L91)*L102 -> 0
B104: Sum 3 squared | C104: =(C103^2) -> 0 | D104: =(D103^2) -> 0 | E104: =(E103^2) -> 0 | F104: =(F103^2) -> 0 | G104: =(G103^2) -> 0 | H104: =(H103^2) -> 0 | I104: =(I103^2) -> 0 | J104: =(J103^2) -> 0 | ... L104: =(L103^2) -> 0
B105: Sum 3 cubed | C105: =(C103^3) -> 0 | D105: =(D103^3) -> 0 | E105: =(E103^3) -> 0 | F105: =(F103^3) -> 0 | G105: =(G103^3) -> 0 | H105: =(H103^3) -> 0 | I105: =(I103^3) -> 0 | J105: =(J103^3) -> 0 | ... L105: =(L103^3) -> 0
A106: OTROS | B106: Corrected Biceps G | C106: =(C98-(C94/10)) -> 0 | D106: =(D98-(D94/10)) -> 0 | E106: =(E98-(E94/10)) -> 0 | F106: =(F98-(F94/10)) -> 0 | G106: =(G98-(G94/10)) -> 0 | H106: =(H98-(H94/10)) -> 0 | I106: =(I98-(I94/10)) -> 0 | J106: =(J98-(J94/10)) -> 0 | ... L106: =(L98-(L94/10)) -> 0
B107: Corrected Calf G | C107: =(C99-(C97/10)) -> 0 | D107: =(D99-(D97/10)) -> 0 | E107: =(E99-(E97/10)) -> 0 | F107: =(F99-(F97/10)) -> 0 | G107: =(G99-(G97/10)) -> 0 | H107: =(H99-(H97/10)) -> 0 | I107: =(I99-(I97/10)) -> 0 | J107: =(J99-(J97/10)) -> 0 | ... L107: =(L99-(L97/10)) -> 0
A108: VALORACIÓN DEL SOMATOTIPO (decimal) | B108: ENDOMORFIA | C108: =(-0.7182+(0.1451*C103)-(0.00068*C104)+(0.0000014*C105)) -> -0.7182 | D108: =(-0.7182+(0.1451*D103)-(0.00068*D104)+(0.0000014*D105)) -> -0.7182 | E108: =(-0.7182+(0.1451*E103)-(0.00068*E104)+(0.0000014*E105)) -> -0.7182 | F108: =(-0.7182+(0.1451*F103)-(0.00068*F104)+(0.0000014*F105)) -> -0.7182 | G108: =(-0.7182+(0.1451*G103)-(0.00068*G104)+(0.0000014*G105)) -> -0.7182 | H108: =(-0.7182+(0.1451*H103)-(0.00068*H104)+(0.0000014*H105)) -> -0.7182 | I108: =(-0.7182+(0.1451*I103)-(0.00068*I104)+(0.0000014*I105)) -> -0.7182 | J108: =(-0.7182+(0.1451*J103)-(0.00068*J104)+(0.0000014*J105)) -> -0.7182 | ... L108: =(-0.7182+(0.1451*L103)-(0.00068*L104)+(0.0000014*L105)) -> -0.7182
...

Sheet ARGO-REF
A1: PESO (kg) | K1: PUNTUACIÓN Z PHANTOM ADIPOSA
A2: Edad | B2: n | C2: Media | D2: Mediana | E2: Desv. Est. | F2: Máximo | G2: Mínimo | H2: IC95%sup | I2: IC95%inf | K2: Edad | L2: n | M2: Media | N2: Mediana | O2: Desv. Est. | P2: Máximo | Q2: Mínimo | R2: IC95%sup | S2: IC95%inf
A3: 7 | B3: 14 | C3: 29.421 | D3: 27.5 | E3: 4.897 | F3: 40 | G3: 23.6 | H3: =C3+(1.96*E3)/(B3)^0.5 -> 31.986205 | I3: =C3-(1.96*E3)/(B3)^0.5 -> 26.855795 | K3: 7 | L3: 14 | M3: -1.086 | N3: -1.5 | O3: 0.921 | P3: 0.7 | Q3: -2.2 | R3: =M3+(1.96*O3)/(L3)^0.5 -> -0.6035507 | S3: =M3-(1.96*O3)/(L3)^0.5 -> -1.5684493
A4: 8 | B4: 39 | C4: 31.313 | D4: 28.6 | E4: 7.714 | F4: 49 | G4: 21 | H4: =C4+(1.96*E4)/(B4)^0.5 -> 33.734048 | I4: =C4-(1.96*E4)/(B4)^0.5 -> 28.891952 | K4: 8 | L4: 39 | M4: -0.541 | N4: -1.2 | O4: 1.544 | P4: 3.1 | Q4: -2.1 | R4: =M4+(1.96*O4)/(L4)^0.5 -> -0.056413776 | S4: =M4-(1.96*O4)/(L4)^0.5 -> -1.0255862
A5: 9 | B5: 57 | C5: 32 | D5: 30 | E5: 7.151 | F5: 62.9 | G5: 20.7 | H5: =C5+(1.96*E5)/(B5)^0.5 -> 33.856459 | I5: =C5-(1.96*E5)/(B5)^0.5 -> 30.143541 | K5: 9 | L5: 57 | M5: -1.065 | N5: -1.5 | O5: 1.172 | P5: 2.8 | Q5: -2.4 | R5: =M5+(1.96*O5)/(L5)^0.5 -> -0.76073902 | S5: =M5-(1.96*O5)/(L5)^0.5 -> -1.369261
A6: 10 | B6: 66 | C6: 35.612 | D6: 32.5 | E6: 8.438 | F6: 61.1 | G6: 22.8 | H6: =C6+(1.96*E6)/(B6)^0.5 -> 37.647746 | I6: =C6-(1.96*E6)/(B6)^0.5 -> 33.576254 | K6: 10 | L6: 66 | M6: -0.617 | N6: -1.05 | O6: 1.535 | P6: 4.6 | Q6: -2.4 | R6: =M6+(1.96*O6)/(L6)^0.5 -> -0.24666694 | S6: =M6-(1.96*O6)/(L6)^0.5 -> -0.98733306
A7: 11 | B7: 55 | C7: 39.996 | D7: 39 | E7: 9.772 | F7: 76 | G7: 24.6 | H7: =C7+(1.96*E7)/(B7)^0.5 -> 42.578606 | I7: =C7-(1.96*E7)/(B7)^0.5 -> 37.413394 | K7: 11 | L7: 55 | M7: -0.76 | N7: -1.4 | O7: 1.59 | P7: 4.4 | Q7: -2.2 | R7: =M7+(1.96*O7)/(L7)^0.5 -> -0.33978471 | S7: =M7-(1.96*O7)/(L7)^0.5 -> -1.1802153
A8: 12 | B8: 35 | C8: 46.289 | D8: 44 | E8: 13.53 | F8: 99.9 | G8: 30.4 | H8: =C8+(1.96*E8)/(B8)^0.5 -> 50.771495 | I8: =C8-(1.96*E8)/(B8)^0.5 -> 41.806505 | K8: 12 | L8: 35 | M8: -0.494 | N8: -0.9 | O8: 1.439 | P8: 4.1 | Q8: -2.3 | R8: =M8+(1.96*O8)/(L8)^0.5 -> -0.017258627 | S8: =M8-(1.96*O8)/(L8)^0.5 -> -0.97074137
A9: 13 | B9: 64 | C9: 51.791 | D9: 51 | E9: 9.914 | F9: 78.9 | G9: 32.4 | H9: =C9+(1.96*E9)/(B9)^0.5 -> 54.21993 | I9: =C9-(1.96*E9)/(B9)^0.5 -> 49.36207 | K9: 13 | L9: 64 | M9: -1.263 | N9: -1.6 | O9: 0.93 | P9: 2.4 | Q9: -2.3 | R9: =M9+(1.96*O9)/(L9)^0.5 -> -1.03515 | S9: =M9-(1.96*O9)/(L9)^0.5 -> -1.49085
A10: 14 | B10: 87 | C10: 58.705 | D10: 57.1 | E10: 14.336 | F10: 132.2 | G10: 34 | H10: =C10+(1.96*E10)/(B10)^0.5 -> 61.717482 | I10: =C10-(1.96*E10)/(B10)^0.5 -> 55.692518 | K10: 14 | L10: 87 | M10: -1.222 | N10: -1.6 | O10: 1.162 | P10: 3.2 | Q10: -2.4 | R10: =M10+(1.96*O10)/(L10)^0.5 -> -0.97782423 | S10: =M10-(1.96*O10)/(L10)^0.5 -> -1.4661758
A11: 15 | B11: 70 | C11: 63.237 | D11: 60.4 | E11: 13.3 | F11: 117.4 | G11: 43.8 | H11: =C11+(1.96*E11)/(B11)^0.5 -> 66.352722 | I11: =C11-(1.96*E11)/(B11)^0.5 -> 60.121278 | K11: 15 | L11: 70 | M11: -1.257 | N11: -1.65 | O11: 1.052 | P11: 2.7 | Q11: -2.5 | R11: =M11+(1.96*O11)/(L11)^0.5 -> -1.0105534 | S11: =M11-(1.96*O11)/(L11)^0.5 -> -1.5034466
A12: 16 | B12: 38 | C12: 66.558 | D12: 62.35 | E12: 17.262 | F12: 133.8 | G12: 46.9 | H12: =C12+(1.96*E12)/(B12)^0.5 -> 72.046522 | I12: =C12-(1.96*E12)/(B12)^0.5 -> 61.069478 | K12: 16 | L12: 38 | M12: -1.132 | N12: -1.6 | O12: 1.307 | P12: 3.9 | Q12: -2.2 | R12: =M12+(1.96*O12)/(L12)^0.5 -> -0.71643414 | S12: =M12-(1.96*O12)/(L12)^0.5 -> -1.5475659
A13: 17 | B13: 30 | C13: 70.98 | D13: 66.75 | E13: 15.423 | F13: 100.3 | G13: 52.4 | H13: =C13+(1.96*E13)/(B13)^0.5 -> 76.49905 | I13: =C13-(1.96*E13)/(B13)^0.5 -> 65.46095 | K13: 17 | L13: 30 | M13: -1.053 | N13: -1.6 | O13: 1.269 | P13: 2.4 | Q13: -2.3 | R13: =M13+(1.96*O13)/(L13)^0.5 -> -0.59889418 | S13: =M13-(1.96*O13)/(L13)^0.5 -> -1.5071058
A14: 18 | B14: 21 | C14: 68.581 | D14: 67.3 | E14: 6.51 | F14: 82.8 | G14: 58 | H14: =C14+(1.96*E14)/(B14)^0.5 -> 71.365373 | I14: =C14-(1.96*E14)/(B14)^0.5 -> 65.796627 | K14: 18 | L14: 21 | M14: -1.51 | N14: -1.7 | O14: 0.731 | P14: 0.4 | Q14: -2.4 | R14: =M14+(1.96*O14)/(L14)^0.5 -> -1.1973461 | S14: =M14-(1.96*O14)/(L14)^0.5 -> -1.8226539
A15: 19 | B15: 7 | C15: 78.243 | D15: 75.7 | E15: 20.635 | F15: 108.3 | G15: 50.4 | H15: =C15+(1.96*E15)/(B15)^0.5 -> 93.529622 | I15: =C15-(1.96*E15)/(B15)^0.5 -> 62.956378 | K15: 19 | L15: 7 | M15: -0.614 | N15: -1.6 | O15: 1.815 | P15: 2.3 | Q15: -2.3 | R15: =M15+(1.96*O15)/(L15)^0.5 -> 0.73057082 | S15: =M15-(1.96*O15)/(L15)^0.5 -> -1.9585708
A18: TALLA (cm) | K18: PUNTUACIÓN Z PHANTOM MUSCULAR
A19: Edad | B19: n | C19: Media | D19: Mediana | E19: Desv. Est. | F19: Máximo | G19: Mínimo | H19: IC95%sup | I19: IC95%inf | K19: Edad | L19: n | M19: Media | N19: Mediana | O19: Desv. Est. | P19: Máximo | Q19: Mínimo | R19: IC95%sup | S19: IC95%inf
A20: 7 | B20: 14 | C20: 130.671 | D20: 131.25 | E20: 3.868 | F20: 136.1 | G20: 124.7 | H20: =C20+(1.96*E20)/(B20)^0.5 -> 132.69718 | I20: =C20-(1.96*E20)/(B20)^0.5 -> 128.64482 | K20: 7 | L20: 14 | M20: -0.243 | N20: -0.3 | O20: 0.697 | P20: 0.9 | Q20: -1.3 | R20: =M20+(1.96*O20)/(L20)^0.5 -> 0.12211093 | S20: =M20-(1.96*O20)/(L20)^0.5 -> -0.60811093
A21: 8 | B21: 39 | C21: 130.044 | D21: 129.9 | E21: 5.271 | F21: 141.2 | G21: 114.5 | H21: =C21+(1.96*E21)/(B21)^0.5 -> 131.69831 | I21: =C21-(1.96*E21)/(B21)^0.5 -> 128.38969 | K21: 8 | L21: 39 | M21: 0.326 | N21: 0 | O21: 1.055 | P21: 3 | Q21: -1.1 | R21: =M21+(1.96*O21)/(L21)^0.5 -> 0.657113 | S21: =M21-(1.96*O21)/(L21)^0.5 -> -0.0051129964
A22: 9 | B22: 57 | C22: 134.733 | D22: 135.7 | E22: 5.623 | F22: 148.1 | G22: 116 | H22: =C22+(1.96*E22)/(B22)^0.5 -> 136.19278 | I22: =C22-(1.96*E22)/(B22)^0.5 -> 133.27322 | K22: 9 | L22: 57 | M22: -0.007018 | N22: 0.1 | O22: 0.827 | P22: 2 | Q22: -1.7 | R22: =M22+(1.96*O22)/(L22)^0.5 -> 0.2076781 | S22: =M22-(1.96*O22)/(L22)^0.5 -> -0.2217141
A23: 10 | B23: 66 | C23: 138.265 | D23: 137.5 | E23: 6.251 | F23: 153.3 | G23: 125.4 | H23: =C23+(1.96*E23)/(B23)^0.5 -> 139.77311 | I23: =C23-(1.96*E23)/(B23)^0.5 -> 136.75689 | K23: 10 | L23: 66 | M23: 0.02727 | N23: 0 | O23: 0.926 | P23: 2.9 | Q23: -1.5 | R23: =M23+(1.96*O23)/(L23)^0.5 -> 0.25067613 | S23: =M23-(1.96*O23)/(L23)^0.5 -> -0.19613613
A24: 11 | B24: 55 | C24: 144.916 | D24: 145.6 | E24: 7.331 | F24: 161.4 | G24: 131.2 | H24: =C24+(1.96*E24)/(B24)^0.5 -> 146.85348 | I24: =C24-(1.96*E24)/(B24)^0.5 -> 142.97852 | K24: 11 | L24: 55 | M24: -0.01091 | N24: 0 | O24: 1.015 | P24: 2.2 | Q24: -2.2 | R24: =M24+(1.96*O24)/(L24)^0.5 -> 0.25734064 | S24: =M24-(1.96*O24)/(L24)^0.5 -> -0.27916064
A25: 12 | B25: 35 | C25: 151.42 | D25: 150.7 | E25: 7.245 | F25: 165.8 | G25: 140.5 | H25: =C25+(1.96*E25)/(B25)^0.5 -> 153.82027 | I25: =C25-(1.96*E25)/(B25)^0.5 -> 149.01973 | K25: 12 | L25: 35 | M25: 0.12 | N25: -0.1 | O25: 1.138 | P25: 4.1 | Q25: -1.4 | R25: =M25+(1.96*O25)/(L25)^0.5 -> 0.49701993 | S25: =M25-(1.96*O25)/(L25)^0.5 -> -0.25701993
A26: 13 | B26: 64 | C26: 161.167 | D26: 161.75 | E26: 8.103 | F26: 177.5 | G26: 142.4 | H26: =C26+(1.96*E26)/(B26)^0.5 -> 163.15223 | I26: =C26-(1.96*E26)/(B26)^0.5 -> 159.18177 | K26: 13 | L26: 64 | M26: -0.003125 | N26: -0.1 | O26: 0.874 | P26: 3 | Q26: -2 | R26: =M26+(1.96*O26)/(L26)^0.5 -> 0.211005 | S26: =M26-(1.96*O26)/(L26)^0.5 -> -0.217255
A27: 14 | B27: 87 | C27: 165.598 | D27: 165.3 | E27: 7.979 | F27: 182.6 | G27: 144.4 | H27: =C27+(1.96*E27)/(B27)^0.5 -> 167.27466 | I27: =C27-(1.96*E27)/(B27)^0.5 -> 163.92134 | K27: 14 | L27: 87 | M27: 0.362 | N27: 0.1 | O27: 1.12 | P27: 4 | Q27: -2.2 | R27: =M27+(1.96*O27)/(L27)^0.5 -> 0.59735014 | S27: =M27-(1.96*O27)/(L27)^0.5 -> 0.12664986
A28: 15 | B28: 70 | C28: 169.761 | D28: 169.2 | E28: 6.317 | F28: 184.7 | G28: 157.9 | H28: =C28+(1.96*E28)/(B28)^0.5 -> 171.24085 | I28: =C28-(1.96*E28)/(B28)^0.5 -> 168.28115 | K28: 15 | L28: 70 | M28: 0.447 | N28: 0.3 | O28: 0.944 | P28: 2.8 | Q28: -1.5 | R28: =M28+(1.96*O28)/(L28)^0.5 -> 0.66814598 | S28: =M28-(1.96*O28)/(L28)^0.5 -> 0.22585402
A29: 16 | B29: 38 | C29: 169.916 | D29: 170 | E29: 5.023 | F29: 184.1 | G29: 159.7 | H29: =C29+(1.96*E29)/(B29)^0.5 -> 171.51308 | I29: =C29-(1.96*E29)/(B29)^0.5 -> 168.31892 | K29: 16 | L29: 38 | M29: 0.871 | N29: 0.45 | O29: 1.268 | P29: 5.2 | Q29: -0.7 | R29: =M29+(1.96*O29)/(L29)^0.5 -> 1.2741657 | S29: =M29-(1.96*O29)/(L29)^0.5 -> 0.46783435
A30: 17 | B30: 30 | C30: 171.887 | D30: 171.15 | E30: 6.468 | F30: 185.9 | G30: 160.9 | H30: =C30+(1.96*E30)/(B30)^0.5 -> 174.20154 | I30: =C30-(1.96*E30)/(B30)^0.5 -> 169.57246 | K30: 17 | L30: 30 | M30: 1.147 | N30: 0.9 | O30: 1.267 | P30: 4.1 | Q30: -1.1 | R30: =M30+(1.96*O30)/(L30)^0.5 -> 1.6003901 | S30: =M30-(1.96*O30)/(L30)^0.5 -> 0.69360987
A31: 18 | B31: 21 | C31: 173.943 | D31: 174.4 | E31: 5.623 | F31: 187.9 | G31: 161.6 | H31: =C31+(1.96*E31)/(B31)^0.5 -> 176.348 | I31: =C31-(1.96*E31)/(B31)^0.5 -> 171.538 | K31: 18 | L31: 21 | M31: 1.043 | N31: 0.9 | O31: 1.121 | P31: 3.3 | Q31: -1.1 | R31: =M31+(1.96*O31)/(L31)^0.5 -> 1.5224596 | S31: =M31-(1.96*O31)/(L31)^0.5 -> 0.56354038
A32: 19 | B32: 7 | C32: 171.943 | D32: 172.9 | E32: 5.977 | F32: 182.5 | G32: 163 | H32: =C32+(1.96*E32)/(B32)^0.5 -> 176.37082 | I32: =C32-(1.96*E32)/(B32)^0.5 -> 167.51518 | K32: 19 | L32: 7 | M32: 1.9 | N32: 1.3 | O32: 1.768 | P32: 5 | Q32: 0 | R32: =M32+(1.96*O32)/(L32)^0.5 -> 3.2097527 | S32: =M32-(1.96*O32)/(L32)^0.5 -> 0.59024727
A35: TALLA SENTADO (cm) | K35: PUNTUACIÓN Z PHANTOM RESIDUAL
A36: Edad | B36: n | C36: Media | D36: Mediana | E36: Desv. Est. | F36: Máximo | G36: Mínimo | H36: IC95%sup | I36: IC95%inf | K36: Edad | L36: n | M36: Media | N36: Mediana | O36: Desv. Est. | P36: Máximo | Q36: Mínimo | R36: IC95%sup | S36: IC95%inf
A37: 7 | B37: 14 | C37: 69.729 | D37: 69.2 | E37: 3.05 | F37: 75.5 | G37: 64.2 | H37: =C37+(1.96*E37)/(B37)^0.5 -> 71.326688 | I37: =C37-(1.96*E37)/(B37)^0.5 -> 68.131312 | K37: 7 | L37: 14 | M37: 0.821 | N37: 0.8 | O37: 0.625 | P37: 2.3 | Q37: 0 | R37: =M37+(1.96*O37)/(L37)^0.5 -> 1.148395 | S37: =M37-(1.96*O37)/(L37)^0.5 -> 0.49360498
A38: 8 | B38: 39 | C38: 70.61 | D38: 70.1 | E38: 3.036 | F38: 76.9 | G38: 64.4 | H38: =C38+(1.96*E38)/(B38)^0.5 -> 71.562852 | I38: =C38-(1.96*E38)/(B38)^0.5 -> 69.657148 | K38: 8 | L38: 39 | M38: 0.995 | N38: 0.7 | O38: 1.075 | P38: 4.5 | Q38: -0.3 | R38: =M38+(1.96*O38)/(L38)^0.5 -> 1.33239 | S38: =M38-(1.96*O38)/(L38)^0.5 -> 0.65760998
A39: 9 | B39: 57 | C39: 71.993 | D39: 71.7 | E39: 2.852 | F39: 81.3 | G39: 65.5 | H39: =C39+(1.96*E39)/(B39)^0.5 -> 72.733403 | I39: =C39-(1.96*E39)/(B39)^0.5 -> 71.252597 | K39: 9 | L39: 57 | M39: 0.74 | N39: 0.7 | O39: 0.935 | P39: 4.3 | Q39: -0.9 | R39: =M39+(1.96*O39)/(L39)^0.5 -> 0.9827338 | S39: =M39-(1.96*O39)/(L39)^0.5 -> 0.4972662
A40: 10 | B40: 66 | C40: 73.539 | D40: 73.35 | E40: 3.285 | F40: 80.7 | G40: 67.5 | H40: =C40+(1.96*E40)/(B40)^0.5 -> 74.331537 | I40: =C40-(1.96*E40)/(B40)^0.5 -> 72.746463 | K40: 10 | L40: 66 | M40: 0.855 | N40: 0.8 | O40: 1.032 | P40: 4 | Q40: -0.9 | R40: =M40+(1.96*O40)/(L40)^0.5 -> 1.1039796 | S40: =M40-(1.96*O40)/(L40)^0.5 -> 0.60602038
A41: 11 | B41: 55 | C41: 76.489 | D41: 76.6 | E41: 4.468 | F41: 89 | G41: 67 | H41: =C41+(1.96*E41)/(B41)^0.5 -> 77.669831 | I41: =C41-(1.96*E41)/(B41)^0.5 -> 75.308169 | K41: 11 | L41: 55 | M41: 0.836 | N41: 0.8 | O41: 1.062 | P41: 5.2 | Q41: -1.2 | R41: =M41+(1.96*O41)/(L41)^0.5 -> 1.1166721 | S41: =M41-(1.96*O41)/(L41)^0.5 -> 0.5553279
A42: 12 | B42: 35 | C42: 79.486 | D42: 78.8 | E42: 4.003 | F42: 89.5 | G42: 73 | H42: =C42+(1.96*E42)/(B42)^0.5 -> 80.812196 | I42: =C42-(1.96*E42)/(B42)^0.5 -> 78.159804 | K42: 12 | L42: 35 | M42: 0.546 | N42: 0.4 | O42: 1.043 | P42: 4.1 | Q42: -1.4 | R42: =M42+(1.96*O42)/(L42)^0.5 -> 0.89154639 | S42: =M42-(1.96*O42)/(L42)^0.5 -> 0.20045361
A43: 13 | B43: 64 | C43: 84.125 | D43: 84.2 | E43: 4.8 | F43: 96.9 | G43: 74 | H43: =C43+(1.96*E43)/(B43)^0.5 -> 85.301 | I43: =C43-(1.96*E43)/(B43)^0.5 -> 82.949 | K43: 13 | L43: 64 | M43: 0.481 | N43: 0.3 | O43: 0.857 | P43: 3.1 | Q43: -1.3 | R43: =M43+(1.96*O43)/(L43)^0.5 -> 0.690965 | S43: =M43-(1.96*O43)/(L43)^0.5 -> 0.271035
A44: 14 | B44: 87 | C44: 87.043 | D44: 87.5 | E44: 4.771 | F44: 97.1 | G44: 72.5 | H44: =C44+(1.96*E44)/(B44)^0.5 -> 88.04555 | I44: =C44-(1.96*E44)/(B44)^0.5 -> 86.04045 | K44: 14 | L44: 87 | M44: 0.734 | N44: 0.7 | O44: 1.083 | P44: 5.1 | Q44: -1.9 | R44: =M44+(1.96*O44)/(L44)^0.5 -> 0.96157518 | S44: =M44-(1.96*O44)/(L44)^0.5 -> 0.50642482
A45: 15 | B45: 70 | C45: 89.369 | D45: 89.5 | E45: 4.213 | F45: 100.2 | G45: 80.5 | H45: =C45+(1.96*E45)/(B45)^0.5 -> 90.355958 | I45: =C45-(1.96*E45)/(B45)^0.5 -> 88.382042 | K45: 15 | L45: 70 | M45: 0.59 | N45: 0.5 | O45: 1.024 | P45: 5.2 | Q45: -1.5 | R45: =M45+(1.96*O45)/(L45)^0.5 -> 0.82988716 | S45: =M45-(1.96*O45)/(L45)^0.5 -> 0.35011284
A46: 16 | B46: 38 | C46: 90.234 | D46: 90.05 | E46: 3.593 | F46: 99.8 | G46: 83.2 | H46: =C46+(1.96*E46)/(B46)^0.5 -> 91.376409 | I46: =C46-(1.96*E46)/(B46)^0.5 -> 89.091591 | K46: 16 | L46: 38 | M46: 0.721 | N46: 0.5 | O46: 1.109 | P46: 4 | Q46: -0.6 | R46: =M46+(1.96*O46)/(L46)^0.5 -> 1.073611 | S46: =M46-(1.96*O46)/(L46)^0.5 -> 0.36838903
A47: 17 | B47: 30 | C47: 90.56 | D47: 90.1 | E47: 2.995 | F47: 97 | G47: 84.8 | H47: =C47+(1.96*E47)/(B47)^0.5 -> 91.631747 | I47: =C47-(1.96*E47)/(B47)^0.5 -> 89.488253 | K47: 17 | L47: 30 | M47: 1.233 | N47: 1 | O47: 1.226 | P47: 4.3 | Q47: -1.2 | R47: =M47+(1.96*O47)/(L47)^0.5 -> 1.6717185 | S47: =M47-(1.96*O47)/(L47)^0.5 -> 0.79428153
A48: 18 | B48: 21 | C48: 91.995 | D48: 92.5 | E48: 3.469 | F48: 99.2 | G48: 84.3 | H48: =C48+(1.96*E48)/(B48)^0.5 -> 93.478716 | I48: =C48-(1.96*E48)/(B48)^0.5 -> 90.511284 | K48: 18 | L48: 21 | M48: 0.581 | N48: 0.5 | O48: 0.863 | P48: 2.5 | Q48: -0.9 | R48: =M48+(1.96*O48)/(L48)^0.5 -> 0.9501112 | S48: =M48-(1.96*O48)/(L48)^0.5 -> 0.2118888
A49: 19 | B49: 7 | C49: 91.343 | D49: 93 | E49: 2.955 | F49: 93.6 | G49: 86 | H49: =C49+(1.96*E49)/(B49)^0.5 -> 93.532095 | I49: =C49-(1.96*E49)/(B49)^0.5 -> 89.153905 | K49: 19 | L49: 7 | M49: 2.129 | N49: 1.6 | O49: 1.947 | P49: 5.3 | Q49: 0.3 | R49: =M49+(1.96*O49)/(L49)^0.5 -> 3.5713578 | S49: =M49-(1.96*O49)/(L49)^0.5 -> 0.68664222
A52: ENVERGADURA (cm) | K52: PUNTUACIÓN Z PHANTOM ÓSEA
A53: Edad | B53: n | C53: Media | D53: Mediana | E53: Desv. Est. | F53: Máximo | G53: Mínimo | H53: IC95%sup | I53: IC95%inf | K53: Edad | L53: n | M53: Media | N53: Mediana | O53: Desv. Est. | P53: Máximo | Q53: Mínimo | R53: IC95%sup | S53: IC95%inf
A54: 7 | B54: 13 | C54: 131.508 | D54: 131.2 | E54: 3.667 | F54: 138.2 | G54: 126.5 | H54: =C54+(1.96*E54)/(B54)^0.5 -> 133.5014 | I54: =C54-(1.96*E54)/(B54)^0.5 -> 129.5146 | K54: 7 | L54: 14 | M54: 0.2 | N54: 0.3 | O54: 0.476 | P54: 1 | Q54: -0.7 | R54: =M54+(1.96*O54)/(L54)^0.5 -> 0.44934405 | S54: =M54-(1.96*O54)/(L54)^0.5 -> -0.049344048
A55: 8 | B55: 39 | C55: 130.636 | D55: 132.5 | E55: 6.406 | F55: 141.6 | G55: 110.9 | H55: =C55+(1.96*E55)/(B55)^0.5 -> 132.64653 | I55: =C55-(1.96*E55)/(B55)^0.5 -> 128.62547 | K55: 8 | L55: 39 | M55: 0.649 | N55: 0.5 | O55: 0.818 | P55: 2.6 | Q55: -0.6 | R55: =M55+(1.96*O55)/(L55)^0.5 -> 0.90573027 | S55: =M55-(1.96*O55)/(L55)^0.5 -> 0.39226973
A56: 9 | B56: 57 | C56: 135.198 | D56: 134.5 | E56: 6.414 | F56: 151.4 | G56: 114.2 | H56: =C56+(1.96*E56)/(B56)^0.5 -> 136.86313 | I56: =C56-(1.96*E56)/(B56)^0.5 -> 133.53287 | K56: 9 | L56: 57 | M56: 0.275 | N56: 0.2 | O56: 0.672 | P56: 2.8 | Q56: -1 | R56: =M56+(1.96*O56)/(L56)^0.5 -> 0.44945681 | S56: =M56-(1.96*O56)/(L56)^0.5 -> 0.10054319
A57: 10 | B57: 66 | C57: 139.564 | D57: 139.25 | E57: 7.549 | F57: 160.2 | G57: 127.3 | H57: =C57+(1.96*E57)/(B57)^0.5 -> 141.38527 | I57: =C57-(1.96*E57)/(B57)^0.5 -> 137.74273 | K57: 10 | L57: 66 | M57: 0.318 | N57: 0.2 | O57: 0.791 | P57: 3.3 | Q57: -0.9 | R57: =M57+(1.96*O57)/(L57)^0.5 -> 0.50883612 | S57: =M57-(1.96*O57)/(L57)^0.5 -> 0.12716388
A58: 11 | B58: 55 | C58: 147.151 | D58: 148.2 | E58: 8.216 | F58: 169.4 | G58: 131.5 | H58: =C58+(1.96*E58)/(B58)^0.5 -> 149.32238 | I58: =C58-(1.96*E58)/(B58)^0.5 -> 144.97962 | K58: 11 | L58: 55 | M58: 0.32 | N58: 0.3 | O58: 0.899 | P58: 3 | Q58: -1.5 | R58: =M58+(1.96*O58)/(L58)^0.5 -> 0.55759343 | S58: =M58-(1.96*O58)/(L58)^0.5 -> 0.082406575
A59: 12 | B59: 35 | C59: 153.789 | D59: 154.4 | E59: 8.901 | F59: 172 | G59: 139.1 | H59: =C59+(1.96*E59)/(B59)^0.5 -> 156.73791 | I59: =C59-(1.96*E59)/(B59)^0.5 -> 150.84009 | K59: 12 | L59: 35 | M59: 0.134 | N59: 0 | O59: 0.918 | P59: 3.5 | Q59: -1.2 | R59: =M59+(1.96*O59)/(L59)^0.5 -> 0.43813383 | S59: =M59-(1.96*O59)/(L59)^0.5 -> -0.17013383
A60: 13 | B60: 54 | C60: 163.794 | D60: 164.25 | E60: 9.199 | F60: 179 | G60: 141.8 | H60: =C60+(1.96*E60)/(B60)^0.5 -> 166.24758 | I60: =C60-(1.96*E60)/(B60)^0.5 -> 161.34042 | K60: 13 | L60: 64 | M60: 0.01094 | N60: 0 | O60: 0.545 | P60: 1.6 | Q60: -1.4 | R60: =M60+(1.96*O60)/(L60)^0.5 -> 0.144465 | S60: =M60-(1.96*O60)/(L60)^0.5 -> -0.122585
A61: 14 | B61: 67 | C61: 168.491 | D61: 169 | E61: 9.029 | F61: 189 | G61: 144.4 | H61: =C61+(1.96*E61)/(B61)^0.5 -> 170.65301 | I61: =C61-(1.96*E61)/(B61)^0.5 -> 166.32899 | K61: 14 | L61: 87 | M61: -0.01379 | N61: 0 | O61: 0.774 | P61: 2.5 | Q61: -1.7 | R61: =M61+(1.96*O61)/(L61)^0.5 -> 0.14885376 | S61: =M61-(1.96*O61)/(L61)^0.5 -> -0.17643376
A62: 15 | B62: 54 | C62: 173.12 | D62: 172.3 | E62: 6.994 | F62: 189.2 | G62: 160 | H62: =C62+(1.96*E62)/(B62)^0.5 -> 174.98546 | I62: =C62-(1.96*E62)/(B62)^0.5 -> 171.25454 | K62: 15 | L62: 70 | M62: -0.136 | N62: -0.1 | O62: 0.568 | P62: 1.6 | Q62: -1.5 | R62: =M62+(1.96*O62)/(L62)^0.5 -> -0.0029375894 | S62: =M62-(1.96*O62)/(L62)^0.5 -> -0.26906241
A63: 16 | B63: 28 | C63: 173.307 | D63: 173.8 | E63: 7.649 | F63: 189.3 | G63: 155.4 | H63: =C63+(1.96*E63)/(B63)^0.5 -> 176.14023 | I63: =C63-(1.96*E63)/(B63)^0.5 -> 170.47377 | K63: 16 | L63: 38 | M63: 0.002632 | N63: -0.1 | O63: 0.776 | P63: 2.6 | Q63: -1.3 | R63: =M63+(1.96*O63)/(L63)^0.5 -> 0.24936429 | S63: =M63-(1.96*O63)/(L63)^0.5 -> -0.24410029
A64: 17 | B64: 27 | C64: 176.322 | D64: 176.7 | E64: 7.071 | F64: 189.5 | G64: 160.3 | H64: =C64+(1.96*E64)/(B64)^0.5 -> 178.9892 | I64: =C64-(1.96*E64)/(B64)^0.5 -> 173.6548 | K64: 17 | L64: 30 | M64: 0.203 | N64: 0.05 | O64: 0.862 | P64: 2.3 | Q64: -1 | R64: =M64+(1.96*O64)/(L64)^0.5 -> 0.51146274 | S64: =M64-(1.96*O64)/(L64)^0.5 -> -0.10546274
A65: 18 | B65: 19 | C65: 176.805 | D65: 177.1 | E65: 7.497 | F65: 193.9 | G65: 161.3 | H65: =C65+(1.96*E65)/(B65)^0.5 -> 180.17606 | I65: =C65-(1.96*E65)/(B65)^0.5 -> 173.43394 | K65: 18 | L65: 21 | M65: -0.05238 | N65: -0.1 | O65: 0.59 | P65: 1.2 | Q65: -1 | R65: =M65+(1.96*O65)/(L65)^0.5 -> 0.19996717 | S65: =M65-(1.96*O65)/(L65)^0.5 -> -0.30472717
A66: 19 | B66: 7 | C66: 177.257 | D66: 173.6 | E66: 9.62 | F66: 190.7 | G66: 165.3 | H66: =C66+(1.96*E66)/(B66)^0.5 -> 184.3836 | I66: =C66-(1.96*E66)/(B66)^0.5 -> 170.1304 | K66: 19 | L66: 7 | M66: 1 | N66: 0.7 | O66: 1.274 | P66: 3 | Q66: -0.3 | R66: =M66+(1.96*O66)/(L66)^0.5 -> 1.9437924 | S66: =M66-(1.96*O66)/(L66)^0.5 -> 0.056207592
A69: LONGITUD ACROMIAL-RADIAL (cm) | K69: DIFERENCIA ENTRE PESO BALANZA Y PESO ESTRUCTURADO (kg)
A70: Edad | B70: n | C70: Media | D70: Mediana | E70: Desv. Est. | F70: Máximo | G70: Mínimo | H70: IC95%sup | I70: IC95%inf | K70: Edad | L70: n | M70: Media | N70: Mediana | O70: Desv. Est. | P70: Máximo | Q70: Mínimo | R70: IC95%sup | S70: IC95%inf
A71: 7 | B71: 14 | C71: 24.743 | D71: 24.6 | E71: 1.345 | F71: 27.4 | G71: 22.8 | H71: =C71+(1.96*E71)/(B71)^0.5 -> 25.447554 | I71: =C71-(1.96*E71)/(B71)^0.5 -> 24.038446 | K71: 7 | L71: 14 | M71: -0.4 | N71: -0.25 | O71: 1.41 | P71: 1.9 | Q71: -3.2 | R71: =M71+(1.96*O71)/(L71)^0.5 -> 0.33860317 | S71: =M71-(1.96*O71)/(L71)^0.5 -> -1.1386032
A72: 8 | B72: 39 | C72: 24.667 | D72: 24.9 | E72: 1.557 | F72: 27.8 | G72: 21.3 | H72: =C72+(1.96*E72)/(B72)^0.5 -> 25.155666 | I72: =C72-(1.96*E72)/(B72)^0.5 -> 24.178334 | K72: 8 | L72: 39 | M72: 0.774 | N72: -0.1 | O72: 2.069 | P72: 5.4 | Q72: -1.7 | R72: =M72+(1.96*O72)/(L72)^0.5 -> 1.4233581 | S72: =M72-(1.96*O72)/(L72)^0.5 -> 0.12464191
A73: 9 | B73: 57 | C73: 25.639 | D73: 25.7 | E73: 1.383 | F73: 29 | G73: 20 | H73: =C73+(1.96*E73)/(B73)^0.5 -> 25.998038 | I73: =C73-(1.96*E73)/(B73)^0.5 -> 25.279962 | K73: 9 | L73: 57 | M73: 0.456 | N73: 0 | O73: 2.169 | P73: 7.3 | Q73: -2.6 | R73: =M73+(1.96*O73)/(L73)^0.5 -> 1.0190905 | S73: =M73-(1.96*O73)/(L73)^0.5 -> -0.10709049
A74: 10 | B74: 66 | C74: 26.308 | D74: 26.35 | E74: 1.74 | F74: 31.3 | G74: 22.1 | H74: =C74+(1.96*E74)/(B74)^0.5 -> 26.727791 | I74: =C74-(1.96*E74)/(B74)^0.5 -> 25.888209 | K74: 10 | L74: 66 | M74: 0.865 | N74: 0.6 | O74: 2.576 | P74: 9.3 | Q74: -6.4 | R74: =M74+(1.96*O74)/(L74)^0.5 -> 1.486484 | S74: =M74-(1.96*O74)/(L74)^0.5 -> 0.24351599
A75: 11 | B75: 55 | C75: 27.844 | D75: 28.1 | E75: 1.468 | F75: 31.1 | G75: 24 | H75: =C75+(1.96*E75)/(B75)^0.5 -> 28.231972 | I75: =C75-(1.96*E75)/(B75)^0.5 -> 27.456028 | K75: 11 | L75: 55 | M75: 0.882 | N75: 0.1 | O75: 3.208 | P75: 10.3 | Q75: -4.6 | R75: =M75+(1.96*O75)/(L75)^0.5 -> 1.7298306 | S75: =M75-(1.96*O75)/(L75)^0.5 -> 0.034169402
A76: 12 | B76: 35 | C76: 29.206 | D76: 29.2 | E76: 1.724 | F76: 33.2 | G76: 25.4 | H76: =C76+(1.96*E76)/(B76)^0.5 -> 29.777162 | I76: =C76-(1.96*E76)/(B76)^0.5 -> 28.634838 | K76: 12 | L76: 35 | M76: 1.583 | N76: 1 | O76: 3.096 | P76: 7.9 | Q76: -3.5 | R76: =M76+(1.96*O76)/(L76)^0.5 -> 2.6087062 | S76: =M76-(1.96*O76)/(L76)^0.5 -> 0.55729375
A77: 13 | B77: 64 | C77: 30.988 | D77: 30.85 | E77: 1.937 | F77: 36.1 | G77: 26.6 | H77: =C77+(1.96*E77)/(B77)^0.5 -> 31.462565 | I77: =C77-(1.96*E77)/(B77)^0.5 -> 30.513435 | K77: 13 | L77: 64 | M77: 0.206 | N77: -0.1 | O77: 2.698 | P77: 8.3 | Q77: -4.7 | R77: =M77+(1.96*O77)/(L77)^0.5 -> 0.86701 | S77: =M77-(1.96*O77)/(L77)^0.5 -> -0.45501
A78: 14 | B78: 87 | C78: 31.772 | D78: 31.8 | E78: 1.831 | F78: 36.9 | G78: 26.3 | H78: =C78+(1.96*E78)/(B78)^0.5 -> 32.156755 | I78: =C78-(1.96*E78)/(B78)^0.5 -> 31.387245 | K78: 14 | L78: 87 | M78: 0.309 | N78: -0.3 | O78: 3.899 | P78: 17 | Q78: -6.5 | R78: =M78+(1.96*O78)/(L78)^0.5 -> 1.1283127 | S78: =M78-(1.96*O78)/(L78)^0.5 -> -0.51031269
A79: 15 | B79: 70 | C79: 32.58 | D79: 32.5 | E79: 1.577 | F79: 36.5 | G79: 29.1 | H79: =C79+(1.96*E79)/(B79)^0.5 -> 32.949436 | I79: =C79-(1.96*E79)/(B79)^0.5 -> 32.210564 | K79: 15 | L79: 70 | M79: 0.03857 | N79: -0.45 | O79: 3.32 | P79: 13.1 | Q79: -4.8 | R79: =M79+(1.96*O79)/(L79)^0.5 -> 0.81632916 | S79: =M79-(1.96*O79)/(L79)^0.5 -> -0.73918916
A80: 16 | B80: 38 | C80: 32.529 | D80: 32.65 | E80: 1.484 | F80: 35.8 | G80: 29.8 | H80: =C80+(1.96*E80)/(B80)^0.5 -> 33.000844 | I80: =C80-(1.96*E80)/(B80)^0.5 -> 32.057156 | K80: 16 | L80: 38 | M80: 0.579 | N80: -0.1 | O80: 3.641 | P80: 9.2 | Q80: -6.1 | R80: =M80+(1.96*O80)/(L80)^0.5 -> 1.7366705 | S80: =M80-(1.96*O80)/(L80)^0.5 -> -0.57867046
A81: 17 | B81: 30 | C81: 33.167 | D81: 33.2 | E81: 1.686 | F81: 37.3 | G81: 30 | H81: =C81+(1.96*E81)/(B81)^0.5 -> 33.770327 | I81: =C81-(1.96*E81)/(B81)^0.5 -> 32.563673 | K81: 17 | L81: 30 | M81: 0.95 | N81: -0.4 | O81: 3.855 | P81: 11.1 | Q81: -3.9 | R81: =M81+(1.96*O81)/(L81)^0.5 -> 2.329494 | S81: =M81-(1.96*O81)/(L81)^0.5 -> -0.42949403
A82: 18 | B82: 21 | C82: 33.429 | D82: 33.4 | E82: 1.59 | F82: 36.9 | G82: 30.4 | H82: =C82+(1.96*E82)/(B82)^0.5 -> 34.109054 | I82: =C82-(1.96*E82)/(B82)^0.5 -> 32.748946 | K82: 18 | L82: 21 | M82: 0.4 | N82: -0.4 | O82: 3.457 | P82: 8.7 | Q82: -6.1 | R82: =M82+(1.96*O82)/(L82)^0.5 -> 1.8785833 | S82: =M82-(1.96*O82)/(L82)^0.5 -> -1.0785833
A83: 19 | B83: 7 | C83: 32.671 | D83: 32.8 | E83: 2.156 | F83: 35.5 | G83: 30 | H83: =C83+(1.96*E83)/(B83)^0.5 -> 34.268187 | I83: =C83-(1.96*E83)/(B83)^0.5 -> 31.073813 | K83: 19 | L83: 7 | M83: 2.543 | N83: 2.2 | O83: 4.014 | P83: 6.8 | Q83: -4.3 | R83: =M83+(1.96*O83)/(L83)^0.5 -> 5.5166128 | S83: =M83-(1.96*O83)/(L83)^0.5 -> -0.43061281
A86: LONGITUD RADIAL-ESTILOIDEA (cm) | K86: ERROR DE PESO ESTRUCTURADO (%)
A87: Edad | B87: n | C87: Media | D87: Mediana | E87: Desv. Est. | F87: Máximo | G87: Mínimo | H87: IC95%sup | I87: IC95%inf | K87: Edad | L87: n | M87: Media | N87: Mediana | O87: Desv. Est. | P87: Máximo | Q87: Mínimo | R87: IC95%sup | S87: IC95%inf
A88: 7 | B88: 14 | C88: 19.193 | D88: 18.95 | E88: 0.92 | F88: 20.8 | G88: 18 | H88: =C88+(1.96*E88)/(B88)^0.5 -> 19.674925 | I88: =C88-(1.96*E88)/(B88)^0.5 -> 18.711075 | K88: 7 | L88: 14 | M88: -0.019286 | N88: -0.01 | O88: 0.05225 | P88: 0.05 | Q88: -0.13 | R88: =M88+(1.96*O88)/(L88)^0.5 -> 0.0080842238 | S88: =M88-(1.96*O88)/(L88)^0.5 -> -0.046656224
A89: 8 | B89: 39 | C89: 18.918 | D89: 19.2 | E89: 1.137 | F89: 21.3 | G89: 15.6 | H89: =C89+(1.96*E89)/(B89)^0.5 -> 19.274849 | I89: =C89-(1.96*E89)/(B89)^0.5 -> 18.561151 | K89: 8 | L89: 39 | M89: 0.0141 | N89: 0 | O89: 0.05354 | P89: 0.13 | Q89: -0.08 | R89: =M89+(1.96*O89)/(L89)^0.5 -> 0.030903592 | S89: =M89-(1.96*O89)/(L89)^0.5 -> -0.0027035923
A90: 9 | B90: 57 | C90: 19.781 | D90: 19.8 | E90: 1.306 | F90: 23.4 | G90: 16.5 | H90: =C90+(1.96*E90)/(B90)^0.5 -> 20.120048 | I90: =C90-(1.96*E90)/(B90)^0.5 -> 19.441952 | K90: 9 | L90: 57 | M90: 0.004912 | N90: 0 | O90: 0.05686 | P90: 0.14 | Q90: -0.1 | R90: =M90+(1.96*O90)/(L90)^0.5 -> 0.01967333 | S90: =M90-(1.96*O90)/(L90)^0.5 -> -0.0098493303
A91: 10 | B91: 66 | C91: 20.232 | D91: 20.05 | E91: 1.235 | F91: 23.4 | G91: 17.9 | H91: =C91+(1.96*E91)/(B91)^0.5 -> 20.529955 | I91: =C91-(1.96*E91)/(B91)^0.5 -> 19.934045 | K91: 10 | L91: 66 | M91: 0.01485 | N91: 0.02 | O91: 0.05954 | P91: 0.15 | Q91: -0.18 | R91: =M91+(1.96*O91)/(L91)^0.5 -> 0.02921458 | S91: =M91-(1.96*O91)/(L91)^0.5 -> 0.00048541995
A92: 11 | B92: 55 | C92: 21.522 | D92: 21.6 | E92: 1.336 | F92: 25.1 | G92: 18.8 | H92: =C92+(1.96*E92)/(B92)^0.5 -> 21.875087 | I92: =C92-(1.96*E92)/(B92)^0.5 -> 21.168913 | K92: 11 | L92: 55 | M92: 0.01091 | N92: 0 | O92: 0.06553 | P92: 0.18 | Q92: -0.13 | R92: =M92+(1.96*O92)/(L92)^0.5 -> 0.028228684 | S92: =M92-(1.96*O92)/(L92)^0.5 -> -0.0064086843
A93: 12 | B93: 35 | C93: 22.629 | D93: 22.5 | E93: 1.547 | F93: 26.1 | G93: 20 | H93: =C93+(1.96*E93)/(B93)^0.5 -> 23.141522 | I93: =C93-(1.96*E93)/(B93)^0.5 -> 22.116478 | K93: 12 | L93: 35 | M93: 0.02486 | N93: 0.03 | O93: 0.06065 | P93: 0.16 | Q93: -0.08 | R93: =M93+(1.96*O93)/(L93)^0.5 -> 0.044953373 | S93: =M93-(1.96*O93)/(L93)^0.5 -> 0.0047666266
A94: 13 | B94: 64 | C94: 23.827 | D94: 24 | E94: 1.445 | F94: 26.2 | G94: 20.4 | H94: =C94+(1.96*E94)/(B94)^0.5 -> 24.181025 | I94: =C94-(1.96*E94)/(B94)^0.5 -> 23.472975 | K94: 13 | L94: 64 | M94: -0.000625 | N94: 0 | O94: 0.04908 | P94: 0.12 | Q94: -0.1 | R94: =M94+(1.96*O94)/(L94)^0.5 -> 0.0113996 | S94: =M94-(1.96*O94)/(L94)^0.5 -> -0.0126496
A95: 14 | B95: 87 | C95: 24.652 | D95: 24.6 | E95: 1.617 | F95: 28.8 | G95: 20.2 | H95: =C95+(1.96*E95)/(B95)^0.5 -> 24.991787 | I95: =C95-(1.96*E95)/(B95)^0.5 -> 24.312213 | K95: 14 | L95: 87 | M95: -0.0027586 | N95: -0.01 | O95: 0.05888 | P95: 0.17 | Q95: -0.13 | R95: =M95+(1.96*O95)/(L95)^0.5 -> 0.0096140933 | S95: =M95-(1.96*O95)/(L95)^0.5 -> -0.015131293
A96: 15 | B96: 70 | C96: 25.183 | D96: 25.3 | E96: 1.143 | F96: 28.3 | G96: 22.6 | H96: =C96+(1.96*E96)/(B96)^0.5 -> 25.450765 | I96: =C96-(1.96*E96)/(B96)^0.5 -> 24.915235 | K96: 15 | L96: 70 | M96: -0.0051429 | N96: -0.01 | O96: 0.04542 | P96: 0.11 | Q96: -0.08 | R96: =M96+(1.96*O96)/(L96)^0.5 -> 0.0054974076 | S96: =M96-(1.96*O96)/(L96)^0.5 -> -0.015783208
A97: 16 | B97: 38 | C97: 25.068 | D97: 25.4 | E97: 1.24 | F97: 27.4 | G97: 21.7 | H97: =C97+(1.96*E97)/(B97)^0.5 -> 25.462263 | I97: =C97-(1.96*E97)/(B97)^0.5 -> 24.673737 | K97: 16 | L97: 38 | M97: 0.001053 | N97: -0.005 | O97: 0.04769 | P97: 0.1 | Q97: -0.1 | R97: =M97+(1.96*O97)/(L97)^0.5 -> 0.016216226 | S97: =M97-(1.96*O97)/(L97)^0.5 -> -0.014110226
A98: 17 | B98: 30 | C98: 25.663 | D98: 25.75 | E98: 1.16 | F98: 27.6 | G98: 22.4 | H98: =C98+(1.96*E98)/(B98)^0.5 -> 26.078101 | I98: =C98-(1.96*E98)/(B98)^0.5 -> 25.247899 | K98: 17 | L98: 30 | M98: 0.007333 | N98: -0.01 | O98: 0.0482 | P98: 0.14 | Q98: -0.07 | R98: =M98+(1.96*O98)/(L98)^0.5 -> 0.024581148 | S98: =M98-(1.96*O98)/(L98)^0.5 -> -0.0099151485
A99: 18 | B99: 21 | C99: 25.71 | D99: 25.7 | E99: 1.36 | F99: 28.1 | G99: 22.8 | H99: =C99+(1.96*E99)/(B99)^0.5 -> 26.291682 | I99: =C99-(1.96*E99)/(B99)^0.5 -> 25.128318 | K99: 18 | L99: 21 | M99: 0.003333 | N99: -0.01 | O99: 0.04882 | P99: 0.12 | Q99: -0.1 | R99: =M99+(1.96*O99)/(L99)^0.5 -> 0.024213659 | S99: =M99-(1.96*O99)/(L99)^0.5 -> -0.017547659
A100: 19 | B100: 7 | C100: 25.657 | D100: 25.7 | E100: 1.896 | F100: 28.3 | G100: 22.3 | H100: =C100+(1.96*E100)/(B100)^0.5 -> 27.061576 | I100: =C100-(1.96*E100)/(B100)^0.5 -> 24.252424 | K100: 19 | L100: 7 | M100: 0.02571 | N100: 0.03 | O100: 0.04577 | P100: 0.07 | Q100: -0.06 | R100: =M100+(1.96*O100)/(L100)^0.5 -> 0.059616891 | S100: =M100-(1.96*O100)/(L100)^0.5 -> -0.0081968905
A103: LONGITUD ESTILOIDEA-DACTILAR (cm) | K103: MASA ADIPOSA (%)
A104: Edad | B104: n | C104: Media | D104: Mediana | E104: Desv. Est. | F104: Máximo | G104: Mínimo | H104: IC95%sup | I104: IC95%inf | K104: Edad | L104: n | M104: Media | N104: Mediana | O104: Desv. Est. | P104: Máximo | Q104: Mínimo | R104: IC95%sup | S104: IC95%inf
A105: 7 | B105: 13 | C105: 15.215 | D105: 15.1 | E105: 0.546 | F105: 16 | G105: 14.4 | H105: =C105+(1.96*E105)/(B105)^0.5 -> 15.511809 | I105: =C105-(1.96*E105)/(B105)^0.5 -> 14.918191 | K105: 7 | L105: 14 | M105: 0.2986 | N105: 0.29 | O105: 0.04555 | P105: 0.38 | Q105: 0.25 | R105: =M105+(1.96*O105)/(L105)^0.5 -> 0.32246055 | S105: =M105-(1.96*O105)/(L105)^0.5 -> 0.27473945
A106: 8 | B106: 39 | C106: 15.338 | D106: 15.3 | E106: 0.738 | F106: 17.3 | G106: 13.7 | H106: =C106+(1.96*E106)/(B106)^0.5 -> 15.569622 | I106: =C106-(1.96*E106)/(B106)^0.5 -> 15.106378 | K106: 8 | L106: 39 | M106: 0.3064 | N106: 0.3 | O106: 0.05417 | P106: 0.42 | Q106: 0.22 | R106: =M106+(1.96*O106)/(L106)^0.5 -> 0.32340132 | S106: =M106-(1.96*O106)/(L106)^0.5 -> 0.28939868
A107: 9 | B107: 57 | C107: 15.761 | D107: 15.7 | E107: 0.611 | F107: 17.1 | G107: 14.5 | H107: =C107+(1.96*E107)/(B107)^0.5 -> 15.919621 | I107: =C107-(1.96*E107)/(B107)^0.5 -> 15.602379 | K107: 9 | L107: 57 | M107: 0.2944 | N107: 0.28 | O107: 0.04862 | P107: 0.45 | Q107: 0.22 | R107: =M107+(1.96*O107)/(L107)^0.5 -> 0.30702216 | S107: =M107-(1.96*O107)/(L107)^0.5 -> 0.28177784
A108: 10 | B108: 66 | C108: 16.211 | D108: 16.2 | E108: 0.927 | F108: 18.1 | G108: 14.2 | H108: =C108+(1.96*E108)/(B108)^0.5 -> 16.434647 | I108: =C108-(1.96*E108)/(B108)^0.5 -> 15.987353 | K108: 10 | L108: 66 | M108: 0.3186 | N108: 0.31 | O108: 0.05694 | P108: 0.47 | Q108: 0.22 | R108: =M108+(1.96*O108)/(L108)^0.5 -> 0.33233731 | S108: =M108-(1.96*O108)/(L108)^0.5 -> 0.30486269
A109: 11 | B109: 55 | C109: 17.096 | D109: 17.1 | E109: 1.13 | F109: 19.7 | G109: 14.8 | H109: =C109+(1.96*E109)/(B109)^0.5 -> 17.394644 | I109: =C109-(1.96*E109)/(B109)^0.5 -> 16.797356 | K109: 11 | L109: 55 | M109: 0.3118 | N109: 0.3 | O109: 0.05618 | P109: 0.46 | Q109: 0.23 | R109: =M109+(1.96*O109)/(L109)^0.5 -> 0.32664761 | S109: =M109-(1.96*O109)/(L109)^0.5 -> 0.29695239
A110: 12 | B110: 35 | C110: 17.934 | D110: 17.7 | E110: 1.14 | F110: 20.3 | G110: 16 | H110: =C110+(1.96*E110)/(B110)^0.5 -> 18.311683 | I110: =C110-(1.96*E110)/(B110)^0.5 -> 17.556317 | K110: 12 | L110: 35 | M110: 0.3323 | N110: 0.33 | O110: 0.05286 | P110: 0.44 | Q110: 0.24 | R110: =M110+(1.96*O110)/(L110)^0.5 -> 0.34981254 | S110: =M110-(1.96*O110)/(L110)^0.5 -> 0.31478746
A111: 13 | B111: 64 | C111: 18.878 | D111: 18.9 | E111: 1.043 | F111: 20.8 | G111: 16.3 | H111: =C111+(1.96*E111)/(B111)^0.5 -> 19.133535 | I111: =C111-(1.96*E111)/(B111)^0.5 -> 18.622465 | K111: 13 | L111: 64 | M111: 0.2956 | N111: 0.29 | O111: 0.0422 | P111: 0.42 | Q111: 0.23 | R111: =M111+(1.96*O111)/(L111)^0.5 -> 0.305939 | S111: =M111-(1.96*O111)/(L111)^0.5 -> 0.285261
A112: 14 | B112: 87 | C112: 19.062 | D112: 19 | E112: 1.117 | F112: 21.2 | G112: 15 | H112: =C112+(1.96*E112)/(B112)^0.5 -> 19.29672 | I112: =C112-(1.96*E112)/(B112)^0.5 -> 18.82728 | K112: 14 | L112: 87 | M112: 0.2867 | N112: 0.28 | O112: 0.04645 | P112: 0.43 | Q112: 0.2 | R112: =M112+(1.96*O112)/(L112)^0.5 -> 0.29646073 | S112: =M112-(1.96*O112)/(L112)^0.5 -> 0.27693927
...

Sheet Predicción de Talla
A1: Predicción de la Talla Adulta utilizando la Madurez a través de las Curvas de Velocidad de Talla Acumulativas
A2: Autores: Lauren B. Sherar, Robert L. Mirwald, Adam D. G. Baxter-Jones y Martine Thoms
A4: Pasos a seguir para realizar el cálculo de la Predicción de la Talla Adulta:
A6: 1) Se deben tener los siguientes datos del niño o adolescente a evaluar:
A7: Ejemplo: | B7: Edad Decimal | C7: =HISTORIA!C7 -> 23.673973
B8: Talla Actual (Cm) | C8: ='ANTROPOMETRÍA DEPORTISTAS'!C9 -> 0
B9: Peso Actual (Kg) | C9: ='ANTROPOMETRÍA DEPORTISTAS'!C7 -> 0
B10: Longitud de la Pierna | C10: =C8-C11 -> #REF! | E10: Recuerdes restarle a la talla sentado el tamaño del Vanco si usaron uno.
B11: Talla Sentada | C11: ='ANTROPOMETRÍA DEPORTISTAS'!#REF! -> #REF!
B12: Interacción entre la Longitud de la Pierna y la Talla Sentada (Multiplicación de ambos valores) | C12: =(C10*C11) -> #REF!
B13: Interacción entre la Edad y la Longitud de la Pierna (Multiplicación de ambos valores) | C13: =(C7*C10) -> #REF!
B14: Interacción entre la Edad y la Talla Sentada (Multiplicación de ambos valores) | C14: =(C7*C11) -> #REF!
B15: Proporción entre la Talla y el Peso | C15: =(C9/C8)*100 -> #DIV/0!
A18: 2) Se debe calcular la Compensación de la Madurez (Maturity Offset) a través de la siguiente fórmula:
B20: Compensación de la Madurez: (Años para alcanzar el Pico de Velocidad de Crecimiento (PHV)) | C20: =-9.236+(0.0002708*C12)+(-0.001663*C13)+(0.007216*C14)+(0.02292*C15) -> #REF! | E20: Este numero ubicalo en la Tabla 2 según el estado de maduracion del chico
A22: 3) Seguidamente, se calcula la edad que el niño o adolescente tendrá cuando llegue al Pico de velocidad de Crecimiento.
B23: Edad en el PHV: | C23: =C7-(C20) -> #REF! | E23: Esto indica la edad a la que se dara ( o dío) el mayor crecimiento
B25: Importante: | D25: Masculino | E25: Femenino
C26: Madurador Promedio | D26: 13 a 15 | E26: 11 a 13
C27: Madurador Temprano | D27: <13 | E27: <11
C28: Madurador Tardío | D28: >15 | E28: >13
A29: 4) Finalmente, se obtiene la Talla Adulta Prevista. (Ver Tabla 1)
B30: Predicción de la Talla Adulta: | C30: 19.88 | E30: Aquí colocas el valor que te da la tabla 2 al hacer el paso 2
C31: =C8+C30 -> 19.88 | E31: ESTA ES LA PROYECCION DE TALLA . TOMA EN CUENTA EL LIMITE INFERIOR Y SUPERIOR.
B32: This method can predict adult height within ±5.35 cm 95% of the time in boys and ±6.81 cm 95% of the time in girls.

Sheet PHV
A1: Tabla 1: Distancia (cm) restante para el crecimiento en maduradores tempranos, promedio y tardíos en hombres y mujeres en diferentes edades biológicas (años para alcanzar el Pico de Velocidad de Crecimiento (PHV)).
C3: Crecimiento en Cm que Faltaría Antes de que la Estatura Adulta sea Alcanzada
C4: Masculino | F4: Femenino
B5: Años para alcanzar el PHV | C5: Temprano | D5: Promedio | E5: Tardío | F5: Temprano | G5: Promedio | H5: Tardío
B6: -4 | C6: 45.29 | D6: 40.09 | E6: 34.73 | F6: 42.61 | G6: 38.81 | H6: 34.35
B7: -3.8 | C7: 44.21 | D7: 39.08 | E7: 33.83 | F7: 41.49 | G7: 37.67 | H7: 33.27
B8: -3.6 | C8: 43.11 | D8: 38.07 | E8: 32.94 | F8: 40.39 | G8: 36.55 | H8: 32.2
B9: -3.4 | C9: 41.99 | D9: 37.06 | E9: 32.05 | F9: 39.3 | G9: 35.44 | H9: 31.14
B10: -3.2 | C10: 40.85 | D10: 36.05 | E10: 31.16 | F10: 38.21 | G10: 34.34 | H10: 30.09
B11: -3 | C11: 39.69 | D11: 35.04 | E11: 30.27 | F11: 37.13 | G11: 33.25 | H11: 29.04
B12: -2.8 | C12: 38.52 | D12: 34.04 | E12: 29.38 | F12: 36.04 | G12: 32.16 | H12: 27.99
B13: -2.6 | C13: 37.33 | D13: 33.05 | E13: 28.49 | F13: 34.94 | G13: 31.04 | H13: 26.93
B14: -2.4 | C14: 36.15 | D14: 32.06 | E14: 27.6 | F14: 33.82 | G14: 29.91 | H14: 25.87
B15: -2.2 | C15: 34.97 | D15: 31.07 | E15: 26.7 | F15: 32.68 | G15: 28.76 | H15: 24.79
B16: -2 | C16: 33.8 | D16: 30.06 | E16: 25.77 | F16: 31.53 | G16: 27.58 | H16: 23.71
B17: -1.8 | C17: 32.62 | D17: 29.03 | E17: 24.79 | F17: 30.44 | G17: 26.39 | H17: 22.63
... B46: 4 | C46: 0 | D46: 0 | E46: 0 | F46: 0 | G46: 0 | H46: 0

Sheet REQUERIMIENTOS
A1: REQUERIMIENTOS Y LISTA DE INTERCAMBIO
A3: Peso actual | B3: ='ANTROPOMETRÍA DEPORTISTAS'!B7 -> 90.05 | C3: Peso usual | D3: ='ANTROPOMETRÍA DEPORTISTAS'!B6 -> 45994 | E3: Peso mínimo | G3: Peso máximo | H3: ='ANTROPOMETRÍA DEPORTISTAS'!B7 -> 90.05 | I3: Peso a utilizar | J3: =B3 -> 90.05 | O3: LBM | P3: LBM
A4: Talla | B4: ='ANTROPOMETRÍA DEPORTISTAS'!B9 -> 186 | I4: Peso Magro | J4: ='ANTROPOMETRÍA DEPORTISTAS'!C58 -> 0 | K4: % de cambio de peso
K5: Tiempo | L5: Significativo | M5: Severo
A6: PESO TEÓRICO | E6: PESO TEÓRICO | I6: Porcentaje de cambio de peso | K6: 1 semana | L6: 1 – 2 % | M6: > 2 %
A7: WEST | C7: Derivada del IMC | E7: Hamwi | I7: =((D3-B3)/D3)*100 -> 99.804214 | K7: 1 mes | L7: 3 – 5 % | M7: > 5 %
A8: Hombres | B8: =22.1*(POWER(B4/100,2)) -> 76.45716 | C8: Hombres | D8: =23*(POWER(B3/100,2)) -> 18.650706 | E8: Hombres | F8: =(B4-152)*1.08+48.5 -> 85.22 | G8: Hombres | H8: =23*(POWER(F4/100,2)) -> 0 | I8: Peso ajustado (Obesidad) | K8: 3 meses | L8: 6 – 8 % | M8: > 8 %
A9: Mujeres | B9: =20.6*(POWER(B4/100,2)) -> 71.26776 | C9: Mujeres | D9: =21.5*(POWER(B3/100,2)) -> 17.434355 | E9: Mujeres | F9: =(B4-152)*0.88+45.5 -> 75.42 | G9: Mujeres | H9: =21.5*(POWER(F4/100,2)) -> 0 | I9: =(B3-F8)*0.25+F8 -> 86.4275 | K9: 6 meses | L9: 9 – 10% | M9: > 10 %
A12: METODO TRADICIONAL | E12: MÉTODO DIRECTO | J12: HARRIS Y BENEDICT | N12: HARRIS Y BENEDICT (ROZA) | S12: CUNNINGHAM (1980) | X12: 1.2 - Sedentary:
A13: Peso Utilizar | C13: =J3 -> 90.05 | E13: Hipocalórica | G13: =(J3*F13) -> 0 | H13: < 25 kcal/kg Peso | J13: RCB (Masculino) | L13: =(66.47+(13.75*J3)+(5*B4)-(6.75*HISTORIA!C7)) -> 2074.8582 | N13: RCB (Masculino) | P13: =88.362+(13.397*J3)+(4.799*B4)-(5.677*HISTORIA!C7) -> 2052.9787 | S13: RCB (Masculino) | U13: =(500+(22*O4)) -> 500 | X13: You work a desk job and don’t exercise
A14: RCB (Masculino) | C14: =(J3*24*1) -> 2161.2 | E14: Normocalórica | G14: =F14*J3 -> 0 | H14: 25-30 kcal/kg Peso | J14: RCB (Femenino) | L14: =(655.1+(9.56*J3)+(1.85*B4)-(4.7*HISTORIA!C7)) -> 1748.8103 | N14: RCB (Femenino) | P14: =447.593+(9.247*J3)+(3.098*B4)-(4.33*HISTORIA!C7) -> 1754.005 | S14: RCB (Femenino) | U14: =(500+(22*P4)) -> 500 | X14: 1.375 - Light Activity:
A15: RCB (Femenino) | C15: =(J3*24*0.98) -> 2117.976 | E15: Hipercalórica | G15: =F15*J3 -> 0 | H15: > 30 kcal/kg Peso | J15: Factor de Actividad | L15: 1.725 | N15: Factor de Actividad | P15: =L15 -> 1.725 | S15: Factor de Actividad | U15: =Q15 -> 0 | X15: You work a desk job but do a bit of regular exercise. Or you don’t exercise but you work at a
A16: ETA (Masculino) | C16: =C14/10 -> 216.12 | J16: Factor de estrés | L16: 1 | N16: RCT (Masculino) | P16: =P13*P15 -> 3541.3883 | S16: RCT (Masculino) | U16: =U13*U15 -> 0 | X16: job that’s pretty active (a nurse, teacher, etc.) where you’re on your for feet most of the day.
A17: ETA (Femenino) | C17: =(C15)/10 -> 211.7976 | E17: MÉTODO HOLLIDAY | J17: RCT (Masculino) | L17: =L13*L15*L16 -> 3579.1304 | N17: RCT (Femenino) | P17: =P14*P15 -> 3025.6587 | S17: RCT (Femenino) | U17: =U14*U15 -> 0 | X17: 1.55 - Moderate Activity:
A18: Actividad Física | C18: 1.5 | E18: 0-10 Kg | F18: 100 Kcal/Kg/día | J18: RCT (Femenino) | L18: =L14*L15*L16 -> 3016.6978 | X18: Most of you will probably fall into this category. Maybe you work a sedentary job, but you
A19: RCT (Masculino) | C19: =(C14*C18)+C16 -> 3457.92 | E19: 10,1-20 Kg | F19: 1000 Kcal + 50 Kcal por cada Kg por encima | X19: train like a madman. Or maybe you train moderately, but you also have a job where you
A20: RCT (Femenino) | C20: =(C15*C18)+C17 -> 3388.7616 | E20: >20 Kg | F20: 1000 Kcal + 20 Kcal por cada Kg por encima de 20 Kg | J20: FACTOR DE ACTIVIDAD FÍSICA | N20: MULLER EQUATION | S20: MIFFLIN - ST.JEOR | X20: stand on your feet all the time. Someone who doesn’t train but works a hard labor job
E21: RCB: | H21: =(J3-20) *20 + 1000 -> 2401 | J21: Sedentary | L21: 1.2 | N21: RCB (Masculino) | P21: =((13.587*'ANTROPOMETRÍA DEPORTISTAS'!B58)+(9.613*'ANTROPOMETRÍA DEPORTISTAS'!B59)+(198*1)-(3.351*HISTORIA!C7)+674) -> 1977.7787 | S21: RCB (Masculino) | U21: =(9.99*J3)+(6.25*B4)-(4.92*HISTORIA!C7)+5 -> 1950.6236 | X21: would also fall into this category.
E22: ENERGÍA DE ACTIVIDAD: | H22: =HISTORIA!K41 -> 0 | J22: Light Activity | L22: 1375 | N22: RCB (Femenino) | P22: =((13.587*'ANTROPOMETRÍA DEPORTISTAS'!B58)+(9.613*'ANTROPOMETRÍA DEPORTISTAS'!B59)+(198*0)-(3.351*HISTORIA!C7)+674) -> 1779.7787 | S22: RCB (Femenino) | U22: =(9.99*J3)+(6.25*B4)-(4.92*HISTORIA!C7)-161 -> 1784.6236 | X22: 1.725 - Very Active:
A23: ACTIVIDAD FÍSICA (AF) | E23: ETA: 10% | G23: =SUM(H21:H22) -> 2401 | H23: =G23*0.1 -> 240.1 | J23: Moderate Activity | L23: 1.55 | N23: Factor de Actividad | P23: =L15 -> 1.725 | S23: Factor de Actividad | U23: 1.375 | X23: You train hard most days of the week, and you also work a job where you’re on your feet
A24: Sedentario | C24: 1 | E24: REQUERIMIENTO CALÓRICO TOTAL | H24: =G23+H23 -> 2641.1 | J24: Very Active | L24: 1.725 | N24: RCT (Masculino) | P24: =P21*P23 -> 3411.6683 | S24: RCT (Masculino) | U24: =U21*U23 -> 2682.1074 | X24: quite a bit. Overall, you’re active most of the day.
A25: Muy Leve | C25: 1.25 | J25: Extra Active | L25: 1.9 | N25: RCT (Femenino) | P25: =P22*P23 -> 3070.1183 | S25: RCT (Femenino) | U25: =U22*U23 -> 2453.8574 | X25: 1.9 - Extra Active:
A26: Leve | C26: 1.5 | X26: You train hard and work a job that is physically intense in nature. As an example, you’re a
A27: Moderada | C27: 1.75 | X27: roofer who also goes to the gym five days a week.
A28: Intensa | C28: 2 | T28: Restricción | V28: Valor (Kcal)
T29: 0.1 | V29: =0.1*P24 -> 341.16683
G30: FORMÚLA DIETÉTICA | M30: Suplementos | T30: 0.12 | V30: 0.12
I31: RCT a Utilizar | J31: =U24-100 -> 2582.1074 | T31: 0.15 | V31: 0.15
G32: MACROS | I32: % | J32: kcal | K32: g | L32: g/kg Peso | M32: Aporte de Macros | T32: 0.2 | V32: 0.2
G33: Proteínas | I33: 29 | J33: =(I33/100)*J31 -> 748.81114 | K33: =J33/4 -> 187.20279 | L33: =(K33+M33)/J3 -> 2.078876 | T33: 0.25 | V33: 0.25
G34: Grasas | I34: 42 | J34: =(I34*J31)/100 -> 1084.4851 | K34: =J34/9 -> 120.49834 | L34: =K34/J3 -> 1.3381271 | T34: 0.3 | V34: 0.3
G35: CHO complejos | I35: =100-I33-I34 -> 29 | J35: =(I35*J31)/100 -> 748.81114 | K35: =J35/4 -> 187.20279 | L35: =K35/J3 -> 2.078876
G36: Colesterol
G37: Fibra | I37: =(L37*J31)/1000 -> 0 | M37: =SUM(J33:J35) -> 2582.1074
G38: Sodio
G39: Agua | I39: =L39*C13 -> 3151.75 | L39: 35
C41: Intervalos de edad.
A42: Rangos óptimos de proteína: | C42: 0-30 | D42: 31-40 | E42: 41-50 | F42: 51-60 | G42: 61-70
A43: No caloric Deficit | C43: 1,8-2,0 | D43: 2,0-2,3 | E43: 2,3-2,6 | F43: 2,6-2,9 | G43: 2,9-3,2 | H43: Kg de masa magra
A44: Deficit Calorico | C44: 2,2-2,4 | D44: 2,4-2,8 | E44: 2,8-3,1 | F44: 3,1-3,5 | G44: 3,5-3,8 | H44: Kg de masa magra
A46: LISTA DE INTERCAMBIO | J46: DISTRIBUCIÓN DE COMIDAS
A47: Alimento | B47: Int | C47: Proteínas | D47: Grasas | E47: CHO | F47: Fibra | G47: Colesterol | H47: Sodio | J47: Comida | K47: Pre Desayuno | L47: Desayuno | M47: Merienda | N47: Almuerzo | P47: Merienda | R47: Cena | S47: Total | T47: Requerimiento
A48: Leche Completa | C48: =B48*8 -> 0 | D48: =B48*8 -> 0 | E48: =B48*12 -> 0 | F48: =B48*0 -> 0 | G48: =B48*33 -> 0 | H48: =B48*115 -> 0 | J48: Leche | K48: 1 | S48: =SUM(K48:R48) -> 1 | T48: =B48 -> 0
A49: Leche Descremada | C49: =B49*8 -> 0 | D49: =B49*2.5 -> 0 | E49: =B49*12 -> 0 | F49: =B49*0 -> 0 | G49: =B49*13.5 -> 0 | H49: =B49*138 -> 0 | J49: Vegetales | N49: 2 | R49: 2 | S49: =SUM(K49:R49) -> 4 | T49: =B50 -> 4
A50: Vegetales | B50: 4 | C50: =B50*2 -> 8 | D50: =B50*0 -> 0 | E50: =B50*5 -> 20 | F50: =B50*1 -> 4 | G50: =B50*0 -> 0 | H50: =B50*11.5 -> 46 | J50: Frutas | K50: 1 | L50: 1 | P50: 1 | S50: =SUM(K50:R50) -> 3 | T50: =B51 -> 2
A51: Frutas | B51: 2 | C51: =B51*0 -> 0 | D51: =B51*0 -> 0 | E51: =B51*15 -> 30 | F51: =B51*2 -> 4 | G51: =B51*0 -> 0 | H51: =B51*0 -> 0 | J51: Almidon | K51: 2 | L51: 3 | N51: 3 | R51: 3 | S51: =SUM(K51:R51) -> 11 | T51: =B53 -> 9
A52: Subtotal | B52: =(K35-E52)/15 -> 9.1468524 | C52: =SUM(C48:C51) -> 8 | D52: =SUM(D48:D51) -> 0 | E52: =SUM(E48:E51) -> 50 | F52: =SUM(F48:F51) -> 8 | G52: =SUM(G48:G51) -> 0 | H52: =SUM(H48:H51) -> 46 | J52: Carnes magras | S52: =SUM(K52:R52) -> 0 | T52: =B55 -> 0
A53: Almidon | B53: 9 | C53: =B53*2 -> 18 | D53: =B53*0 -> 0 | E53: =B53*15 -> 135 | F53: =B53*2.5 -> 22.5 | G53: =B53*0 -> 0 | H53: =B53*46 -> 414 | J53: Carnes semi | K53: 4 | L53: 5 | N53: 7 | P53: 3 | R53: 7 | S53: =SUM(K53:R53) -> 26 | T53: =B56 -> 23
A54: Subtotal | B54: =(K33-C54)/7 -> 23.028969 | C54: =SUM(C48:C51,C53) -> 26 | D54: =SUM(D48:D51,D53) -> 0 | E54: =SUM(E48:E51,E53) -> 185 | F54: =SUM(F48:F51,F53) -> 30.5 | G54: =SUM(G48:G51,G53) -> 0 | H54: =SUM(H48:H51,H53) -> 460 | J54: Grasas | K54: 3 | L54: 2 | R54: 2 | S54: =SUM(K54:R54) -> 7 | T54: =B58 -> 4
A55: Carnes magras | C55: =B55*7 -> 0 | D55: =B55*3 -> 0 | E55: =B55*0 -> 0 | F55: =B55*0 -> 0 | G55: =B55*25 -> 0 | H55: =B55*2 -> 0 | J55: Azúcar o similar | S55: =SUM(K55:R55) -> 0 | T55: =#REF!/15 -> #REF!
A56: Carnes semimagras | B56: 23 | C56: =B56*7 -> 161 | D56: =B56*4 -> 92 | E56: =B56*0 -> 0 | F56: =B56*0 -> 0 | G56: =B56*25 -> 575 | H56: =B56*2 -> 46
A57: Subtotal | B57: =(K34-D57)/5 -> 5.699669 | C57: =SUM(C54:C56) -> 187 | D57: =SUM(D54:D56) -> 92 | E57: =SUM(E54:E56) -> 185 | F57: =SUM(F54:F56) -> 30.5 | G57: =SUM(G54:G56) -> 575 | H57: =SUM(H54:H56) -> 506 | S57: Calorías | T57: =(S48*150)+(S49*25)+(S50*60)+(S51*80)+(S52*55)+(S53*70)+(S54*45)+(S55*60) -> 3445
A58: Grasas | B58: 4 | C58: =B58*0 -> 0 | D58: =B58*5 -> 20 | E58: =B58*0 -> 0 | F58: =B58*0 -> 0 | G58: =B58*2 -> 8 | H58: =B58*2 -> 8
A59: Total | C59: =C57+C58 -> 187 | D59: =D57+D58 -> 112 | E59: =E57+E58 -> 185 | F59: =F57+F58 -> 30.5 | G59: =G57+G58 -> 583 | H59: =H57+H58 -> 514
A60: Requerimiento | C60: =K33-M33 -> 187.20279 | D60: =K34-M34 -> 120.49834 | E60: =K35 -> 187.20279 | F60: =I37 -> 0 | G60: =I36 -> 0 | H60: =I38 -> 0
A61: Adecuación | C61: =(C59*100)/C60 -> 99.891676 | D61: =(D59*100)/D60 -> 92.947335 | E61: =(E59*100)/E60 -> 98.823316 | F61: =(F59*100)/F60 -> #DIV/0! | G61: =(G59*100)/G60 -> #DIV/0! | H61: =(H59*100)/H60 -> #DIV/0!

Sheet RESUMEN ANTROPOMETRICO
D1: RESUMEN DE INDICADORES ANTROPOMETRICOS
D4: Evaluación | F4: 1 | G4: 2 | H4: 3 | I4: 4 | J4: 5 | K4: 6 | L4: 7 | M4: 8 | N4: 9 | O4: 10
D5: Fecha | F5: ='ANTROPOMETRÍA DEPORTISTAS'!B6 -> 45994 | G5: ='ANTROPOMETRÍA DEPORTISTAS'!C6 -> 0 | H5: ='ANTROPOMETRÍA DEPORTISTAS'!D6 -> 0 | I5: ='ANTROPOMETRÍA DEPORTISTAS'!E6 -> 0 | J5: ='ANTROPOMETRÍA DEPORTISTAS'!F6 -> 0 | K5: ='ANTROPOMETRÍA DEPORTISTAS'!G6 -> 0 | L5: ='ANTROPOMETRÍA DEPORTISTAS'!H6 -> 0 | M5: ='ANTROPOMETRÍA DEPORTISTAS'!I6 -> 0 | ... O5: ='ANTROPOMETRÍA DEPORTISTAS'!K6 -> 0
D6: Peso (Kg) | F6: ='ANTROPOMETRÍA DEPORTISTAS'!B7 -> 90.05 | G6: ='ANTROPOMETRÍA DEPORTISTAS'!C7 -> 0 | H6: ='ANTROPOMETRÍA DEPORTISTAS'!D7 -> 0 | I6: ='ANTROPOMETRÍA DEPORTISTAS'!E7 -> 0 | J6: ='ANTROPOMETRÍA DEPORTISTAS'!F7 -> 0 | K6: ='ANTROPOMETRÍA DEPORTISTAS'!G7 -> 0 | L6: ='ANTROPOMETRÍA DEPORTISTAS'!H7 -> 0 | M6: ='ANTROPOMETRÍA DEPORTISTAS'!I7 -> 0 | ... O6: ='ANTROPOMETRÍA DEPORTISTAS'!K7 -> 0
D7: Talla parada (cm) | F7: ='ANTROPOMETRÍA DEPORTISTAS'!B9 -> 186 | G7: ='ANTROPOMETRÍA DEPORTISTAS'!C9 -> 0 | H7: ='ANTROPOMETRÍA DEPORTISTAS'!D9 -> 0 | I7: ='ANTROPOMETRÍA DEPORTISTAS'!E9 -> 0 | J7: ='ANTROPOMETRÍA DEPORTISTAS'!F9 -> 0 | K7: ='ANTROPOMETRÍA DEPORTISTAS'!G9 -> 0 | L7: ='ANTROPOMETRÍA DEPORTISTAS'!H9 -> 0 | M7: ='ANTROPOMETRÍA DEPORTISTAS'!I9 -> 0 | ... O7: ='ANTROPOMETRÍA DEPORTISTAS'!K9 -> 0
D8: ='ANTROPOMETRÍA DEPORTISTAS'!A52 -> % Grasa (Carter 1986) | F8: ='ANTROPOMETRÍA DEPORTISTAS'!B52 -> 10.73025 | G8: ='ANTROPOMETRÍA DEPORTISTAS'!C52 -> 2.585 | H8: ='ANTROPOMETRÍA DEPORTISTAS'!D52 -> 2.585 | I8: ='ANTROPOMETRÍA DEPORTISTAS'!E52 -> 2.585 | J8: ='ANTROPOMETRÍA DEPORTISTAS'!F52 -> 2.585 | K8: ='ANTROPOMETRÍA DEPORTISTAS'!G52 -> 2.585 | L8: ='ANTROPOMETRÍA DEPORTISTAS'!H52 -> 2.585 | M8: ='ANTROPOMETRÍA DEPORTISTAS'!I52 -> 2.585 | ... O8: ='ANTROPOMETRÍA DEPORTISTAS'!K52 -> 2.585
D9: ='ANTROPOMETRÍA DEPORTISTAS'!A53 -> % Grasa (Durnin y W. 1974) | F9: ='ANTROPOMETRÍA DEPORTISTAS'!B53 -> 15.230089 | G9: ='ANTROPOMETRÍA DEPORTISTAS'!C53 -> #NUM! | H9: ='ANTROPOMETRÍA DEPORTISTAS'!D53 -> #NUM! | I9: ='ANTROPOMETRÍA DEPORTISTAS'!E53 -> #NUM! | J9: ='ANTROPOMETRÍA DEPORTISTAS'!F53 -> #N/A | K9: ='ANTROPOMETRÍA DEPORTISTAS'!G53 -> -2.18 | L9: ='ANTROPOMETRÍA DEPORTISTAS'!H53 -> -2.18 | M9: ='ANTROPOMETRÍA DEPORTISTAS'!I53 -> -2.18 | ... O9: ='ANTROPOMETRÍA DEPORTISTAS'!K53 -> -2.18
D10: Interpretación | F10: =IF('ANTROPOMETRÍA DEPORTISTAS'!B53<10, "Atleta", IF('ANTROPOMETRÍA DEPORTISTAS'!B53<=20, "Saludable", IF('ANTROPOMETRÍA DEPORTISTAS'!B53<=25, "Sobrepeso", "Obesidad"))) -> Saludable | G10: =IF('ANTROPOMETRÍA DEPORTISTAS'!C53<10, "Atleta", IF('ANTROPOMETRÍA DEPORTISTAS'!C53<=20, "Saludable", IF('ANTROPOMETRÍA DEPORTISTAS'!C53<=25, "Sobrepeso", "Obesidad"))) -> #NUM!
D11: Kg de Masa Magra | F11: ='ANTROPOMETRÍA DEPORTISTAS'!B58 -> 80.38741 | G11: ='ANTROPOMETRÍA DEPORTISTAS'!C58 -> 0 | H11: ='ANTROPOMETRÍA DEPORTISTAS'!D58 -> 0 | I11: ='ANTROPOMETRÍA DEPORTISTAS'!E58 -> 0 | J11: ='ANTROPOMETRÍA DEPORTISTAS'!F58 -> 0 | K11: ='ANTROPOMETRÍA DEPORTISTAS'!G58 -> 0 | L11: ='ANTROPOMETRÍA DEPORTISTAS'!H58 -> 0 | M11: ='ANTROPOMETRÍA DEPORTISTAS'!I58 -> 0 | ... O11: ='ANTROPOMETRÍA DEPORTISTAS'!K58 -> 0
D12: Kg de Grasa | F12: ='ANTROPOMETRÍA DEPORTISTAS'!B59 -> 9.6625901 | G12: ='ANTROPOMETRÍA DEPORTISTAS'!C59 -> 0 | H12: ='ANTROPOMETRÍA DEPORTISTAS'!D59 -> 0 | I12: ='ANTROPOMETRÍA DEPORTISTAS'!E59 -> 0 | J12: ='ANTROPOMETRÍA DEPORTISTAS'!F59 -> 0 | K12: ='ANTROPOMETRÍA DEPORTISTAS'!G59 -> 0 | L12: ='ANTROPOMETRÍA DEPORTISTAS'!H59 -> 0 | M12: ='ANTROPOMETRÍA DEPORTISTAS'!I59 -> 0 | ... O12: ='ANTROPOMETRÍA DEPORTISTAS'!K59 -> 0
D13: Masa Muscular (Kg) | F13: ='ANTROPOMETRÍA DEPORTISTAS'!B64 -> 51.016377 | G13: ='ANTROPOMETRÍA DEPORTISTAS'!C64 -> #DIV/0! | H13: ='ANTROPOMETRÍA DEPORTISTAS'!D64 -> #DIV/0! | I13: ='ANTROPOMETRÍA DEPORTISTAS'!E64 -> #DIV/0! | J13: ='ANTROPOMETRÍA DEPORTISTAS'!F64 -> #DIV/0! | K13: ='ANTROPOMETRÍA DEPORTISTAS'!G64 -> #DIV/0! | L13: ='ANTROPOMETRÍA DEPORTISTAS'!H64 -> #DIV/0! | M13: ='ANTROPOMETRÍA DEPORTISTAS'!I64 -> #DIV/0! | ... O13: ='ANTROPOMETRÍA DEPORTISTAS'!K64 -> #DIV/0!
D14: Masa Adiposa (Kg) | F14: ='ANTROPOMETRÍA DEPORTISTAS'!B63 -> 23.434141 | G14: ='ANTROPOMETRÍA DEPORTISTAS'!C63 -> #DIV/0! | H14: ='ANTROPOMETRÍA DEPORTISTAS'!D63 -> #DIV/0! | I14: ='ANTROPOMETRÍA DEPORTISTAS'!E63 -> #DIV/0! | J14: ='ANTROPOMETRÍA DEPORTISTAS'!F63 -> #DIV/0! | K14: ='ANTROPOMETRÍA DEPORTISTAS'!G63 -> #DIV/0! | L14: ='ANTROPOMETRÍA DEPORTISTAS'!H63 -> #DIV/0! | M14: ='ANTROPOMETRÍA DEPORTISTAS'!I63 -> #DIV/0! | ... O14: ='ANTROPOMETRÍA DEPORTISTAS'!K63 -> #DIV/0!
D15: Sumatoria de 6 pliegues | F15: ='ANTROPOMETRÍA DEPORTISTAS'!B54 -> 77.5 | G15: ='ANTROPOMETRÍA DEPORTISTAS'!C54 -> 0 | H15: ='ANTROPOMETRÍA DEPORTISTAS'!D54 -> 0 | I15: ='ANTROPOMETRÍA DEPORTISTAS'!E54 -> 0 | J15: ='ANTROPOMETRÍA DEPORTISTAS'!F54 -> 0 | K15: ='ANTROPOMETRÍA DEPORTISTAS'!G54 -> 0 | L15: ='ANTROPOMETRÍA DEPORTISTAS'!H54 -> 0 | M15: ='ANTROPOMETRÍA DEPORTISTAS'!I54 -> 0 | ... O15: ='ANTROPOMETRÍA DEPORTISTAS'!K54 -> 0
D16: Somatotipo | F16: =IF(AND('ANTROPOMETRÍA DEPORTISTAS'!B68>'ANTROPOMETRÍA DEPORTISTAS'!B67, 'ANTROPOMETRÍA DEPORTISTAS'!B68>'ANTROPOMETRÍA DEPORTISTAS'!B66), "Endomorfo", IF(AND('ANTROPOMETRÍA DEPORTISTAS'!B67>'ANTROPOMETRÍA DEPORTISTAS'!B68, 'ANTROPOMETRÍA DEPORTISTAS'!B67>'ANTROPOMETRÍA DEPORTISTAS'!B66), "Mesomorfo", IF(AND('ANTROPOMETRÍA DEPORTISTAS'!B66>'ANTROPOMETRÍA DEPORTISTAS'!B68, 'ANTROPOMETRÍA DEPORTISTAS'!B66>'ANTROPOMETRÍA DEPORTISTAS'!B67), "Ectomorfo", "Somatotipo Balanceado"))) -> Mesomorfo
D18: Evaluación | F18: 1 | G18: 2 | H18: 3 | I18: 4 | J18: 5 | K18: 6 | L18: 7 | M18: 8 | N18: 9 | O18: 10 | P18: 11
D19: Fecha | F19: ='5 COMPONENTES'!C2 -> 0 | G19: ='5 COMPONENTES'!D2 -> 0 | H19: ='5 COMPONENTES'!E2 -> 0 | I19: ='5 COMPONENTES'!F2 -> 0 | J19: ='5 COMPONENTES'!G2 -> 0 | K19: ='5 COMPONENTES'!H2 -> 0 | L19: ='5 COMPONENTES'!I2 -> 0 | M19: ='5 COMPONENTES'!J2 -> 0 | ... P19: ='5 COMPONENTES'!M2 -> 0
D20: Peso (Kg) | F20: ='5 COMPONENTES'!C5 -> 0 | G20: ='5 COMPONENTES'!D5 -> 0 | H20: ='5 COMPONENTES'!E5 -> 0 | I20: ='5 COMPONENTES'!F5 -> 0 | J20: ='5 COMPONENTES'!G5 -> 0 | K20: ='5 COMPONENTES'!H5 -> 0 | L20: ='5 COMPONENTES'!I5 -> 0 | M20: ='5 COMPONENTES'!J5 -> 0 | ... P20: ='5 COMPONENTES'!M5 -> 0
D21: Talla parada (cm) | F21: ='5 COMPONENTES'!C6 -> 185 | G21: ='5 COMPONENTES'!D6 -> 185 | H21: ='5 COMPONENTES'!E6 -> 185 | I21: ='5 COMPONENTES'!F6 -> 185 | J21: ='5 COMPONENTES'!G6 -> 185 | K21: ='5 COMPONENTES'!H6 -> 185 | L21: ='5 COMPONENTES'!I6 -> 185 | M21: ='5 COMPONENTES'!J6 -> 185 | ... P21: ='5 COMPONENTES'!M6 -> 0
D22: % Grasa (Carter 1986) | F22: ='5 COMPONENTES'!C80 -> 2.585 | G22: ='5 COMPONENTES'!D80 -> 2.585 | H22: ='5 COMPONENTES'!E80 -> 2.585 | I22: ='5 COMPONENTES'!F80 -> 2.585 | J22: ='5 COMPONENTES'!G80 -> 2.585 | K22: ='5 COMPONENTES'!H80 -> 2.585 | L22: ='5 COMPONENTES'!I80 -> 2.585 | M22: ='5 COMPONENTES'!J80 -> 2.585 | ... P22: ='5 COMPONENTES'!M80 -> 0
D23: Kg de Masa Magra | F23: ='5 COMPONENTES'!C82 -> 0 | G23: ='5 COMPONENTES'!D82 -> 0 | H23: ='5 COMPONENTES'!E82 -> 0 | I23: ='5 COMPONENTES'!F82 -> 0 | J23: ='5 COMPONENTES'!G82 -> 0 | K23: ='5 COMPONENTES'!H82 -> 0 | L23: ='5 COMPONENTES'!I82 -> 0 | M23: ='5 COMPONENTES'!J82 -> 0 | ... P23: ='5 COMPONENTES'!M82 -> 0
D24: Kg de Grasa | F24: ='5 COMPONENTES'!C83 -> 0 | G24: ='5 COMPONENTES'!D83 -> 0 | H24: ='5 COMPONENTES'!E83 -> 0 | I24: ='5 COMPONENTES'!F83 -> 0 | J24: ='5 COMPONENTES'!G83 -> 0 | K24: ='5 COMPONENTES'!H83 -> 0 | L24: ='5 COMPONENTES'!I83 -> 0 | M24: ='5 COMPONENTES'!J83 -> 0 | ... P24: ='5 COMPONENTES'!M83 -> 0
D25: Masa muscular total (Kg) | F25: ='5 COMPONENTES'!C66 -> 0 | G25: ='5 COMPONENTES'!D66 -> 0 | H25: ='5 COMPONENTES'!E66 -> 0 | I25: ='5 COMPONENTES'!F66 -> 0 | J25: ='5 COMPONENTES'!G66 -> 0 | K25: ='5 COMPONENTES'!H66 -> 0 | L25: ='5 COMPONENTES'!I66 -> 0 | M25: ='5 COMPONENTES'!J66 -> 0 | ... P25: ='5 COMPONENTES'!M66 -> 0
D26: Masa ósea total (Kg) | F26: ='5 COMPONENTES'!C64 -> 0 | G26: ='5 COMPONENTES'!D64 -> 0 | H26: ='5 COMPONENTES'!E64 -> 0 | I26: ='5 COMPONENTES'!F64 -> 0 | J26: ='5 COMPONENTES'!G64 -> 0 | K26: ='5 COMPONENTES'!H64 -> 0 | L26: ='5 COMPONENTES'!I64 -> 0 | M26: ='5 COMPONENTES'!J64 -> 0 | ... P26: ='5 COMPONENTES'!M64 -> 0
D27: Masa residual (Kg) | F27: ='5 COMPONENTES'!C67 -> 0 | G27: ='5 COMPONENTES'!D67 -> 0 | H27: ='5 COMPONENTES'!E67 -> 0 | I27: ='5 COMPONENTES'!F67 -> 0 | J27: ='5 COMPONENTES'!G67 -> 0 | K27: ='5 COMPONENTES'!H67 -> 0 | L27: ='5 COMPONENTES'!I67 -> 0 | M27: ='5 COMPONENTES'!J67 -> 0 | ... P27: ='5 COMPONENTES'!M67 -> 0
D28: ='5 COMPONENTES'!B63 -> Masa de la piel (Kg) | F28: ='5 COMPONENTES'!C63 -> 0 | G28: ='5 COMPONENTES'!D63 -> 0 | H28: ='5 COMPONENTES'!E63 -> 0 | I28: ='5 COMPONENTES'!F63 -> 0 | J28: ='5 COMPONENTES'!G63 -> 0 | K28: ='5 COMPONENTES'!H63 -> 0 | L28: ='5 COMPONENTES'!I63 -> 0 | M28: ='5 COMPONENTES'!J63 -> 0 | ... P28: ='5 COMPONENTES'!M63 -> 0
D29: Masa Adiposa (Kg) | F29: ='5 COMPONENTES'!C65 -> 0 | G29: ='5 COMPONENTES'!D65 -> 0 | H29: ='5 COMPONENTES'!E65 -> 0 | I29: ='5 COMPONENTES'!F65 -> 0 | J29: ='5 COMPONENTES'!G65 -> 0 | K29: ='5 COMPONENTES'!H65 -> 0 | L29: ='5 COMPONENTES'!I65 -> 0 | M29: ='5 COMPONENTES'!J65 -> 0 | ... P29: ='5 COMPONENTES'!M65 -> 0
D30: Sumatoria de 6 pliegues | F30: ='5 COMPONENTES'!C70 -> 0 | G30: ='5 COMPONENTES'!D70 -> 0 | H30: ='5 COMPONENTES'!E70 -> 0 | I30: ='5 COMPONENTES'!F70 -> 0 | J30: ='5 COMPONENTES'!G70 -> 0 | K30: ='5 COMPONENTES'!H70 -> 0 | L30: ='5 COMPONENTES'!I70 -> 0 | M30: ='5 COMPONENTES'!J70 -> 0 | ... P30: ='5 COMPONENTES'!M70 -> 0
D31: Somatotipo | F31: Mesomorfo | G31: Mesomorfo | H31: Mesomorfo | I31: Mesomorfo | J31: Mesomorfo | K31: Mesomorfo | L31: Mesomorfo | M31: Mesomorfo | N31: Mesomorfo | O31: Mesomorfo | P31: Mesomorfo
D32: Cociente muscular/óseo | F32: ='5 COMPONENTES'!C71 -> 2.4024574 | G32: ='5 COMPONENTES'!D71 -> 2.4024574 | H32: ='5 COMPONENTES'!E71 -> 2.4024574 | I32: ='5 COMPONENTES'!F71 -> 2.4024574 | J32: ='5 COMPONENTES'!G71 -> 2.4024574 | K32: ='5 COMPONENTES'!H71 -> 2.4024574 | L32: ='5 COMPONENTES'!I71 -> 2.4024574 | M32: ='5 COMPONENTES'!J71 -> 2.4024574 | ... P32: ='5 COMPONENTES'!M71 -> 0
D34: DATOS DEL INFORME
E36: ='ANTROPOMETRÍA DEPORTISTAS'!A6 -> Fecha de evaluación | F36: ='ANTROPOMETRÍA DEPORTISTAS'!B6 -> 45994 | G36: ='ANTROPOMETRÍA DEPORTISTAS'!C6 -> 0 | H36: ='ANTROPOMETRÍA DEPORTISTAS'!D6 -> 0 | I36: ='ANTROPOMETRÍA DEPORTISTAS'!E6 -> 0 | J36: ='ANTROPOMETRÍA DEPORTISTAS'!F6 -> 0 | K36: ='ANTROPOMETRÍA DEPORTISTAS'!G6 -> 0
E37: ='ANTROPOMETRÍA DEPORTISTAS'!A7 -> Peso actual (kg) | F37: ='ANTROPOMETRÍA DEPORTISTAS'!B7 -> 90.05 | G37: ='ANTROPOMETRÍA DEPORTISTAS'!C7 -> 0 | H37: ='ANTROPOMETRÍA DEPORTISTAS'!D7 -> 0 | I37: ='ANTROPOMETRÍA DEPORTISTAS'!E7 -> 0 | J37: ='ANTROPOMETRÍA DEPORTISTAS'!F7 -> 0 | K37: ='ANTROPOMETRÍA DEPORTISTAS'!G7 -> 0
E38: ='ANTROPOMETRÍA DEPORTISTAS'!A8 -> Talla (m) | F38: ='ANTROPOMETRÍA DEPORTISTAS'!B8 -> 1.86 | G38: ='ANTROPOMETRÍA DEPORTISTAS'!C8 -> 0 | H38: ='ANTROPOMETRÍA DEPORTISTAS'!D8 -> 0 | I38: ='ANTROPOMETRÍA DEPORTISTAS'!E8 -> 0 | J38: ='ANTROPOMETRÍA DEPORTISTAS'!F8 -> 0 | K38: ='ANTROPOMETRÍA DEPORTISTAS'!G8 -> 0
E39: ='ANTROPOMETRÍA DEPORTISTAS'!A9 -> Talla (cm) | F39: ='ANTROPOMETRÍA DEPORTISTAS'!B9 -> 186 | G39: ='ANTROPOMETRÍA DEPORTISTAS'!C9 -> 0 | H39: ='ANTROPOMETRÍA DEPORTISTAS'!D9 -> 0 | I39: ='ANTROPOMETRÍA DEPORTISTAS'!E9 -> 0 | J39: ='ANTROPOMETRÍA DEPORTISTAS'!F9 -> 0 | K39: ='ANTROPOMETRÍA DEPORTISTAS'!G9 -> 0
E40: ='ANTROPOMETRÍA DEPORTISTAS'!A11 -> Circunferencias(cm)
E41: ='ANTROPOMETRÍA DEPORTISTAS'!A12 -> Brazo relajado (cm) | F41: ='ANTROPOMETRÍA DEPORTISTAS'!B12 -> 39.1 | G41: ='ANTROPOMETRÍA DEPORTISTAS'!C12 -> 0 | H41: ='ANTROPOMETRÍA DEPORTISTAS'!D12 -> 0 | I41: ='ANTROPOMETRÍA DEPORTISTAS'!E12 -> 0 | J41: ='ANTROPOMETRÍA DEPORTISTAS'!F12 -> 0 | K41: ='ANTROPOMETRÍA DEPORTISTAS'!G12 -> 0
E42: ='ANTROPOMETRÍA DEPORTISTAS'!A13 -> Brazo Flexionado en Tensión (cm) | F42: ='ANTROPOMETRÍA DEPORTISTAS'!B13 -> 41.5 | G42: ='ANTROPOMETRÍA DEPORTISTAS'!C13 -> 0 | H42: ='ANTROPOMETRÍA DEPORTISTAS'!D13 -> 0 | I42: ='ANTROPOMETRÍA DEPORTISTAS'!E13 -> 0 | J42: ='ANTROPOMETRÍA DEPORTISTAS'!F13 -> 0 | K42: ='ANTROPOMETRÍA DEPORTISTAS'!G13 -> 0
E43: ='ANTROPOMETRÍA DEPORTISTAS'!A14 -> Antebrazo máximo (cm) | F43: ='ANTROPOMETRÍA DEPORTISTAS'!B14 -> 31 | G43: ='ANTROPOMETRÍA DEPORTISTAS'!C14 -> 0 | H43: ='ANTROPOMETRÍA DEPORTISTAS'!D14 -> 0 | I43: ='ANTROPOMETRÍA DEPORTISTAS'!E14 -> 0 | J43: ='ANTROPOMETRÍA DEPORTISTAS'!F14 -> 0 | K43: ='ANTROPOMETRÍA DEPORTISTAS'!G14 -> 0
E44: ='ANTROPOMETRÍA DEPORTISTAS'!A15 -> Tórax (Mesoesternal) (cm) | F44: ='ANTROPOMETRÍA DEPORTISTAS'!B15 -> 108 | G44: ='ANTROPOMETRÍA DEPORTISTAS'!C15 -> 0 | H44: ='ANTROPOMETRÍA DEPORTISTAS'!D15 -> 0 | I44: ='ANTROPOMETRÍA DEPORTISTAS'!E15 -> 0 | J44: ='ANTROPOMETRÍA DEPORTISTAS'!F15 -> 0 | K44: ='ANTROPOMETRÍA DEPORTISTAS'!G15 -> 0
E45: ='ANTROPOMETRÍA DEPORTISTAS'!A16 -> Cintura mínimo (cm) | F45: ='ANTROPOMETRÍA DEPORTISTAS'!B16 -> 85 | G45: ='ANTROPOMETRÍA DEPORTISTAS'!C16 -> 0 | H45: ='ANTROPOMETRÍA DEPORTISTAS'!D16 -> 0 | I45: ='ANTROPOMETRÍA DEPORTISTAS'!E16 -> 0 | J45: ='ANTROPOMETRÍA DEPORTISTAS'!F16 -> 0 | K45: ='ANTROPOMETRÍA DEPORTISTAS'!G16 -> 0
E46: ='ANTROPOMETRÍA DEPORTISTAS'!A17 -> Cadera máximo (cm) | F46: ='ANTROPOMETRÍA DEPORTISTAS'!B17 -> 99.8 | G46: ='ANTROPOMETRÍA DEPORTISTAS'!C17 -> 0 | H46: ='ANTROPOMETRÍA DEPORTISTAS'!D17 -> 0 | I46: ='ANTROPOMETRÍA DEPORTISTAS'!E17 -> 0 | J46: ='ANTROPOMETRÍA DEPORTISTAS'!F17 -> 0 | K46: ='ANTROPOMETRÍA DEPORTISTAS'!G17 -> 0
E47: ='ANTROPOMETRÍA DEPORTISTAS'!A18 -> Muslo máximo (cm) | F47: ='ANTROPOMETRÍA DEPORTISTAS'!B18 -> 61.3 | G47: ='ANTROPOMETRÍA DEPORTISTAS'!C18 -> 0 | H47: ='ANTROPOMETRÍA DEPORTISTAS'!D18 -> 0 | I47: ='ANTROPOMETRÍA DEPORTISTAS'!E18 -> 0 | J47: ='ANTROPOMETRÍA DEPORTISTAS'!F18 -> 0 | K47: ='ANTROPOMETRÍA DEPORTISTAS'!G18 -> 0
E48: ='ANTROPOMETRÍA DEPORTISTAS'!A19 -> Muslo medial (cm) | F48: ='ANTROPOMETRÍA DEPORTISTAS'!B19 -> 58.3 | G48: ='ANTROPOMETRÍA DEPORTISTAS'!C19 -> 0 | H48: ='ANTROPOMETRÍA DEPORTISTAS'!D19 -> 0 | I48: ='ANTROPOMETRÍA DEPORTISTAS'!E19 -> 0 | J48: ='ANTROPOMETRÍA DEPORTISTAS'!F19 -> 0 | K48: ='ANTROPOMETRÍA DEPORTISTAS'!G19 -> 0
E49: ='ANTROPOMETRÍA DEPORTISTAS'!A20 -> Pantorrilla máximo (cm) | F49: ='ANTROPOMETRÍA DEPORTISTAS'!B20 -> 38.6 | G49: ='ANTROPOMETRÍA DEPORTISTAS'!C20 -> 0 | H49: ='ANTROPOMETRÍA DEPORTISTAS'!D20 -> 0 | I49: ='ANTROPOMETRÍA DEPORTISTAS'!E20 -> 0 | J49: ='ANTROPOMETRÍA DEPORTISTAS'!F20 -> 0 | K49: ='ANTROPOMETRÍA DEPORTISTAS'!G20 -> 0
E50: ='ANTROPOMETRÍA DEPORTISTAS'!A21 -> Pliegues (mm)
E51: ='ANTROPOMETRÍA DEPORTISTAS'!A22 -> Bíceps (mm) | F51: ='ANTROPOMETRÍA DEPORTISTAS'!B22 -> 3.5 | G51: ='ANTROPOMETRÍA DEPORTISTAS'!C22 -> 0 | H51: ='ANTROPOMETRÍA DEPORTISTAS'!D22 -> 0 | I51: ='ANTROPOMETRÍA DEPORTISTAS'!E22 -> 0 | J51: ='ANTROPOMETRÍA DEPORTISTAS'!F22 -> 0 | K51: ='ANTROPOMETRÍA DEPORTISTAS'!G22 -> 0
E52: ='ANTROPOMETRÍA DEPORTISTAS'!A23 -> Tríceps (mm) | F52: ='ANTROPOMETRÍA DEPORTISTAS'!B23 -> 6.5 | G52: ='ANTROPOMETRÍA DEPORTISTAS'!C23 -> 0 | H52: ='ANTROPOMETRÍA DEPORTISTAS'!D23 -> 0 | I52: ='ANTROPOMETRÍA DEPORTISTAS'!E23 -> 0 | J52: ='ANTROPOMETRÍA DEPORTISTAS'!F23 -> 0 | K52: ='ANTROPOMETRÍA DEPORTISTAS'!G23 -> 0
E53: ='ANTROPOMETRÍA DEPORTISTAS'!A24 -> Subescapular (mm) | F53: ='ANTROPOMETRÍA DEPORTISTAS'!B24 -> 11.5 | G53: ='ANTROPOMETRÍA DEPORTISTAS'!C24 -> 0 | H53: ='ANTROPOMETRÍA DEPORTISTAS'!D24 -> 0 | I53: ='ANTROPOMETRÍA DEPORTISTAS'!E24 -> 0 | J53: ='ANTROPOMETRÍA DEPORTISTAS'!F24 -> 0 | K53: ='ANTROPOMETRÍA DEPORTISTAS'!G24 -> 0
E54: ='ANTROPOMETRÍA DEPORTISTAS'!A25 -> Ileo-crestal (mm) | F54: ='ANTROPOMETRÍA DEPORTISTAS'!B25 -> 15.5 | G54: ='ANTROPOMETRÍA DEPORTISTAS'!C25 -> 0 | H54: ='ANTROPOMETRÍA DEPORTISTAS'!D25 -> 0 | I54: ='ANTROPOMETRÍA DEPORTISTAS'!E25 -> 0 | J54: ='ANTROPOMETRÍA DEPORTISTAS'!F25 -> 0 | K54: ='ANTROPOMETRÍA DEPORTISTAS'!G25 -> 0
E55: ='ANTROPOMETRÍA DEPORTISTAS'!A26 -> Supra-espinal (mm) | F55: ='ANTROPOMETRÍA DEPORTISTAS'!B26 -> 14 | G55: ='ANTROPOMETRÍA DEPORTISTAS'!C26 -> 0 | H55: ='ANTROPOMETRÍA DEPORTISTAS'!D26 -> 0 | I55: ='ANTROPOMETRÍA DEPORTISTAS'!E26 -> 0 | J55: ='ANTROPOMETRÍA DEPORTISTAS'!F26 -> 0 | K55: ='ANTROPOMETRÍA DEPORTISTAS'!G26 -> 0
E56: ='ANTROPOMETRÍA DEPORTISTAS'!A27 -> Abdominal (mm) | F56: ='ANTROPOMETRÍA DEPORTISTAS'!B27 -> 28.5 | G56: ='ANTROPOMETRÍA DEPORTISTAS'!C27 -> 0 | H56: ='ANTROPOMETRÍA DEPORTISTAS'!D27 -> 0 | I56: ='ANTROPOMETRÍA DEPORTISTAS'!E27 -> 0 | J56: ='ANTROPOMETRÍA DEPORTISTAS'!F27 -> 0 | K56: ='ANTROPOMETRÍA DEPORTISTAS'!G27 -> 0
E57: ='ANTROPOMETRÍA DEPORTISTAS'!A28 -> Muslo frontal (mm) | F57: ='ANTROPOMETRÍA DEPORTISTAS'!B28 -> 10.5 | G57: ='ANTROPOMETRÍA DEPORTISTAS'!C28 -> 0 | H57: ='ANTROPOMETRÍA DEPORTISTAS'!D28 -> 0 | I57: ='ANTROPOMETRÍA DEPORTISTAS'!E28 -> 0 | J57: ='ANTROPOMETRÍA DEPORTISTAS'!F28 -> 0 | K57: ='ANTROPOMETRÍA DEPORTISTAS'!G28 -> 0
E58: ='ANTROPOMETRÍA DEPORTISTAS'!A29 -> Pantorrilla (mm) | F58: ='ANTROPOMETRÍA DEPORTISTAS'!B29 -> 6.5 | G58: ='ANTROPOMETRÍA DEPORTISTAS'!C29 -> 0 | H58: ='ANTROPOMETRÍA DEPORTISTAS'!D29 -> 0 | I58: ='ANTROPOMETRÍA DEPORTISTAS'!E29 -> 0 | J58: ='ANTROPOMETRÍA DEPORTISTAS'!F29 -> 0 | K58: ='ANTROPOMETRÍA DEPORTISTAS'!G29 -> 0
E59: ='ANTROPOMETRÍA DEPORTISTAS'!A30 -> Diametros óseos (cm)
E60: ='ANTROPOMETRÍA DEPORTISTAS'!A35 -> Humeral (Biepicondilar) | F60: ='ANTROPOMETRÍA DEPORTISTAS'!B35 -> 8 | G60: ='ANTROPOMETRÍA DEPORTISTAS'!C35 -> 0 | H60: ='ANTROPOMETRÍA DEPORTISTAS'!D35 -> 0 | I60: ='ANTROPOMETRÍA DEPORTISTAS'!E35 -> 0 | J60: ='ANTROPOMETRÍA DEPORTISTAS'!F35 -> 0 | K60: ='ANTROPOMETRÍA DEPORTISTAS'!G35 -> 0
E61: ='ANTROPOMETRÍA DEPORTISTAS'!A36 -> Femoral (Biepicondilar) | F61: ='ANTROPOMETRÍA DEPORTISTAS'!B36 -> 10.5 | G61: ='ANTROPOMETRÍA DEPORTISTAS'!C36 -> 0 | H61: ='ANTROPOMETRÍA DEPORTISTAS'!D36 -> 0 | I61: ='ANTROPOMETRÍA DEPORTISTAS'!E36 -> 0 | J61: ='ANTROPOMETRÍA DEPORTISTAS'!F36 -> 0 | K61: ='ANTROPOMETRÍA DEPORTISTAS'!G36 -> 0

Sheet Hoja1

Sheet DATOS ANTROPOMÉTRICOS
A14: DATOS ANTROPOMETRICOS
B16: FECHA DE EVALUACION
A17: BASICOS
A18: Peso (kg)
A19: Talla (cm)
A20: PLIEGUES CUTANEOS (mm)
A21: Tríceps
A22: Subescapular
A23: Bíceps
A24: Cresta Iliaca
A25: Supraespinal
A26: Abdominal
A27: Muslo Frontal
A28: Pantorrilla Medial
... A38: ESTIMACIÓN DE VARIABLES ANTROPOMETRICAS
A39: % Grasa Durning & W. (adultos 17 años y mas) | B39: =IF(HISTORIA!C10="masculino",(495/(1.1765-(0.0744*LOG10(B21+B22+B23+B24)))-450),(495/(1.1567-(0.0717*LOG10(B21+B22+B23+B24)))-450)) -> #NUM! | C39: =IF(HISTORIA!C10="masculino",(495/(1.1765-(0.0744*LOG10(C21+C22+C23+C24)))-450),(495/(1.1567-(0.0717*LOG10(C21+C22+C23+C24)))-450)) -> #NUM! | D39: =IF(HISTORIA!C10="masculino",(495/(1.1765-(0.0744*LOG10(D21+D22+D23+D24)))-450),(495/(1.1567-(0.0717*LOG10(D21+D22+D23+D24)))-450)) -> #NUM! | E39: =IF(HISTORIA!C10="masculino",(495/(1.1765-(0.0744*LOG10(E21+E22+E23+E24)))-450),(495/(1.1567-(0.0717*LOG10(E21+E22+E23+E24)))-450)) -> #NUM! | F39: =IF(HISTORIA!C10="masculino",(495/(1.1765-(0.0744*LOG10(F21+F22+F23+F24)))-450),(495/(1.1567-(0.0717*LOG10(F21+F22+F23+F24)))-450)) -> #NUM! | G39: =IF(HISTORIA!C10="masculino",(495/(1.1765-(0.0744*LOG10(G21+G22+G23+G24)))-450),(495/(1.1567-(0.0717*LOG10(G21+G22+G23+G24)))-450)) -> #NUM! | H39: =IF(HISTORIA!C10="masculino",(495/(1.1765-(0.0744*LOG10(H21+H22+H23+H24)))-450),(495/(1.1567-(0.0717*LOG10(H21+H22+H23+H24)))-450)) -> #NUM! | I39: =IF(HISTORIA!C10="masculino",(495/(1.1765-(0.0744*LOG10(I21+I22+I23+I24)))-450),(495/(1.1567-(0.0717*LOG10(I21+I22+I23+I24)))-450)) -> #NUM! | J39: =IF(HISTORIA!C10="masculino",(495/(1.1765-(0.0744*LOG10(J21+J22+J23+J24)))-450),(495/(1.1567-(0.0717*LOG10(J21+J22+J23+J24)))-450)) -> #NUM! | K39: =IF(HISTORIA!C10="masculino",(495/(1.1765-(0.0744*LOG10(K21+K22+K23+K24)))-450),(495/(1.1567-(0.0717*LOG10(K21+K22+K23+K24)))-450)) -> #NUM! | L39: =IF(HISTORIA!C10="masculino",(495/(1.1765-(0.0744*LOG10(L21+L22+L23+L24)))-450),(495/(1.1567-(0.0717*LOG10(L21+L22+L23+L24)))-450)) -> #NUM! | M39: =IF(HISTORIA!C10="masculino",(495/(1.1765-(0.0744*LOG10(M21+M22+M23+M24)))-450),(495/(1.1567-(0.0717*LOG10(M21+M22+M23+M24)))-450)) -> #NUM!
A40: % Grasa Carter-Yuhasz (Atletas) | B40: =IF(HISTORIA!C10="masculino",(0.1051*(B21+B22+B25+B26+B27+B28)+2.585),(0.1548*(B21+B22+B25+B26+B27+B28)+3.58)) -> 2.585 | C40: =IF(HISTORIA!C10="masculino",(0.1051*(C21+C22+C25+C26+C27+C28)+2.585),(0.1548*(C21+C22+C25+C26+C27+C28)+3.58)) -> 2.585 | D40: =IF(HISTORIA!C10="masculino",(0.1051*(D21+D22+D25+D26+D27+D28)+2.585),(0.1548*(D21+D22+D25+D26+D27+D28)+3.58)) -> 2.585 | E40: =IF(HISTORIA!C10="masculino",(0.1051*(E21+E22+E25+E26+E27+E28)+2.585),(0.1548*(E21+E22+E25+E26+E27+E28)+3.58)) -> 2.585 | F40: =IF(HISTORIA!C10="masculino",(0.1051*(F21+F22+F25+F26+F27+F28)+2.585),(0.1548*(F21+F22+F25+F26+F27+F28)+3.58)) -> 2.585 | G40: =IF(HISTORIA!C10="masculino",(0.1051*(G21+G22+G25+G26+G27+G28)+2.585),(0.1548*(G21+G22+G25+G26+G27+G28)+3.58)) -> 2.585 | H40: =IF(HISTORIA!C10="masculino",(0.1051*(H21+H22+H25+H26+H27+H28)+2.585),(0.1548*(H21+H22+H25+H26+H27+H28)+3.58)) -> 2.585 | I40: =IF(HISTORIA!C10="masculino",(0.1051*(I21+I22+I25+I26+I27+I28)+2.585),(0.1548*(I21+I22+I25+I26+I27+I28)+3.58)) -> 2.585 | J40: =IF(HISTORIA!C10="masculino",(0.1051*(J21+J22+J25+J26+J27+J28)+2.585),(0.1548*(J21+J22+J25+J26+J27+J28)+3.58)) -> 2.585 | K40: =IF(HISTORIA!C10="masculino",(0.1051*(K21+K22+K25+K26+K27+K28)+2.585),(0.1548*(K21+K22+K25+K26+K27+K28)+3.58)) -> 2.585 | L40: =IF(HISTORIA!C10="masculino",(0.1051*(L21+L22+L25+L26+L27+L28)+2.585),(0.1548*(L21+L22+L25+L26+L27+L28)+3.58)) -> 2.585 | M40: =IF(HISTORIA!C10="masculino",(0.1051*(M21+M22+M25+M26+M27+M28)+2.585),(0.1548*(M21+M22+M25+M26+M27+M28)+3.58)) -> 2.585
A41: % Grasa Durnin ADULTOS | B41: =(((0.2467)*(B21+B22++B23+B24))+((0.12*B32)))+4.98 -> 4.98 | C41: =(((0.2467)*(C21+C22++C23+C24))+((0.12*C32)))+4.98 -> 4.98 | D41: =(((0.2467)*(D21+D22++D23+D24))+((0.12*D32)))+4.98 -> 4.98 | E41: =(((0.2467)*(E21+E22++E23+E24))+((0.12*E32)))+4.98 -> 4.98 | F41: =(((0.2467)*(F21+F22++F23+F24))+((0.12*F32)))+4.98 -> 4.98 | G41: =(((0.2467)*(G21+G22++G23+G24))+((0.12*G32)))+4.98 -> 4.98 | H41: =(((0.2467)*(H21+H22++H23+H24))+((0.12*H32)))+4.98 -> 4.98 | I41: =(((0.2467)*(I21+I22++I23+I24))+((0.12*I32)))+4.98 -> 4.98 | ... M41: =(((0.2467)*(M21+M22++M23+M24))+((0.12*M32)))+4.98 -> 4.98
A42: % Grasa Brook (1-11 años) | B42: =IF(HISTORIA!C10="masculino",(530/(1.169-(0.078*LOG10(B21+B22+B23+B25)))-489),(530/(1.2063-(0.0999*LOG10(B21+B22+B23+B25)))-489)) -> #NUM! | C42: =IF(HISTORIA!C10="masculino",(530/(1.169-(0.078*LOG10(C21+C22+C23+C25)))-489),(530/(1.2063-(0.0999*LOG10(C21+C22+C23+C25)))-489)) -> #NUM! | D42: =IF(HISTORIA!C10="masculino",(530/(1.169-(0.078*LOG10(D21+D22+D23+D25)))-489),(530/(1.2063-(0.0999*LOG10(D21+D22+D23+D25)))-489)) -> #NUM! | E42: =IF(HISTORIA!C10="masculino",(530/(1.169-(0.078*LOG10(E21+E22+E23+E25)))-489),(530/(1.2063-(0.0999*LOG10(E21+E22+E23+E25)))-489)) -> #NUM! | F42: =IF(HISTORIA!C10="masculino",(530/(1.169-(0.078*LOG10(F21+F22+F23+F25)))-489),(530/(1.2063-(0.0999*LOG10(F21+F22+F23+F25)))-489)) -> #NUM! | G42: =IF(HISTORIA!C10="masculino",(530/(1.169-(0.078*LOG10(G21+G22+G23+G25)))-489),(530/(1.2063-(0.0999*LOG10(G21+G22+G23+G25)))-489)) -> #NUM! | H42: =IF(HISTORIA!C10="masculino",(530/(1.169-(0.078*LOG10(H21+H22+H23+H25)))-489),(530/(1.2063-(0.0999*LOG10(H21+H22+H23+H25)))-489)) -> #NUM! | I42: =IF(HISTORIA!C10="masculino",(530/(1.169-(0.078*LOG10(I21+I22+I23+I25)))-489),(530/(1.2063-(0.0999*LOG10(I21+I22+I23+I25)))-489)) -> #NUM! | J42: =IF(HISTORIA!C10="masculino",(530/(1.169-(0.078*LOG10(J21+J22+J23+J25)))-489),(530/(1.2063-(0.0999*LOG10(J21+J22+J23+J25)))-489)) -> #NUM! | K42: =IF(HISTORIA!C10="masculino",(530/(1.169-(0.078*LOG10(K21+K22+K23+K25)))-489),(530/(1.2063-(0.0999*LOG10(K21+K22+K23+K25)))-489)) -> #NUM! | L42: =IF(HISTORIA!C10="masculino",(530/(1.169-(0.078*LOG10(L21+L22+L23+L25)))-489),(530/(1.2063-(0.0999*LOG10(L21+L22+L23+L25)))-489)) -> #NUM! | M42: =IF(HISTORIA!C10="masculino",(530/(1.169-(0.078*LOG10(M21+M22+M23+M25)))-489),(530/(1.2063-(0.0999*LOG10(M21+M22+M23+M25)))-489)) -> #NUM!
A43: % Grasa Durnin (12-16 años) | B43: =IF(HISTORIA!C10="masculino",(530/(1.1533-(0.0643*LOG10(B21+B22+B23+B25)))-489),(530/(1.1369-(0.0598*LOG10(B21+B22+B23+B25)))-489)) -> #NUM! | C43: =IF(HISTORIA!C10="masculino",(530/(1.1533-(0.0643*LOG10(C21+C22+C23+C25)))-489),(530/(1.1369-(0.0598*LOG10(C21+C22+C23+C25)))-489)) -> #NUM! | D43: =IF(HISTORIA!C10="masculino",(530/(1.1533-(0.0643*LOG10(D21+D22+D23+D25)))-489),(530/(1.1369-(0.0598*LOG10(D21+D22+D23+D25)))-489)) -> #NUM! | E43: =IF(HISTORIA!C10="masculino",(530/(1.1533-(0.0643*LOG10(E21+E22+E23+E25)))-489),(530/(1.1369-(0.0598*LOG10(E21+E22+E23+E25)))-489)) -> #NUM! | F43: =IF(HISTORIA!C10="masculino",(530/(1.1533-(0.0643*LOG10(F21+F22+F23+F25)))-489),(530/(1.1369-(0.0598*LOG10(F21+F22+F23+F25)))-489)) -> #NUM! | G43: =IF(HISTORIA!C10="masculino",(530/(1.1533-(0.0643*LOG10(G21+G22+G23+G25)))-489),(530/(1.1369-(0.0598*LOG10(G21+G22+G23+G25)))-489)) -> #NUM! | H43: =IF(HISTORIA!C10="masculino",(530/(1.1533-(0.0643*LOG10(H21+H22+H23+H25)))-489),(530/(1.1369-(0.0598*LOG10(H21+H22+H23+H25)))-489)) -> #NUM! | I43: =IF(HISTORIA!C10="masculino",(530/(1.1533-(0.0643*LOG10(I21+I22+I23+I25)))-489),(530/(1.1369-(0.0598*LOG10(I21+I22+I23+I25)))-489)) -> #NUM! | J43: =IF(HISTORIA!C10="masculino",(530/(1.1533-(0.0643*LOG10(J21+J22+J23+J25)))-489),(530/(1.1369-(0.0598*LOG10(J21+J22+J23+J25)))-489)) -> #NUM! | K43: =IF(HISTORIA!C10="masculino",(530/(1.1533-(0.0643*LOG10(K21+K22+K23+K25)))-489),(530/(1.1369-(0.0598*LOG10(K21+K22+K23+K25)))-489)) -> #NUM! | L43: =IF(HISTORIA!C10="masculino",(530/(1.1533-(0.0643*LOG10(L21+L22+L23+L25)))-489),(530/(1.1369-(0.0598*LOG10(L21+L22+L23+L25)))-489)) -> #NUM! | M43: =IF(HISTORIA!C10="masculino",(530/(1.1533-(0.0643*LOG10(M21+M22+M23+M25)))-489),(530/(1.1369-(0.0598*LOG10(M21+M22+M23+M25)))-489)) -> #NUM!
A44: % Grasa Seleccionado | B44: 22.4 | C44: 31.8
A45: % Grasa Minimo Permitido | B45: 15 | C45: 15
A46: % Grasa Maximo Permitido | B46: 20 | C46: 20
A47: Peso de la Grasa (pg) | B47: =(B18*(B44/100)) -> 0 | C47: =(C18*(C44/100)) -> 0 | D47: =(D18*(D44/100)) -> 0 | E47: =(E18*(E44/100)) -> 0 | F47: =(F18*(F44/100)) -> 0 | G47: =(G18*(G44/100)) -> 0 | H47: =(H18*(H44/100)) -> 0 | I47: =(I18*(I44/100)) -> 0 | ... M47: =(M18*(M44/100)) -> 0
A48: Peso Magro (pm) | B48: =B18-B47 -> 0 | C48: =C18-C47 -> 0 | D48: =D18-D47 -> 0 | E48: =E18-E47 -> 0 | F48: =F18-F47 -> 0 | G48: =G18-G47 -> 0 | H48: =H18-H47 -> 0 | I48: =I18-I47 -> 0 | ... M48: =M18-M47 -> 0
A49: % Peso Magro (%pm) | B49: =(B48*100)/B18 -> #DIV/0! | C49: =(C48*100)/C18 -> #DIV/0! | D49: =(D48*100)/D18 -> #DIV/0! | E49: =(E48*100)/E18 -> #DIV/0! | F49: =(F48*100)/F18 -> #DIV/0! | G49: =(G48*100)/G18 -> #DIV/0! | H49: =(H48*100)/H18 -> #DIV/0! | I49: =(I48*100)/I18 -> #DIV/0! | ... M49: =(M48*100)/M18 -> #DIV/0!
A50: Indice de Masa Corporal (IMC) | B50: =B18/(POWER(B19/100,2)) -> #DIV/0! | C50: =C18/(POWER(C19/100,2)) -> #DIV/0! | D50: =D18/(POWER(D19/100,2)) -> #DIV/0! | E50: =E18/(POWER(E19/100,2)) -> #DIV/0! | F50: =F18/(POWER(F19/100,2)) -> #DIV/0! | G50: =G18/(POWER(G19/100,2)) -> #DIV/0! | H50: =H18/(POWER(H19/100,2)) -> #DIV/0! | I50: =I18/(POWER(I19/100,2)) -> #DIV/0! | ... M50: =M18/(POWER(M19/100,2)) -> #DIV/0!
A51: Relacion Cintura/Cadera (ICC) | B51: =B32/B33 -> #DIV/0! | C51: =C32/C33 -> #DIV/0! | D51: =D32/D33 -> #DIV/0! | E51: =E32/E33 -> #DIV/0! | F51: =F32/F33 -> #DIV/0! | G51: =G32/G33 -> #DIV/0! | H51: =H32/H33 -> #DIV/0! | I51: =I32/I33 -> #DIV/0! | ... M51: =M32/M33 -> #DIV/0!
A52: Adiposidad Relativa (AR) | B52: =(B21+B22+B24+B26+B27+B28)*(170.18/B19) -> #DIV/0! | C52: =(C21+C22+C24+C26+C27+C28)*(170.18/C19) -> #DIV/0! | D52: =(D21+D22+D24+D26+D27+D28)*(170.18/D19) -> #DIV/0! | E52: =(E21+E22+E24+E26+E27+E28)*(170.18/E19) -> #DIV/0! | F52: =(F21+F22+F24+F26+F27+F28)*(170.18/F19) -> #DIV/0! | G52: =(G21+G22+G24+G26+G27+G28)*(170.18/G19) -> #DIV/0! | H52: =(H21+H22+H24+H26+H27+H28)*(170.18/H19) -> #DIV/0! | I52: =(I21+I22+I24+I26+I27+I28)*(170.18/I19) -> #DIV/0! | ... M52: =(M21+M22+M24+M26+M27+M28)*(170.18/M19) -> #DIV/0!
A53: Peso Proporcional (PP) | B53: =B18*(POWER(170.18/B19,3)) -> #DIV/0! | C53: =C18*(POWER(170.18/C19,3)) -> #DIV/0! | D53: =D18*(POWER(170.18/D19,3)) -> #DIV/0! | E53: =E18*(POWER(170.18/E19,3)) -> #DIV/0! | F53: =F18*(POWER(170.18/F19,3)) -> #DIV/0! | G53: =G18*(POWER(170.18/G19,3)) -> #DIV/0! | H53: =H18*(POWER(170.18/H19,3)) -> #DIV/0! | I53: =I18*(POWER(170.18/I19,3)) -> #DIV/0! | ... M53: =M18*(POWER(170.18/M19,3)) -> #DIV/0!
A54: Sumatoria de 4 Pliegues | B54: =B21+B22+B23+B24 -> 0 | C54: =C21+C22+C23+C24 -> 0 | D54: =D21+D22+D23+D24 -> 0 | E54: =E21+E22+E23+E24 -> 0 | F54: =F21+F22+F23+F24 -> 0 | G54: =G21+G22+G23+G24 -> 0 | H54: =H21+H22+H23+H24 -> 0 | I54: =I21+I22+I23+I24 -> 0 | ... M54: =M21+M22+M23+M24 -> 0
A55: Sumatoria de 6 Pliegues | B55: =B21+B22+B25+B26+B27+B28 -> 0 | C55: =C21+C22+C25+C26+C27+C28 -> 0 | D55: =D21+D22+D25+D26+D27+D28 -> 0 | E55: =E21+E22+E25+E26+E27+E28 -> 0 | F55: =F21+F22+F25+F26+F27+F28 -> 0 | G55: =G21+G22+G25+G26+G27+G28 -> 0 | H55: =H21+H22+H25+H26+H27+H28 -> 0 | I55: =I21+I22+I25+I26+I27+I28 -> 0 | ... M55: =M21+M22+M25+M26+M27+M28 -> 0
A56: Sumatoria de 8 Pliegues | B56: =SUM(B21:B28) -> 0 | C56: =SUM(C21:C28) -> 0 | D56: =SUM(D21:D28) -> 0 | E56: =SUM(E21:E28) -> 0 | F56: =SUM(F21:F28) -> 0 | G56: =SUM(G21:G28) -> 0 | H56: =SUM(H21:H28) -> 0 | I56: =SUM(I21:I28) -> 0 | ... M56: =SUM(M21:M28) -> 0
A57: PESO
A58: Peso Minimo Permitido | B58: =(B48*100)/(100-B45) -> 0 | C58: =(C48*100)/(100-C45) -> 0 | D58: =(D48*100)/(100-D45) -> 0 | E58: =(E48*100)/(100-E45) -> 0 | F58: =(F48*100)/(100-F45) -> 0 | G58: =(G48*100)/(100-G45) -> 0 | H58: =(H48*100)/(100-H45) -> 0 | I58: =(I48*100)/(100-I45) -> 0 | ... M58: =(M48*100)/(100-M45) -> 0
A59: Peso Maximo Permitido | B59: =(B48*100)/(100-B46) -> 0 | C59: =(C48*100)/(100-C46) -> 0 | D59: =(D48*100)/(100-D46) -> 0 | E59: =(E48*100)/(100-E46) -> 0 | F59: =(F48*100)/(100-F46) -> 0 | G59: =(G48*100)/(100-G46) -> 0 | H59: =(H48*100)/(100-H46) -> 0 | I59: =(I48*100)/(100-I46) -> 0 | ... M59: =(M48*100)/(100-M46) -> 0
A60: Peso Objetivo | B60: 84 | C60: 84
A61: Kg a Subir o Bajar | B61: =B18-B60 -> -84 | C61: =C18-C60 -> -84 | D61: =D18-D60 -> 0 | E61: =E18-E60 -> 0 | F61: =F18-F60 -> 0 | G61: =G18-G60 -> 0 | H61: =H18-H60 -> 0 | I61: =I18-I60 -> 0 | ... M61: =M18-M60 -> 0
A62: SOMATOTIPO
A63: Endomorfia | B63: =(0.1451*((B21+B22+B25)*(170.18/B19)))-(0.00068* POWER(((B21+B22+B25)*(170.18/B19)),2))+(0.00000014*POWER(((B21+B22+B25)*(170.18/B19)),3))-0.7182 -> #DIV/0! | C63: =(0.1451*((C21+C22+C25)*(170.18/C19)))-(0.00068* POWER(((C21+C22+C25)*(170.18/C19)),2))+(0.00000014*POWER(((C21+C22+C25)*(170.18/C19)),3))-0.7182 -> #DIV/0! | D63: =(0.1451*((D21+D22+D25)*(170.18/D19)))-(0.00068* POWER(((D21+D22+D25)*(170.18/D19)),2))+(0.00000014*POWER(((D21+D22+D25)*(170.18/D19)),3))-0.7182 -> #DIV/0! | E63: =(0.1451*((E21+E22+E25)*(170.18/E19)))-(0.00068* POWER(((E21+E22+E25)*(170.18/E19)),2))+(0.00000014*POWER(((E21+E22+E25)*(170.18/E19)),3))-0.7182 -> #DIV/0! | F63: =(0.1451*((F21+F22+F25)*(170.18/F19)))-(0.00068* POWER(((F21+F22+F25)*(170.18/F19)),2))+(0.00000014*POWER(((F21+F22+F25)*(170.18/F19)),3))-0.7182 -> #DIV/0! | G63: =(0.1451*((G21+G22+G25)*(170.18/G19)))-(0.00068* POWER(((G21+G22+G25)*(170.18/G19)),2))+(0.00000014*POWER(((G21+G22+G25)*(170.18/G19)),3))-0.7182 -> #DIV/0! | H63: =(0.1451*((H21+H22+H25)*(170.18/H19)))-(0.00068* POWER(((H21+H22+H25)*(170.18/H19)),2))+(0.00000014*POWER(((H21+H22+H25)*(170.18/H19)),3))-0.7182 -> #DIV/0! | I63: =(0.1451*((I21+I22+I25)*(170.18/I19)))-(0.00068* POWER(((I21+I22+I25)*(170.18/I19)),2))+(0.00000014*POWER(((I21+I22+I25)*(170.18/I19)),3))-0.7182 -> #DIV/0! | ... M63: =(0.1451*((M21+M22+M25)*(170.18/M19)))-(0.00068* POWER(((M21+M22+M25)*(170.18/M19)),2))+(0.00000014*POWER(((M21+M22+M25)*(170.18/M19)),3))-0.7182 -> #DIV/0!
A64: Mesomorfia | B64: =(0.858*B36)+(0.601*B37)+(0.188*(B31-(B21/10)))+(0.161*(B34-(B28/10)))-(0.131*B19)+4.5 -> 4.5 | C64: =(0.858*C36)+(0.601*C37)+(0.188*(C31-(C21/10)))+(0.161*(C34-(C28/10)))-(0.131*C19)+4.5 -> 4.5 | D64: =(0.858*D36)+(0.601*D37)+(0.188*(D31-(D21/10)))+(0.161*(D34-(D28/10)))-(0.131*D19)+4.5 -> 4.5 | E64: =(0.858*E36)+(0.601*E37)+(0.188*(E31-(E21/10)))+(0.161*(E34-(E28/10)))-(0.131*E19)+4.5 -> 4.5 | F64: =(0.858*F36)+(0.601*F37)+(0.188*(F31-(F21/10)))+(0.161*(F34-(F28/10)))-(0.131*F19)+4.5 -> 4.5 | G64: =(0.858*G36)+(0.601*G37)+(0.188*(G31-(G21/10)))+(0.161*(G34-(G28/10)))-(0.131*G19)+4.5 -> 4.5 | H64: =(0.858*H36)+(0.601*H37)+(0.188*(H31-(H21/10)))+(0.161*(H34-(H28/10)))-(0.131*H19)+4.5 -> 4.5 | I64: =(0.858*I36)+(0.601*I37)+(0.188*(I31-(I21/10)))+(0.161*(I34-(I28/10)))-(0.131*I19)+4.5 -> 4.5 | ... M64: =(0.858*M36)+(0.601*M37)+(0.188*(M31-(M21/10)))+(0.161*(M34-(M28/10)))-(0.131*M19)+4.5 -> 4.5
A65: Ectomorfia | B65: =IF(B66>=40.75,(B66*0.732)-28.58,IF(AND(B66<40.15,B66>38.25),(B66*0.463)-17.63,IF(B66<=38.25,0.1))) -> #DIV/0! | C65: =IF(C66>=40.75,(C66*0.732)-28.58,IF(AND(C66<40.15,C66>38.25),(C66*0.463)-17.63,IF(C6<=38.25,0.1))) -> #DIV/0! | D65: =IF(D66>=40.75,(D66*0.732)-28.58,IF(AND(D66<40.15,D66>38.25),(D66*0.463)-17.63,IF(D6<=38.25,0.1))) -> #DIV/0! | E65: =IF(E66>=40.75,(E66*0.732)-28.58,IF(AND(E66<40.15,E66>38.25),(E66*0.463)-17.63,IF(E6<=38.25,0.1))) -> #DIV/0! | F65: =IF(F66>=40.75,(F66*0.732)-28.58,IF(AND(F66<40.15,F66>38.25),(F66*0.463)-17.63,IF(F6<=38.25,0.1))) -> #DIV/0! | G65: =IF(G66>=40.75,(G66*0.732)-28.58,IF(AND(G66<40.15,G66>38.25),(G66*0.463)-17.63,IF(G6<=38.25,0.1))) -> #DIV/0! | H65: =IF(H66>=40.75,(H66*0.732)-28.58,IF(AND(H66<40.15,H66>38.25),(H66*0.463)-17.63,IF(H6<=38.25,0.1))) -> #DIV/0! | I65: =IF(I66>=40.75,(I66*0.732)-28.58,IF(AND(I66<40.15,I66>38.25),(I66*0.463)-17.63,IF(I6<=38.25,0.1))) -> #DIV/0! | J65: =IF(J66>=40.75,(J66*0.732)-28.58,IF(AND(J66<40.15,J66>38.25),(J66*0.463)-17.63,IF(J6<=38.25,0.1))) -> #DIV/0! | ... M65: =IF(M66>=40.75,(M66*0.732)-28.58,IF(AND(M66<40.15,M66>38.25),(M66*0.463)-17.63,IF(M6<=38.25,0.1))) -> #DIV/0!
A66: HWR* | B66: =B19/POWER(B18,1/3) -> #DIV/0! | C66: =C19/POWER(C18,1/3) -> #DIV/0! | D66: =D19/POWER(D18,1/3) -> #DIV/0! | E66: =E19/POWER(E18,1/3) -> #DIV/0! | F66: =F19/POWER(F18,1/3) -> #DIV/0! | G66: =G19/POWER(G18,1/3) -> #DIV/0! | H66: =H19/POWER(H18,1/3) -> #DIV/0! | I66: =I19/POWER(I18,1/3) -> #DIV/0! | ... M66: =M19/POWER(M18,1/3) -> #DIV/0!
A84: FEMENINO
A85: MASCULINO

Sheet SOMATOCARTA
A14: ANÁLISIS ANTROPOMÉTRICO
B15: Fecha | C15: Endomorfia | D15: Mesomorfia | E15: Ectomorfia | F15: Coodenada X | G15: Coordanda Y
B16: ='DATOS ANTROPOMÉTRICOS'!B17 -> 0 | C16: ='DATOS ANTROPOMÉTRICOS'!B63 -> #DIV/0! | D16: ='DATOS ANTROPOMÉTRICOS'!B64 -> 4.5 | E16: ='DATOS ANTROPOMÉTRICOS'!B65 -> #DIV/0! | F16: =E16-C16 -> #DIV/0! | G16: =(2*D16)-(E16+C16) -> #DIV/0!
B17: ='DATOS ANTROPOMÉTRICOS'!C17 -> 0 | C17: ='DATOS ANTROPOMÉTRICOS'!C63 -> #DIV/0! | D17: ='DATOS ANTROPOMÉTRICOS'!C64 -> 4.5 | E17: ='DATOS ANTROPOMÉTRICOS'!C65 -> #DIV/0! | F17: =E17-C17 -> #DIV/0! | G17: =(2*D17)-(E17+C17) -> #DIV/0!
B18: ='DATOS ANTROPOMÉTRICOS'!D17 -> 0 | C18: ='DATOS ANTROPOMÉTRICOS'!D63 -> #DIV/0! | D18: ='DATOS ANTROPOMÉTRICOS'!D64 -> 4.5 | E18: ='DATOS ANTROPOMÉTRICOS'!D65 -> #DIV/0! | F18: =E18-C18 -> #DIV/0! | G18: =(2*D18)-(E18+C18) -> #DIV/0!
B19: ='DATOS ANTROPOMÉTRICOS'!B20 -> 0 | C19: ='DATOS ANTROPOMÉTRICOS'!D63 -> #DIV/0! | D19: ='DATOS ANTROPOMÉTRICOS'!E64 -> 4.5 | E19: ='DATOS ANTROPOMÉTRICOS'!E65 -> #DIV/0! | F19: =E19-C19 -> #DIV/0! | G19: =(2*D19)-(E19+C19) -> #DIV/0!
B20: ='DATOS ANTROPOMÉTRICOS'!E17 -> 0 | C20: ='DATOS ANTROPOMÉTRICOS'!E63 -> #DIV/0! | D20: ='DATOS ANTROPOMÉTRICOS'!F64 -> 4.5 | E20: ='DATOS ANTROPOMÉTRICOS'!E65 -> #DIV/0! | F20: =E20-C20 -> #DIV/0! | G20: =(2*D20)-(E20+C20) -> #DIV/0!
B21: ='DATOS ANTROPOMÉTRICOS'!F17 -> 0 | C21: ='DATOS ANTROPOMÉTRICOS'!F63 -> #DIV/0! | D21: ='DATOS ANTROPOMÉTRICOS'!G64 -> 4.5 | E21: ='DATOS ANTROPOMÉTRICOS'!F65 -> #DIV/0! | F21: =E21-C21 -> #DIV/0! | G21: =(2*D21)-(E21+C21) -> #DIV/0!
B22: ='DATOS ANTROPOMÉTRICOS'!G17 -> 0 | C22: ='DATOS ANTROPOMÉTRICOS'!G63 -> #DIV/0! | D22: ='DATOS ANTROPOMÉTRICOS'!F64 -> 4.5 | E22: ='DATOS ANTROPOMÉTRICOS'!G65 -> #DIV/0! | F22: =E22-C22 -> #DIV/0! | G22: =(2*D22)-(E22+C22) -> #DIV/0!
B23: ='DATOS ANTROPOMÉTRICOS'!H17 -> 0 | C23: ='DATOS ANTROPOMÉTRICOS'!H63 -> #DIV/0! | D23: ='DATOS ANTROPOMÉTRICOS'!H64 -> 4.5 | E23: ='DATOS ANTROPOMÉTRICOS'!H65 -> #DIV/0! | F23: =E23-C23 -> #DIV/0! | G23: =(2*D23)-(E23+C23) -> #DIV/0!
B24: ='DATOS ANTROPOMÉTRICOS'!I17 -> 0 | C24: ='DATOS ANTROPOMÉTRICOS'!I63 -> #DIV/0! | D24: ='DATOS ANTROPOMÉTRICOS'!I64 -> 4.5 | E24: ='DATOS ANTROPOMÉTRICOS'!I65 -> #DIV/0! | F24: =E24-C24 -> #DIV/0! | G24: =(2*D24)-(E24+C24) -> #DIV/0!
B25: ='DATOS ANTROPOMÉTRICOS'!J17 -> 0 | C25: ='DATOS ANTROPOMÉTRICOS'!J63 -> #DIV/0! | D25: ='DATOS ANTROPOMÉTRICOS'!J64 -> 4.5 | E25: ='DATOS ANTROPOMÉTRICOS'!J65 -> #DIV/0! | F25: =E25-C25 -> #DIV/0! | G25: =(2*D25)-(E25+C25) -> #DIV/0!
B26: ='DATOS ANTROPOMÉTRICOS'!K17 -> 0 | C26: ='DATOS ANTROPOMÉTRICOS'!K63 -> #DIV/0! | D26: ='DATOS ANTROPOMÉTRICOS'!K64 -> 4.5 | E26: ='DATOS ANTROPOMÉTRICOS'!K65 -> #DIV/0! | F26: =E26-C26 -> #DIV/0! | G26: =(2*D26)-(E26+C26) -> #DIV/0!

Sheet INFORME 2 COMPONENTES PEDIATRIA
A4: INFORME NUTRICIONAL ANTROPOMÉTRICO
E5: 2 COMPONENTES
A7: DATOS PERSONALES
A9: Nombre y Apellido | C9: =HISTORIA!C4 -> Javier Ignacio Alvarez Izaguirre | E9: Fecha de Nacimiento | G9: =HISTORIA!C8 -> 0 | I9: Deporte
A11: MEDICIONES CORPORALES
A12: Numero de Evaluacion | C12: 1 | E12: 2 | G12: 3 | I12: 4
A13: Fecha de Evaluacion
A14: BASICAS
A15: Peso (kg) | B15: Peso (kg)
A16: Talla (cm) | B16: Talla (cm)
A17: PLIEGUES CUTÁNEOS (mm)
A18: Tricep | B18: Tricep
A19: Subescapular | B19: Subescapular
A20: Bícep | B20: Bícep
A21: Cresta Ilíaca | B21: Cresta Ilíaca
A22: Supraespinal | B22: Supraespinal
A23: Abdominal | B23: Abdominal
A24: Muslo Medio | B24: Muslo Medio
A25: Pantorrilla | B25: Pantorrilla
A26: CIRCUNFERENCIAS (cm)
A27: Brazo relajado | B27: Brazo relajado
A28: Brazo flexionado | B28: Brazo flexionado en tensión
A29: Cintura (Mínimo) | B29: Cintura (Mínimo)
A30: Cadera (Máximo) | B30: Cadera (Máximo)
A31: Muslo máximo | B31: Muslo máximo
A32: Muslo medio | B32: Muslo medio
A33: Pantorrilla | B33: Pantorrilla
A34: RESULTADOS DE COMPOSICIÓN CORPORAL - METODO DE 2 COMPONENTES
A35: Indicadores | C35: 1 | E35: 2 | G35: 3 | I35: 4
C36: Valor | D36: Categoria | E36: Valor | F36: Categoria | G36: Valor | H36: Categoria | I36: Valor | J36: Categoria
A37: % Grasa Brook (1-11 años) | C37: =IF($A37="% Grasa (Durnin y W., 1974)",#REF!,IF($A37="% Grasa (Carter, 1986)",#REF!,IF($A37="% Grasa Brook (1-11 años)",#REF!,IF($A37="% Grasa Durnin (12-16 años)",#REF!)))) -> #REF! | E37: =IF($A37="% Grasa (Durnin y W., 1974)",#REF!,IF($A37="% Grasa (Carter, 1986)",#REF!,IF($A37="% Grasa Brook (1-11 años)",#REF!,IF($A37="% Grasa Durnin (12-16 años)",#REF!)))) -> #REF! | G37: =IF($A37="% Grasa (Durnin y W., 1974)",#REF!,IF($A37="% Grasa (Carter, 1986)",#REF!,IF($A37="% Grasa Brook (1-11 años)",#REF!,IF($A37="% Grasa Durnin (12-16 años)",#REF!)))) -> #REF! | I37: =IF($A37="% Grasa (Durnin y W., 1974)",#REF!,IF($A37="% Grasa (Carter, 1986)",#REF!,IF($A37="% Grasa Brook (1-11 años)",#REF!,IF($A37="% Grasa Durnin (12-16 años)",#REF!)))) -> #REF!
A38: % Peso Magro | C38: =#REF! -> #REF! | E38: =#REF! -> #REF! | G38: =#REF! -> #REF! | I38: =#REF! -> #REF!
A39: Sum de 8 pliegues (mm) | C39: =IF($A39="Sum de 8 pliegues (mm)",#REF!,IF($A39="Sum de 6 pliegues (mm)",#REF!,IF($A39="Sum de 4 pliegues (mm)",#REF!))) -> #REF! | E39: =IF($A39="Sum de 8 pliegues (mm)",#REF!,IF($A39="Sum de 6 pliegues (mm)",#REF!,IF($A39="Sum de 4 pliegues (mm)",#REF!))) -> #REF! | G39: =IF($A39="Sum de 8 pliegues (mm)",#REF!,IF($A39="Sum de 6 pliegues (mm)",#REF!,IF($A39="Sum de 4 pliegues (mm)",#REF!))) -> #REF! | I39: =IF($A39="Sum de 8 pliegues (mm)",#REF!,IF($A39="Sum de 6 pliegues (mm)",#REF!,IF($A39="Sum de 4 pliegues (mm)",#REF!))) -> #REF!
A40: DAGNOSTICO NUTRICIONAL ANTROPOMÉTRICO
A41: Indicadores | C41: 1 | E41: 2 | G41: 3 | I41: 4
C42: Valor | D42: Categoria | E42: Valor | F42: Categoria | G42: Valor | H42: Categoria | I42: Valor | J42: Categoria
A43: Talla adulta | C43: =#REF! -> #REF! | E43: =#REF! -> #REF! | G43: =#REF! -> #REF! | I43: =#REF! -> #REF!
A44: PGP | C44: =#REF! -> #REF! | E44: =#REF! -> #REF! | G44: =#REF! -> #REF! | I44: =#REF! -> #REF!
A45: Peso/Edad | C45: =#REF! -> #REF! | D45: =IF($C45="+3DE",#REF!,IF($C45="P97 - +3DE",#REF!,IF($C45="P97",#REF!,IF($C45="P90 - P97",#REF!,IF($C45="p90",#REF!,IF($C45="P90 - P50",#REF!,IF($C45="P50",#REF!,IF($C45="P50 - P10",#REF!,IF($C45="P10",#REF!,IF($C45="P10 - P3",#REF!,IF($C45="P3",#REF!,IF($C45="P3 - -3DE",#REF!,IF($C45="-3DE",#REF!,IF($C45="-3DE - -4DE",#REF!,IF($C45="-4DE",#REF!))))))))))))))) -> #REF! | E45: =#REF! -> #REF! | F45: =IF($E45="+3DE",#REF!,IF($E45="P97 - +3DE",#REF!,IF($E45="P97",#REF!,IF($E45="P90 - P97",#REF!,IF($E45="p90",#REF!,IF($E45="P90 - P50",#REF!,IF($E45="P50",#REF!,IF($E45="P50 - P10",#REF!,IF($E45="P10",#REF!,IF($E45="P10 - P3",#REF!,IF($E45="P3",#REF!,IF($E45="P3 - -3DE",#REF!,IF($E45="-3DE",#REF!,IF($E45="-3DE - -4DE",#REF!,IF($E45="-4DE",#REF!))))))))))))))) -> #REF! | G45: =#REF! -> #REF! | H45: =IF($G45="+3DE",#REF!,IF($G45="P97 - +3DE",#REF!,IF($G45="P97",#REF!,IF($G45="P90 - P97",#REF!,IF($G45="p90",#REF!,IF($G45="P90 - P50",#REF!,IF($G45="P50",#REF!,IF($G45="P50 - P10",#REF!,IF($G45="P10",#REF!,IF($G45="P10 - P3",#REF!,IF($G45="P3",#REF!,IF($G45="P3 - -3DE",#REF!,IF($G45="-3DE",#REF!,IF($G45="-3DE - -4DE",#REF!,IF($G45="-4DE",#REF!))))))))))))))) -> #REF! | I45: =#REF! -> #REF! | J45: =IF($I45="+3DE",#REF!,IF($I45="P97 - +3DE",#REF!,IF($I45="P97",#REF!,IF($I45="P90 - P97",#REF!,IF($I45="p90",#REF!,IF($I45="P90 - P50",#REF!,IF($I45="P50",#REF!,IF($I45="P50 - P10",#REF!,IF($I45="P10",#REF!,IF($I45="P10 - P3",#REF!,IF($I45="P3",#REF!,IF($I45="P3 - -3DE",#REF!,IF($I45="-3DE",#REF!,IF($I45="-3DE - -4DE",#REF!,IF($I45="-4DE",#REF!))))))))))))))) -> #REF!
A46: Talla/Edad | C46: =#REF! -> #REF! | D46: =IF($C46="+3DE",#REF!,IF($C46="P97 - +3DE",#REF!,IF($C46="P97",#REF!,IF($C46="P90 - P97",#REF!,IF($C46="p90",#REF!,IF($C46="P90 - P50",#REF!,IF($C46="P50",#REF!,IF($C46="P50 - P10",#REF!,IF($C46="P10",#REF!,IF($C46="P10 - P3",#REF!,IF($C46="P3",#REF!,IF($C46="P3 - -3DE",#REF!,IF($C46="-3DE",#REF!,IF($C46="-3DE - -4DE",#REF!,IF($C46="-4DE",#REF!))))))))))))))) -> #REF! | E46: =#REF! -> #REF! | F46: =IF($E46="+3DE",#REF!,IF($E46="P97 - +3DE",#REF!,IF($E46="P97",#REF!,IF($E46="P90 - P97",#REF!,IF($E46="p90",#REF!,IF($E46="P90 - P50",#REF!,IF($E46="P50",#REF!,IF($E46="P50 - P10",#REF!,IF($E46="P10",#REF!,IF($E46="P10 - P3",#REF!,IF($E46="P3",#REF!,IF($E46="P3 - -3DE",#REF!,IF($E46="-3DE",#REF!,IF($E46="-3DE - -4DE",#REF!,IF($E46="-4DE",#REF!))))))))))))))) -> #REF! | G46: =#REF! -> #REF! | H46: =IF($G46="+3DE",#REF!,IF($G46="P97 - +3DE",#REF!,IF($G46="P97",#REF!,IF($G46="P90 - P97",#REF!,IF($G46="p90",#REF!,IF($G46="P90 - P50",#REF!,IF($G46="P50",#REF!,IF($G46="P50 - P10",#REF!,IF($G46="P10",#REF!,IF($G46="P10 - P3",#REF!,IF($G46="P3",#REF!,IF($G46="P3 - -3DE",#REF!,IF($G46="-3DE",#REF!,IF($G46="-3DE - -4DE",#REF!,IF($G46="-4DE",#REF!))))))))))))))) -> #REF! | I46: =#REF! -> #REF! | J46: =IF($I46="+3DE",#REF!,IF($I46="P97 - +3DE",#REF!,IF($I46="P97",#REF!,IF($I46="P90 - P97",#REF!,IF($I46="p90",#REF!,IF($I46="P90 - P50",#REF!,IF($I46="P50",#REF!,IF($I46="P50 - P10",#REF!,IF($I46="P10",#REF!,IF($I46="P10 - P3",#REF!,IF($I46="P3",#REF!,IF($I46="P3 - -3DE",#REF!,IF($I46="-3DE",#REF!,IF($I46="-3DE - -4DE",#REF!,IF($I46="-4DE",#REF!))))))))))))))) -> #REF!
A47: Peso/Talla | C47: =#REF! -> #REF! | D47: =IF($C47="+3DE",#REF!,IF($C47="P97 - +3DE",#REF!,IF($C47="P97",#REF!,IF($C47="P90 - P97",#REF!,IF($C47="p90",#REF!,IF($C47="P90 - P50",#REF!,IF($C47="P50",#REF!,IF($C47="P50 - P10",#REF!,IF($C47="P10",#REF!,IF($C47="P10 - P3",#REF!,IF($C47="P3",#REF!,IF($C47="P3 - -3DE",#REF!,IF($C47="-3DE",#REF!,IF($C47="-3DE - -4DE",#REF!,IF($C47="-4DE",#REF!))))))))))))))) -> #REF! | E47: =#REF! -> #REF! | F47: =IF($E47="+3DE",#REF!,IF($E47="P97 - +3DE",#REF!,IF($E47="P97",#REF!,IF($E47="P90 - P97",#REF!,IF($E47="p90",#REF!,IF($E47="P90 - P50",#REF!,IF($E47="P50",#REF!,IF($E47="P50 - P10",#REF!,IF($E47="P10",#REF!,IF($E47="P10 - P3",#REF!,IF($E47="P3",#REF!,IF($E47="P3 - -3DE",#REF!,IF($E47="-3DE",#REF!,IF($E47="-3DE - -4DE",#REF!,IF($E47="-4DE",#REF!))))))))))))))) -> #REF! | G47: =#REF! -> #REF! | H47: =IF($G47="+3DE",#REF!,IF($G47="P97 - +3DE",#REF!,IF($G47="P97",#REF!,IF($G47="P90 - P97",#REF!,IF($G47="p90",#REF!,IF($G47="P90 - P50",#REF!,IF($G47="P50",#REF!,IF($G47="P50 - P10",#REF!,IF($G47="P10",#REF!,IF($G47="P10 - P3",#REF!,IF($G47="P3",#REF!,IF($G47="P3 - -3DE",#REF!,IF($G47="-3DE",#REF!,IF($G47="-3DE - -4DE",#REF!,IF($G47="-4DE",#REF!))))))))))))))) -> #REF! | I47: =#REF! -> #REF! | J47: =IF($I47="+3DE",#REF!,IF($I47="P97 - +3DE",#REF!,IF($I47="P97",#REF!,IF($I47="P90 - P97",#REF!,IF($I47="p90",#REF!,IF($I47="P90 - P50",#REF!,IF($I47="P50",#REF!,IF($I47="P50 - P10",#REF!,IF($I47="P10",#REF!,IF($I47="P10 - P3",#REF!,IF($I47="P3",#REF!,IF($I47="P3 - -3DE",#REF!,IF($I47="-3DE",#REF!,IF($I47="-3DE - -4DE",#REF!,IF($I47="-4DE",#REF!))))))))))))))) -> #REF!
A48: IMC/Edad | C48: =#REF! -> #REF! | D48: =IF($C48="+3DE",#REF!,IF($C48="P97 - +3DE",#REF!,IF($C48="P97",#REF!,IF($C48="P90 - P97",#REF!,IF($C48="p90",#REF!,IF($C48="P90 - P50",#REF!,IF($C48="P50",#REF!,IF($C48="P50 - P10",#REF!,IF($C48="P10",#REF!,IF($C48="P10 - P3",#REF!,IF($C48="P3",#REF!,IF($C48="P3 - -3DE",#REF!,IF($C48="-3DE",#REF!,IF($C48="-3DE - -4DE",#REF!,IF($C48="-4DE",#REF!))))))))))))))) -> #REF! | E48: =#REF! -> #REF! | F48: =IF($E48="+3DE",#REF!,IF($E48="P97 - +3DE",#REF!,IF($E48="P97",#REF!,IF($E48="P90 - P97",#REF!,IF($E48="p90",#REF!,IF($E48="P90 - P50",#REF!,IF($E48="P50",#REF!,IF($E48="P50 - P10",#REF!,IF($E48="P10",#REF!,IF($E48="P10 - P3",#REF!,IF($E48="P3",#REF!,IF($E48="P3 - -3DE",#REF!,IF($E48="-3DE",#REF!,IF($E48="-3DE - -4DE",#REF!,IF($E48="-4DE",#REF!))))))))))))))) -> #REF! | G48: =#REF! -> #REF! | H48: =IF($G48="+3DE",#REF!,IF($G48="P97 - +3DE",#REF!,IF($G48="P97",#REF!,IF($G48="P90 - P97",#REF!,IF($G48="p90",#REF!,IF($G48="P90 - P50",#REF!,IF($G48="P50",#REF!,IF($G48="P50 - P10",#REF!,IF($G48="P10",#REF!,IF($G48="P10 - P3",#REF!,IF($G48="P3",#REF!,IF($G48="P3 - -3DE",#REF!,IF($G48="-3DE",#REF!,IF($G48="-3DE - -4DE",#REF!,IF($G48="-4DE",#REF!))))))))))))))) -> #REF! | I48: =#REF! -> #REF! | J48: =IF($I48="+3DE",#REF!,IF($I48="P97 - +3DE",#REF!,IF($I48="P97",#REF!,IF($I48="P90 - P97",#REF!,IF($I48="p90",#REF!,IF($I48="P90 - P50",#REF!,IF($I48="P50",#REF!,IF($I48="P50 - P10",#REF!,IF($I48="P10",#REF!,IF($I48="P10 - P3",#REF!,IF($I48="P3",#REF!,IF($I48="P3 - -3DE",#REF!,IF($I48="-3DE",#REF!,IF($I48="-3DE - -4DE",#REF!,IF($I48="-4DE",#REF!))))))))))))))) -> #REF!
A49: DIAGNOSTICO
A51: SOMATOTIPO (HEATH - CARTER, 1990)
A53: El somatotipo describe numéricamente tus características físicas, qué aspecto tienes como atleta y qué tanto te asemejas a un futbolista promedio. Esto se hace a través de tres números, cada uno representa tu forma física: la gordura o adiposidad (endomorfia), la robustez músculo-esquelética (mesomorfia) y la delgadez (ectomorfia). Dependiendo del deporte que estes realizando y la posición de la misma dichos valores pueden variar de un sujeto a otro. En tu evaluación, los valores obtenidos fueron:
A58: Deporte | D58: Endomorfia | F58: Mesomorfia | H58: Ectomorfia
A59: EDAD
A61: Resultados sujeto evaluado | D61: Ectomorfia | F61: Mesomorfia | H61: Ectomorfia
A62: -1 | D62: =IF($A62=#REF!,#REF!,IF($A62=#REF!,#REF!,IF($A62=#REF!,#REF!,IF($A62=#REF!,#REF!)))) -> #REF! | F62: =IF($A62=#REF!,#REF!,IF($A62=#REF!,#REF!,IF($A62=#REF!,#REF!,IF($A62=#REF!,#REF!)))) -> #REF! | H62: =IF($A62=#REF!,#REF!,IF($A62=#REF!,#REF!,IF($A62=#REF!,#REF!,IF($A62=#REF!,#REF!)))) -> #REF!
D64: Clasificacion
A94: CONCLUSIONES Y RECOMENDACIONES
A99: Protocolo de medición: ISAK. Instrumentos empleados: Balanza (precisión 100 g), Calibrador de pliegues cutáneos Slim Guide (0,5 mm), Cinta métrica Luftkin (0,1 mm), Vernier Rosscraft (0,1 mm).
